Workbook
Name _cum3: '[1]BALANCE N'!$L:$L
Name _cum4: '[1]BALANCE N'!$M:$M
Name _dFin: 42735
Name _mc1: 'Balance N-1'!$N$3:$N$2201
Name _md1: 'Balance N-1'!$M$3:$M$2201
Name _sfc1: 'Balance N-1'!$P$3:$P$2201
Name _sfd1: 'Balance N-1'!$O$3:$O$2201
Name _sic1: 'Balance N-1'!$L$3:$L$2201
Name _sid1: 'Balance N-1'!$K$3:$K$2201
Name _soNumFisc: 3201201523617
Name _soSigle: "PYTHAGORE CONSULTAN"
Name Cptes: 'Balance N'!$I$3:$I$2201
Name Cptes1: 'Balance N-1'!$I$3:$I$2201
Name Exercice: 'INFORMATIONS GENERALES'!$B$3
Name mc: 'Balance N'!$N$3:$N$2201
Name md: 'Balance N'!$M$3:$M$2201
Name sfc: 'Balance N'!$P$3:$P$2201
Name sfd: 'Balance N'!$O$3:$O$2201
Name sic: 'Balance N'!$L$3:$L$2201
Name sid: 'Balance N'!$K$3:$K$2201

Sheet Présentation
A1: États financiers des projets de développement et assimilés (Systèmes normal)
A3: Contenu des états financiers
A4: Les états financiers des projets de développement et assimilés comprennent :
A5: · Le tableau emploies ressources ;
A6: · Le tableau d’exécution du budgétaire ;
A7: · Le tableau de réconciliation de trésorerie ;
A8: · Le bilan ;
A9: · Le compte d’exploitation ;
A10: · Et les Notes annexes.
A11: ATTENTION
A12: Compte d’exploitation : le résultat dégagé par les opérations est intitulé : solde des opérations de l’exercice qui doit être nul.
A13: Notes annexes: Les Notes non documentées ne doivent pas être jointes aux états financiers. Leur contenu peut être amélioré par les entités. Par ailleurs, dans une note, les lignes non chiffrées doivent être supprimées.
A14: Par exemple, dans la note 17 Services extérieurs, lorsque la ligne sous-traitance générale n’est pas chiffrée, elle ne doit pas figurer dans cette note.

Sheet Plan Comptable
F1: SYCEBNL (Système Comptable des Entités à But Non Lucratif)
F3: CLASSE 1: COMPTES DE RESSOURCES DURABLES
F4: 10. | G4: DOTATION
F5: 101 | G5: Dotationb non consomptible sans droit de reprise
F6: 1011 | G6: en numéraire
F7: 1015 | G7: en nature
F8: 102 | G8: Dotationb non consomptible avec droit de reprise
F9: 1021 | G9: en numéraire
F10: 1025 | G10: en nature
F11: 103 | G11: Droit d'entrée
F12: 104 | G12: Dotation consomptible
F13: 1041 | G13: Dotation consomptible
F14: 1049 | G14: Dotation consomptible inscrite au compte de résultat
F15: 106 | G15: Ecarts de réévaluation
F16: 1061 | G16: Ecarts de réévaluation sur des biens sans droit de reprise
... F21: 10622 | G21: Ecarts de réévaluation sur les biens avec droit de reprise-immobilisations financières
F22: 11. | G22: RESERVES
F23: 112 | G23: Réserves statutaires ou contactuelles
F24: 118 | G24: Autres réserves
F25: 12. | G25: REPORT A NOUVEAU
F26: 121 | G26: Rapport à nouveau des excédents
F27: 1211 | G27: Repport à nouveau des excédents-résultat*
F28: 1213 | G28: Repport à nouveau des excédents-changement de méthode comptamble*
F29: 1214 | G29: Report à nouveau des excédents-corrections d'erreurs significatives*
F30: 1218 | G30: Report à nouveau des excédents-autres reports*
F31: 128 | G31: Résultat net en instance d'affectation
F32: 1281 | G32: Résultat net en instance d'affectation:Excédent*
F33: 1289 | G33: Résultat net en instance d'affectation:Déficit*
F34: 129 | G34: Report à nouveau des déficits
F35: 1291 | G35: Report à nouveau des déficits-résultat*
F36: 1293 | G36: Report à nouveau des déficits -changement de méthode comptable*
F37: 1294 | G37: Report à nouveau des déficits-corrections d'erreurs significatives*
F38: 1298 | G38: Report à nouveau des déficits-autres reports*
F39: 13. | G39: RESULTAT NET DE L'EXERCICE
F40: 131 | G40: Excédent de l'exercice
F41: 139 | G41: Déficit de l'exercice
F42: 14. | G42: SUBVENTIONS D'INVESTISSEMENT
F43: 141 | G43: Subventions d'équipement
F44: 1411 | G44: Etat
F45: 1412 | G45: Regions
F46: 1413 | G46: Départements
F47: 1414 | G47: Commines et collectivités publiques décentralisées
F48: 1415 | G48: Entités publiques ou mixtes
F49: 1416 | G49: Entités et organismes internatinaux
F50: 1417 | G50: Organismes internationaux
F51: 1418 | G51: Autres
F52: 148 | G52: Autres subventions d'investissement
F53: 15. | G53: PROVISIONS REGLEMENTEES ET FONDS ASSIMILES
F54: 154 | G54: Provisions spéciales de réévaluation
F55: 158 | G55: Autres provisions réglementées et fonds assimilés
F56: 16. | G56: FONDS AFFECTES
F57: 161 | G57: Fonds projet de développement-avances de fonds à justifier
F58: 162 | G58: Fonds affectés aux investissements du projet de développement-bailleurs de fonds
F59: 163 | G59: Fonds affectés aux investissements du projet de développement-l'Etat
F60: 164 | G60: Fonds affectés aux investissements des autres organismes de financement assimilés
F61: 165 | G61: Fonds affectés à un projet spécifique
F62: 167 | G62: Fonds provenant de dons et legs d'immobilisations
F63: 1671 | G63: Affectés
F64: 1672 | G64: Non affectés
F65: 1679 | G65: Engagements auprés du donateur
F66: 168 | G66: Autres fonds affectés
F67: 169 | G67: Fonds affectés à recevoir
F68: 17. | G68: FONDS REPORTES
F69: 171 | G69: Donation temporaire d'usufruit
F70: 172 | G70: Donations et legs non encore reçus d'immobilisations destinnées à la vente
F71: 178 | G71: Autres fonds reportés
F72: 18 | G72: EMPRUNTS ET DETTES ASSIMILEES
F73: 181 | G73: Emprunts obligatoires
F74: 182 | G74: Emprunts et dettes auprés des établissements de crédit
F75: 183 | G75: Avances reçues de l'Etat
F76: 185 | G76: Dépôts et cautionnements reçus
F77: 1851 | G77: Dépôts
F78: 1852 | G78: Cautionnements
F79: 186 | G79: Intérêts courus
F80: 1861 | G80: Sur emprunts obligatoires
... F99: 1988 | G99: Provisions pour divers risque et charge
F100: CLASSE 2: COMPTES D'ACTIF IMMOBILISE
F101: 20 | G101: IMMOBILISATIONS DESTINEES A LA VENTE PROVENANT DE DONS ET LEGS NON ENCORE RECUS ET USUFRUIT TEMPORAIRE
F102: 201 | G102: Immobilisations incorporelles
F103: 2011 | G103: Usufruit temporaire
F104: 2012 | G104: Brevets,licences,concesseions et droits similaires
F105: 2013 | G105: Logisciels et sites internet
F106: 2014 | G106: Marques
F107: 2017 | G107: Autres
F108: 202 | G108: Terrains
F109: 203 | G109: Bâtiments
F110: 204 | G110: Matériels
F111: 205 | G111: Titres de particioations
F112: 21 | G112: IMMOBILISATIONS INCORPORELLES
... F154: 2298 | G154: Autres terrains
F155: 23. | G155: BATIMENT, INSTALLATIONS TECHNIQUES ET AGENCEMENTRAPPORT DE
F156: 231 | G156: Bâtiments industriels, agricoles, administratifs, commerciaux, religieux et autres sur sol propre
F157: 2311 | G157: Bâtiments Industriels
F158: 2312 | G158: Bâtiments agricoles
F159: 2313 | G159: Bâtimentsadministratifs et commerciaux
F160: 2314 | G160: Bâtimentsaffectés au logement personnel
F161: 2315 | G161: Bâtiments-immeubles de placement
F162: 2316 | G162: Bâtiments de location-acquisition
F163: 2317 | G163: Edifices religieux et assimilés
F164: 2318 | G164: Autres bâtiments sur sol propre
...

Sheet MENU PRINCIPAL
B1: N° | C1: INTITULE | D1: RENVOIE | E1: N° | F1: INTITULE | G1: RENVOIE
B2: 1 | C2: Informations générales | D2: Entité | E2: =B27+1 -> 27 | F2: Subventions | G2: NOTE 10
B3: 2 | C3: Balance générale de l'exercice N | D3: Balance N | E3: =E2+1 -> 28 | F3: Dettes financières et ressources assimilées | G3: NOTE 11
B4: 3 | C4: Balance générale de l'exercice N-1 | D4: Balance N-1 | E4: =E3+1 -> 29 | F4: Dettes fournisseurs et assimilées, dettes fiscales et sociales | G4: NOTE 12
B5: 4 | C5: Contrôle d'équilibre des balances et bilans | D5: Contrôles | E5: =E4+1 -> 30 | F5: Banques, crédit d'escompte et de trésorerie | G5: NOTE 13
B6: 5 | C6: Page de couveture des états financiers annuels | D6: Couverture | E6: =E5+1 -> 31 | F6: Revenus et autres produits | G6: NOTE 14
B7: 6 | C7: Page de garde des états financiers annuels | D7: Page garde | E7: =E6+1 -> 32 | F7: Achats | G7: NOTE 15
B8: 7 | C8: Fiche d'identification et renseignements divers 1 | D8: Fiche R1 | E8: =E7+1 -> 33 | F8: Transports | G8: NOTE 16
B9: 8 | C9: Fiche d'identification et renseignements divers 2 | D9: Fiche R2 | E9: =E8+1 -> 34 | F9: Services extérieurs | G9: NOTE 17
B10: 9 | C10: Tableau emplois-ressources | D10: TER | E10: =E9+1 -> 35 | F10: Impôts et taxes | G10: NOTE 18
B11: 10 | C11: Tableau de reconciliation de trésorerie | D11: TRC | E11: =E10+1 -> 36 | F11: Autres charges | G11: NOTE 19
B12: 11 | C12: Tableau d'exécution budgétaire | D12: TEB | E12: =E11+1 -> 37 | F12: Charges de personnel | G12: NOTE 20A
B13: 12 | C13: Bilan en paysage | D13: Bilan | E13: =E12+1 -> 38 | F13: Effectifs, masse salariale et personnel extérieur | G13: NOTE 20B | K13: AFFICHER OU MASQUER NOTES
B14: 13 | C14: Bilan-Actif | D14: Bilan-Actif | E14: =E13+1 -> 39 | F14: Charges et revenus financiers | G14: NOTE 21 | K14: VALEURS | L14: NOTES
B15: 14 | C15: Bilan-Passif | D15: Bilan-Passif | E15: =E14+1 -> 40 | F15: Dotations et charges pour provisions | G15: NOTE 22 | K15: =[2]R4!L9 -> 0 | L15: NOTE 1
B16: 15 | C16: Compte de résultat | D16: Résultat | E16: =E15+1 -> 41 | F16: Autres charges et produits HAO | G16: NOTE 23 | K16: =[2]R4!L10 -> 0 | L16: NOTE 2
B17: 16 | C17: Fiche recapitulative des Notes annexes présentées | D17: Fiche R3 | E17: =E16+1 -> 42 | F17: Tableau d'exécution budgétaire | G17: NOTE 24 | K17: =[2]R4!L11 -> 1 | L17: NOTE 3A
B18: 17 | C18: Informations obligatoires | D18: NOTE 1 | E18: =E17+1 -> 43 | F18: Table des commentaires | G18: COMMENTAIRE | K18: =[2]R4!L12 -> 0 | L18: NOTE 3B
B19: 18 | C19: Informations spécifiques | D19: NOTE 2 | E19: =E18+1 -> 44 | F19: Etats supplémentaires | G19: GARDE (DGI-INS) | K19: =[2]R4!L13 -> 1 | L19: NOTE 3C
B20: 19 | C20: Immobilisations brutes | D20: NOTE 3A | E20: =E19+1 -> 45 | F20: Fiche récapitulative des états supplémentaires DGI & INS | G20: NOTES DGI - INS | K20: =[2]R4!L14 -> 0 | L20: NOTE 3C BIS
B21: 20 | C21: Biens pris en location acquisition | D21: NOTE 3B | E21: =E20+1 -> 46 | F21: Etat complementaire DGI/Comptabilite Nationale | G21: COMP-CHARGES | K21: =[2]R4!L15 -> 0 | L21: NOTE 3D
B22: 21 | C22: Actif circulant et dettes circulantes HAO | D22: NOTE 4 | E22: =E21+1 -> 47 | F22: Etat complementaire DGI/Comptabilite Nationale | G22: COMP-TVA | K22: =[2]R4!L16 -> 1 | L22: NOTE 3E
B23: 22 | C23: Stocks et encours | D23: NOTE 5 | E23: =E22+1 -> 48 | F23: Etat complementaire DGI/Comptabilite Nationale | G23: COMP-TVA (2) | K23: =[2]R4!L17 -> 1 | L23: NOTE 4
B24: 23 | C24: Clients-usagers et autres créances | D24: NOTE 6 | E24: =E23+1 -> 49 | F24: Tableau des amortissements et inventaire des immobilisations | G24: SUPPL1 | K24: =[2]R4!L18 -> 1 | L24: NOTE 5
B25: 24 | C25: Disponibilités | D25: NOTE 7 | E25: =E24+1 -> 50 | F25: Détail des frais accessoires sur achats | G25: SUPPL2 | K25: =[2]R4!L19 -> 1 | L25: NOTE 6
B26: 25 | C26: Ecarts de conversion et transferts de charges | D26: NOTE 8 | E26: =E25+1 -> 51 | F26: Détail des avantages en nature et en espèces imposes (Pl) | G26: SUPPL3 | K26: =[2]R4!L20 -> 1 | L26: NOTE 7
B27: 26 | C27: Fonds du bailleur | D27: NOTE 9 | E27: =E26+1 -> 52 | K27: =[2]R4!L21 -> 1 | L27: NOTE 8
K28: =[2]R4!L40 -> 1 | L28: NOTE 20
K29: =[2]R4!L41 -> 1 | L29: NOTE 21
K30: =[2]R4!L42 -> 1 | L30: NOTE 22
K31: =[2]R4!L43 -> 1 | L31: NOTE 23
K32: =[2]R4!L44 -> 1 | L32: NOTE 24
K33: =[2]R4!L45 -> 1 | L33: NOTE 25
K34: =[2]R4!L46 -> 1 | L34: NOTE 26
K35: =[2]R4!L47 -> 1 | L35: NOTE 27A
K36: =[2]R4!L48 -> 0 | L36: NOTE 27B
K37: =[2]R4!L49 -> 1 | L37: NOTE 28
K38: =[2]R4!L50 -> 1 | L38: NOTE 29
K39: =[2]R4!L51 -> 0 | L39: NOTE 30
... K44: =[2]R4!L56 -> 0 | L44: NOTE 35
K45: =[2]R4!L58 -> 1 | L45: NOTE 37
K46: =[2]R4!L59 -> 0 | L46: NOTE 38
K47: =[2]R4!L60 -> 0 | L47: NOTE 39
K48: =[2]R4!L61 -> 1 | L48: GARDE (DGI-INS)
K51: =[2]R4!L65 -> 1 | L51: NOTES DGI - INS
K52: =[2]R4!L66 -> 1 | L52: COMP-CHARGES
K53: =[2]R4!L67 -> 1 | L53: COMP-TVA
K54: =[2]R4!L68 -> 0 | L54: COMP-TVA (2)
K55: =[2]R4!L69 -> 0 | L55: SUPPL1
K56: =[2]R4!L70 -> 0 | L56: SUPPL2
K57: =[2]R4!L71 -> 0 | L57: SUPPL3
K58: =[2]R4!L72 -> 1 | L58: SUPPL4
K59: =[2]R4!L73 -> 0 | L59: SUPPL5
K60: =[2]R4!L74 -> 0 | L60: SUPPL6
K61: =[2]R4!L75 -> 0 | L61: SUPPL7
K62: =[2]R4!L76 -> 1 | L62: GARDE (BIC)
... K68: =[2]R4!L82 -> 1 | L68: COMMENTAIRE
K69: =[2]R4!L83 -> 0
K70: =[2]R4!L84 -> 0
K71: =[2]R4!L85 -> 0
K72: =[2]R4!L86 -> 0
K73: =[2]R4!L87 -> 0
K74: =[2]R4!L88 -> 0
K75: =[2]R4!L89 -> 0
K76: =[2]R4!L90 -> 0
K77: =[2]R4!L90 -> 0

Sheet INFORMATIONS GENERALES
AD1: =IF(YEAR(U9)>1900,U9,"") -> 45657 | AE1: =MONTH(I15) -> 1
AD2: =IF(YEAR(U9)>1900,EDATE(U9,3),"") -> 45747 | AE2: =YEAR(I15) -> 1900
AD3: Date d'arrêt | AE3: =IF(AE1>=7,AE2+1,AE2) -> 1900
AE4: Date de Création
C7: INFORMATIONS GENERALES DE L'ENTITE | AH7: =IF(AND([2]RESULTAT!I18<>0,E62<>0,E62<>""),(Z30)/[2]RESULTAT!I18,0) -> 0
AH8: =IF(AND([2]RESULTAT!J18<>0,E62<>0,E62<>""),(Z56/E62)/[2]RESULTAT!J18,0) -> 0
C9: ZA | E9: EXERCICE COMPTABLE : | O9: DU: | P9: 45292 | T9: AU: | U9: 45657
Z10: 1900 | AA10: =IF(Z10>1900,Z10,"N") -> N
C11: ZB | D11: DATE D'ARRETE EFFECTIF DES COMPTES : | J11: 45747 | Z11: 1900 | AA11: =IF(Z11>1900,Z11,"N-1") -> N-1
C13: ZC | D13: EXERCICE PRECEDENT CLOS LE : | J13: 45657 | M13: ZD | O13: DUREE EXERCICE PRECEDENT EN MOIS : | W13: 12
C15: ZE | E15: 10 | L15: ZF
E16: Greffe | F16: N°Registre du Commerce | I16: Date de Création | M16: N° Répertoire des entités
C18: ZG | G18: ZH | R18: ZI | S18: A0101
E19: N° de caisse sociale | H19: N° Code Importateur
C21: ZJ | E21: DSO Services | L21: DSO Services
E22: Désignation de l'entité | L22: Sigle
C24: ZK | E24: 76191918 | G24: scheckoumard@gmail.com | K24: 01 | L24: 13 | N24: Bobo-Dioulasso
E25: N° de téléphone | G25: Adresse email | K25: Code | L25: BP | N25: Ville
S26: Code activités
C28: ZL | E28: Rue Alphamoi Djénèpo, secteur 01, Bobo-Dioulasso, Burkina Faso
E29: Adresse géographique complète (Immeuble, rue, quartier, ville, pays)
C31: ZM | R31: 1
E32: Désignation précise de l'activité principale exercée par l'entité | R32: % Capacité production utile
AG33: 0
C34: ZO
E35: Nom | G35: Adresse Personne à contacter en cas de demande | K35: Téléphone | M35: Adresse e-mail | U35: Qualité
C37: ZP
E38: Nom | G38: Adresse | M38: Téléphone | Q38: Adresse e-mail
E39: Salarié de l'entité ou professionnel comptable inscrit à l'Ordre des Experts-comptables ayant établi les états financiers
C41: ZQ
E42: Nom, adresse, téléphone, e-mail et numéro d'inscription à l'Ordre des Experts-comptables de l'Expert comptable ayant délivré l'attestation de visa
C45: ZR
E46: Nom, adresse, téléphone, e-mail et numéro d'inscription à l'Ordre des Experts-comptables de l'Expert comptablble ayant délivré l'attestation d'exécution de la mission du commissariat aux comptes
C50: ZS | S50: Oui
P51: Etats financiers approuvés par l'Assemblée Générale (cocher la case)
O53: NCC | P53: 00000101A
E54: Centre d'impôt | I54: Commune | P54: Numéro de conte contribuable
E56: Personne morale | G56: SARL | I56: Réel normal | J56: Côte d'Ivoire | O56: NTD | P56: Néant
E57: Type de personne | G57: Forme juridique | I57: Régime fiscal | J57: Pays du siège social | P57: Numéro de télédéclarant
E59: Impôt BIC | G59: 0.25 | J59: 0.005 | L59: ZW
E60: Régime d'imposition du bénéfice | G60: Taux de l'Impôt | J60: Taux de l'IMF | L60: Domiciliations bancaires
L61: Banque | S61: Numéro de compte
E62: 0.18
E63: Tx. TVA | F63: =IF(YEAR(U9)>1900,CONCATENATE("Prorata déduction TVA ",YEAR(U9)),"Prorata déduction TVA N") -> Prorata déduction TVA 2024 | H63: =IF(YEAR(J13)>1900,CONCATENATE("Prorata déduction TVA ",YEAR(J13)),"Prorata déduction TVA N-1") -> Prorata déduction TVA 2024
C65: ZT
E66: Nom du signataire des états financiers
C68: ZU
E69: Qualité du signataire des états financiers

Sheet Balance N
I1: CPTE | J1: INTITULES DES COMPTES | K1: MOUV.N-1. DEBIT | L1: MOUV.N-1.CREBIT | M1: MOUV.N DEBIT | N1: MOUV.N CREDIT | O1: S.F. DEBIT | P1: S.F. CREDIT
K2: =SUM(sid) -> 0 | L2: =SUM(sic) -> 0 | M2: =SUM(md) -> 0 | N2: =SUM(mc) -> 0 | O2: =SUM(sfd) -> 0 | P2: =SUM(sfc) -> 0
A3: =IF(Cptes="","",LEFT(Cptes,2)) | B3: =IF(Cptes="","",LEFT(Cptes,3)) | C3: =IF(Cptes="","",LEFT(Cptes,4)) | D3: =IF(Cptes="","",LEFT(Cptes,5)) | E3: =IF(Cptes="","",LEFT(Cptes,6)) | F3: =IF(Cptes="","",LEFT(Cptes,7)) | G3: =IF(Cptes="","",LEFT(Cptes,7)) | H3: =IF(Cptes="","",LEFT(Cptes,7))
A4: =IF(Cptes="","",LEFT(Cptes,2)) | B4: =IF(Cptes="","",LEFT(Cptes,3)) | C4: =IF(Cptes="","",LEFT(Cptes,4)) | D4: =IF(Cptes="","",LEFT(Cptes,5)) | E4: =IF(Cptes="","",LEFT(Cptes,6)) | F4: =IF(Cptes="","",LEFT(Cptes,7)) | G4: =IF(Cptes="","",LEFT(Cptes,7)) | H4: =IF(Cptes="","",LEFT(Cptes,7))
A5: =IF(Cptes="","",LEFT(Cptes,2)) | B5: =IF(Cptes="","",LEFT(Cptes,3)) | C5: =IF(Cptes="","",LEFT(Cptes,4)) | D5: =IF(Cptes="","",LEFT(Cptes,5)) | E5: =IF(Cptes="","",LEFT(Cptes,6)) | F5: =IF(Cptes="","",LEFT(Cptes,7)) | G5: =IF(Cptes="","",LEFT(Cptes,7)) | H5: =IF(Cptes="","",LEFT(Cptes,7))
A6: =IF(Cptes="","",LEFT(Cptes,2)) | B6: =IF(Cptes="","",LEFT(Cptes,3)) | C6: =IF(Cptes="","",LEFT(Cptes,4)) | D6: =IF(Cptes="","",LEFT(Cptes,5)) | E6: =IF(Cptes="","",LEFT(Cptes,6)) | F6: =IF(Cptes="","",LEFT(Cptes,7)) | G6: =IF(Cptes="","",LEFT(Cptes,7)) | H6: =IF(Cptes="","",LEFT(Cptes,7))
A7: =IF(Cptes="","",LEFT(Cptes,2)) | B7: =IF(Cptes="","",LEFT(Cptes,3)) | C7: =IF(Cptes="","",LEFT(Cptes,4)) | D7: =IF(Cptes="","",LEFT(Cptes,5)) | E7: =IF(Cptes="","",LEFT(Cptes,6)) | F7: =IF(Cptes="","",LEFT(Cptes,7)) | G7: =IF(Cptes="","",LEFT(Cptes,7)) | H7: =IF(Cptes="","",LEFT(Cptes,7))
A8: =IF(Cptes="","",LEFT(Cptes,2)) | B8: =IF(Cptes="","",LEFT(Cptes,3)) | C8: =IF(Cptes="","",LEFT(Cptes,4)) | D8: =IF(Cptes="","",LEFT(Cptes,5)) | E8: =IF(Cptes="","",LEFT(Cptes,6)) | F8: =IF(Cptes="","",LEFT(Cptes,7)) | G8: =IF(Cptes="","",LEFT(Cptes,7)) | H8: =IF(Cptes="","",LEFT(Cptes,7))
A9: =IF(Cptes="","",LEFT(Cptes,2)) | B9: =IF(Cptes="","",LEFT(Cptes,3)) | C9: =IF(Cptes="","",LEFT(Cptes,4)) | D9: =IF(Cptes="","",LEFT(Cptes,5)) | E9: =IF(Cptes="","",LEFT(Cptes,6)) | F9: =IF(Cptes="","",LEFT(Cptes,7)) | G9: =IF(Cptes="","",LEFT(Cptes,7)) | H9: =IF(Cptes="","",LEFT(Cptes,7))
A10: =IF(Cptes="","",LEFT(Cptes,2)) | B10: =IF(Cptes="","",LEFT(Cptes,3)) | C10: =IF(Cptes="","",LEFT(Cptes,4)) | D10: =IF(Cptes="","",LEFT(Cptes,5)) | E10: =IF(Cptes="","",LEFT(Cptes,6)) | F10: =IF(Cptes="","",LEFT(Cptes,7)) | G10: =IF(Cptes="","",LEFT(Cptes,7)) | H10: =IF(Cptes="","",LEFT(Cptes,7))
A11: =IF(Cptes="","",LEFT(Cptes,2)) | B11: =IF(Cptes="","",LEFT(Cptes,3)) | C11: =IF(Cptes="","",LEFT(Cptes,4)) | D11: =IF(Cptes="","",LEFT(Cptes,5)) | E11: =IF(Cptes="","",LEFT(Cptes,6)) | F11: =IF(Cptes="","",LEFT(Cptes,7)) | G11: =IF(Cptes="","",LEFT(Cptes,7)) | H11: =IF(Cptes="","",LEFT(Cptes,7))
A12: =IF(Cptes="","",LEFT(Cptes,2)) | B12: =IF(Cptes="","",LEFT(Cptes,3)) | C12: =IF(Cptes="","",LEFT(Cptes,4)) | D12: =IF(Cptes="","",LEFT(Cptes,5)) | E12: =IF(Cptes="","",LEFT(Cptes,6)) | F12: =IF(Cptes="","",LEFT(Cptes,7)) | G12: =IF(Cptes="","",LEFT(Cptes,7)) | H12: =IF(Cptes="","",LEFT(Cptes,7))
A13: =IF(Cptes="","",LEFT(Cptes,2)) | B13: =IF(Cptes="","",LEFT(Cptes,3)) | C13: =IF(Cptes="","",LEFT(Cptes,4)) | D13: =IF(Cptes="","",LEFT(Cptes,5)) | E13: =IF(Cptes="","",LEFT(Cptes,6)) | F13: =IF(Cptes="","",LEFT(Cptes,7)) | G13: =IF(Cptes="","",LEFT(Cptes,7)) | H13: =IF(Cptes="","",LEFT(Cptes,7))
A14: =IF(Cptes="","",LEFT(Cptes,2)) | B14: =IF(Cptes="","",LEFT(Cptes,3)) | C14: =IF(Cptes="","",LEFT(Cptes,4)) | D14: =IF(Cptes="","",LEFT(Cptes,5)) | E14: =IF(Cptes="","",LEFT(Cptes,6)) | F14: =IF(Cptes="","",LEFT(Cptes,7)) | G14: =IF(Cptes="","",LEFT(Cptes,7)) | H14: =IF(Cptes="","",LEFT(Cptes,7))
... A2201: =IF(Cptes="","",LEFT(Cptes,2)) | B2201: =IF(Cptes="","",LEFT(Cptes,3)) | C2201: =IF(Cptes="","",LEFT(Cptes,4)) | D2201: =IF(Cptes="","",LEFT(Cptes,5)) | E2201: =IF(Cptes="","",LEFT(Cptes,6)) | F2201: =IF(Cptes="","",LEFT(Cptes,7)) | G2201: =IF(Cptes="","",LEFT(Cptes,7)) | H2201: =IF(Cptes="","",LEFT(Cptes,7))

Sheet Balance N-1
I1: CPTE | J1: INTITULES DES COMPTES | K1: MOUV.N-2. DEBIT | L1: MOUV.N-2.CREBIT | M1: MOUV.N-1 DEBIT | N1: MOUV.N-1 CREDIT | O1: S.F. DEBIT N-1 | P1: S.F. CREDIT N-1
K2: =SUM(_sid1) -> 0 | L2: =SUM(_sic1) -> 0 | M2: =SUM(_md1) -> 0 | N2: =SUM(_mc1) -> 0 | O2: =SUM(_sfd1) -> 0 | P2: =SUM(_sfc1) -> 0
A3: =IF(Cptes1="","",LEFT(Cptes1,2)) | B3: =IF(Cptes1="","",LEFT(Cptes1,3)) | C3: =IF(Cptes1="","",LEFT(Cptes1,4)) | D3: =IF(Cptes1="","",LEFT(Cptes1,5)) | E3: =IF(Cptes1="","",LEFT(Cptes1,6)) | F3: =IF(Cptes1="","",LEFT(Cptes1,7)) | G3: =IF(Cptes1="","",LEFT(Cptes1,7)) | H3: =IF(Cptes1="","",LEFT(Cptes1,7))
A4: =IF(Cptes1="","",LEFT(Cptes1,2)) | B4: =IF(Cptes1="","",LEFT(Cptes1,3)) | C4: =IF(Cptes1="","",LEFT(Cptes1,4)) | D4: =IF(Cptes1="","",LEFT(Cptes1,5)) | E4: =IF(Cptes1="","",LEFT(Cptes1,6)) | F4: =IF(Cptes1="","",LEFT(Cptes1,7)) | G4: =IF(Cptes1="","",LEFT(Cptes1,7)) | H4: =IF(Cptes1="","",LEFT(Cptes1,7))
A5: =IF(Cptes1="","",LEFT(Cptes1,2)) | B5: =IF(Cptes1="","",LEFT(Cptes1,3)) | C5: =IF(Cptes1="","",LEFT(Cptes1,4)) | D5: =IF(Cptes1="","",LEFT(Cptes1,5)) | E5: =IF(Cptes1="","",LEFT(Cptes1,6)) | F5: =IF(Cptes1="","",LEFT(Cptes1,7)) | G5: =IF(Cptes1="","",LEFT(Cptes1,7)) | H5: =IF(Cptes1="","",LEFT(Cptes1,7))
A6: =IF(Cptes1="","",LEFT(Cptes1,2)) | B6: =IF(Cptes1="","",LEFT(Cptes1,3)) | C6: =IF(Cptes1="","",LEFT(Cptes1,4)) | D6: =IF(Cptes1="","",LEFT(Cptes1,5)) | E6: =IF(Cptes1="","",LEFT(Cptes1,6)) | F6: =IF(Cptes1="","",LEFT(Cptes1,7)) | G6: =IF(Cptes1="","",LEFT(Cptes1,7)) | H6: =IF(Cptes1="","",LEFT(Cptes1,7))
A7: =IF(Cptes1="","",LEFT(Cptes1,2)) | B7: =IF(Cptes1="","",LEFT(Cptes1,3)) | C7: =IF(Cptes1="","",LEFT(Cptes1,4)) | D7: =IF(Cptes1="","",LEFT(Cptes1,5)) | E7: =IF(Cptes1="","",LEFT(Cptes1,6)) | F7: =IF(Cptes1="","",LEFT(Cptes1,7)) | G7: =IF(Cptes1="","",LEFT(Cptes1,7)) | H7: =IF(Cptes1="","",LEFT(Cptes1,7))
A8: =IF(Cptes1="","",LEFT(Cptes1,2)) | B8: =IF(Cptes1="","",LEFT(Cptes1,3)) | C8: =IF(Cptes1="","",LEFT(Cptes1,4)) | D8: =IF(Cptes1="","",LEFT(Cptes1,5)) | E8: =IF(Cptes1="","",LEFT(Cptes1,6)) | F8: =IF(Cptes1="","",LEFT(Cptes1,7)) | G8: =IF(Cptes1="","",LEFT(Cptes1,7)) | H8: =IF(Cptes1="","",LEFT(Cptes1,7))
A9: =IF(Cptes1="","",LEFT(Cptes1,2)) | B9: =IF(Cptes1="","",LEFT(Cptes1,3)) | C9: =IF(Cptes1="","",LEFT(Cptes1,4)) | D9: =IF(Cptes1="","",LEFT(Cptes1,5)) | E9: =IF(Cptes1="","",LEFT(Cptes1,6)) | F9: =IF(Cptes1="","",LEFT(Cptes1,7)) | G9: =IF(Cptes1="","",LEFT(Cptes1,7)) | H9: =IF(Cptes1="","",LEFT(Cptes1,7))
A10: =IF(Cptes1="","",LEFT(Cptes1,2)) | B10: =IF(Cptes1="","",LEFT(Cptes1,3)) | C10: =IF(Cptes1="","",LEFT(Cptes1,4)) | D10: =IF(Cptes1="","",LEFT(Cptes1,5)) | E10: =IF(Cptes1="","",LEFT(Cptes1,6)) | F10: =IF(Cptes1="","",LEFT(Cptes1,7)) | G10: =IF(Cptes1="","",LEFT(Cptes1,7)) | H10: =IF(Cptes1="","",LEFT(Cptes1,7))
A11: =IF(Cptes1="","",LEFT(Cptes1,2)) | B11: =IF(Cptes1="","",LEFT(Cptes1,3)) | C11: =IF(Cptes1="","",LEFT(Cptes1,4)) | D11: =IF(Cptes1="","",LEFT(Cptes1,5)) | E11: =IF(Cptes1="","",LEFT(Cptes1,6)) | F11: =IF(Cptes1="","",LEFT(Cptes1,7)) | G11: =IF(Cptes1="","",LEFT(Cptes1,7)) | H11: =IF(Cptes1="","",LEFT(Cptes1,7))
A12: =IF(Cptes1="","",LEFT(Cptes1,2)) | B12: =IF(Cptes1="","",LEFT(Cptes1,3)) | C12: =IF(Cptes1="","",LEFT(Cptes1,4)) | D12: =IF(Cptes1="","",LEFT(Cptes1,5)) | E12: =IF(Cptes1="","",LEFT(Cptes1,6)) | F12: =IF(Cptes1="","",LEFT(Cptes1,7)) | G12: =IF(Cptes1="","",LEFT(Cptes1,7)) | H12: =IF(Cptes1="","",LEFT(Cptes1,7))
A13: =IF(Cptes1="","",LEFT(Cptes1,2)) | B13: =IF(Cptes1="","",LEFT(Cptes1,3)) | C13: =IF(Cptes1="","",LEFT(Cptes1,4)) | D13: =IF(Cptes1="","",LEFT(Cptes1,5)) | E13: =IF(Cptes1="","",LEFT(Cptes1,6)) | F13: =IF(Cptes1="","",LEFT(Cptes1,7)) | G13: =IF(Cptes1="","",LEFT(Cptes1,7)) | H13: =IF(Cptes1="","",LEFT(Cptes1,7))
A14: =IF(Cptes1="","",LEFT(Cptes1,2)) | B14: =IF(Cptes1="","",LEFT(Cptes1,3)) | C14: =IF(Cptes1="","",LEFT(Cptes1,4)) | D14: =IF(Cptes1="","",LEFT(Cptes1,5)) | E14: =IF(Cptes1="","",LEFT(Cptes1,6)) | F14: =IF(Cptes1="","",LEFT(Cptes1,7)) | G14: =IF(Cptes1="","",LEFT(Cptes1,7)) | H14: =IF(Cptes1="","",LEFT(Cptes1,7))
... A2201: =IF(Cptes1="","",LEFT(Cptes1,2)) | B2201: =IF(Cptes1="","",LEFT(Cptes1,3)) | C2201: =IF(Cptes1="","",LEFT(Cptes1,4)) | D2201: =IF(Cptes1="","",LEFT(Cptes1,5)) | E2201: =IF(Cptes1="","",LEFT(Cptes1,6)) | F2201: =IF(Cptes1="","",LEFT(Cptes1,7)) | G2201: =IF(Cptes1="","",LEFT(Cptes1,7)) | H2201: =IF(Cptes1="","",LEFT(Cptes1,7))

Sheet CONTROLE BALANCE
A1: EQUILIBRE DE LA BALANCE
A2: BALANCE N | B2: Solde Initial Débit | C2: Solde Initial Crédit | D2: Mouvements Débit | E2: Mouvements Crédit | F2: Solde Final Débit | G2: Solde Final Crédit
B3: =SUM(sid) -> 0 | C3: =SUM(sic) -> 0 | D3: =SUM(md) -> 0 | E3: =SUM(mc) -> 0 | F3: =SUM(sfd) -> 0 | G3: =SUM(sfc) -> 0
B4: =IF((B3-C3)>0,"Déséquilibre : Débit > de "&TEXT((B3-C3),"# ##0"),IF((B3-C3)<0,"Déséquilibre : Crédit > de "&-TEXT((B3-C3),"# ##0"),IF((B3-C3)=0,"Equilibre",0))) -> Equilibre | D4: =IF((D3-E3)>0,"Déséquilibre : Débit > de "&TEXT((D3-E3),"# ##0"),IF((D3-E3)<0,"Déséquilibre : Crédit > de "&-TEXT((D3-E3),"# ##0"),IF((D3-E3)=0,"Equilibre",0))) -> Equilibre | F4: =IF((F3-G3)>0,"Equilibre : Débit > de "&TEXT((F3-G3),"# ##0"),IF((F3-G3)<0,"Déséquilibre : Crédit > de "&-TEXT((F3-G3),"# ##0"),IF((F3-G3)=0,"Equilibre",0))) -> Equilibre
A5: BALANCE N-1 | B5: Solde Initial Débit | C5: Solde Initial Crédit | D5: Mouvements Débit | E5: Mouvements Crédit | F5: Solde Final Débit | G5: Solde Final Crédit
B6: =SUM(_sid1) -> 0 | C6: =SUM(_sic1) -> 0 | D6: =SUM(_md1) -> 0 | E6: =SUM(_mc1) -> 0 | F6: =SUM(_sfd1) -> 0 | G6: =SUM(_sfc1) -> 0
B7: =IF((B6-C6)>0,"Déséquilibre : Débit > de "&TEXT((B6-C6),"# ##0"),IF((B6-C6)<0,"Déséquilibre : Crédit > de "&-TEXT((B6-C6),"# ##0"),IF((B6-C6)=0,"Equilibre",0))) -> Equilibre | D7: =IF((D6-E6)>0,"Déséquilibre : Débit > de "&TEXT((D6-E6),"# ##0"),IF((D6-E6)<0,"Déséquilibre : Crédit > de "&-TEXT((D6-E6),"# ##0"),IF((D6-E6)=0,"Equilibre",0))) -> Equilibre | F7: =IF((F6-G6)>0,"Equilibre : Débit > de "&TEXT((F6-G6),"# ##0"),IF((F6-G6)<0,"Déséquilibre : Crédit > de "&-TEXT((F6-G6),"# ##0"),IF((F6-G6)=0,"Equilibre",0))) -> Equilibre

Sheet EQUILIBRE BALANCE N
A1: CPTE | B1: INTITULES DES COMPTES | C1: S.I. DEBIT | D1: S.I. CREDIT | E1: MOUV. DEBIT | F1: MOUV. CREDIT | G1: S.F. DEBIT | H1: S.F. CREDIT | I1: MONTANT DESEQUILIBRE
A2: ='Balance N'!I5 -> 0 | B2: ='Balance N'!J5 -> 0 | C2: ='Balance N'!K5 -> 0 | D2: ='Balance N'!L5 -> 0 | E2: ='Balance N'!M5 -> 0 | F2: ='Balance N'!N5 -> 0 | G2: ='Balance N'!O5 -> 0 | H2: ='Balance N'!P5 -> 0 | I2: =(C2-D2)+(E2-F2)-(G2-H2) -> 0
A3: ='Balance N'!I6 -> 0 | B3: ='Balance N'!J6 -> 0 | C3: ='Balance N'!K6 -> 0 | D3: ='Balance N'!L6 -> 0 | E3: ='Balance N'!M6 -> 0 | F3: ='Balance N'!N6 -> 0 | G3: ='Balance N'!O6 -> 0 | H3: ='Balance N'!P6 -> 0 | I3: =(C3-D3)+(E3-F3)-(G3-H3) -> 0
A4: ='Balance N'!I7 -> 0 | B4: ='Balance N'!J7 -> 0 | C4: ='Balance N'!K7 -> 0 | D4: ='Balance N'!L7 -> 0 | E4: ='Balance N'!M7 -> 0 | F4: ='Balance N'!N7 -> 0 | G4: ='Balance N'!O7 -> 0 | H4: ='Balance N'!P7 -> 0 | I4: =(C4-D4)+(E4-F4)-(G4-H4) -> 0
A5: ='Balance N'!I8 -> 0 | B5: ='Balance N'!J8 -> 0 | C5: ='Balance N'!K8 -> 0 | D5: ='Balance N'!L8 -> 0 | E5: ='Balance N'!M8 -> 0 | F5: ='Balance N'!N8 -> 0 | G5: ='Balance N'!O8 -> 0 | H5: ='Balance N'!P8 -> 0 | I5: =(C5-D5)+(E5-F5)-(G5-H5) -> 0
A6: ='Balance N'!I9 -> 0 | B6: ='Balance N'!J9 -> 0 | C6: ='Balance N'!K9 -> 0 | D6: ='Balance N'!L9 -> 0 | E6: ='Balance N'!M9 -> 0 | F6: ='Balance N'!N9 -> 0 | G6: ='Balance N'!O9 -> 0 | H6: ='Balance N'!P9 -> 0 | I6: =(C6-D6)+(E6-F6)-(G6-H6) -> 0
A7: ='Balance N'!I10 -> 0 | B7: ='Balance N'!J10 -> 0 | C7: ='Balance N'!K10 -> 0 | D7: ='Balance N'!L10 -> 0 | E7: ='Balance N'!M10 -> 0 | F7: ='Balance N'!N10 -> 0 | G7: ='Balance N'!O10 -> 0 | H7: ='Balance N'!P10 -> 0 | I7: =(C7-D7)+(E7-F7)-(G7-H7) -> 0
A8: ='Balance N'!I11 -> 0 | B8: ='Balance N'!J11 -> 0 | C8: ='Balance N'!K11 -> 0 | D8: ='Balance N'!L11 -> 0 | E8: ='Balance N'!M11 -> 0 | F8: ='Balance N'!N11 -> 0 | G8: ='Balance N'!O11 -> 0 | H8: ='Balance N'!P11 -> 0 | I8: =(C8-D8)+(E8-F8)-(G8-H8) -> 0
A9: ='Balance N'!I12 -> 0 | B9: ='Balance N'!J12 -> 0 | C9: ='Balance N'!K12 -> 0 | D9: ='Balance N'!L12 -> 0 | E9: ='Balance N'!M12 -> 0 | F9: ='Balance N'!N12 -> 0 | G9: ='Balance N'!O12 -> 0 | H9: ='Balance N'!P12 -> 0 | I9: =(C9-D9)+(E9-F9)-(G9-H9) -> 0
A10: ='Balance N'!I13 -> 0 | B10: ='Balance N'!J13 -> 0 | C10: ='Balance N'!K13 -> 0 | D10: ='Balance N'!L13 -> 0 | E10: ='Balance N'!M13 -> 0 | F10: ='Balance N'!N13 -> 0 | G10: ='Balance N'!O13 -> 0 | H10: ='Balance N'!P13 -> 0 | I10: =(C10-D10)+(E10-F10)-(G10-H10) -> 0
A11: ='Balance N'!I14 -> 0 | B11: ='Balance N'!J14 -> 0 | C11: ='Balance N'!K14 -> 0 | D11: ='Balance N'!L14 -> 0 | E11: ='Balance N'!M14 -> 0 | F11: ='Balance N'!N14 -> 0 | G11: ='Balance N'!O14 -> 0 | H11: ='Balance N'!P14 -> 0 | I11: =(C11-D11)+(E11-F11)-(G11-H11) -> 0
A12: ='Balance N'!I15 -> 0 | B12: ='Balance N'!J15 -> 0 | C12: ='Balance N'!K15 -> 0 | D12: ='Balance N'!L15 -> 0 | E12: ='Balance N'!M15 -> 0 | F12: ='Balance N'!N15 -> 0 | G12: ='Balance N'!O15 -> 0 | H12: ='Balance N'!P15 -> 0 | I12: =(C12-D12)+(E12-F12)-(G12-H12) -> 0
A13: ='Balance N'!I16 -> 0 | B13: ='Balance N'!J16 -> 0 | C13: ='Balance N'!K16 -> 0 | D13: ='Balance N'!L16 -> 0 | E13: ='Balance N'!M16 -> 0 | F13: ='Balance N'!N16 -> 0 | G13: ='Balance N'!O16 -> 0 | H13: ='Balance N'!P16 -> 0 | I13: =(C13-D13)+(E13-F13)-(G13-H13) -> 0
... A7689: ='Balance N'!I7692 -> 0 | B7689: ='Balance N'!J7692 -> 0 | C7689: ='Balance N'!K7692 -> 0 | D7689: ='Balance N'!L7692 -> 0 | E7689: ='Balance N'!M7692 -> 0 | F7689: ='Balance N'!N7692 -> 0 | G7689: ='Balance N'!O7692 -> 0 | H7689: ='Balance N'!P7692 -> 0 | I7689: =(C7689-D7689)+(E7689-F7689)-(G7689-H7689) -> 0

Sheet EQUILIBRE BALANCE N-1
A1: CPTE | B1: INTITULES DES COMPTES | C1: S.I. DEBIT | D1: S.I. CREDIT | E1: MOUV. DEBIT | F1: MOUV. CREDIT | G1: S.F. DEBIT | H1: S.F. CREDIT | I1: MONTANT DESEQUILIBRE
A2: ='Balance N-1'!I5 -> 0 | B2: ='Balance N-1'!J5 -> 0 | C2: ='Balance N-1'!K5 -> 0 | D2: ='Balance N-1'!L5 -> 0 | E2: ='Balance N-1'!M5 -> 0 | F2: ='Balance N-1'!N5 -> 0 | G2: ='Balance N-1'!O5 -> 0 | H2: ='Balance N-1'!P5 -> 0 | I2: =(C2-D2)+(E2-F2)-(G2-H2) -> 0
A3: ='Balance N-1'!I6 -> 0 | B3: ='Balance N-1'!J6 -> 0 | C3: ='Balance N-1'!K6 -> 0 | D3: ='Balance N-1'!L6 -> 0 | E3: ='Balance N-1'!M6 -> 0 | F3: ='Balance N-1'!N6 -> 0 | G3: ='Balance N-1'!O6 -> 0 | H3: ='Balance N-1'!P6 -> 0 | I3: =(C3-D3)+(E3-F3)-(G3-H3) -> 0
A4: ='Balance N-1'!I7 -> 0 | B4: ='Balance N-1'!J7 -> 0 | C4: ='Balance N-1'!K7 -> 0 | D4: ='Balance N-1'!L7 -> 0 | E4: ='Balance N-1'!M7 -> 0 | F4: ='Balance N-1'!N7 -> 0 | G4: ='Balance N-1'!O7 -> 0 | H4: ='Balance N-1'!P7 -> 0 | I4: =(C4-D4)+(E4-F4)-(G4-H4) -> 0
A5: ='Balance N-1'!I8 -> 0 | B5: ='Balance N-1'!J8 -> 0 | C5: ='Balance N-1'!K8 -> 0 | D5: ='Balance N-1'!L8 -> 0 | E5: ='Balance N-1'!M8 -> 0 | F5: ='Balance N-1'!N8 -> 0 | G5: ='Balance N-1'!O8 -> 0 | H5: ='Balance N-1'!P8 -> 0 | I5: =(C5-D5)+(E5-F5)-(G5-H5) -> 0
A6: ='Balance N-1'!I9 -> 0 | B6: ='Balance N-1'!J9 -> 0 | C6: ='Balance N-1'!K9 -> 0 | D6: ='Balance N-1'!L9 -> 0 | E6: ='Balance N-1'!M9 -> 0 | F6: ='Balance N-1'!N9 -> 0 | G6: ='Balance N-1'!O9 -> 0 | H6: ='Balance N-1'!P9 -> 0 | I6: =(C6-D6)+(E6-F6)-(G6-H6) -> 0
A7: ='Balance N-1'!I10 -> 0 | B7: ='Balance N-1'!J10 -> 0 | C7: ='Balance N-1'!K10 -> 0 | D7: ='Balance N-1'!L10 -> 0 | E7: ='Balance N-1'!M10 -> 0 | F7: ='Balance N-1'!N10 -> 0 | G7: ='Balance N-1'!O10 -> 0 | H7: ='Balance N-1'!P10 -> 0 | I7: =(C7-D7)+(E7-F7)-(G7-H7) -> 0
A8: ='Balance N-1'!I11 -> 0 | B8: ='Balance N-1'!J11 -> 0 | C8: ='Balance N-1'!K11 -> 0 | D8: ='Balance N-1'!L11 -> 0 | E8: ='Balance N-1'!M11 -> 0 | F8: ='Balance N-1'!N11 -> 0 | G8: ='Balance N-1'!O11 -> 0 | H8: ='Balance N-1'!P11 -> 0 | I8: =(C8-D8)+(E8-F8)-(G8-H8) -> 0
A9: ='Balance N-1'!I12 -> 0 | B9: ='Balance N-1'!J12 -> 0 | C9: ='Balance N-1'!K12 -> 0 | D9: ='Balance N-1'!L12 -> 0 | E9: ='Balance N-1'!M12 -> 0 | F9: ='Balance N-1'!N12 -> 0 | G9: ='Balance N-1'!O12 -> 0 | H9: ='Balance N-1'!P12 -> 0 | I9: =(C9-D9)+(E9-F9)-(G9-H9) -> 0
A10: ='Balance N-1'!I13 -> 0 | B10: ='Balance N-1'!J13 -> 0 | C10: ='Balance N-1'!K13 -> 0 | D10: ='Balance N-1'!L13 -> 0 | E10: ='Balance N-1'!M13 -> 0 | F10: ='Balance N-1'!N13 -> 0 | G10: ='Balance N-1'!O13 -> 0 | H10: ='Balance N-1'!P13 -> 0 | I10: =(C10-D10)+(E10-F10)-(G10-H10) -> 0
A11: ='Balance N-1'!I14 -> 0 | B11: ='Balance N-1'!J14 -> 0 | C11: ='Balance N-1'!K14 -> 0 | D11: ='Balance N-1'!L14 -> 0 | E11: ='Balance N-1'!M14 -> 0 | F11: ='Balance N-1'!N14 -> 0 | G11: ='Balance N-1'!O14 -> 0 | H11: ='Balance N-1'!P14 -> 0 | I11: =(C11-D11)+(E11-F11)-(G11-H11) -> 0
A12: ='Balance N-1'!I15 -> 0 | B12: ='Balance N-1'!J15 -> 0 | C12: ='Balance N-1'!K15 -> 0 | D12: ='Balance N-1'!L15 -> 0 | E12: ='Balance N-1'!M15 -> 0 | F12: ='Balance N-1'!N15 -> 0 | G12: ='Balance N-1'!O15 -> 0 | H12: ='Balance N-1'!P15 -> 0 | I12: =(C12-D12)+(E12-F12)-(G12-H12) -> 0
A13: ='Balance N-1'!I16 -> 0 | B13: ='Balance N-1'!J16 -> 0 | C13: ='Balance N-1'!K16 -> 0 | D13: ='Balance N-1'!L16 -> 0 | E13: ='Balance N-1'!M16 -> 0 | F13: ='Balance N-1'!N16 -> 0 | G13: ='Balance N-1'!O16 -> 0 | H13: ='Balance N-1'!P16 -> 0 | I13: =(C13-D13)+(E13-F13)-(G13-H13) -> 0
... A7689: ='Balance N-1'!I7692 -> 0 | B7689: ='Balance N-1'!J7692 -> 0 | C7689: ='Balance N-1'!K7692 -> 0 | D7689: ='Balance N-1'!L7692 -> 0 | E7689: ='Balance N-1'!M7692 -> 0 | F7689: ='Balance N-1'!N7692 -> 0 | G7689: ='Balance N-1'!O7692 -> 0 | H7689: ='Balance N-1'!P7692 -> 0 | I7689: =(C7689-D7689)+(E7689-F7689)-(G7689-H7689) -> 0

Sheet COUVERTURE
F4: REPUBLIQUE DE……..
C6: MINISTERE DE L'ECONOMIE DES FINANCES ET DU DEVELOPPEMENT
F8: DIRECTION GENERALE DES IMPOTS
E31: LIASSE SYSTEME NORMAL

Sheet GARDE
B2: BURKINA FASO
B3: MINISTERE DE L'ECONOMIE DES FINANCES ET DU DEVELOPPEMENT
B4: DIRECTION GENERALE DES IMPOTS
C8: CENTRE DE DEPOT DE
D9: =+'INFORMATIONS GENERALES'!E11 -> 0
B12: ETATS FINANCIERS NORMALISES DU SYSTEME COMPTABLE DES ENTITES A BUT NON LUCRATIF (SYCEBNL)
B15: Projets de développement et assimilés
E17: EXERCICE CLOS LE
E18: =+'INFORMATIONS GENERALES'!J13 -> 45657
D21: DESIGNATION DE L'ENTITE
B23: DENOMINATION SOCIALE : | D23: =+'INFORMATIONS GENERALES'!E21 -> DSO Services
B24: (ou nom et prénoms de l'exploitant)
B27: SIGLE USUEL : | C27: =+'INFORMATIONS GENERALES'!L21 -> DSO Services
B29: ADRESSE COMPLETE : | C29: =+'INFORMATIONS GENERALES'!E28 -> Rue Alphamoi Djénèpo, secteur 01, Bobo-Dioulasso, Burkina Faso
B31: N° IFU DU CONTRIBUABLE : | D31: =+'INFORMATIONS GENERALES'!P53 -> 00000101A
B32: N° DE TELEDECLARANT (NES): | D32: =+'INFORMATIONS GENERALES'!P56 -> Néant
B33: SYSTEME NORMAL
B34: Documents déposés | H34: Réservé à la Direction Générale des Impôts
B36: Fiche d'identification et renseignements divers | H36: Date de dépôt
B37: Bilan
B38: Compte de résultat
B39: Tableau des flux de trésorerie
B40: Notes annexes | H40: Nom de l'agent de la DGI ayant réceptionné le dépôt
B41: Etats supplémentaires DGI
B45: Nombre de pages déposées par exemplaire : | H45: Signature de l'agent et cachet du service
B46: Nombre d'exemplaires déposés :

Sheet FICHE R1
A1: - 1 -
R2: FICHE R1
A3: Dénomination sociale de l'entité : | E3: =+'INFORMATIONS GENERALES'!E21 -> DSO Services
A4: Adresse : | D4: =+'INFORMATIONS GENERALES'!E28 -> Rue Alphamoi Djénèpo, secteur 01, Bobo-Dioulasso, Burkina Faso | P4: Sigle usuel : | S4: =+'INFORMATIONS GENERALES'!L21 -> DSO Services
A5: N° IFU du contribuable : | E5: =+'INFORMATIONS GENERALES'!P53 -> 00000101A | H5: Exercice clos le : | J5: =+'INFORMATIONS GENERALES'!J13 -> 45657 | Q5: Durée (en mois) : | U5: =+'INFORMATIONS GENERALES'!W13 -> 12
A6: N° de télédéclarant (NES) : | E6: =+'INFORMATIONS GENERALES'!P56 -> Néant
A7: FICHE R1 : FICHE D'IDENTIFICATION ET RENSEIGNEMENTS DIVERS 1
A8: ZA | C8: EXERCICE COMPTABLE : | M8: DU: | N8: =+'INFORMATIONS GENERALES'!P9 -> 45292 | R8: AU: | S8: =+'INFORMATIONS GENERALES'!U9 -> 45657
A10: ZB | C10: DATE D'ARRETE EFFECTIF DES COMPTES : | H10: =+'INFORMATIONS GENERALES'!J11 -> 45747 | T10: ZD
A12: ZC | C12: EXERCICE PRECEDENT CLOS LE : | H12: =+'INFORMATIONS GENERALES'!J13 -> 45657 | K12: DUREE EXERCICE PRECEDENT EN MOIS : | U12: =+'INFORMATIONS GENERALES'!W13 -> 12
A14: ZE | C14: =+'INFORMATIONS GENERALES'!E15 -> 10 | D14: =+'INFORMATIONS GENERALES'!F15 -> 0 | J14: ZF | K14: ='INFORMATIONS GENERALES'!M15 -> 0
C15: Greffe | D15: N°Registre du Commerce | K15: N° Répertoire des entités
A17: ZG | C17: =+'INFORMATIONS GENERALES'!E18 -> 0 | E17: ZH | F17: =+'INFORMATIONS GENERALES'!H18 -> 0 | P17: ZI | Q17: =+'INFORMATIONS GENERALES'!S18 -> A0101
C18: N° de caisse sociale | F18: N° Code Importateur | Q18: Code activité principale
A20: ZJ | C20: =+'INFORMATIONS GENERALES'!E21 -> DSO Services | Q20: =+'INFORMATIONS GENERALES'!L21 -> DSO Services
C21: Désignation de l'entité | Q21: Sigle
A23: ZK | C23: ='INFORMATIONS GENERALES'!E24 -> 76191918 | E23: =+'INFORMATIONS GENERALES'!G24 -> scheckoumard@gmail.com | K23: =+'INFORMATIONS GENERALES'!K24 -> 01 | N23: =+'INFORMATIONS GENERALES'!L24 -> 13 | Q23: =+'INFORMATIONS GENERALES'!N24 -> Bobo-Dioulasso
C24: N° de téléphone | E24: Adresse e-mail | K24: Code | N24: Boîte Postale | Q24: Ville
A26: ZL | C26: =+'INFORMATIONS GENERALES'!E28 -> Rue Alphamoi Djénèpo, secteur 01, Bobo-Dioulasso, Burkina Faso
C27: Adresse géographique complète (Immeuble, rue, quartier, ville, pays)
P28: ZN
A29: ZM | C29: =+'INFORMATIONS GENERALES'!E31 -> 0 | P29: =+'INFORMATIONS GENERALES'!R31 -> 1
C30: Désignation précise de l'activité principale exercée par l'entité | P30: % Capacité production utile
A32: ZO
C33: Nom, adresse, téléphone, adresse e-mail et qualité de la personne à contacter en cas de demande
A35: ZP
C36: Nom, adresse, téléphone et e-mail du salarié de l'entité ou
C37: du professionnel comptable inscrit à l'Ordre des Experts-comptables ayant établi les états financiers
A39: ZQ
A43: ZR
C44: Nom, adresse, téléphone, e-mail et numéro d'inscription à l'Ordre des Experts-comptables
C45: de l'Expert comptablble ayant délivré l'attestation d'exécution de la mission du commissariat aux comptes
A47: ZS | O47: Non | T47: Oui
N48: Etats financiers approuvés par l'Assemblée Générale (cocher la case)
J49: ZW
A50: ZT | J50: Domiciliations bancaires
C51: Nom du signataire des états financiers | J51: Banque | Q51: Numéro de compte
A53: ZU
C54: Qualité du signataire des états financiers
A56: ZV
C57: Date de signature
C63: Signature

Sheet FICHE R2
A1: - 2 -
AG2: FICHE R2
A3: Dénomination sociale de l'entité : | I3: =+GARDE!D23 -> DSO Services
A4: Adresse : | E4: =+GARDE!C29 -> Rue Alphamoi Djénèpo, secteur 01, Bobo-Dioulasso, Burkina Faso | AC4: Sigle usuel : | AI4: =+GARDE!C27 -> DSO Services
A5: N° IFU du contribuable : | I5: =+GARDE!D31 -> 00000101A | Q5: Exercice clos le : | W5: =+GARDE!E18 -> 45657 | AC5: Durée (en mois) : | AI5: =+'FICHE R1'!U5 -> 12
A6: N° de télédéclarant (NES) : | I6: =+GARDE!D32 -> Néant
A7: FICHE D'IDENTIFICATION ET RENSEIGNEMENTS DIVERS
A8: EQUIPE DE L'ENTITE A BUT NON LUCRATIF
A9: Nom et Prénoms | I9: Nationalité | P9: Autre nationalité (à préciser) | V9: Qualité | AB9: N° d'identification fiscale | AG9: Adresse (BP, ville, pays, adresse géographique et adresse email)

Sheet TER
A1: - 5 -
G2: TABLEAU EMPLOIS - RESSOURCES PAGE 1/1
A3: Dénomination sociale : | C3: =+'FICHE R2'!I3 -> DSO Services
A4: Adresse : | C4: =+'FICHE R2'!E4 -> Rue Alphamoi Djénèpo, secteur 01, Bobo-Dioulasso, Burkina Faso | G4: Sigle usuel : | H4: =+'FICHE R2'!AI4 -> DSO Services
A5: N° IFU du contribuable : | C5: =+'FICHE R2'!I5 -> 00000101A | E5: Exercice clos le : | F5: =+'FICHE R2'!W5 -> 45657 | G5: Durée (en mois) : | H5: =+'FICHE R2'!AI5 -> 12
A6: N° de télédéclarant (NES) : | C6: =+'FICHE R2'!I6 -> Néant
A7: TABLEAU EMPLOIS RESSOURCES
A8: =CONCATENATE("TABLEAU EMPLOIS - RESSOURCES AU 31/12/"&" "&TEXT('INFORMATIONS GENERALES'!J13,"aaaa")) -> TABLEAU EMPLOIS - RESSOURCES AU 31/12/ 2024
A9: REF | B9: DESIGNATION | F9: SOLDE CUMULE DEBUT EXERCICE N | G9: EXERCICE N | H9: SOLDE CUMULE FIN EXERCICE N
A10: FA | B10: Fonds reçus, Bailleurs | F10: =SUMIF('Balance N'!B:B,161,'Balance N'!L:L)+SUMIF('Balance N'!B:B,162,'Balance N'!L:L)+SUMIF('Balance N'!B:B,462,'Balance N'!L:L) -> 0 | G10: =SUMIF('Balance N'!B:B,161,'Balance N'!N:N)+SUMIF('Balance N'!B:B,162,'Balance N'!N:N)+SUMIF('Balance N'!B:B,462,'Balance N'!N:N) -> 0 | H10: =+F10+G10 -> 0
A11: FB | B11: Fonds reçus, Bailleurs | F11: 0 | G11: 0 | H11: =+F11+G11 -> 0
A12: FC | B12: Fonds contrepartie État | F12: =SUMIF('Balance N'!B:B,163,'Balance N'!L:L)+SUMIF('Balance N'!B:B,463,'Balance N'!L:L) -> 0 | G12: =SUMIF('Balance N'!B:B,163,'Balance N'!N:N)+SUMIF('Balance N'!B:B,463,'Balance N'!N:N) -> 0 | H12: =+F12+G12 -> 0
A13: FD | B13: Autres fonds reçus | F13: =SUMIF('Balance N'!B:B,164,'Balance N'!L:L)+SUMIF('Balance N'!B:B,464,'Balance N'!L:L)+SUMIF('Balance N'!B:B,707,'Balance N'!L:L)+SUMIF('Balance N'!A:A,77,'Balance N'!L:L) -> 0 | G13: =SUMIF('Balance N'!B:B,164,'Balance N'!N:N)+SUMIF('Balance N'!B:B,464,'Balance N'!N:N)+SUMIF('Balance N'!B:B,707,'Balance N'!N:N)+SUMIF('Balance N'!A:A,77,'Balance N'!N:N) -> 0 | H13: =+F13+G13 -> 0
A14: GR | B14: I.RESSOURCES | F14: =SUM(F10:F13) -> 0 | G14: =SUM(G10:G13) -> 0 | H14: =SUM(H10:H13) -> 0
A15: FE | B15: Immobilisations incorporelle | F15: =SUMIF('Balance N'!A:A,21,'Balance N'!K:K) -> 0 | G15: =SUMIF('Balance N'!A:A,21,'Balance N'!M:M)-(SUMIF('Balance N-1'!C:C,4811,'Balance N-1'!P:P)-SUMIF('Balance N'!C:C,4811,'Balance N'!P:P))-SUMIF('Balance N'!C:C,4813,'Balance N'!P:P) -> 0 | H15: =+F15+G15 -> 0
A16: FF | B16: Terrains | F16: =SUMIF('Balance N'!A:A,22,'Balance N'!K:K) -> 0 | G16: =SUMIF('Balance N'!A:A,22,'Balance N'!M:M)-(SUMIF('Balance N-1'!C:C,4812,'Balance N-1'!P:P)-SUMIF('Balance N'!C:C,4812,'Balance N'!P:P))-SUMIF('Balance N'!C:C,4813,'Balance N'!P:P) -> 0 | H16: =+F16+G16 -> 0
A17: FG | B17: Bâtiments | F17: =SUMIF('Balance N-1'!B:B,231,'Balance N-1'!K:K)+SUMIF('Balance N'!B:B,232,'Balance N'!K:K)+SUMIF('Balance N'!B:B,233,'Balance N'!K:K)+SUMIF('Balance N'!C:C,2391,'Balance N'!K:K)+SUMIF('Balance N'!C:C,2392,'Balance N'!K:K)+SUMIF('Balance N'!C:C,2393,'Balance N'!K:K)+SUMIF('Balance N'!C:C,2396,'Balance N'!K:K) -> 0 | G17: =SUMIF('Balance N'!B:B,231,'Balance N'!M:M)+SUMIF('Balance N'!B:B,232,'Balance N'!M:M)+SUMIF('Balance N'!B:B,233,'Balance N'!M:M)+SUMIF('Balance N'!C:C,2391,'Balance N'!M:M)+SUMIF('Balance N'!C:C,2392,'Balance N'!M:M)+SUMIF('Balance N'!C:C,2393,'Balance N'!M:M)+SUMIF('Balance N'!C:C,2396,'Balance N'!M:M)-(SUMIF('Balance N-1'!C:C,4812,'Balance N-1'!P:P)-SUMIF('Balance N'!C:C,4812,'Balance N'!P:P))-SUMIF('Balance N'!C:C,4813,'Balance N'!P:P) -> 0 | H17: =+F17+G17 -> 0
A18: FH | B18: Aménagements, agencements et installations | F18: =SUMIF('Balance N-1'!B:B,234,'Balance N-1'!K:K)+SUMIF('Balance N'!B:B,235,'Balance N'!K:K)+SUMIF('Balance N'!B:B,238,'Balance N'!K:K)+SUMIF('Balance N'!C:C,2394,'Balance N'!K:K)+SUMIF('Balance N'!C:C,2395,'Balance N'!K:K)+SUMIF('Balance N'!C:C,2398,'Balance N'!K:K) -> 0 | G18: =SUMIF('Balance N'!B:B,234,'Balance N'!M:M)+SUMIF('Balance N'!B:B,235,'Balance N'!M:M)+SUMIF('Balance N'!B:B,238,'Balance N'!M:M)+SUMIF('Balance N'!C:C,2394,'Balance N'!M:M)+SUMIF('Balance N'!C:C,2395,'Balance N'!M:M)+SUMIF('Balance N'!C:C,2398,'Balance N'!M:M)-(SUMIF('Balance N-1'!C:C,4812,'Balance N-1'!P:P)-SUMIF('Balance N'!C:C,4812,'Balance N'!P:P))-SUMIF('Balance N'!C:C,4813,'Balance N'!P:P) -> 0 | H18: =+F18+G18 -> 0
A19: FI | B19: Matériel, mobilier et actifs biologiques | F19: =SUMIF('Balance N'!A:A,24,'Balance N'!K:K) -> 0 | G19: =SUMIF('Balance N'!A:A,24,'Balance N'!M:M)-(SUMIF('Balance N-1'!C:C,4812,'Balance N-1'!P:P)-SUMIF('Balance N'!C:C,4812,'Balance N'!P:P))-SUMIF('Balance N'!C:C,4813,'Balance N'!P:P)-SUMIF('Balance N'!B:B,245,'Balance N'!M:M)-SUMIF('Balance N'!C:C,2495,'Balance N'!M:M) -> 0 | H19: =+F19+G19 -> 0
A20: FJ | B20: Matériel de transport | F20: =SUMIF('Balance N'!B:B,245,'Balance N'!K:K)+SUMIF('Balance N'!C:C,2495,'Balance N'!K:K) -> 0 | G20: =SUMIF('Balance N'!B:B,245,'Balance N'!M:M)+SUMIF('Balance N'!C:C,2495,'Balance N'!M:M)-(SUMIF('Balance N-1'!C:C,4812,'Balance N-1'!P:P)-SUMIF('Balance N'!C:C,4812,'Balance N'!P:P)) -> 0 | H20: =+F20+G20 -> 0
A21: FK | B21: Avances et acomptes sur immobilisations | F21: =SUMIF('Balance N'!A:A,25,'Balance N'!K:K) -> 0 | G21: =SUMIF('Balance N'!A:A,25,'Balance N'!M:M) -> 0 | H21: =+F21+G21 -> 0
A22: FL | B22: Immobilisation financières | F22: =SUMIF('Balance N'!A:A,26,'Balance N'!K:K)+SUMIF('Balance N'!A:A,27,'Balance N'!K:K) -> 0 | G22: =SUMIF('Balance N'!A:A,26,'Balance N'!M:M)+SUMIF('Balance N'!A:A,27,'Balance N'!M:M)-(SUMIF('Balance N-1'!C:C,4813,'Balance N-1'!O:O)-SUMIF('Balance N'!C:C,4813,'Balance N-1'!O:O))-SUMIF('Balance N-1'!B:B,276,'Balance N-1'!M:M) -> 0 | H22: =+F22+G22 -> 0
A23: GS | B23: A-TOTAL DES IMMOBILISATION | F23: =SUM(F15:F22) -> 0 | G23: =SUM(G15:G22) -> 0 | H23: =SUM(H15:H22) -> 0
A24: FM | B24: Achats de biens et services | F24: =SUMIF('Balance N'!A:A,60,'Balance N'!K:K) -> 0 | G24: =SUMIF('Balance N'!A:A,60,'Balance N'!M:M)-(SUMIF('Balance N-1'!B:B,4011,'Balance N'!O:O)-SUMIF('Balance N'!B:B,4011,'Balance N'!O:O))-(SUMIF('Balance N-1'!B:B,603,'Balance N'!O:O)-SUMIF('Balance N'!B:B,603,'Balance N'!P:P)) -> 0 | H24: =+F24+G24 -> 0
A25: FN | B25: Transport | F25: =SUMIF('Balance N'!A:A,61,'Balance N'!K:K) -> 0 | G25: =SUMIF('Balance N'!A:A,61,'Balance N'!M:M)-(SUMIF('Balance N-1'!C:C,4011,'Balance N'!O:O)-SUMIF('Balance N'!C:C,4011,'Balance N'!O:O)) -> 0 | H25: =+F25+G25 -> 0
A26: FO | B26: Services extérieurs | F26: =SUMIF('Balance N'!A:A,62,'Balance N'!K:K)+SUMIF('Balance N'!A:A,63,'Balance N'!K:K) -> 0 | G26: =SUMIF('Balance N'!A:A,62,'Balance N'!M:M)+SUMIF('Balance N'!A:A,63,'Balance N'!M:M)-(SUMIF('Balance N-1'!C:C,4013,'Balance N'!O:O)-SUMIF('Balance N'!C:C,4013,'Balance N'!O:O)) -> 0 | H26: =+F26+G26 -> 0
A27: FP | B27: Impôts et taxes | F27: =SUMIF('Balance N'!A:A,64,'Balance N'!K:K) -> 0 | G27: =SUMIF('Balance N'!A:A,64,'Balance N'!M:M)-(SUMIF('Balance N-1'!A:A,44,'Balance N'!O:O)-SUMIF('Balance N'!A:A,44,'Balance N'!O:O)) -> 0 | H27: =+F27+G27 -> 0
A28: FQ | B28: Autres charges | F28: =SUMIF('Balance N'!A:A,65,'Balance N'!K:K) -> 0 | G28: =SUMIF('Balance N'!A:A,65,'Balance N'!M:M)-(SUMIF('Balance N-1'!B:B,416,'Balance N'!O:O)-SUMIF('Balance N'!B:B,416,'Balance N'!O:O))-SUMIF('Balance N'!B:B,499,'Balance N'!O:O) -> 0 | H28: =+F28+G28 -> 0
A29: FR | B29: Charges de personnel | F29: =SUMIF('Balance N'!A:A,66,'Balance N'!K:K) -> 0 | G29: =SUMIF('Balance N'!A:A,66,'Balance N'!M:M)-(SUMIF('Balance N-1'!A:A,42,'Balance N'!O:O)-SUMIF('Balance N'!A:A,42,'Balance N'!O:O))-(SUMIF('Balance N-1'!A:A,43,'Balance N'!O:O)-SUMIF('Balance N'!A:A,43,'Balance N'!O:O)) -> 0 | H29: =+F29+G29 -> 0
A30: FS | B30: Charges financières | F30: =SUMIF('Balance N'!A:A,67,'Balance N'!K:K) -> 0 | G30: =SUMIF('Balance N'!A:A,67,'Balance N'!M:M)-SUMIF('Balance N'!B:B,166,'Balance N'!N:N) -> 0 | H30: =+F30+G30 -> 0
A31: FT | B31: Avances sur charges (à justifier) | F31: =SUMIF('Balance N'!C:C,4091,'Balance N'!K:K)+SUMIF('Balance N'!C:C,4093,'Balance N'!K:K) -> 0 | G31: =SUMIF('Balance N'!C:C,4091,'Balance N'!O:O)+SUMIF('Balance N'!C:C,4093,'Balance N'!O:O) -> 0 | H31: =+F31+G31 -> 0
A32: GT | B32: B-TOTAL DES CHARGES DE FONCTIONNEMENT | F32: =SUM(F24:F31) -> 0 | G32: =SUM(G24:G31) -> 0 | H32: =SUM(H24:H31) -> 0
A33: GU | B33: II.EMPLOIS (A+B) | F33: =+F23+F32 -> 0 | G33: =+G23+G32 -> 0 | H33: =+H23+H32 -> 0
A34: GV | B34: III.EXEDENT/DEFICIT DES FONDS RECUS SUR LES EMPLOIS (I-II) | F34: =+F14-F33 -> 0 | G34: =+G14-G33 -> 0 | H34: =+H14-H33 -> 0
A35: FU | B35: Fonds bailleur en début exercice N | F35: 0 | G35: =SUMIF('Balance N-1'!A:A,162,'Balance N-1'!O:O) -> 0 | H35: =+F35+G35 -> 0
A36: FV | B36: Fonds de contrepartie État en début exercice N | F36: 0 | G36: =SUMIF('Balance N-1'!A:A,163,'Balance N-1'!O:O) -> 0 | H36: =+F36+G36 -> 0
A37: FW | B37: Autres fons en début exercice N | F37: 0 | G37: =SUMIF('Balance N-1'!A:A,164,'Balance N-1'!O:O)+SUMIF('Balance N-1'!A:A,165,'Balance N-1'!O:O)+SUMIF('Balance N-1'!A:A,167,'Balance N-1'!O:O)+SUMIF('Balance N-1'!A:A,168,'Balance N-1'!O:O) -> 0 | H37: =+F37+G37 -> 0
A38: GW | B38: IV.FONDS DISPONIBLE EN DEBUT EXERCICE | F38: =SUM(F35:F37) -> 0 | G38: =SUM(G35:G37) -> 0 | H38: =SUM(H35:H37) -> 0
A39: GX | B39: V.MONTANT NET DE L'ENCAISSE DISPONIBLE (III+IV) | F39: =+F34+F38 -> 0 | G39: =+G34+G38 -> 0 | H39: =+H34+H38 -> 0
A40: FX | B40: Fonds bailleur en fin d'exercice N | F40: 0 | G40: =SUMIF('Balance N'!A:A,162,'Balance N'!O:O) -> 0 | H40: =+F40+G40 -> 0
A41: FY | B41: Fonds de contrepartie État en fin exercice N | F41: 0 | G41: =SUMIF('Balance N'!A:A,163,'Balance N'!O:O) -> 0 | H41: =+F41+G41 -> 0
A42: FZ | B42: Autres fonds en fin d'exercice N | F42: 0 | G42: =SUMIF('Balance N'!A:A,164,'Balance N'!O:O)+SUMIF('Balance N'!A:A,165,'Balance N'!O:O)+SUMIF('Balance N'!A:A,167,'Balance N'!O:O)+SUMIF('Balance N'!A:A,168,'Balance N'!O:O) -> 0 | H42: =+F42+G42 -> 0
A43: GY | B43: VI.FONDS DISPONIBLES EN FIN EXERCICE | F43: =SUM(F40:F42) -> 0 | G43: =SUM(G40:G42) -> 0 | H43: =SUM(H40:H42) -> 0
A44: GZ | B44: VII.CONTROLE : TOTAL V = TOTAL VI | F44: =F39-F43 -> 0 | G44: =G39-G43 -> 0 | H44: =H39-H43 -> 0

Sheet TRC
A1: - 6 -
F2: TABLEAU RECONCILIATION TRESO PAGE 1/1
A3: Dénomination sociale : | B3: =+TER!C3 -> DSO Services
A4: Adresse : | B4: =+TER!C4 -> Rue Alphamoi Djénèpo, secteur 01, Bobo-Dioulasso, Burkina Faso | E4: Sigle usuel : | G4: =+TER!H4 -> DSO Services
A5: N° IFU du contribuable : | B5: =+TER!C5 -> 00000101A | C5: Exercice clos le : | D5: =+TER!F5 -> 45657 | E5: Durée (en mois) : | G5: =+TER!H5 -> 12
A6: N° de télédéclarant (NES) : | B6: =+TER!C6 -> Néant
A7: TABLEAU DE RECONCILIATION DE TRESORERIE
A8: TABLEAU DE RECONCILIATION DE LA TRESORERIE DU 01/01202N AU 31/121/202N
A9: LIBELLE | G9: MONTANT
A11: TRESORERIE EN DEBUT EXERCICE N | F11: A
A14: FONDS RECUS DES BAILLEURS AU COURS DE L'EXERCICE N | F14: B
A17: INTERETS RECUS AU COURS DE L'EXERCICE N | F17: C
A20: AUTRES FONDS RECUS AU COURS DE L'EXERCICE N | F20: D
A23: VIREMENTS SUR COMPTES OPERATIONNELS | F23: E
A26: DEPENSES DE L'EXERCICE N | F26: F
A29: TRESORERIE EN FIN D'EXERCICE N (A+B+C+D-E-F) | F29: G | G29: =+G11+G14+G17+G20-G23-G26 -> 0
A32: PAIEMENTS EN INSTANCE | F32: H
A35: TRESORERIE NET DES PAIEMENTS EN INSTANCE (G-H) | F35: I | G35: =+G29-G32 -> 0

Sheet TEB
A1: - 7 -
G2: TABLEAU EXECUTION BUDGETAIRE PAGE 1/1
A3: Dénomination sociale : | B3: =+TRC!B3 -> DSO Services
A4: Adresse : | B4: =+TRC!B4 -> Rue Alphamoi Djénèpo, secteur 01, Bobo-Dioulasso, Burkina Faso | G4: Sigle usuel : | H4: =+TRC!G4 -> DSO Services
A5: N° IFU du contribuable : | B5: =+TRC!B5 -> 00000101A | D5: Exercice clos le | E5: =+TRC!D5 -> 45657 | G5: Durée (en mois) : | H5: =+TRC!G5 -> 12
A6: N° de télédéclarant (NES) : | B6: =+TRC!B6 -> Néant
A9: TABLEAU D'EXECUTION BUDGETAIRE
A11: TABLEAU SUIVI EXECUTION BUDGETAIRE DU 01/01/202N AU 31/12/202N
A14: Code | B14: Libellé | C14: Budget de l'exercice | D14: Décaissement | E14: Engagement | F14: Réalisation | G14: Crédit Disponible | H14: Exécution budget (%)
C15: 1 | D15: 2 | E15: 3 | F15: 4=2+3 | G15: 5=1-4 | H15: 4\1
F16: =+D16+E16 -> 0 | G16: =+C16-F16 -> 0 | H16: =IFERROR(+F16/C16,"")
F17: =+D17+E17 -> 0 | G17: =+C17-F17 -> 0 | H17: =IFERROR(+F17/C17,"")
F18: =+D18+E18 -> 0 | G18: =+C18-F18 -> 0 | H18: =IFERROR(+F18/C18,"")
F19: =+D19+E19 -> 0 | G19: =+C19-F19 -> 0 | H19: =IFERROR(+F19/C19,"")
F20: =+D20+E20 -> 0 | G20: =+C20-F20 -> 0 | H20: =IFERROR(+F20/C20,"")
F21: =+D21+E21 -> 0 | G21: =+C21-F21 -> 0 | H21: =IFERROR(+F21/C21,"")
F22: =+D22+E22 -> 0 | G22: =+C22-F22 -> 0 | H22: =IFERROR(+F22/C22,"")
F23: =+D23+E23 -> 0 | G23: =+C23-F23 -> 0 | H23: =IFERROR(+F23/C23,"")
F24: =+D24+E24 -> 0 | G24: =+C24-F24 -> 0 | H24: =IFERROR(+F24/C24,"")
F25: =+D25+E25 -> 0 | G25: =+C25-F25 -> 0 | H25: =IFERROR(+F25/C25,"")
F26: =+D26+E26 -> 0 | G26: =+C26-F26 -> 0 | H26: =IFERROR(+F26/C26,"")
F27: =+D27+E27 -> 0 | G27: =+C27-F27 -> 0 | H27: =IFERROR(+F27/C27,"")
... F44: =+D44+E44 -> 0 | G44: =+C44-F44 -> 0 | H44: =IFERROR(+F44/C44,"")
A45: TOTAL | C45: =SUM(C16:C44) -> 0 | D45: =SUM(D16:D44) -> 0 | E45: =SUM(E16:E44) -> 0 | F45: =SUM(F16:F44) -> 0 | G45: =SUM(G16:G44) -> 0 | H45: =SUM(H16:H44) -> 0
A47: Remplir, code et libellé, suivant la nomenclature budgétaire du projet
A48: (a) Remplir, code et libellé, suivant la nomenclature budgétaire du projet.
A49: (b) Le plan comptable doit être conçu en tenant compte du budget du projet.
A50: Cette rubrique sera remplie au vu du budget de l’exercice du projet compte par compte.
A51: © Si le plan comptable est conçu sur la base du budget, indiquer le décaissement pour chaque item qui doit correspondre à la somme algébrique suivante :
A52: ●mouvement débit balance N des compte immobilisations (compte2) a
A53: L’exception des virements de compte à compte +( solde créditeur N-1 du compte 481- solde créditeur N du compte 481)
A54: · Mouvement débit balance N des comptes de charges (comptes 6 et 8)+ (solde créditeur N-1 du compte 40 sauf 409-solde créditeur N du compte 40 sauf 409) +(solde débiteur balance N du compte 409-solde débiteur balance N-1 du compte 409) .
A55: (d) le montant de l’engagement pour chaque item doit correspondre :
A56: · Au solde créditeur balance N des comptes fournisseurs d’exploitation
A57: (compte 40) et d’investissement (compte 481) ,
A58: · Bons de commande des biens et services remis aux fournisseurs au cours de l’exercice budgétaire non exécutés,
A59: · Contrats signés par les parties prenantes au cours de l’exercice budgétaire non exécutés .

Sheet BILAN PAYSAGE
A1: - 8 -
C2: =+TEB!B3 -> DSO Services | K2: BILAN SYSTÈME NORMAL PAGE 1/1
B3: Dénomination sociale de l'entité : | C3: =+TEB!B4 -> Rue Alphamoi Djénèpo, secteur 01, Bobo-Dioulasso, Burkina Faso
B4: Adresse : | C4: =+TEB!B5 -> 00000101A | K4: Sigle usuel : | L4: =+TEB!H4 -> DSO Services
B5: N° IFU du contribuable : | C5: =+TEB!B6 -> Néant | G5: Exercice clos le : | I5: =+TEB!E5 -> 45657 | K5: Durée (en mois) : | L5: =+TEB!H5 -> 12
B6: N° de télédéclarant (NES):
A8: =CONCATENATE("Bilan au 31 Décembre"&" "&TEXT('INFORMATIONS GENERALES'!J13,"aaaa")) -> Bilan au 31 Décembre 2024
A10: REF | B10: ACTIF | C10: NOTE | F10: EXERCICE AU 31/12/ N | G10: EXERCICE AU 31/12/N-1 | H10: REF | I10: PASSIF | J10: NOTE | K10: EXERCICE AU 31/12/N | L10: EXERCICE AU 31/12/N-1
D11: Brut | E11: Amort/Dépréc | F11: Net | G11: Net | K11: Net | L11: Net
A12: AA | B12: Immobilisations incorporelles | D12: =SUMIF('Balance N'!A:A,21,'Balance N'!O:O) -> 0 | E12: =SUMIF('Balance N'!B:B,281,'Balance N'!P:P)+SUMIF('Balance N'!B:B,291,'Balance N'!P:P) -> 0 | F12: =D12-E12 -> 0 | G12: =SUMIF('Balance N-1'!A:A,21,'Balance N-1'!O:O)-(SUMIF('Balance N-1'!B:B,281,'Balance N-1'!P:P)+SUMIF('Balance N-1'!B:B,291,'Balance N-1'!P:P)) -> 0 | H12: CA | I12: Fonds affectés aux investissements | K12: =SUMIF('Balance N'!A:A,16,'Balance N'!P:P) -> 0 | L12: =SUMIF('Balance N-1'!A:A,16,'Balance N-1'!P:P) -> 0
A13: AB | B13: Terrains et bâtiments | D13: =SUMIF('Balance N'!A:A,22,'Balance N'!O:O)+SUMIF('Balance N'!B:B,231,'Balance N'!O:O)+SUMIF('Balance N'!B:B,233,'Balance N'!O:O)+SUMIF('Balance N'!C:C,2391,'Balance N'!O:O)+SUMIF('Balance N'!C:C,2392,'Balance N'!O:O)+SUMIF('Balance N'!C:C,2393,'Balance N'!O:O)+SUMIF('Balance N'!C:C,2396,'Balance N'!O:O) -> 0 | E13: =SUMIF('Balance N'!B:B,282,'Balance N'!P:P)+SUMIF('Balance N'!C:C,2831,'Balance N'!P:P)+SUMIF('Balance N'!C:C,2832,'Balance N'!P:P)+SUMIF('Balance N'!C:C,2833,'Balance N'!P:P)+SUMIF('Balance N'!B:B,292,'Balance N'!P:P)+SUMIF('Balance N'!C:C,2931,'Balance N'!P:P)+SUMIF('Balance N'!C:C,2932,'Balance N'!P:P)+SUMIF('Balance N'!C:C,2933,'Balance N'!P:P)+SUMIF('Balance N'!C:C,2939,'Balance N'!P:P) -> 0 | F13: =D13-E13 -> 0 | G13: =SUMIF('Balance N-1'!A:A,22,'Balance N-1'!O:O)+SUMIF('Balance N-1'!B:B,231,'Balance N-1'!O:O)+SUMIF('Balance N-1'!B:B,233,'Balance N-1'!O:O)+SUMIF('Balance N-1'!C:C,2391,'Balance N-1'!O:O)+SUMIF('Balance N-1'!C:C,2392,'Balance N-1'!O:O)+SUMIF('Balance N-1'!C:C,2393,'Balance N-1'!O:O)+SUMIF('Balance N-1'!C:C,2396,'Balance N-1'!O:O)-(SUMIF('Balance N-1'!B:B,282,'Balance N-1'!P:P)+SUMIF('Balance N-1'!C:C,2831,'Balance N-1'!P:P)+SUMIF('Balance N-1'!C:C,2832,'Balance N-1'!P:P)+SUMIF('Balance N-1'!C:C,2833,'Balance N-1'!P:P)+SUMIF('Balance N-1'!B:B,292,'Balance N-1'!P:P)+SUMIF('Balance N-1'!C:C,2931,'Balance N-1'!P:P)+SUMIF('Balance N-1'!C:C,2932,'Balance N-1'!P:P)+SUMIF('Balance N-1'!C:C,2933,'Balance N-1'!P:P)+SUMIF('Balance N-1'!C:C,2939,'Balance N-1'!P:P)) -> 0 | H13: CB | I13: Repot à nouveau (+ou-) | K13: =SUMIF('Balance N'!B:B,121,'Balance N'!P:P)-SUMIF('Balance N'!B:B,129,'Balance N'!O:O) -> 0 | L13: =SUMIF('Balance N-1'!B:B,121,'Balance N-1'!P:P)-SUMIF('Balance N-1'!B:B,129,'Balance N-1'!O:O) -> 0
A14: AC | B14: Aménagements, agencements et installations | D14: =SUMIF('Balance N'!B:B,234,'Balance N'!O:O)+SUMIF('Balance N'!B:B,235,'Balance N'!O:O)+SUMIF('Balance N'!B:B,238,'Balance N'!O:O)+SUMIF('Balance N'!C:C,2394,'Balance N'!O:O)+SUMIF('Balance N'!C:C,2395,'Balance N'!O:O)+SUMIF('Balance N'!C:C,2398,'Balance N'!O:O) -> 0 | E14: =SUMIF('Balance N'!C:C,2834,'Balance N'!P:P)+SUMIF('Balance N'!C:C,2835,'Balance N'!P:P)+SUMIF('Balance N'!C:C,2838,'Balance N'!P:P)+SUMIF('Balance N'!C:C,2934,'Balance N'!P:P)+SUMIF('Balance N'!C:C,2935,'Balance N'!P:P)+SUMIF('Balance N'!C:C,2938,'Balance N'!P:P)+SUMIF('Balance N'!C:C,2939,'Balance N'!P:P) -> 0 | F14: =D14-E14 -> 0 | G14: =SUMIF('Balance N-1'!B:B,234,'Balance N-1'!O:O)+SUMIF('Balance N-1'!B:B,235,'Balance N-1'!O:O)+SUMIF('Balance N-1'!B:B,238,'Balance N-1'!O:O)+SUMIF('Balance N-1'!C:C,2394,'Balance N-1'!O:O)+SUMIF('Balance N-1'!C:C,2395,'Balance N-1'!O:O)+SUMIF('Balance N-1'!C:C,2398,'Balance N-1'!O:O)-(SUMIF('Balance N-1'!C:C,2834,'Balance N-1'!P:P)+SUMIF('Balance N-1'!C:C,2835,'Balance N-1'!P:P)+SUMIF('Balance N-1'!C:C,2838,'Balance N-1'!P:P)+SUMIF('Balance N-1'!C:C,2934,'Balance N-1'!P:P)+SUMIF('Balance N-1'!C:C,2935,'Balance N-1'!P:P)+SUMIF('Balance N-1'!C:C,2938,'Balance N-1'!P:P)+SUMIF('Balance N-1'!C:C,2939,'Balance N-1'!P:P)) -> 0 | H14: CC | I14: solde des opérations de l'exercice | K14: =+'Compte d''exploitation'!H31 -> 0 | L14: =+'Compte d''exploitation'!I31 -> 0
A15: AD | B15: Matériel, mobilier et actif biologiques | C15: 3 | D15: =SUMIF('Balance N'!A:A,24,'Balance N'!O:O)-SUMIF('Balance N'!B:B,245,'Balance N'!O:O)-SUMIF('Balance N'!C:C,2495,'Balance N'!O:O) -> 0 | E15: =SUMIF('Balance N'!B:B,284,'Balance N'!P:P)-SUMIF('Balance N'!C:C,2845,'Balance N'!P:P)+SUMIF('Balance N'!B:B,294,'Balance N'!P:P)-SUMIF('Balance N'!C:C,2945,'Balance N'!P:P)-SUMIF('Balance N'!C:C,2949,'Balance N'!P:P) -> 0 | F15: =D15-E15 -> 0 | G15: =SUMIF('Balance N-1'!A:A,24,'Balance N-1'!O:O)-SUMIF('Balance N-1'!B:B,245,'Balance N-1'!O:O)-SUMIF('Balance N-1'!C:C,2495,'Balance N-1'!O:O)-(SUMIF('Balance N-1'!B:B,284,'Balance N-1'!P:P)-SUMIF('Balance N-1'!C:C,2845,'Balance N-1'!P:P)+SUMIF('Balance N-1'!B:B,294,'Balance N-1'!P:P)-SUMIF('Balance N-1'!C:C,2945,'Balance N-1'!P:P)-SUMIF('Balance N-1'!C:C,2949,'Balance N-1'!P:P)) -> 0 | H15: CD | I15: Subvention d'investissement | J15: 9 | K15: =SUMIF('Balance N'!A:A,14,'Balance N'!P:P) -> 0 | L15: =SUMIF('Balance N-1'!A:A,14,'Balance N-1'!P:P) -> 0
A16: AE | B16: Matériel de transport | D16: =SUMIF('Balance N'!B:B,245,'Balance N'!O:O)+SUMIF('Balance N'!C:C,2495,'Balance N'!O:O) -> 0 | E16: =SUMIF('Balance N'!C:C,2845,'Balance N'!P:P)+SUMIF('Balance N'!C:C,2945,'Balance N'!P:P)+SUMIF('Balance N'!C:C,2949,'Balance N'!P:P) -> 0 | F16: =D16-E16 -> 0 | G16: =SUMIF('Balance N-1'!B:B,245,'Balance N-1'!O:O)+SUMIF('Balance N-1'!C:C,2495,'Balance N-1'!O:O)-(SUMIF('Balance N-1'!C:C,2845,'Balance N-1'!P:P)+SUMIF('Balance N-1'!C:C,2945,'Balance N-1'!P:P)+SUMIF('Balance N-1'!C:C,2949,'Balance N-1'!P:P)) -> 0 | H16: CZ | I16: TOTAL RESSOURCES PROPRES ET ASSIMILES | K16: =SUM(K12:K15) -> 0 | L16: =SUM(L12:L15) -> 0
A17: AF | B17: Avances et acomptes versés sur immobilisations | D17: =SUMIF('Balance N'!A:A,25,'Balance N'!O:O) -> 0 | E17: =SUMIF('Balance N'!B:B,295,'Balance N'!P:P) -> 0 | F17: =D17-E17 -> 0 | G17: =SUMIF('Balance N-1'!A:A,25,'Balance N-1'!O:O)-(SUMIF('Balance N-1'!B:B,295,'Balance N-1'!P:P)) -> 0 | H17: DA | I17: Emprunts et assimilées | K17: =SUMIF('Balance N'!A:A,18,'Balance N'!P:P) -> 0 | L17: =SUMIF('Balance N-1'!A:A,18,'Balance N-1'!P:P) -> 0
A18: AG | B18: Dépôts et cautionnements | D18: =SUMIF('Balance N'!B:B,275,'Balance N'!O:O) -> 0 | E18: =SUMIF('Balance N'!C:C,2975,'Balance N'!P:P) -> 0 | F18: =D18-E18 -> 0 | G18: =SUMIF('Balance N-1'!B:B,275,'Balance N-1'!O:O)-(SUMIF('Balance N-1'!C:C,2975,'Balance N-1'!P:P)) -> 0 | H18: DB | I18: Provisions pour risques et charges | K18: =SUMIF('Balance N'!A:A,19,'Balance N'!P:P) -> 0 | L18: =SUMIF('Balance N-1'!A:A,19,'Balance N-1'!P:P) -> 0
A19: AH | B19: Autre immobilisations corporelles et financières | D19: =SUMIF('Balance N'!A:A,26,'Balance N'!O:O)+SUMIF('Balance N'!A:A,27,'Balance N'!O:O)-SUMIF('Balance N'!B:B,275,'Balance N'!O:O) -> 0 | E19: =SUMIF('Balance N'!B:B,296,'Balance N'!P:P)+SUMIF('Balance N'!B:B,297,'Balance N'!P:P)-SUMIF('Balance N'!C:C,2975,'Balance N'!P:P) -> 0 | F19: =D19-E19 -> 0 | G19: =SUMIF('Balance N-1'!A:A,26,'Balance N-1'!O:O)+SUMIF('Balance N-1'!A:A,27,'Balance N-1'!O:O)-SUMIF('Balance N-1'!B:B,275,'Balance N-1'!O:O)-(SUMIF('Balance N-1'!B:B,296,'Balance N-1'!P:P)+SUMIF('Balance N-1'!B:B,297,'Balance N-1'!P:P)-SUMIF('Balance N-1'!C:C,2975,'Balance N-1'!P:P)) -> 0 | H19: DC | I19: TOTAL DETTES FINANCIERES ET RESSOURCES ASSIMILEES | K19: =SUM(K17:K18) -> 0 | L19: =SUM(L17:L18) -> 0
A20: AZ | B20: TOTAL ACTIF IMMOBILISE | D20: =SUM(D12:D19) -> 0 | E20: =SUM(E12:E19) -> 0 | F20: =SUM(F12:F19) -> 0 | G20: =SUM(G12:G19) -> 0 | H20: DD | I20: TOTAL RESSOURCES STABLES | K20: =K16+K19 -> 0 | L20: =L16+L19 -> 0
A21: AI | B21: Actif circulant HAO | C21: 3 | D21: =SUMIF('Balance N'!B:B,485,'Balance N'!O:O) -> 0 | E21: =SUMIF('Balance N'!B:B,498,'Balance N'!P:P) -> 0 | F21: =D21-E21 -> 0 | G21: =SUMIF('Balance N-1'!B:B,485,'Balance N-1'!O:O)-(SUMIF('Balance N-1'!B:B,498,'Balance N-1'!P:P)) -> 0 | H21: DE | I21: Dette circulanttes HAO | K21: =SUMIF('Balance N'!B:B,481,'Balance N'!P:P)+SUMIF('Balance N'!B:B,484,'Balance N'!P:P)+SUMIF('Balance N'!B:B,4998,'Balance N'!P:P) -> 0 | L21: =SUMIF('Balance N-1'!B:B,481,'Balance N-1'!P:P)+SUMIF('Balance N-1'!B:B,484,'Balance N-1'!P:P)+SUMIF('Balance N-1'!B:B,4998,'Balance N-1'!P:P) -> 0
A22: AJ | B22: Stocks et encours | D22: =SUMIF('Balance N'!A:A,31,'Balance N'!O:O)+SUMIF('Balance N'!A:A,32,'Balance N'!O:O)+SUMIF('Balance N'!A:A,33,'Balance N'!O:O)+SUMIF('Balance N'!A:A,34,'Balance N'!O:O)+SUMIF('Balance N'!A:A,35,'Balance N'!O:O)+SUMIF('Balance N'!A:A,36,'Balance N'!O:O)+SUMIF('Balance N'!A:A,37,'Balance N'!O:O)+SUMIF('Balance N'!A:A,38,'Balance N'!O:O) -> 0 | E22: =SUMIF('Balance N'!A:A,39,'Balance N'!P:P) -> 0 | F22: =D22-E22 -> 0 | G22: =(SUMIF('Balance N-1'!A:A,31,'Balance N-1'!O:O)+SUMIF('Balance N-1'!A:A,32,'Balance N-1'!O:O)+SUMIF('Balance N-1'!A:A,33,'Balance N-1'!O:O)+SUMIF('Balance N-1'!A:A,34,'Balance N-1'!O:O)+SUMIF('Balance N-1'!A:A,36,'Balance N-1'!O:O)+SUMIF('Balance N-1'!A:A,38,'Balance N-1'!O:O))-SUMIF('Balance N-1'!A:A,39,'Balance N-1'!P:P) -> 0 | H22: DF | I22: Fonds d'administration | K22: =SUMIF('Balance N'!A:A,46,'Balance N'!P:P) -> 0 | L22: =SUMIF('Balance N-1'!A:A,46,'Balance N-1'!P:P) -> 0
A23: AK | B23: fournisseurs débiteurs | C23: 3 | D23: =SUMIF('Balance N'!B:B,409,'Balance N'!O:O) -> 0 | E23: =SUMIF('Balance N'!B:B,490,'Balance N'!P:P) -> 0 | F23: =D23-E23 -> 0 | G23: =SUMIF('Balance N-1'!A:A,40,'Balance N-1'!O:O)-(SUMIF('Balance N-1'!B:B,490,'Balance N-1'!P:P)) -> 0 | H23: DG | I23: Fournisseurs | K23: =SUMIF('Balance N'!A:A,40,'Balance N'!P:P) -> 0 | L23: =SUMIF('Balance N-1'!A:A,40,'Balance N-1'!P:P) -> 0
A24: AL | B24: Clients-usagers | C24: 3 | D24: =SUMIF('Balance N'!A:A,41,'Balance N'!O:O)-SUMIF('Balance N'!B:B,419,'Balance N'!O:O) -> 0 | E24: =SUMIF('Balance N'!B:B,491,'Balance N'!P:P) -> 0 | F24: =D24-E24 -> 0 | G24: =(SUMIF('Balance N-1'!A:A,41,'Balance N-1'!O:O)-SUMIF('Balance N-1'!B:B,419,'Balance N-1'!O:O))-(SUMIF('Balance N-1'!B:B,491,'Balance N-1'!P:P)) -> 0 | H24: DH | I24: Autres dettes | J24: 10 | K24: =SUMIF('Balance N'!A:A,42,'Balance N'!P:P)+SUMIF('Balance N'!A:A,43,'Balance N'!P:P)+SUMIF('Balance N'!A:A,44,'Balance N'!P:P)+SUMIF('Balance N'!A:A,47,'Balance N'!P:P)-SUMIF('Balance N'!B:B,479,'Balance N'!P:P)-SUMIF('Balance N'!C:C,4998,'Balance N'!P:P)+SUMIF('Balance N'!A:A,41,'Balance N'!P:P) -> 0 | L24: =SUMIF('Balance N-1'!A:A,42,'Balance N-1'!P:P)+SUMIF('Balance N-1'!A:A,43,'Balance N-1'!P:P)+SUMIF('Balance N-1'!A:A,44,'Balance N-1'!P:P)+SUMIF('Balance N-1'!A:A,47,'Balance N-1'!P:P)-SUMIF('Balance N-1'!B:B,479,'Balance N-1'!P:P)-SUMIF('Balance N-1'!C:C,4998,'Balance N-1'!P:P)+SUMIF('Balance N-1'!A:A,41,'Balance N-1'!P:P) -> 0
A25: AM | B25: Autres créances | C25: 3 | D25: =SUMIF('Balance N'!A:A,42,'Balance N'!O:O)+SUMIF('Balance N'!A:A,43,'Balance N'!O:O)+SUMIF('Balance N'!A:A,44,'Balance N'!O:O)+SUMIF('Balance N'!B:B,469,'Balance N'!O:O)+SUMIF('Balance N'!A:A,47,'Balance N'!O:O)-SUMIF('Balance N'!B:B,478,'Balance N'!O:O) -> 0 | E25: =SUMIF('Balance N'!B:B,492,'Balance N'!P:P)+SUMIF('Balance N'!B:B,493,'Balance N'!P:P)+SUMIF('Balance N'!B:B,494,'Balance N'!P:P)+SUMIF('Balance N'!B:B,497,'Balance N'!P:P) -> 0 | F25: =D25-E25 -> 0 | G25: =(SUMIF('Balance N-1'!A:A,42,'Balance N-1'!O:O)+SUMIF('Balance N-1'!A:A,43,'Balance N-1'!O:O)+SUMIF('Balance N-1'!A:A,44,'Balance N-1'!O:O)+SUMIF('Balance N-1'!A:A,45,'Balance N-1'!O:O)+SUMIF('Balance N-1'!A:A,46,'Balance N-1'!O:O)+SUMIF('Balance N-1'!A:A,47,'Balance N-1'!O:O)-SUMIF('Balance N-1'!B:B,478,'Balance N-1'!O:O))-(SUMIF('Balance N-1'!B:B,492,'Balance N-1'!P:P)+SUMIF('Balance N-1'!B:B,493,'Balance N-1'!P:P)+SUMIF('Balance N-1'!B:B,494,'Balance N-1'!P:P)+SUMIF('Balance N-1'!B:B,497,'Balance N-1'!P:P)) -> 0 | H25: DI | I25: Provisions pour risques et charges à court terme | K25: =SUMIF('Balance N'!B:B,499,'Balance N'!P:P)+SUMIF('Balance N'!B:B,599,'Balance N'!P:P) -> 0 | L25: =SUMIF('Balance N-1'!B:B,499,'Balance N-1'!P:P)+SUMIF('Balance N-1'!B:B,599,'Balance N-1'!P:P) -> 0
A26: AN | B26: TOTAL ACTIF CIRCULANT | C26: 3 | D26: =SUM(D21:D25) -> 0 | E26: =SUM(E21:E25) -> 0 | F26: =SUM(F21:F25) -> 0 | G26: =SUM(G21:G25) -> 0 | H26: DJ | I26: TOTAL PASSIF CIRCULANT | J26: 11 | K26: =SUM(K21:K25) -> 0 | L26: =SUM(L21:L25) -> 0
A27: BV | B27: Valeurs à encaisser | D27: =SUMIF('Balance N'!A:A,51,'Balance N'!O:O) -> 0 | E27: =SUMIF('Balance N'!B:B,591,'Balance N'!P:P) -> 0 | F27: =D27-E27 -> 0 | G27: =SUMIF('Balance N-1'!A:A,51,'Balance N-1'!O:O)-(SUMIF('Balance N-1'!B:B,591,'Balance N-1'!P:P)) -> 0
A28: BW | B28: Banques, établissements financiers, caisses et assimilés | C28: 3 | D28: =SUMIF('Balance N'!A:A,52,'Balance N'!O:O)+SUMIF('Balance N'!A:A,53,'Balance N'!O:O)+SUMIF('Balance N'!A:A,55,'Balance N'!O:O)+SUMIF('Balance N'!A:A,57,'Balance N'!O:O) -> 0 | E28: =SUMIF('Balance N'!B:B,592,'Balance N'!P:P)+SUMIF('Balance N'!B:B,593,'Balance N'!P:P)+SUMIF('Balance N'!B:B,595,'Balance N'!P:P) -> 0 | F28: =D28-E28 -> 0 | G28: =SUMIF('Balance N-1'!A:A,52,'Balance N-1'!O:O)+SUMIF('Balance N-1'!A:A,53,'Balance N-1'!O:O)+SUMIF('Balance N-1'!A:A,55,'Balance N-1'!O:O)+SUMIF('Balance N-1'!A:A,57,'Balance N-1'!O:O)-(SUMIF('Balance N-1'!B:B,592,'Balance N-1'!P:P)+SUMIF('Balance N-1'!B:B,593,'Balance N-1'!P:P)+SUMIF('Balance N-1'!B:B,595,'Balance N-1'!P:P)) -> 0 | H28: DW | I28: Banques etablisements financierset credit de tresorerie | K28: =SUMIF('Balance N'!B:B,565,'Balance N'!P:P)+SUMIF('Balance N'!A:A,52,'Balance N'!P:P)+SUMIF('Balance N'!A:A,53,'Balance N'!P:P)+SUMIF('Balance N'!B:B,561,'Balance N'!P:P)+SUMIF('Balance N'!B:B,566,'Balance N'!P:P) -> 0 | L28: =SUMIF('Balance N-1'!B:B,565,'Balance N-1'!P:P)+SUMIF('Balance N-1'!A:A,52,'Balance N-1'!P:P)+SUMIF('Balance N-1'!A:A,53,'Balance N-1'!P:P)+SUMIF('Balance N-1'!B:B,561,'Balance N-1'!P:P)+SUMIF('Balance N-1'!B:B,566,'Balance N-1'!P:P) -> 0
A29: BX | B29: TOTAL TRESORERIE ACTIF | C29: 3 | D29: =SUM(D27:D28) -> 0 | E29: =SUM(E27:E28) -> 0 | F29: =SUM(F27:F28) -> 0 | G29: =SUM(G27:G28) -> 0 | H29: DX | I29: TOTAL TRESORERIE PASSIF | J29: 11 | K29: =SUM(K28) -> 0 | L29: =SUM(L28) -> 0
A30: BY | B30: Ecart de conversion-actif | D30: =SUMIF('Balance N'!B:B,478,'Balance N'!O:O) -> 0 | F30: =D30-E30 -> 0 | G30: =SUMIF('Balance N-1'!B:B,478,'Balance N-1'!O:O) -> 0 | H30: DY | I30: Ecart de conversion-Passif | K30: =SUMIF('Balance N'!B:B,479,'Balance N'!P:P) -> 0 | L30: =SUMIF('Balance N-1'!B:B,479,'Balance N-1'!P:P) -> 0
A31: BZ | B31: TOTAL GENERAL | C31: 4 | D31: =SUM(D20,D26,D29,D30) -> 0 | E31: =SUM(E20,E26,E29,E30) -> 0 | F31: =SUM(F20,F26,F29,F30) -> 0 | G31: =SUM(G20,G26,G29,G30) -> 0 | H31: DE | I31: TOTAL GENERAL | J31: 4 | K31: =SUM(K20,K26,K29,K30) -> 0 | L31: =SUM(L20,L26,L29,L30) -> 0

Sheet Bilan Actif
A1: - 9 -
I2: BILAN SYSTÈME NORMAL page 1/2
A3: Dénomination sociale de l'entité : | C3: =+'BILAN PAYSAGE'!C2 -> DSO Services
A4: Adresse : | C4: =+'BILAN PAYSAGE'!C3 -> Rue Alphamoi Djénèpo, secteur 01, Bobo-Dioulasso, Burkina Faso | I4: Sigle usuel : | J4: =+'BILAN PAYSAGE'!L4 -> DSO Services
A5: N° IFU du contribuable : | C5: =+'BILAN PAYSAGE'!C4 -> 00000101A | D5: Exercice clos le : | E5: =+'BILAN PAYSAGE'!I5 -> 45657 | I5: Durée (mois) | J5: =+'BILAN PAYSAGE'!L5 -> 12
A6: N° de télédéclarant (NES): | C6: =+'BILAN PAYSAGE'!C5 -> Néant
A8: =CONCATENATE("Bilan au 31 Décembre"&" "&TEXT('INFORMATIONS GENERALES'!J13,"aaaa")) -> Bilan au 31 Décembre 2024
A9: REF | B9: ACTIF | F9: NOTE | G9: EXERCICE AU 31/12/ N | I9: EXERCICE AU 31/12/N | J9: EXERCICE AU 31/12/N-1
G10: Brut | H10: Amort/Dépréc
I11: Net | J11: Net
A12: AA | B12: Immobilisations incorporelles | F12: 3 | G12: =SUMIF('Balance N'!A:A,21,'Balance N'!O:O) -> 0 | H12: =SUMIF('Balance N'!B:B,281,'Balance N'!P:P)+SUMIF('Balance N'!B:B,291,'Balance N'!P:P) -> 0 | I12: =G12-H12 -> 0 | J12: =SUMIF('Balance N-1'!A:A,21,'Balance N-1'!O:O)-(SUMIF('Balance N-1'!B:B,281,'Balance N-1'!P:P)+SUMIF('Balance N-1'!B:B,291,'Balance N-1'!P:P)) -> 0
A13: AB | B13: Terrains et bâtiments | F13: 3 | G13: =SUMIF('Balance N'!A:A,22,'Balance N'!O:O)+SUMIF('Balance N'!B:B,231,'Balance N'!O:O)+SUMIF('Balance N'!B:B,233,'Balance N'!O:O)+SUMIF('Balance N'!C:C,2391,'Balance N'!O:O)+SUMIF('Balance N'!C:C,2392,'Balance N'!O:O)+SUMIF('Balance N'!C:C,2393,'Balance N'!O:O)+SUMIF('Balance N'!C:C,2396,'Balance N'!O:O) -> 0 | H13: =SUMIF('Balance N'!B:B,282,'Balance N'!P:P)+SUMIF('Balance N'!C:C,2831,'Balance N'!P:P)+SUMIF('Balance N'!C:C,2832,'Balance N'!P:P)+SUMIF('Balance N'!C:C,2833,'Balance N'!P:P)+SUMIF('Balance N'!B:B,292,'Balance N'!P:P)+SUMIF('Balance N'!C:C,2931,'Balance N'!P:P)+SUMIF('Balance N'!C:C,2932,'Balance N'!P:P)+SUMIF('Balance N'!C:C,2933,'Balance N'!P:P)+SUMIF('Balance N'!C:C,2939,'Balance N'!P:P) -> 0 | I13: =G13-H13 -> 0 | J13: =SUMIF('Balance N-1'!A:A,22,'Balance N-1'!O:O)+SUMIF('Balance N-1'!B:B,231,'Balance N-1'!O:O)+SUMIF('Balance N-1'!B:B,233,'Balance N-1'!O:O)+SUMIF('Balance N-1'!C:C,2391,'Balance N-1'!O:O)+SUMIF('Balance N-1'!C:C,2392,'Balance N-1'!O:O)+SUMIF('Balance N-1'!C:C,2393,'Balance N-1'!O:O)+SUMIF('Balance N-1'!C:C,2396,'Balance N-1'!O:O)-(SUMIF('Balance N-1'!B:B,282,'Balance N-1'!P:P)+SUMIF('Balance N-1'!C:C,2831,'Balance N-1'!P:P)+SUMIF('Balance N-1'!C:C,2832,'Balance N-1'!P:P)+SUMIF('Balance N-1'!C:C,2833,'Balance N-1'!P:P)+SUMIF('Balance N-1'!B:B,292,'Balance N-1'!P:P)+SUMIF('Balance N-1'!C:C,2931,'Balance N-1'!P:P)+SUMIF('Balance N-1'!C:C,2932,'Balance N-1'!P:P)+SUMIF('Balance N-1'!C:C,2933,'Balance N-1'!P:P)+SUMIF('Balance N-1'!C:C,2939,'Balance N-1'!P:P)) -> 0
A14: AC | B14: Aménagements, agencements et installations | F14: 3 | G14: =SUMIF('Balance N'!B:B,234,'Balance N'!O:O)+SUMIF('Balance N'!B:B,235,'Balance N'!O:O)+SUMIF('Balance N'!B:B,238,'Balance N'!O:O)+SUMIF('Balance N'!C:C,2394,'Balance N'!O:O)+SUMIF('Balance N'!C:C,2395,'Balance N'!O:O)+SUMIF('Balance N'!C:C,2398,'Balance N'!O:O) -> 0 | H14: =SUMIF('Balance N'!C:C,2834,'Balance N'!P:P)+SUMIF('Balance N'!C:C,2835,'Balance N'!P:P)+SUMIF('Balance N'!C:C,2838,'Balance N'!P:P)+SUMIF('Balance N'!C:C,2934,'Balance N'!P:P)+SUMIF('Balance N'!C:C,2935,'Balance N'!P:P)+SUMIF('Balance N'!C:C,2938,'Balance N'!P:P)+SUMIF('Balance N'!C:C,2939,'Balance N'!P:P) -> 0 | I14: =G14-H14 -> 0 | J14: =SUMIF('Balance N-1'!B:B,234,'Balance N-1'!O:O)+SUMIF('Balance N-1'!B:B,235,'Balance N-1'!O:O)+SUMIF('Balance N-1'!B:B,238,'Balance N-1'!O:O)+SUMIF('Balance N-1'!C:C,2394,'Balance N-1'!O:O)+SUMIF('Balance N-1'!C:C,2395,'Balance N-1'!O:O)+SUMIF('Balance N-1'!C:C,2398,'Balance N-1'!O:O)-(SUMIF('Balance N-1'!C:C,2834,'Balance N-1'!P:P)+SUMIF('Balance N-1'!C:C,2835,'Balance N-1'!P:P)+SUMIF('Balance N-1'!C:C,2838,'Balance N-1'!P:P)+SUMIF('Balance N-1'!C:C,2934,'Balance N-1'!P:P)+SUMIF('Balance N-1'!C:C,2935,'Balance N-1'!P:P)+SUMIF('Balance N-1'!C:C,2938,'Balance N-1'!P:P)+SUMIF('Balance N-1'!C:C,2939,'Balance N-1'!P:P)) -> 0
A15: AD | B15: Matériel, mobilier et actifs biologiques | F15: 3 | G15: =SUMIF('Balance N'!A:A,24,'Balance N'!O:O)-SUMIF('Balance N'!B:B,245,'Balance N'!O:O)-SUMIF('Balance N'!C:C,2495,'Balance N'!O:O) -> 0 | H15: =SUMIF('Balance N'!B:B,284,'Balance N'!P:P)-SUMIF('Balance N'!C:C,2845,'Balance N'!P:P)+SUMIF('Balance N'!B:B,294,'Balance N'!P:P)-SUMIF('Balance N'!C:C,2945,'Balance N'!P:P)-SUMIF('Balance N'!C:C,2949,'Balance N'!P:P) -> 0 | I15: =G15-H15 -> 0 | J15: =SUMIF('Balance N-1'!A:A,24,'Balance N-1'!O:O)-SUMIF('Balance N-1'!B:B,245,'Balance N-1'!O:O)-SUMIF('Balance N-1'!C:C,2495,'Balance N-1'!O:O)-(SUMIF('Balance N-1'!B:B,284,'Balance N-1'!P:P)-SUMIF('Balance N-1'!C:C,2845,'Balance N-1'!P:P)+SUMIF('Balance N-1'!B:B,294,'Balance N-1'!P:P)-SUMIF('Balance N-1'!C:C,2945,'Balance N-1'!P:P)-SUMIF('Balance N-1'!C:C,2949,'Balance N-1'!P:P)) -> 0
A16: AE | B16: Matériel de transport | F16: 3 | G16: =SUMIF('Balance N'!B:B,245,'Balance N'!O:O)+SUMIF('Balance N'!C:C,2495,'Balance N'!O:O) -> 0 | H16: =SUMIF('Balance N'!C:C,2845,'Balance N'!P:P)+SUMIF('Balance N'!C:C,2945,'Balance N'!P:P)+SUMIF('Balance N'!C:C,2949,'Balance N'!P:P) -> 0 | I16: =G16-H16 -> 0 | J16: =SUMIF('Balance N-1'!B:B,245,'Balance N-1'!O:O)+SUMIF('Balance N-1'!C:C,2495,'Balance N-1'!O:O)-(SUMIF('Balance N-1'!C:C,2845,'Balance N-1'!P:P)+SUMIF('Balance N-1'!C:C,2945,'Balance N-1'!P:P)+SUMIF('Balance N-1'!C:C,2949,'Balance N-1'!P:P)) -> 0
A17: AF | B17: Avances et acomptes versés sur immobilisations | F17: 3 | G17: =SUMIF('Balance N'!A:A,25,'Balance N'!O:O) -> 0 | H17: =SUMIF('Balance N'!B:B,295,'Balance N'!P:P) -> 0 | I17: =G17-H17 -> 0 | J17: =SUMIF('Balance N-1'!A:A,25,'Balance N-1'!O:O)-(SUMIF('Balance N-1'!B:B,295,'Balance N-1'!P:P)) -> 0
A18: AG | B18: Dépôts et cautionnements | F18: 3 | G18: =SUMIF('Balance N'!B:B,275,'Balance N'!O:O) -> 0 | H18: =SUMIF('Balance N'!C:C,2975,'Balance N'!P:P) -> 0 | I18: =G18-H18 -> 0 | J18: =SUMIF('Balance N-1'!B:B,275,'Balance N-1'!O:O)-(SUMIF('Balance N-1'!C:C,2975,'Balance N-1'!P:P)) -> 0
A19: AH | B19: Autres immobilisations corporelles et financières | F19: 3 | G19: =SUMIF('Balance N'!A:A,26,'Balance N'!O:O)+SUMIF('Balance N'!A:A,27,'Balance N'!O:O)-SUMIF('Balance N'!B:B,275,'Balance N'!O:O) -> 0 | H19: =SUMIF('Balance N'!B:B,296,'Balance N'!P:P)+SUMIF('Balance N'!B:B,297,'Balance N'!P:P)-SUMIF('Balance N'!C:C,2975,'Balance N'!P:P) -> 0 | I19: =G19-H19 -> 0 | J19: =SUMIF('Balance N-1'!A:A,26,'Balance N-1'!O:O)+SUMIF('Balance N-1'!A:A,27,'Balance N-1'!O:O)-SUMIF('Balance N-1'!B:B,275,'Balance N-1'!O:O)-(SUMIF('Balance N-1'!B:B,296,'Balance N-1'!P:P)+SUMIF('Balance N-1'!B:B,297,'Balance N-1'!P:P)-SUMIF('Balance N-1'!C:C,2975,'Balance N-1'!P:P)) -> 0
A20: AZ | B20: TOTAL ACTIF IMMOBILISE | G20: =+SUM(G12:G19) -> 0 | H20: =+SUM(H12:H19) -> 0 | I20: =+SUM(I12:I19) -> 0 | J20: =+SUM(J12:J19) -> 0
A21: BA | B21: Actif circulant HAO | F21: 4 | G21: =SUMIF('Balance N'!B:B,485,'Balance N'!O:O) -> 0 | H21: =SUMIF('Balance N'!B:B,498,'Balance N'!P:P) -> 0 | I21: =G21-H21 -> 0 | J21: =SUMIF('Balance N-1'!B:B,485,'Balance N-1'!O:O)-(SUMIF('Balance N-1'!B:B,498,'Balance N-1'!P:P)) -> 0
A22: BB | B22: Stocks et encours | F22: 5 | G22: =SUMIF('Balance N'!A:A,31,'Balance N'!O:O)+SUMIF('Balance N'!A:A,32,'Balance N'!O:O)+SUMIF('Balance N'!A:A,33,'Balance N'!O:O)+SUMIF('Balance N'!A:A,34,'Balance N'!O:O)+SUMIF('Balance N'!A:A,35,'Balance N'!O:O)+SUMIF('Balance N'!A:A,36,'Balance N'!O:O)+SUMIF('Balance N'!A:A,37,'Balance N'!O:O)+SUMIF('Balance N'!A:A,38,'Balance N'!O:O) -> 0 | H22: =SUMIF('Balance N'!A:A,39,'Balance N'!P:P) -> 0 | I22: =G22-H22 -> 0 | J22: =SUMIF('Balance N-1'!A:A,31,'Balance N-1'!O:O)+SUMIF('Balance N-1'!A:A,32,'Balance N-1'!O:O)+SUMIF('Balance N-1'!A:A,33,'Balance N-1'!O:O)+SUMIF('Balance N-1'!A:A,34,'Balance N-1'!O:O)+SUMIF('Balance N-1'!A:A,35,'Balance N-1'!O:O)+SUMIF('Balance N-1'!A:A,36,'Balance N-1'!O:O)+SUMIF('Balance N-1'!A:A,37,'Balance N-1'!O:O)+SUMIF('Balance N-1'!A:A,38,'Balance N-1'!O:O)-(SUMIF('Balance N-1'!A:A,39,'Balance N-1'!P:P)) -> 0
A23: BC | B23: Fournisseurs débiteurs | F23: 6 | G23: =SUMIF('Balance N'!B:B,409,'Balance N'!O:O) -> 0 | H23: =SUMIF('Balance N'!B:B,490,'Balance N'!P:P) -> 0 | I23: =G23-H23 -> 0 | J23: =SUMIF('Balance N-1'!B:B,409,'Balance N-1'!O:O)-(SUMIF('Balance N-1'!B:B,490,'Balance N-1'!P:P)) -> 0
A24: BD | B24: Clients- usagers | F24: 6 | G24: =SUMIF('Balance N'!A:A,41,'Balance N'!O:O)-SUMIF('Balance N'!B:B,419,'Balance N'!O:O) -> 0 | H24: =SUMIF('Balance N'!B:B,491,'Balance N'!P:P) -> 0 | I24: =G24-H24 -> 0 | J24: =SUMIF('Balance N-1'!A:A,41,'Balance N-1'!O:O)-SUMIF('Balance N-1'!B:B,419,'Balance N-1'!O:O)-(SUMIF('Balance N-1'!B:B,491,'Balance N-1'!P:P)) -> 0
A25: BE | B25: Autres créances | F25: 6 | G25: =SUMIF('Balance N'!A:A,42,'Balance N'!O:O)+SUMIF('Balance N'!A:A,43,'Balance N'!O:O)+SUMIF('Balance N'!A:A,44,'Balance N'!O:O)+SUMIF('Balance N'!B:B,469,'Balance N'!O:O)+SUMIF('Balance N'!A:A,47,'Balance N'!O:O)-SUMIF('Balance N'!B:B,478,'Balance N'!O:O) -> 0 | H25: =SUMIF('Balance N'!B:B,492,'Balance N'!P:P)+SUMIF('Balance N'!B:B,493,'Balance N'!P:P)+SUMIF('Balance N'!B:B,494,'Balance N'!P:P)+SUMIF('Balance N'!B:B,497,'Balance N'!P:P) -> 0 | I25: =G25-H25 -> 0 | J25: =SUMIF('Balance N-1'!A:A,42,'Balance N-1'!O:O)+SUMIF('Balance N-1'!A:A,43,'Balance N-1'!O:O)+SUMIF('Balance N-1'!A:A,44,'Balance N-1'!O:O)+SUMIF('Balance N-1'!B:B,469,'Balance N-1'!O:O)+SUMIF('Balance N-1'!A:A,47,'Balance N-1'!O:O)-SUMIF('Balance N-1'!B:B,478,'Balance N-1'!O:O)-(SUMIF('Balance N-1'!B:B,492,'Balance N-1'!P:P)+SUMIF('Balance N-1'!B:B,493,'Balance N-1'!P:P)+SUMIF('Balance N-1'!B:B,494,'Balance N-1'!P:P)+SUMIF('Balance N-1'!B:B,497,'Balance N-1'!P:P)) -> 0
A26: BF | B26: TOTAL ACTIF CIRCULANT | G26: =+SUM(G21:G25) -> 0 | H26: =+SUM(H21:H25) -> 0 | I26: =+SUM(I21:I25) -> 0 | J26: =+SUM(J21:J25) -> 0
A27: BV | B27: Valeurs à encaisser | F27: 6 | G27: =SUMIF('Balance N'!A:A,51,'Balance N'!O:O) -> 0 | H27: =SUMIF('Balance N'!B:B,591,'Balance N'!P:P) -> 0 | I27: =G27-H27 -> 0 | J27: =SUMIF('Balance N-1'!A:A,51,'Balance N-1'!O:O)-(SUMIF('Balance N-1'!B:B,591,'Balance N-1'!P:P)) -> 0
A28: BW | B28: Banques, établissements financières, caisses et assimilés | F28: 6 | G28: =SUMIF('Balance N'!A:A,52,'Balance N'!O:O)+SUMIF('Balance N'!A:A,53,'Balance N'!O:O)+SUMIF('Balance N'!A:A,55,'Balance N'!O:O)+SUMIF('Balance N'!A:A,57,'Balance N'!O:O) -> 0 | H28: =SUMIF('Balance N'!B:B,592,'Balance N'!P:P)+SUMIF('Balance N'!B:B,593,'Balance N'!P:P)+SUMIF('Balance N'!B:B,595,'Balance N'!P:P) -> 0 | I28: =G28-H28 -> 0 | J28: =SUMIF('Balance N-1'!A:A,52,'Balance N-1'!O:O)+SUMIF('Balance N-1'!A:A,53,'Balance N-1'!O:O)+SUMIF('Balance N-1'!A:A,55,'Balance N-1'!O:O)+SUMIF('Balance N-1'!A:A,57,'Balance N-1'!O:O)-(SUMIF('Balance N-1'!B:B,592,'Balance N-1'!P:P)+SUMIF('Balance N-1'!B:B,593,'Balance N-1'!P:P)+SUMIF('Balance N-1'!B:B,595,'Balance N-1'!P:P)) -> 0
A29: BX | B29: TOTAL TRESORERIE ACTIF | G29: =+SUM(G27:G28) -> 0 | H29: =+SUM(H27:H28) -> 0 | I29: =+SUM(I27:I28) -> 0 | J29: =+SUM(J27:J28) -> 0
A30: BY | B30: Ecart de conversion-Actif | F30: 7 | G30: =SUMIF('Balance N'!B:B,478,'Balance N'!O:O) -> 0 | I30: =G30-H30 -> 0 | J30: =SUMIF('Balance N-1'!B:B,478,'Balance N-1'!O:O) -> 0
A31: BZ | B31: TOTAL GENERAL | G31: =+G20+G26+G29-G30 -> 0 | H31: =+H20+H26+H29-H30 -> 0 | I31: =+I20+I26+I29-I30 -> 0 | J31: =+J20+J26+J29-J30 -> 0

Sheet Bilan Passif
A1: - 10 -
H2: BILAN SYSTÈME NORMAL page 2/2
A3: Dénomination sociale de l'entité : | C3: =+'Bilan Actif'!C3 -> DSO Services
A4: Adresse : | C4: =+'Bilan Actif'!C4 -> Rue Alphamoi Djénèpo, secteur 01, Bobo-Dioulasso, Burkina Faso | H4: Sigle usuel : | I4: =+'Bilan Actif'!J4 -> DSO Services
A5: N° IFU du contribuable : | C5: =+'Bilan Actif'!C5 -> 00000101A | E5: Exercice clos le : | F5: =+'Bilan Actif'!E5 -> 45657 | H5: Durée (mois) | I5: =+'Bilan Actif'!J5 -> 12
A6: N° de télédéclarant (NES): | C6: =+'Bilan Actif'!C6 -> Néant
A8: =+'Bilan Actif'!A8 -> Bilan au 31 Décembre 2024
A9: REF | B9: PASSIF | G9: NOTE | H9: EXERCICE AU 31/12/N | I9: EXERCICE AU 31/12/N-1
H10: Net | I10: Net
A11: CA | B11: Fonds affectés aux investissements | G11: 9 | H11: =SUMIF('Balance N'!A:A,16,'Balance N'!P:P) -> 0 | I11: =SUMIF('Balance N-1'!A:A,16,'Balance N-1'!P:P) -> 0
A12: CB | B12: Report à nouveau (+ ou -) | H12: =SUMIF('Balance N'!B:B,121,'Balance N'!P:P)-SUMIF('Balance N'!B:B,129,'Balance N'!O:O) -> 0 | I12: =SUMIF('Balance N-1'!B:B,121,'Balance N-1'!P:P)-SUMIF('Balance N-1'!B:B,129,'Balance N-1'!O:O) -> 0
A13: CC | B13: Solde des opérations de l'exercice | H13: =+'Compte d''exploitation'!H31 -> 0 | I13: =+'Compte d''exploitation'!I31 -> 0
A14: CD | B14: Subvention d'investissement | G14: 10 | H14: =SUMIF('Balance N'!A:A,14,'Balance N'!P:P) -> 0 | I14: =SUMIF('Balance N-1'!A:A,14,'Balance N-1'!P:P) -> 0
A15: CZ | B15: TOTAL RESSOURCES PROPRES ET ASSIMILEES | H15: =+SUM(H11:H14) -> 0 | I15: =+SUM(I11:I14) -> 0
A16: DA | B16: Emprunts et dettes assimilés | G16: 11 | H16: =SUMIF('Balance N'!A:A,18,'Balance N'!P:P) -> 0 | I16: =SUMIF('Balance N-1'!A:A,18,'Balance N-1'!P:P) -> 0
A17: DB | B17: Provisions pour risques et charges | G17: 11 | H17: =SUMIF('Balance N'!A:A,19,'Balance N'!P:P) -> 0 | I17: =SUMIF('Balance N-1'!A:A,19,'Balance N-1'!P:P) -> 0
A18: DC | B18: TOTAL DETTES FINANCIERS ET RESSOURCES ASSIMILEES | H18: =+SUM(H16:H17) -> 0 | I18: =+SUM(I16:I17) -> 0
A19: DD | B19: TOTAL RESSOURCES STABLES | H19: =+H15+H18 -> 0 | I19: =+I15+I18 -> 0
A20: DE | B20: Dettes circulant HAO | G20: 4 | H20: =SUMIF('Balance N'!B:B,481,'Balance N'!P:P)+SUMIF('Balance N'!B:B,484,'Balance N'!P:P)+SUMIF('Balance N'!B:B,4998,'Balance N'!P:P) -> 0 | I20: =SUMIF('Balance N-1'!B:B,481,'Balance N-1'!P:P)+SUMIF('Balance N-1'!B:B,484,'Balance N-1'!P:P)+SUMIF('Balance N-1'!B:B,4998,'Balance N-1'!P:P) -> 0
A21: DF | B21: Fonds d'administration | G21: 9 | H21: =SUMIF('Balance N'!A:A,46,'Balance N'!P:P) -> 0 | I21: =SUMIF('Balance N-1'!A:A,46,'Balance N-1'!P:P) -> 0
A22: DG | B22: Fournisseurs | G22: 12 | H22: =SUMIF('Balance N'!A:A,40,'Balance N'!P:P) -> 0 | I22: =SUMIF('Balance N-1'!A:A,40,'Balance N-1'!P:P) -> 0
A23: DH | B23: Autres dettes | G23: 12 | H23: =SUMIF('Balance N'!A:A,42,'Balance N'!P:P)+SUMIF('Balance N'!A:A,43,'Balance N'!P:P)+SUMIF('Balance N'!A:A,44,'Balance N'!P:P)+SUMIF('Balance N'!A:A,47,'Balance N'!P:P)-SUMIF('Balance N'!B:B,479,'Balance N'!P:P)-SUMIF('Balance N'!C:C,4998,'Balance N'!P:P)+SUMIF('Balance N'!A:A,41,'Balance N'!P:P) -> 0 | I23: =SUMIF('Balance N-1'!A:A,42,'Balance N-1'!P:P)+SUMIF('Balance N-1'!A:A,43,'Balance N-1'!P:P)+SUMIF('Balance N-1'!A:A,44,'Balance N-1'!P:P)+SUMIF('Balance N-1'!A:A,47,'Balance N-1'!P:P)-SUMIF('Balance N-1'!B:B,479,'Balance N-1'!P:P)-SUMIF('Balance N-1'!C:C,4998,'Balance N-1'!P:P)+SUMIF('Balance N-1'!A:A,41,'Balance N-1'!P:P) -> 0
A24: DI | B24: Provisions pour risques et charges à court terme | G24: 21 | H24: =SUMIF('Balance N'!B:B,499,'Balance N'!P:P)+SUMIF('Balance N'!B:B,599,'Balance N'!P:P) -> 0 | I24: =SUMIF('Balance N-1'!B:B,499,'Balance N-1'!P:P)+SUMIF('Balance N-1'!B:B,599,'Balance N-1'!P:P) -> 0
A25: DJ | B25: TOTAL PASSIF CIRCULANT | H25: =+SUM(H20:H24) -> 0 | I25: =+SUM(I20:I24) -> 0
A26: DW | B26: Banques, établissements financiers et crédits de trésorerie | G26: 12 | H26: =SUMIF('Balance N'!B:B,565,'Balance N'!P:P)+SUMIF('Balance N'!A:A,52,'Balance N'!P:P)+SUMIF('Balance N'!A:A,53,'Balance N'!P:P)+SUMIF('Balance N'!B:B,561,'Balance N'!P:P)+SUMIF('Balance N'!B:B,566,'Balance N'!P:P) -> 0 | I26: =SUMIF('Balance N-1'!B:B,565,'Balance N-1'!P:P)+SUMIF('Balance N-1'!A:A,52,'Balance N-1'!P:P)+SUMIF('Balance N-1'!A:A,53,'Balance N-1'!P:P)+SUMIF('Balance N-1'!B:B,561,'Balance N-1'!P:P)+SUMIF('Balance N-1'!B:B,566,'Balance N-1'!P:P) -> 0
A27: DX | B27: TOTAL TRESORERIE PASSIF | H27: =+SUM(H26) -> 0 | I27: =+SUM(I26) -> 0
A28: DY | B28: Ecart de conversion-Passif | G28: 7 | H28: =SUMIF('Balance N'!B:B,479,'Balance N'!P:P) -> 0 | I28: =SUMIF('Balance N-1'!B:B,479,'Balance N-1'!P:P) -> 0
A29: DZ | B29: TOTAL GENERAL | H29: =+SUM(H19+H25+H27-H28) -> 0 | I29: =+SUM(I19+I25+I27-I28) -> 0

Sheet Compte d'exploitation
A1: - 11 -
H2: COMPTE DE RESULTAT SYSTEME NORMAL PAGE 1/1
A3: Dénomination sociale de l'entité : | C3: =+'Bilan Passif'!C3 -> DSO Services
A4: Adresse : | C4: =+'Bilan Passif'!C4 -> Rue Alphamoi Djénèpo, secteur 01, Bobo-Dioulasso, Burkina Faso | H4: Sigle usuel : | I4: =+'Bilan Passif'!I4 -> DSO Services
A5: N° de compte contribuable (NCC) : | C5: =+'Bilan Passif'!C5 -> 00000101A | D5: Exercice clos le : | E5: =+'Bilan Passif'!F5 -> 45657 | H5: Durées (mois) : | I5: =+'Bilan Passif'!I5 -> 12
A6: N° de télédéclarant (NTD): | C6: =+'Bilan Passif'!C6 -> Néant
A8: =CONCATENATE("Compte d'exploitation au 31 Décembre"&" "&TEXT('INFORMATIONS GENERALES'!J13,"aaaa")) -> Compte d'exploitation au 31 Décembre 2024
A9: REF | B9: LIBELLES | G9: NOTE | H9: EXERCICE AU 31/12/N | I9: EXERCICE AU 31/12/N-1
H11: NET | I11: NET
A12: RA | B12: Fonds d'administration | C12: Fonds d'administration | D12: Fonds d'administration | E12: Fonds d'administration | F12: + | G12: 23 | H12: =(SUMIF('Balance N'!B:B,702,'Balance N'!P:P)-SUMIF('Balance N'!B:B,702,'Balance N'!O:O)) -> 0 | I12: =(SUMIF('Balance N-1'!B:B,702,'Balance N-1'!P:P)-SUMIF('Balance N-1'!B:B,702,'Balance N-1'!O:O)) -> 0
A13: RB | B13: Ventes de marchandises, produits finis et prestations de services | C13: Ventes de marchandises, produits finis et prestations de services | D13: Ventes de marchandises, produits finis et prestations de services | E13: Ventes de marchandises, produits finis et prestations de services | F13: + | G13: 23 | H13: =SUMIF('Balance N'!B:B,705,'Balance N'!P:P)-SUMIF('Balance N'!B:B,705,'Balance N'!O:O) -> 0 | I13: =SUMIF('Balance N-1'!B:B,705,'Balance N-1'!P:P)-SUMIF('Balance N-1'!B:B,705,'Balance N-1'!O:O) -> 0
A14: RC | B14: Subventions d'exploitations | C14: Subventions d'exploitations | D14: Subventions d'exploitations | E14: Subventions d'exploitations | F14: + | G14: 23 | H14: =SUMIF('Balance N'!A:A,71,'Balance N'!P:P)-SUMIF('Balance N'!A:A,71,'Balance N'!O:O) -> 0 | I14: =SUMIF('Balance N-1'!A:A,71,'Balance N-1'!P:P)-SUMIF('Balance N-1'!A:A,71,'Balance N-1'!O:O) -> 0
A15: RD | B15: Autres produits et transferts de charges | C15: Autres produits et transferts de charges | D15: Autres produits et transferts de charges | E15: Autres produits et transferts de charges | F15: + | G15: 23 | H15: =(SUMIF('Balance N'!B:B,707,'Balance N'!P:P)-(SUMIF('Balance N'!B:B,707,'Balance N'!O:O)))+(SUMIF('Balance N'!A:A,72,'Balance N'!P:P)-SUMIF('Balance N'!A:A,72,'Balance N'!O:O))+(SUMIF('Balance N'!A:A,73,'Balance N'!P:P)-SUMIF('Balance N'!A:A,73,'Balance N'!O:O))+(SUMIF('Balance N'!A:A,75,'Balance N'!P:P)-SUMIF('Balance N'!A:A,75,'Balance N'!O:O))+(SUMIF('Balance N'!A:A,77,'Balance N'!P:P)-SUMIF('Balance N'!A:A,77,'Balance N'!O:O))+(SUMIF('Balance N'!A:A,78,'Balance N'!P:P)-SUMIF('Balance N'!A:A,78,'Balance N'!O:O)) -> 0 | I15: =(SUMIF('Balance N-1'!B:B,707,'Balance N-1'!P:P)-(SUMIF('Balance N-1'!B:B,707,'Balance N-1'!O:O)))+(SUMIF('Balance N-1'!A:A,72,'Balance N-1'!P:P)-SUMIF('Balance N-1'!A:A,72,'Balance N-1'!O:O))+(SUMIF('Balance N-1'!A:A,73,'Balance N-1'!P:P)-SUMIF('Balance N-1'!A:A,73,'Balance N-1'!O:O))+(SUMIF('Balance N-1'!A:A,75,'Balance N-1'!P:P)-SUMIF('Balance N-1'!A:A,75,'Balance N-1'!O:O))+(SUMIF('Balance N-1'!A:A,77,'Balance N-1'!P:P)-SUMIF('Balance N-1'!A:A,77,'Balance N-1'!O:O))+(SUMIF('Balance N-1'!A:A,78,'Balance N-1'!P:P)-SUMIF('Balance N-1'!A:A,78,'Balance N-1'!O:O)) -> 0
A16: RE | B16: Reprises de provisions | C16: Reprises de provisions | D16: Reprises de provisions | E16: Reprises de provisions | F16: + | G16: 23 | H16: =SUMIF('Balance N'!B:B,791,'Balance N'!P:P)+SUMIF('Balance N'!B:B,792,'Balance N'!P:P)+SUMIF('Balance N'!B:B,795,'Balance N'!P:P)+SUMIF('Balance N'!B:B,796,'Balance N'!P:P)+SUMIF('Balance N'!B:B,797,'Balance N'!P:P)+SUMIF('Balance N'!B:B,798,'Balance N'!P:P)+SUMIF('Balance N'!B:B,799,'Balance N'!P:P) -> 0 | I16: =SUMIF('Balance N-1'!B:B,791,'Balance N-1'!P:P)+SUMIF('Balance N-1'!B:B,792,'Balance N-1'!P:P)+SUMIF('Balance N-1'!B:B,795,'Balance N-1'!P:P)+SUMIF('Balance N-1'!B:B,796,'Balance N-1'!P:P)+SUMIF('Balance N-1'!B:B,797,'Balance N-1'!P:P)+SUMIF('Balance N-1'!B:B,798,'Balance N-1'!P:P)+SUMIF('Balance N-1'!B:B,799,'Balance N-1'!P:P) -> 0
A17: XA | B17: REVENUS (Somme RA à RE) | H17: =+SUM(H12:H16) -> 0 | I17: =+SUM(I12:I16) -> 0
A18: TA | B18: Achats de biens, marchandises, matières premières et fournitures liées | C18: Achats de biens, marchandises, matières premières et fournitures liées | D18: Achats de biens, marchandises, matières premières et fournitures liées | E18: Achats de biens, marchandises, matières premières et fournitures liées | F18: + | G18: 24 | H18: =SUMIF('Balance N'!B:B,601,'Balance N'!O:O)+SUMIF('Balance N'!B:B,602,'Balance N'!O:O) -> 0 | I18: =SUMIF('Balance N-1'!B:B,601,'Balance N-1'!O:O)+SUMIF('Balance N-1'!B:B,602,'Balance N-1'!O:O) -> 0
A19: TB | B19: Autres achats | C19: Autres achats | D19: Autres achats | E19: Autres achats | F19: + | H19: =SUMIF('Balance N'!B:B,604,'Balance N'!O:O)+SUMIF('Balance N'!B:B,605,'Balance N'!O:O)+SUMIF('Balance N'!B:B,606,'Balance N'!O:O)+SUMIF('Balance N'!B:B,608,'Balance N'!O:O) -> 0 | I19: =SUMIF('Balance N-1'!B:B,604,'Balance N-1'!O:O)+SUMIF('Balance N-1'!B:B,605,'Balance N-1'!O:O)+SUMIF('Balance N-1'!B:B,606,'Balance N-1'!O:O)+SUMIF('Balance N-1'!B:B,608,'Balance N-1'!O:O) -> 0
A20: TC | B20: Variation de stocks de biens, marchandises, matières premières et fournitures et autres | C20: Variation de stocks de biens, marchandises, matières premières et fournitures et autres | D20: Variation de stocks de biens, marchandises, matières premières et fournitures et autres | E20: Variation de stocks de biens, marchandises, matières premières et fournitures et autres | F20: (+ / -) | G20: 24 | H20: =(SUMIF('Balance N'!B:B,603,'Balance N'!O:O)-SUMIF('Balance N'!B:B,603,'Balance N'!P:P)) -> 0 | I20: =(SUMIF('Balance N-1'!B:B,603,'Balance N-1'!O:O)-SUMIF('Balance N-1'!B:B,603,'Balance N-1'!P:P)) -> 0
A21: TD | B21: Transports | C21: Transports | D21: Transports | E21: Transports | F21: + | H21: =SUMIF('Balance N'!A:A,61,'Balance N'!O:O) -> 0 | I21: =SUMIF('Balance N-1'!A:A,61,'Balance N-1'!O:O) -> 0
A22: TG | B22: Services extérieurs | C22: Services extérieurs | D22: Services extérieurs | E22: Services extérieurs | F22: + | H22: =SUMIF('Balance N'!A:A,62,'Balance N'!O:O)+SUMIF('Balance N'!A:A,63,'Balance N'!O:O) -> 0 | I22: =SUMIF('Balance N-1'!A:A,62,'Balance N-1'!O:O)+SUMIF('Balance N-1'!A:A,63,'Balance N-1'!O:O) -> 0
A23: TH | B23: Impôts et taxes | C23: Impôts et taxes | D23: Impôts et taxes | E23: Impôts et taxes | F23: + | H23: =SUMIF('Balance N'!A:A,64,'Balance N'!O:O) -> 0 | I23: =SUMIF('Balance N-1'!A:A,64,'Balance N-1'!O:O) -> 0
A24: TI | B24: Autres charges | C24: Autres charges | D24: Autres charges | E24: Autres charges | F24: + | H24: =SUMIF('Balance N'!A:A,65,'Balance N'!O:O) -> 0 | I24: =SUMIF('Balance N-1'!A:A,65,'Balance N-1'!O:O) -> 0
A25: TJ | B25: Charges de personnel | C25: Charges de personnel | D25: Charges de personnel | E25: Charges de personnel | F25: + | H25: =SUMIF('Balance N'!A:A,66,'Balance N'!O:O)+SUMIF('Balance N'!A:A,66,'Balance N'!P:P) -> 0 | I25: =SUMIF('Balance N-1'!A:A,66,'Balance N-1'!O:O)+SUMIF('Balance N-1'!A:A,66,'Balance N-1'!P:P) -> 0
A26: TK | B26: Frais financiers et charges assimilées | C26: Frais financiers et charges assimilées | D26: Frais financiers et charges assimilées | E26: Frais financiers et charges assimilées | F26: + | H26: =SUMIF('Balance N'!A:A,67,'Balance N'!O:O) -> 0 | I26: =SUMIF('Balance N-1'!A:A,67,'Balance N-1'!O:O) -> 0
A27: TJ | B27: Dotations aux provisions | C27: Dotations aux provisions | D27: Dotations aux provisions | E27: Dotations aux provisions | F27: + | H27: =SUMIF('Balance N'!A:A,69,'Balance N'!O:O) -> 0 | I27: =SUMIF('Balance N-1'!A:A,69,'Balance N-1'!O:O) -> 0
A28: TK | B28: Produits H.A.O. | C28: Produits H.A.O. | D28: Produits H.A.O. | E28: Produits H.A.O. | F28: - | H28: =SUMIF('Balance N'!A:A,82,'Balance N'!P:P)+SUMIF('Balance N'!A:A,84,'Balance N'!P:P)+SUMIF('Balance N'!A:A,86,'Balance N'!P:P)+SUMIF('Balance N'!A:A,88,'Balance N'!P:P) -> 0 | I28: =+SUMIF('Balance N-1'!A:A,82,'Balance N-1'!P:P)+SUMIF('Balance N-1'!A:A,84,'Balance N-1'!P:P)+SUMIF('Balance N-1'!A:A,86,'Balance N-1'!P:P)+SUMIF('Balance N-1'!A:A,88,'Balance N-1'!P:P) -> 0
A29: TL | B29: Charges H.A.O. | C29: Charges H.A.O. | D29: Charges H.A.O. | E29: Charges H.A.O. | F29: + | H29: =SUMIF('Balance N'!A:A,81,'Balance N'!O:O)+SUMIF('Balance N'!A:A,83,'Balance N'!O:O)+SUMIF('Balance N'!A:A,85,'Balance N'!O:O)+(SUMIF('Balance N'!A:A,87,'Balance N'!O:O)-SUMIF('Balance N'!A:A,87,'Balance N'!P:P)) -> 0 | I29: =SUMIF('Balance N-1'!A:A,81,'Balance N-1'!O:O)+SUMIF('Balance N-1'!A:A,83,'Balance N-1'!O:O)+SUMIF('Balance N-1'!A:A,85,'Balance N-1'!O:O)+(SUMIF('Balance N-1'!A:A,87,'Balance N-1'!O:O)-SUMIF('Balance N-1'!A:A,87,'Balance N-1'!P:P)) -> 0
A30: XB | B30: CHARGES DE FONCTIONNEMENT ( Somme TA àTL) | C30: CHARGES DE FONCTIONNEMENT ( Somme TA àTL) | D30: CHARGES DE FONCTIONNEMENT ( Somme TA àTL) | E30: CHARGES DE FONCTIONNEMENT ( Somme TA àTL) | F30: CHARGES DE FONCTIONNEMENT ( Somme TA àTL) | G30: CHARGES DE FONCTIONNEMENT ( Somme TA àTL) | H30: =SUM(H18:H27)+H29-H28 -> 0 | I30: =SUM(I18:I27)+I29-I28 -> 0
A31: XC | B31: RESULTAT DES ACTIVITES ORDINAIRES (XA-XB) | H31: =H17-H30 -> 0 | I31: =I17-I30 -> 0
A32: TM
A33: TN
A34: XD
A35: XC

Sheet FICHE R3
A1: - 12 -
I2: FICHE R3
A3: Dénomination sociale de l'entité : | C3: =+'Compte d''exploitation'!C3 -> DSO Services
A4: Adresse : | C4: =+'Compte d''exploitation'!C4 -> Rue Alphamoi Djénèpo, secteur 01, Bobo-Dioulasso, Burkina Faso | H4: Sigle usuel : | I4: =+'Compte d''exploitation'!I4 -> DSO Services
A5: N° de compte contribuable (NCC) : | C5: =+'Compte d''exploitation'!C5 -> 00000101A | E5: Exercice clos le : | F5: =+'Compte d''exploitation'!E5 -> 45657 | H5: Durée (en mois) : | I5: =+'Compte d''exploitation'!I5 -> 12
A6: N° de télédéclarant (NTD): | C6: =+'Compte d''exploitation'!C6 -> Néant
A7: FICHE RECAPITULATIVE DES NOTES ANNEXES PRESENTEES
A8: NOTES | B8: INTITULES | I8: A | J8: N/A
A9: Partie 1 : Informations générales
A10: Note 1 | B10: Informations obligatoires
A11: Partie 2 : Notes sur le : Tableau emplois-ressources, Tableau d'exécution budgétaire, Tableau de reconciliation de trésorerie
A12: Note 2 | B12: Informations spécifiques
A13: Partie 3 : Notes sur le bilan
A14: Note 3A | B14: Immobilisations brutes
A15: Note 3B | B15: Biens pris en location - acquisition
A16: Note 4 | B16: Actif circulant et dettes circulantes HAO
A17: Note 5 | B17: Stocks et encours
A18: Note 6 | B18: Clients-usagers et autres créances
A19: Note 7 | B19: Disponibilités
A20: Note 8 | B20: Ecarts de conversion
A21: Note 9 | B21: Fonds du bailleur
A22: Note 10 | B22: Subventions
A23: Note 11 | B23: Dettes financières et ressources assimilées
A24: Note 12 | B24: Dettes fournisseurs et assimilées, dettes fiscales et sociales
A25: Note 13 | B25: Banques, crédit d'escompte et de trésorerie
A26: Partie 4 : Notes sur le Compte d'exploitation
A27: Note 14 | B27: Revenus et autres produits
A28: Note 15 | B28: Achats
A29: Note 16 | B29: Transports
A30: Note 17 | B30: Services extérieurs
A31: Note 18 | B31: Impôts et taxes
A32: Note 19 | B32: Autres charges
A33: Note 20A | B33: Charges de personnel
A34: Note 20B | B34: Effectifs, masse salariale et personnel extérieur
A35: Note 21 | B35: Charges et revenus financiers
A36: Note 22 | B36: Dotations et charges pour provisions
A37: Note 23 | B37: Autres charges et produits HAO
A38: Note 24 | B38: Tableau d'exécution budgétaire
A39: (1) les notes non documentées ne doivent pas être jointes aux états financiers.
A40: Leur contenu peut être amélioré par les entités par ailleurs, dans une note, les lignes non chiffrées doivent être supprimées. Par exemple, dans la note 17 services extérieurs,
A41: lorsque la ligne sous-traitance générale n’est pas chiffrée, elle ne doit pas figurer dans cette note.
A42: A : Applicable N/A : Non applicable.
A43: Par exemple pour une entité qui n’a pas de stocks et en-cours, elle doit cocher à l’intersection (ligne ‘’NOTE’’ 5 & ‘’colonne N/A’’)

Sheet NOTE 1
A1: - 13 -
H2: NOTE 1 SYSTEME NORMAL
A3: Dénomination sociale de l'entité : | C3: =+'FICHE R3'!C3 -> DSO Services
A4: Adresse : | C4: =+'FICHE R3'!C4 -> Rue Alphamoi Djénèpo, secteur 01, Bobo-Dioulasso, Burkina Faso | H4: Sigle usuel : | I4: =+'FICHE R3'!I4 -> DSO Services
A5: N° de compte contribuable (NCC) : | C5: =+'FICHE R3'!C5 -> 00000101A | F5: Exercice clos le : | G5: =+'FICHE R3'!F5 -> 45657 | H5: Durée (en mois) : | I5: =+'FICHE R3'!I5 -> 12
A6: N° de télédéclarant (NTD): | C6: =+'FICHE R3'!C6 -> Néant
A7: NOTE 1: INFORMATIONS OBLIGATOIRES | K7: #NAME?
A8: A - IDENTITE, ORGANISATION (2000 caractères maximum)
A9: L’entité doit :
A10: - Décrire brièvement l’identité de l’entité (date de début du projet, nature du projet de développement, activité ou mission réalisée)
A11: - Décrire brièvement l’organisation de l’entité avec des données chiffrées (effectifs, total des ressources affectées au projet, moyens utilisés)
A17: B - DECLARATION DE CONFORMITE AU SYSTÈME COMPTABLE DES ENTITES A BUT NON LUCRATIF ET FAITS MARQUANTS DE L'EXERCICE (2000 caractères maximum)
A19: C- REGLES, METHODES COMPTABLES ET DEROGATION AUX PRINCIPES COMPTABLES (2000 caractères maximum)
A21: D - INFORMATIONS COMPLEMENTAIRES RELATIVES AU BILAN ET AU COMPTES D’EXPLOITATION (2000 caractères maximum)
A24: Commentaire :
A25: · Seuls les éléments ayants une incidence comptable significative ou qui nuisent à la comparabilité des exercices doivent être mentionné (par exemples : des modifications significatives concernant une convention avec un bailleur…)
A26: · Décrire les règles et méthodes utilisées pour l’établissement des états financiers

Sheet NOTE 2
A1: - 14 -
H2: NOTE 2 SYSTEME NORMAL
A3: Dénomination sociale de l'entité : | C3: =+'NOTE 1'!C3 -> DSO Services
A4: Adresse : | C4: =+'NOTE 1'!C4 -> Rue Alphamoi Djénèpo, secteur 01, Bobo-Dioulasso, Burkina Faso | H4: Sigle usuel : | I4: =+'NOTE 1'!I4 -> DSO Services
A5: N° de compte contribuable (NCC) : | C5: =+'NOTE 1'!C5 -> 00000101A | E5: Exercice clos le : | F5: =+'NOTE 1'!G5 -> 45657 | H5: Durée (en mois) : | I5: =+'NOTE 1'!I5 -> 12
A6: N° de télédéclarant (NTD): | C6: =+'NOTE 1'!C6 -> Néant
A7: NOTE 2 : INFORMATIONS SPECIFIQUES
A8: A- TABLEAU EMPLOIS RESSOURCES
A16: B- TABLEAU D'EXECUTION BUGETAIRE
A24: C- TABLEAU DE RECONCILIATION DE TRESORERIE
A33: Commentaire :
A34: · Indiquer les frais marquants pour chaque état financier ;
A35: · Expliquer les écarts significatifs entre budget et réalisation du tableau d’exécution budgétaire

Sheet NOTE 3A
A1: - 15 -
I2: NOTE 3A SYSTEME NORMAL
A3: Dénomination sociale de l'entité : | C3: =+'NOTE 2'!C3 -> DSO Services | K3: NB: Certaines rubriques de cette pages seront, selon les cas, renseignées mannuellement.
A4: Adresse : | C4: =+'NOTE 2'!C4 -> Rue Alphamoi Djénèpo, secteur 01, Bobo-Dioulasso, Burkina Faso | I4: Sigle usuel : | J4: =+'NOTE 2'!I4 -> DSO Services
A5: N° d'identification fiscale : | C5: =+'NOTE 2'!C5 -> 00000101A | F5: Exercice clos le : | G5: =+'NOTE 2'!F5 -> 45657 | I5: Durée (en mois) : | J5: =+'NOTE 2'!I5 -> 12
A6: N° de télédéclarant (NTD): | C6: =+'NOTE 2'!C6 -> Néant
A7: NOTE 3A : IMMOBILISATIONS (BRUTES) | L7: 1
A8: SITUATIONS ET MOUVEMENTS | D8: A | E8: AUGMENTATIONS B | H8: DIMINUTIONS C | J8: D = A + B - C
D9: MONTANT BRUT A L'OUVERTURE DE L'EXERCICE | E9: Acquisitions Apports Créations | F9: Virements de poste à poste | G9: Suite à une réévaluation pratiquée au cours de l'exercice | H9: Cessions Scissions Hors service | I9: Virements de poste à poste | J9: MONTANT BRUT A LA CLOTURE DE L'EXERCICE
A10: RUBRIQUES
A11: IMMOBILISATIONS INCORPORELLES | D11: =SUM(D12:D14) -> 0 | E11: =SUM(E12:E14) -> 0 | F11: =SUM(F12:F14) -> 0 | G11: =SUM(G12:G14) -> 0 | H11: =SUM(H12:H14) -> 0 | I11: =SUM(I12:I14) -> 0 | J11: =SUM(J12:J14) -> 0
A12: Brevets, licences, logiciels, et droits similaires | D12: =SUMIF('Balance N'!B:B,212,'Balance N'!K:K) -> 0 | E12: =SUMIF('Balance N'!B:B,212,'Balance N'!M:M)-G12 -> 0 | H12: =SUMIF('Balance N'!B:B,212,'Balance N'!N:N) -> 0 | J12: =(D12+E12+F12+G12)-(H12+I12) -> 0
A13: Avances et acomptes sur immobilisations incorporelles | B13: Avances et acomptes sur immobilisations incorporelles | C13: Avances et acomptes sur immobilisations incorporelles | D13: =SUMIF('Balance N'!B:B,213,'Balance N'!K:K)+SUMIF('Balance N'!B:B,214,'Balance N'!K:K) -> 0 | E13: =SUMIF('Balance N'!B:B,213,'Balance N'!M:M)+SUMIF('Balance N'!B:B,214,'Balance N'!M:M)-G13 -> 0 | H13: =SUMIF('Balance N'!B:B,213,'Balance N'!N:N)+SUMIF('Balance N'!B:B,214,'Balance N'!N:N) -> 0 | J13: =(D13+E13+F13+G13)-(H13+I13) -> 0
A14: Autres immobilisations incorporelles | B14: Autres immobilisations incorporelles | C14: Autres immobilisations incorporelles | D14: =SUMIF('Balance N'!B:B,218,'Balance N'!K:K)+SUMIF('Balance N'!B:B,219,'Balance N'!K:K) -> 0 | E14: =SUMIF('Balance N'!B:B,218,'Balance N'!M:M)+SUMIF('Balance N'!B:B,219,'Balance N'!M:M)-G14 -> 0 | H14: =SUMIF('Balance N'!B:B,218,'Balance N'!N:N)+SUMIF('Balance N'!B:B,219,'Balance N'!N:N) -> 0 | J14: =(D14+E14+F14+G14)-(H14+I14) -> 0
A15: IMMOBILISATIONS CORPORELLES | D15: =SUM(D16:D22) -> 0 | E15: =SUM(E16:E22) -> 0 | F15: =SUM(F16:F22) -> 0 | G15: =SUM(G16:G22) -> 0 | H15: =SUM(H16:H22) -> 0 | I15: =SUM(I16:I22) -> 0 | J15: =SUM(J16:J22) -> 0
A16: Terrains hors immeuble de placement | B16: Terrains hors immeuble de placement | C16: Terrains hors immeuble de placement | D16: =SUMIF('Balance N'!A:A,22,'Balance N'!K:K)-(SUMIF('Balance N'!C:C,2281,'Balance N'!K:K)) -> 0 | E16: =(SUMIF('Balance N'!A:A,22,'Balance N'!M:M)-(SUMIF('Balance N'!C:C,2281,'Balance N'!M:M))-G16) -> 0 | H16: =(SUMIF('Balance N'!A:A,22,'Balance N'!N:N)-(SUMIF('Balance N'!C:C,2281,'Balance N'!N:N))) -> 0 | J16: =(D16+E16+F16+G16)-(H16+I16) -> 0
A17: Terrains-immeuble de placement | B17: Terrains-immeuble de placement | C17: Terrains-immeuble de placement | D17: =SUMIF('Balance N'!C:C,2281,'Balance N'!K:K) -> 0 | E17: =(SUMIF('Balance N'!C:C,2281,'Balance N'!M:M))-G17 -> 0 | H17: =(SUMIF('Balance N'!C:C,2281,'Balance N'!N:N)) -> 0 | J17: =(D17+E17+F17+G17)-(H17+I17) -> 0
A18: Bâtiments hors immeubles de placement | B18: Bâtiments hors immeubles de placement | C18: Bâtiments hors immeubles de placement | D18: =(SUMIF('Balance N'!B:B,231,'Balance N'!K:K)+SUMIF('Balance N'!B:B,232,'Balance N'!K:K)+SUMIF('Balance N'!B:B,233,'Balance N'!K:K)+SUMIF('Balance N'!C:C,2391,'Balance N'!K:K)+SUMIF('Balance N'!C:C,2921,'Balance N'!K:K)+SUMIF('Balance N'!C:C,2393,'Balance N'!K:K)+SUMIF('Balance N'!C:C,2396,'Balance N'!K:K))-(SUMIF('Balance N'!C:C,2315,'Balance N'!K:K)+SUMIF('Balance N'!C:C,2325,'Balance N'!K:K)) -> 0 | E18: =(SUMIF('Balance N'!B:B,231,'Balance N'!M:M)+SUMIF('Balance N'!B:B,232,'Balance N'!M:M)+SUMIF('Balance N'!B:B,233,'Balance N'!M:M)+SUMIF('Balance N'!C:C,2391,'Balance N'!M:M)+SUMIF('Balance N'!C:C,2921,'Balance N'!M:M)+SUMIF('Balance N'!C:C,2393,'Balance N'!M:M)+SUMIF('Balance N'!C:C,2396,'Balance N'!M:M))-(SUMIF('Balance N'!C:C,2315,'Balance N'!M:M)+SUMIF('Balance N'!C:C,2325,'Balance N'!M:M))-G18 -> 0 | H18: =(SUMIF('Balance N'!B:B,231,'Balance N'!N:N)+SUMIF('Balance N'!B:B,232,'Balance N'!N:N)+SUMIF('Balance N'!B:B,233,'Balance N'!N:N)+SUMIF('Balance N'!C:C,2391,'Balance N'!N:N)+SUMIF('Balance N'!C:C,2921,'Balance N'!N:N)+SUMIF('Balance N'!C:C,2393,'Balance N'!N:N)+SUMIF('Balance N'!C:C,2396,'Balance N'!N:N))-(SUMIF('Balance N'!C:C,2315,'Balance N'!N:N)+SUMIF('Balance N'!C:C,2325,'Balance N'!N:N)) -> 0 | J18: =(D18+E18+F18+G18)-(H18+I18) -> 0
A19: Bâtiments-immeuble de placement | B19: Bâtiments-immeuble de placement | C19: Bâtiments-immeuble de placement | D19: =(SUMIF('Balance N'!C:C,2315,'Balance N'!K:K)+SUMIF('Balance N'!C:C,2325,'Balance N'!K:K)) -> 0 | E19: =(SUMIF('Balance N'!C:C,2315,'Balance N'!M:M)+SUMIF('Balance N'!C:C,2325,'Balance N'!M:M))-G19 -> 0 | H19: =(SUMIF('Balance N'!C:C,2315,'Balance N'!N:N)+SUMIF('Balance N'!C:C,2325,'Balance N'!N:N)) -> 0 | J19: =(D19+E19+F19+G19)-(H19+I19) -> 0
A20: Aménagement, agencements et installations | B20: Aménagement, agencements et installations | C20: Aménagement, agencements et installations | D20: =SUMIF('Balance N'!B:B,234,'Balance N'!K:K)+SUMIF('Balance N'!B:B,235,'Balance N'!K:K)+SUMIF('Balance N'!B:B,238,'Balance N'!K:K)+SUMIF('Balance N'!C:C,2394,'Balance N'!K:K)+SUMIF('Balance N'!C:C,2395,'Balance N'!K:K)+SUMIF('Balance N'!C:C,2398,'Balance N'!K:K) -> 0 | E20: =SUMIF('Balance N'!B:B,234,'Balance N'!M:M)+SUMIF('Balance N'!B:B,235,'Balance N'!M:M)+SUMIF('Balance N'!B:B,238,'Balance N'!M:M)+SUMIF('Balance N'!C:C,2394,'Balance N'!M:M)+SUMIF('Balance N'!C:C,2395,'Balance N'!M:M)+SUMIF('Balance N'!C:C,2398,'Balance N'!M:M)-G20 -> 0 | H20: =SUMIF('Balance N'!B:B,234,'Balance N'!N:N)+SUMIF('Balance N'!B:B,235,'Balance N'!N:N)+SUMIF('Balance N'!B:B,238,'Balance N'!N:N)+SUMIF('Balance N'!C:C,2394,'Balance N'!N:N)+SUMIF('Balance N'!C:C,2395,'Balance N'!N:N)+SUMIF('Balance N'!C:C,2398,'Balance N'!N:N) -> 0 | J20: =(D20+E20+F20+G20)-(H20+I20) -> 0
A21: Matériel, mobilier et actifs biologiques | B21: Matériel, mobilier et actifs biologiques | C21: Matériel, mobilier et actifs biologiques | D21: =SUMIF('Balance N'!A:A,24,'Balance N'!K:K)-SUMIF('Balance N'!B:B,245,'Balance N'!K:K)-SUMIF('Balance N'!C:C,2495,'Balance N'!K:K) -> 0 | E21: =SUMIF('Balance N'!A:A,24,'Balance N'!M:M)-SUMIF('Balance N'!B:B,245,'Balance N'!M:M)-SUMIF('Balance N'!C:C,2495,'Balance N'!M:M)-G21 -> 0 | H21: =SUMIF('Balance N'!A:A,24,'Balance N'!N:N)-SUMIF('Balance N'!B:B,245,'Balance N'!N:N)-SUMIF('Balance N'!C:C,2495,'Balance N'!N:N) -> 0 | J21: =(D21+E21+F21+G21)-(H21+I21) -> 0
A22: Matériel de transport | B22: Matériel de transport | C22: Matériel de transport | D22: =SUMIF('Balance N'!B:B,245,'Balance N'!K:K)+SUMIF('Balance N'!C:C,2495,'Balance N'!K:K) -> 0 | E22: =(SUMIF('Balance N'!B:B,245,'Balance N'!M:M)+SUMIF('Balance N'!C:C,2495,'Balance N'!M:M))-G22 -> 0 | H22: =(SUMIF('Balance N'!B:B,245,'Balance N'!N:N)+SUMIF('Balance N'!C:C,2495,'Balance N'!N:N)) -> 0 | J22: =(D22+E22+F22+G22)-(H22+I22) -> 0
A23: Avance et acomptes sur les immobilisations corporelles | B23: Avance et acomptes sur les immobilisations corporelles | C23: Avance et acomptes sur les immobilisations corporelles
A24: IMMOBILISATIONS FINANCIERES | D24: =SUM(D25:D26) -> 0 | E24: =SUM(E25:E26) -> 0 | F24: =SUM(F25:F26) -> 0 | G24: =SUM(G25:G26) -> 0 | H24: =SUM(H25:H26) -> 0 | I24: =SUM(I25:I26) -> 0 | J24: =SUM(J25:J26) -> 0
A25: Dépôts et cautionnement | B25: Dépôts et cautionnement | C25: Dépôts et cautionnement | D25: =SUMIF('Balance N'!A:A,26,'Balance N'!K:K) -> 0 | E25: =SUMIF('Balance N'!A:A,26,'Balance N'!M:M)-G25 -> 0 | H25: =SUMIF('Balance N'!A:A,26,'Balance N'!N:N) -> 0 | J25: =(D25+E25+F25+G25)-(H25+I25) -> 0
A26: Autres immobilisations financières | B26: Autres immobilisations financières | C26: Autres immobilisations financières | D26: =SUMIF('Balance N'!A:A,27,'Balance N'!K:K) -> 0 | E26: =SUMIF('Balance N'!A:A,27,'Balance N'!M:M)-G26 -> 0 | H26: =SUMIF('Balance N'!A:A,27,'Balance N'!N:N) -> 0 | J26: =(D26+E26+F26+G26)-(H26+I26) -> 0
A27: TOTAL GENERAL | D27: =D11+D15+D24 -> 0 | E27: =E11+E15+E24 -> 0 | F27: =F11+F15+F24 -> 0 | G27: =G11+G15+G24 -> 0 | H27: =H11+H15+H24 -> 0 | I27: =I11+I15+I24 -> 0 | J27: =J11+J15+J24 -> 0
A28: Commentaire :
A29: ● Toute variation significative doit être commentée. | E29: ● Indiquer les créances du groupe avec nature et date d'échéance.
A30: ● Détailler les éléments constitutifs du fonds commercial et indiquer la date d'acquisition. | E30: ● Pour les banques, DAT indiquer le nom de la banque le montant et la date d'échéance.
A31: ● Pour l'immobilisation incorporelle relative à la concession faire un descriptif de l'accord. | E31: ● Pour les frais de développement, donner toutes les informations mentionnées dans la partie Opérations et problèmes spécifiques.
A32: ● Indiquer : | E32: ● Donner le détail des produits et charges liés aux immeubles de placement.
A33: - la nature de la créance ;
A34: - la durée de la concession ;
A35: - l'échéance.

Sheet NOTE 3B
A1: - 16 -
K2: NOTE 3B SYSTEME NORMAL
A3: Dénomination sociale de l'entité : | C3: =+'NOTE 3A'!C3 -> DSO Services | M3: NB: Certaines rubriques de cette pages seront, selon les cas, renseignées mannuellement.
A4: Adresse : | C4: =+'NOTE 3A'!C4 -> Rue Alphamoi Djénèpo, secteur 01, Bobo-Dioulasso, Burkina Faso | K4: Sigle usuel : | L4: =+'NOTE 3A'!J4 -> DSO Services
A5: N° d'identification fiscale : | C5: =+'NOTE 3A'!C5 -> 00000101A | H5: Exercice clos le : | I5: =+'NOTE 3A'!G5 -> 45657 | K5: Durée (en mois) : | L5: =+'NOTE 3A'!J5 -> 12 | M5: Vous aurez à repartir les montants dans les rubriques adequates
A6: N° de télédéclarant (NTD): | C6: =+'NOTE 3A'!C6 -> Néant
A7: NOTE 3B : BIENS PRIS EN LOCATION - ACQUISITION | N7: 0
A8: SITUATIONS ET MOUVEMENTS | F8: A | G8: AUGMENTATIONS B | J8: DIMINUTIONS C | L8: D = A + B - C
E9: NATURE DU CONTRAT (I ; M ; A) [1] | F9: MONTANT BRUT A L'OUVERTURE DE L'EXERCICE | G9: Acquisitions Apports Créations | H9: Virements de poste à poste | I9: Suite à une réévaluation pratiquée au cours de l'exercice | J9: Cessions Scissions Hors service | K9: Virements de poste à poste | L9: MONTANT BRUT A LA CLOTURE DE L'EXERCICE
A10: RUBRIQUES
A11: Terrains | F11: =SUMIF('Balance N'!C:C,2286,'Balance N'!K:K) -> 0 | G11: =SUMIF('Balance N'!C:C,2286,'Balance N'!M:M) -> 0 | J11: =SUMIF('Balance N'!C:C,2286,'Balance N'!N:N) -> 0 | L11: =(F11+G11+H11+I11)-(J11+K11) -> 0
A12: Bâtiments | F12: =SUMIF('Balance N'!C:C,2316,'Balance N'!K:K)+SUMIF('Balance N'!C:C,2326,'Balance N'!K:K) -> 0 | G12: =SUMIF('Balance N'!C:C,2316,'Balance N'!M:M)+SUMIF('Balance N'!C:C,2326,'Balance N'!M:M) -> 0 | J12: =SUMIF('Balance N'!C:C,2316,'Balance N'!N:N)+SUMIF('Balance N'!C:C,2326,'Balance N'!N:N) -> 0 | L12: =(F12+G12+H12+I12)-(J12+K12) -> 0
A13: Matériel, mobilier | F13: =SUMIF('Balance N'!C:C,2416,'Balance N'!K:K)+SUMIF('Balance N'!C:C,2426,'Balance N'!K:K)+SUMIF('Balance N'!C:C,2446,'Balance N'!K:K) -> 0 | G13: =SUMIF('Balance N'!C:C,2416,'Balance N'!M:M)+SUMIF('Balance N'!C:C,2426,'Balance N'!M:M)+SUMIF('Balance N'!C:C,2446,'Balance N'!M:M) -> 0 | J13: =SUMIF('Balance N'!C:C,2416,'Balance N'!N:N)+SUMIF('Balance N'!C:C,2426,'Balance N'!N:N)+SUMIF('Balance N'!C:C,2446,'Balance N'!N:N) -> 0 | L13: =(F13+G13+H13+I13)-(J13+K13) -> 0
A14: Matériel de transport | F14: =SUMIF('Balance N'!C:C,2456,'Balance N'!K:K) -> 0 | G14: =SUMIF('Balance N'!C:C,2456,'Balance N'!M:M) -> 0 | J14: =SUMIF('Balance N'!C:C,2456,'Balance N'!N:N) -> 0 | L14: =(F14+G14+H14+I14)-(J14+K14) -> 0
A15: TOTAL IMMOBILISATIONS EN LOCATION-ACQUISITION | F15: =SUM(F11:F14) -> 0 | G15: =SUM(G11:G14) -> 0 | H15: =SUM(H11:H14) -> 0 | I15: =SUM(I11:I14) -> 0 | J15: =SUM(J11:J14) -> 0 | K15: =SUM(K11:K14) -> 0 | L15: =SUM(L11:L14) -> 0
A16: [1] I : Crédit-bail immobilier ; M : Crédit-bail mobilier ; A : Autres contrats (dédoubler le poste si montants
A17: Commentaire:
A18: ● Indiquer la nature du bien, le nom du bailleur et la durée du bail.

Sheet NOTE 4
A1: - 17 -
H2: NOTE 4 SYSTEME NORMAL
A3: Dénomination sociale de l'entité : | C3: =+'NOTE 3B'!C3 -> DSO Services
A4: Adresse : | C4: =+'NOTE 3B'!C4 -> Rue Alphamoi Djénèpo, secteur 01, Bobo-Dioulasso, Burkina Faso | H4: Sigle usuel : | I4: =+'NOTE 3B'!L4 -> DSO Services
A5: N° d'identification fiscale : | C5: =+'NOTE 3B'!C5 -> 00000101A | E5: Exercice clos le : | F5: =+'NOTE 3B'!I5 -> 45657 | H5: Durée (en mois) : | I5: =+'NOTE 3B'!L5 -> 12
A6: N° de télédéclarant (NTD): | C6: =+'NOTE 3B'!C6 -> Néant
A7: NOTE 4 : ACTIF CIRCULANT ET DETTES CIRCULANTES HAO | K7: 1
A8: ACTIF CIRCULANT HAO
A9: Libellés | E9: Année N | G9: Année N-1 | I9: Variation en %
A10: Créances sur cessions d'immobilisations | E10: =SUMIF('Balance N'!B:B,485,'Balance N'!O:O) -> 0 | G10: =SUMIF('Balance N-1'!B:B,485,'Balance N-1'!O:O) -> 0 | I10: =IF(G10<>0,(E10-G10)/(G10),0) -> 0
A11: Autres créances hors activités ordinaires | E11: =SUMIF('Balance N'!B:B,488,'Balance N'!O:O) -> 0 | G11: =SUMIF('Balance N-1'!B:B,488,'Balance N-1'!O:O) -> 0 | I11: =IF(G11<>0,(E11-G11)/(G11),0) -> 0
A12: TOTAL BRUT | E12: =SUM(E10:F11) -> 0 | G12: =SUM(G10:H11) -> 0 | I12: -0.89786756
A13: Dépréciations des créances HAO | E13: =SUMIF('Balance N'!B:B,498,'Balance N'!O:O) -> 0 | G13: =SUMIF('Balance N-1'!B:B,498,'Balance N-1'!O:O) -> 0 | I13: =IF(G13<>0,(E13-G13)/(G13),0) -> 0
A14: TOTAL NET DE DEPRECIATIONS | E14: =E12-E13 -> 0 | G14: =G12-G13 -> 0 | I14: =I12-I13 -> -0.89786756
A15: Commentaire:
A16: • Commenter toute variation significative.
A17: • Dépréciation : indiquer les évènements et les circonstances qui ont motivé la dépréciation ou la reprise.
A19: DETTES CIRCULANTES HAO
A21: Libellés | E21: Année N | G21: Année N-1 | I21: Variation en %
A22: Fournisseurs d'investissements | E22: =SUMIF('Balance N'!B:B,481,'Balance N'!P:P)-SUMIF('Balance N'!C:C,4813,'Balance N'!P:P) -> 0 | G22: =SUMIF('Balance N-1'!B:B,481,'Balance N-1'!P:P)-SUMIF('Balance N-1'!C:C,4813,'Balance N-1'!P:P) -> 0 | I22: =IF(G22<>0,(E22-G22)/(G22),0) -> 0
A23: Autres dettes hors activités ordinaires | E23: =SUMIF('Balance N'!B:B,484,'Balance N'!P:P) -> 0 | G23: =SUMIF('Balance N-1'!B:B,484,'Balance N-1'!P:P) -> 0 | I23: =IF(G23<>0,(E23-G23)/(G23),0) -> 0
A24: TOTAL | E24: =SUM(E22:F23) -> 0 | G24: =SUM(G22:H23) -> 0 | I24: 0
A25: Commentaire:
A26: ● Indiquer la date de cession et la nature de l'immobilisation achetée et/ou cédée.
A27: ● Expliciter toute variation significative.

Sheet NOTE 5
A1: - 18 -
I2: NOTE 5 SYSTEME NORMAL
A3: Dénomination sociale de l'entité : | C3: =+'NOTE 4'!C3 -> DSO Services
A4: Adresse : | C4: =+'NOTE 4'!C4 -> Rue Alphamoi Djénèpo, secteur 01, Bobo-Dioulasso, Burkina Faso | I4: Sigle usuel : | J4: =+'NOTE 4'!I4 -> DSO Services
A5: N° d'identification fiscale : | C5: =+'NOTE 4'!C5 -> 00000101A | E5: Exercice clos le : | F5: =+'NOTE 4'!F5 -> 45657 | I5: Durée (en mois) : | J5: =+'NOTE 4'!I5 -> 12
A6: N° de télédéclarant (NTD): | C6: =+'NOTE 4'!C6 -> Néant
A7: NOTE 5 : STOCKS ET EN COURS | L7: 1
A8: Libellés | E8: Année N | G8: Année N-1 | I8: Variation
I9: Valeur | J9: %
A10: Biens et services liés à l'activité | E10: =SUMIF('Balance N'!A:A,31,'Balance N'!O:O) -> 0 | G10: =SUMIF('Balance N-1'!A:A,31,'Balance N-1'!O:O) -> 0 | I10: =E10-G10 -> 0 | J10: =IF(G10,(E10-G10)/G10,IF(ISBLANK(G10),"",IF(E10,IF( E10 > 0,1,-1),"")))
A11: Marchandises | E11: =SUMIF('Balance N'!B:B,321,'Balance N'!O:O)+SUMIF('Balance N'!B:B,322,'Balance N'!O:O) -> 0 | G11: =SUMIF('Balance N-1'!B:B,321,'Balance N-1'!O:O)+SUMIF('Balance N-1'!B:B,322,'Balance N-1'!O:O) -> 0 | I11: =E11-G11 -> 0 | J11: =IF(G11,(E11-G11)/G11,IF(ISBLANK(G11),"",IF(E11,IF( E11 > 0,1,-1),"")))
A12: Matières premières et fournitures liées | E12: =SUMIF('Balance N'!B:B,323,'Balance N'!O:O)+SUMIF('Balance N'!B:B,324,'Balance N'!O:O)+SUMIF('Balance N'!B:B,325,'Balance N'!O:O) -> 0 | G12: =SUMIF('Balance N-1'!B:B,323,'Balance N-1'!O:O)+SUMIF('Balance N-1'!B:B,324,'Balance N-1'!O:O)+SUMIF('Balance N-1'!B:B,325,'Balance N-1'!O:O) -> 0 | I12: =E12-G12 -> 0 | J12: =IF(G12,(E12-G12)/G12,IF(ISBLANK(G12),"",IF(E12,IF( E12 > 0,1,-1),"")))
A13: Autres approvisionnements | E13: =SUMIF('Balance N'!A:A,33,'Balance N'!O:O) -> 0 | G13: =SUMIF('Balance N-1'!A:A,33,'Balance N-1'!O:O) -> 0 | I13: =E13-G13 -> 0 | J13: =IF(G13,(E13-G13)/G13,IF(ISBLANK(G13),"",IF(E13,IF( E13 > 0,1,-1),"")))
A14: Produits en-cours | E14: =SUMIF('Balance N'!A:A,34,'Balance N'!O:O) -> 0 | G14: =SUMIF('Balance N-1'!A:A,34,'Balance N-1'!O:O) -> 0 | I14: =E14-G14 -> 0 | J14: =IF(G14,(E14-G14)/G14,IF(ISBLANK(G14),"",IF(E14,IF( E14 > 0,1,-1),"")))
A15: Services en-cours | E15: =SUMIF('Balance N'!A:A,35,'Balance N'!O:O) -> 0 | G15: =SUMIF('Balance N-1'!A:A,35,'Balance N-1'!O:O) -> 0 | I15: =E15-G15 -> 0 | J15: =IF(G15,(E15-G15)/G15,IF(ISBLANK(G15),"",IF(E15,IF( E15 > 0,1,-1),"")))
A16: Produits finis | E16: =SUMIF('Balance N'!B:B,361,'Balance N'!O:O)+SUMIF('Balance N'!B:B,362,'Balance N'!O:O)+SUMIF('Balance N'!B:B,363,'Balance N'!O:O) -> 0 | G16: =SUMIF('Balance N-1'!B:B,361,'Balance N-1'!O:O)+SUMIF('Balance N-1'!B:B,362,'Balance N-1'!O:O)+SUMIF('Balance N-1'!B:B,363,'Balance N-1'!O:O) -> 0 | I16: =E16-G16 -> 0 | J16: =IF(G16,(E16-G16)/G16,IF(ISBLANK(G16),"",IF(E16,IF( E16 > 0,1,-1),"")))
A17: Produits intermédiaires | E17: =SUMIF('Balance N'!B:B,367,'Balance N'!O:O) -> 0 | G17: =SUMIF('Balance N-1'!B:B,367,'Balance N-1'!O:O) -> 0 | I17: =E17-G17 -> 0 | J17: =IF(G17,(E17-G17)/G17,IF(ISBLANK(G17),"",IF(E17,IF( E17 > 0,1,-1),"")))
A18: Stock HAO | E18: =SUMIF('Balance N'!A:A,38,'Balance N'!O:O)-SUMIF('Balance N'!B:B,388,'Balance N'!O:O) -> 0 | G18: =SUMIF('Balance N-1'!A:A,38,'Balance N-1'!O:O)-SUMIF('Balance N-1'!B:B,388,'Balance N-1'!O:O) -> 0 | I18: =E18-G18 -> 0 | J18: =IF(G18,(E18-G18)/G18,IF(ISBLANK(G18),"",IF(E18,IF( E18 > 0,1,-1),"")))
A19: Stocks en cours de route en consignation ou en dépôt | E19: =SUMIF('Balance N'!B:B,388,'Balance N'!O:O) -> 0 | G19: =SUMIF('Balance N-1'!B:B,388,'Balance N-1'!O:O) -> 0 | I19: =E19-G19 -> 0 | J19: =IF(G19,(E19-G19)/G19,IF(ISBLANK(G19),"",IF(E19,IF( E19 > 0,1,-1),"")))
A20: TOTAL BRUT STOCKS ET EN COURS | E20: =SUM(E10:F17) -> 0 | G20: =SUM(G10:H17) -> 0 | I20: =E20-G20 -> 0 | J20: =IF(G20,(E20-G20)/G20,IF(ISBLANK(G20),"",IF(E20,IF( E20 > 0,1,-1),"")))
A21: Dépréciations des stocks | E21: =SUMIF('Balance N'!A:A,39,'Balance N'!P:P) -> 0 | G21: =SUMIF('Balance N-1'!A:A,39,'Balance N-1'!P:P) -> 0 | I21: 0 | J21: =IF(G21,(E21-G21)/G21,IF(ISBLANK(G21),"",IF(E21,IF( E21 > 0,1,-1),"")))
A22: TOTAL NET DE DEPRECIATIONS | E22: =SUM(E21:E21) -> 0 | G22: =SUM(G21:G21) -> 0 | I22: =I20-I21 -> 0 | J22: =IF(G22,(E22-G22)/G22,IF(ISBLANK(G22),"",IF(E22,IF( E22 > 0,1,-1),"")))
A24: Commentaire :
A25: ● Indiquer la date de prise d'inventaire et décrire brièvement la procédure, les méthodes comptables adoptées pour évaluer le stock.
A26: ● Commenter toute variation significative des stocks.
A27: ● Indiquer le détail des stocks dépréciés et les évènements et circonstances qui ont conduit à la dépréciation et à la reprise.

Sheet NOTE 6
A1: - 19 -
J2: NOTE 6 SYSTEME NORMAL
A3: Dénomination sociale de l'entité : | C3: =+'NOTE 5'!C3 -> DSO Services | L3: NB: Certaines rubriques de cette pages seront, selon les cas, renseignées mannuellement.
A4: Adresse : | C4: =+'NOTE 5'!C4 -> Rue Alphamoi Djénèpo, secteur 01, Bobo-Dioulasso, Burkina Faso | J4: Sigle usuel : | K4: =+'NOTE 5'!J4 -> DSO Services
A5: N° d'identification fiscale : | C5: =+'NOTE 5'!C5 -> 00000101A | F5: Exercice clos le : | G5: =+'NOTE 5'!F5 -> 45657 | J5: Durée (en mois) : | K5: =+'NOTE 5'!J5 -> 12 | L5: Vous aurez à repartir les montants dans les rubriques adequates
A6: N° de télédéclarant (NTD): | C6: =+'NOTE 5'!C6 -> Néant
A7: NOTE 6 : CLIENTS – USAGERS ET AUTRES CREANCES | M7: 1
A8: Libellés | E8: Année N | F8: Année N-1 | G8: Variation | I8: Créances à un an au plus | J8: Créances à plus d'un an et à deux ans au plus | K8: Créances à plus de deux ans
G9: Valeur | H9: %
A10: Fournisseurs débiteurs | B10: Fournisseurs débiteurs | C10: Fournisseurs débiteurs | D10: Fournisseurs débiteurs | E10: =SUMIF('Balance N'!B:B,409,'Balance N'!O:O)-(SUMIF('Balance N'!C:C,4091,'Balance N'!O:O)) -> 0 | F10: =SUMIF('Balance N-1'!B:B,409,'Balance N-1'!O:O)-(SUMIF('Balance N-1'!C:C,4091,'Balance N-1'!O:O)) -> 0 | G10: =(E10-F10) -> 0 | H10: =IF(F10,(E10-F10)/F10,IF(ISBLANK(F10),"",IF(E10,IF( E10 > 0,1,-1),""))) | J10: =E10-(I10+K10) -> 0
A11: Cients - usagers | B11: Cients - usagers | C11: Cients - usagers | D11: Cients - usagers | E11: =+SUMIF('Balance N'!B:B,412,'Balance N'!O:O) -> 0 | F11: =+SUMIF('Balance N-1'!B:B,412,'Balance N-1'!O:O) -> 0 | G11: =(E11-F11) -> 0 | H11: =IF(F11,(E11-F11)/F11,IF(ISBLANK(F11),"",IF(E11,IF( E11 > 0,1,-1),""))) | J11: =E11-(I11+K11) -> 0
A12: Personnel | B12: Personnel | C12: Personnel | D12: Personnel | E12: =SUMIF('Balance N'!A:A,42,'Balance N'!O:O) -> 0 | F12: =SUMIF('Balance N-1'!A:A,42,'Balance N-1'!O:O) -> 0 | G12: =(E12-F12) -> 0 | H12: =IF(F12,(E12-F12)/F12,IF(ISBLANK(F12),"",IF(E12,IF( E12 > 0,1,-1),""))) | J12: =E12-(I12+K12) -> 0
A13: Organismes sociaux | B13: Organismes sociaux | C13: Organismes sociaux | D13: Organismes sociaux | E13: =SUMIF('Balance N'!A:A,43,'Balance N'!O:O) -> 0 | F13: =SUMIF('Balance N-1'!A:A,43,'Balance N-1'!O:O) -> 0 | G13: =(E13-F13) -> 0 | H13: =IF(F13,(E13-F13)/F13,IF(ISBLANK(F13),"",IF(E13,IF( E13 > 0,1,-1),""))) | J13: =E13-(I13+K13) -> 0
A14: Etat et collectivité publiques | B14: Etat et collectivité publiques | C14: Etat et collectivité publiques | D14: Etat et collectivité publiques | E14: =SUMIF('Balance N'!A:A,44,'Balance N'!O:O) -> 0 | F14: =SUMIF('Balance N-1'!A:A,44,'Balance N-1'!O:O) -> 0 | G14: =(E14-F14) -> 0 | H14: =IF(F14,(E14-F14)/F14,IF(ISBLANK(F14),"",IF(E14,IF( E14 > 0,1,-1),"")))
A15: Autres débiteurs divers | B15: Autres débiteurs divers | C15: Autres débiteurs divers | D15: Autres débiteurs divers | E15: =SUMIF('Balance N'!A:A,47,'Balance N'!O:O)-(SUMIF('Balance N'!B:B,475,'Balance N'!O:O)) -> 0 | F15: =SUMIF('Balance N-1'!A:A,47,'Balance N-1'!O:O)-(SUMIF('Balance N-1'!B:B,475,'Balance N-1'!O:O)) -> 0 | G15: =(E15-F15) -> 0 | H15: =IF(F15,(E15-F15)/F15,IF(ISBLANK(F15),"",IF(E15,IF( E15 > 0,1,-1),"")))
A16: TOTAL BRUT | E16: 2925734404 | F16: 3831311266 | G16: =(E16-F16) -> -905576862 | H16: =IF(F16,(E16-F16)/F16,IF(ISBLANK(F16),"",IF(E16,IF( E16 > 0,1,-1),""))) -> -0.23636212
A17: Dépréciation des créances | B17: Dépréciation des créances | C17: Dépréciation des créances | D17: Dépréciation des créances | E17: =SUMIF('Balance N'!B:B,492,'Balance N'!P:P)+SUMIF('Balance N'!B:B,493,'Balance N'!P:P)+SUMIF('Balance N'!B:B,494,'Balance N'!P:P)+SUMIF('Balance N'!B:B,497,'Balance N'!P:P) -> 0 | F17: =SUMIF('Balance N-1'!B:B,492,'Balance N-1'!P:P)+SUMIF('Balance N-1'!B:B,493,'Balance N-1'!P:P)+SUMIF('Balance N-1'!B:B,494,'Balance N-1'!P:P)+SUMIF('Balance N-1'!B:B,497,'Balance N-1'!P:P) -> 0 | G17: =(E17-F17) -> 0 | H17: =IF(F17,(E17-F17)/F17,IF(ISBLANK(F17),"",IF(E17,IF( E17 > 0,1,-1),"")))
A18: TOTAL NET DE DEPRECIATIONS | B18: TOTAL NET DE DEPRECIATIONS | C18: TOTAL NET DE DEPRECIATIONS | D18: TOTAL NET DE DEPRECIATIONS | E18: 2534884445 | F18: 3566447837 | G18: =(E18-F18) -> -1031563392 | H18: =IF(F18,(E18-F18)/F18,IF(ISBLANK(F18),"",IF(E18,IF( E18 > 0,1,-1),""))) -> -0.28924113 | I18: =SUM(I17:I17) -> 0 | J18: =SUM(J17:J17) -> 0 | K18: =SUM(K17:K17) -> 0
A19: Commentaire :
A20: · Justifier toute variation significative ;
A21: · Détailler les créances dont le montant est significatif ;
A22: · Justifier les créances anciennes ;
A23: · Indiquer les évènements et les circonstances qui ont conduit à la dépréciation et à la reprise.

Sheet NOTE 7
A1: - 20 -
I2: NOTE 7 SYSTEME NORMAL
A3: Dénomination sociale de l'entité : | C3: =+'NOTE 6'!C3 -> DSO Services
A4: Adresse : | C4: =+'NOTE 6'!C4 -> Rue Alphamoi Djénèpo, secteur 01, Bobo-Dioulasso, Burkina Faso | H4: Sigle usuel : | I4: =+'NOTE 6'!K4 -> DSO Services
A5: N° de compte contribuable (NCC) : | C5: =+'NOTE 6'!C5 -> 00000101A | E5: Exercice clos le : | F5: =+'NOTE 6'!G5 -> 45657 | H5: Durée (en mois) : | I5: =+'NOTE 6'!K5 -> 12
A6: N° de télédéclarant (NTD): | C6: =+'NOTE 6'!C6 -> Néant
A7: NOTE 7 : DISPONIBILITES | L7: 1
A8: Libellés | E8: Année N | G8: Année N-1 | I8: Variation en
I9: Valeur | J9: %
A10: Chèques à encaisser | E10: =SUMIF('Balance N'!B:B,513,'Balance N'!O:O) -> 0 | G10: =SUMIF('Balance N-1'!B:B,513,'Balance N-1'!O:O) -> 0 | I10: =(E10-G10) -> 0 | J10: =IF(G10,(E10-G10)/G10,IF(ISBLANK(G10),"",IF(E10,IF( E10 > 0,1,-1),"")))
A11: Chèques à l'encaissement | E11: =SUMIF('Balance N'!B:B,514,'Balance N'!O:O) -> 0 | G11: =SUMIF('Balance N-1'!B:B,514,'Balance N-1'!O:O) -> 0 | I11: =(E11-G11) -> 0 | J11: =IF(G11,(E11-G11)/G11,IF(ISBLANK(G11),"",IF(E11,IF( E11 > 0,1,-1),"")))
A12: Cartes de crédit à encaisser | E12: =SUMIF('Balance N'!B:B,515,'Balance N'!O:O) -> 0 | G12: =SUMIF('Balance N-1'!B:B,515,'Balance N-1'!O:O) -> 0 | I12: =(E12-G12) -> 0 | J12: =IF(G12,(E12-G12)/G12,IF(ISBLANK(G12),"",IF(E12,IF( E12 > 0,1,-1),"")))
A13: Autres valeurs à encaisser | E13: =SUMIF('Balance N'!B:B,518,'Balance N'!O:O) -> 0 | G13: =SUMIF('Balance N-1'!B:B,518,'Balance N-1'!O:O) -> 0 | I13: =(E13-G13) -> 0 | J13: =IF(G13,(E13-G13)/G13,IF(ISBLANK(G13),"",IF(E13,IF( E13 > 0,1,-1),"")))
A14: TOTAL BRUT VALEURS A ENCAISSER | E14: =+SUM(E10:F13) -> 0 | G14: =+SUM(G10:H13) -> 0 | I14: =(E14-G14) -> 0 | J14: =IF(G14,(E14-G14)/G14,IF(ISBLANK(G14),"",IF(E14,IF( E14 > 0,1,-1),"")))
A15: Banques locales | E15: =SUMIF('Balance N'!B:B,521,'Balance N'!O:O) -> 0 | G15: =SUMIF('Balance N-1'!B:B,521,'Balance N-1'!O:O) -> 0 | I15: =(E15-G15) -> 0 | J15: =IF(G15,(E15-G15)/G15,IF(ISBLANK(G15),"",IF(E15,IF( E15 > 0,1,-1),"")))
A16: Banques autres états région | E16: =SUMIF('Balance N'!B:B,522,'Balance N'!O:O) -> 0 | G16: =SUMIF('Balance N-1'!B:B,522,'Balance N-1'!O:O) -> 0 | I16: =(E16-G16) -> 0 | J16: =IF(G16,(E16-G16)/G16,IF(ISBLANK(G16),"",IF(E16,IF( E16 > 0,1,-1),"")))
A17: Banques, dépôt à terme et assimilés | E17: =SUMIF('Balance N'!B:B,525,'Balance N'!O:O) -> 0 | G17: =SUMIF('Balance N-1'!B:B,525,'Balance N-1'!O:O) -> 0 | I17: =(E17-G17) -> 0 | J17: =IF(G17,(E17-G17)/G17,IF(ISBLANK(G17),"",IF(E17,IF( E17 > 0,1,-1),"")))
A18: Autres Banques | E18: =SUMIF('Balance N'!B:B,523,'Balance N'!O:O)+SUMIF('Balance N'!B:B,524,'Balance N'!O:O) -> 0 | G18: =SUMIF('Balance N-1'!B:B,523,'Balance N-1'!O:O)+SUMIF('Balance N-1'!B:B,524,'Balance N-1'!O:O) -> 0 | I18: =(E18-G18) -> 0 | J18: =IF(G18,(E18-G18)/G18,IF(ISBLANK(G18),"",IF(E18,IF( E18 > 0,1,-1),"")))
A19: Banques intérêts courus | E19: =SUMIF('Balance N'!B:B,526,'Balance N'!O:O) -> 0 | G19: =SUMIF('Balance N-1'!B:B,526,'Balance N-1'!O:O) -> 0 | I19: =(E19-G19) -> 0 | J19: =IF(G19,(E19-G19)/G19,IF(ISBLANK(G19),"",IF(E19,IF( E19 > 0,1,-1),"")))
A20: Banques postales | E20: =SUMIF('Balance N'!B:B,531,'Balance N'!O:O) -> 0 | G20: =SUMIF('Balance N-1'!B:B,531,'Balance N-1'!O:O) -> 0 | I20: =(E20-G20) -> 0 | J20: =IF(G20,(E20-G20)/G20,IF(ISBLANK(G20),"",IF(E20,IF( E20 > 0,1,-1),"")))
A21: Autres établissement financiers | E21: =SUMIF('Balance N'!B:B,532,'Balance N'!O:O)+SUMIF('Balance N'!B:B,533,'Balance N'!O:O)+SUMIF('Balance N'!B:B,538,'Balance N'!O:O) -> 0 | G21: =SUMIF('Balance N-1'!B:B,532,'Balance N-1'!O:O)+SUMIF('Balance N-1'!B:B,533,'Balance N-1'!O:O)+SUMIF('Balance N-1'!B:B,538,'Balance N-1'!O:O) -> 0 | I21: =(E21-G21) -> 0 | J21: =IF(G21,(E21-G21)/G21,IF(ISBLANK(G21),"",IF(E21,IF( E21 > 0,1,-1),"")))
A22: Etablissement financiers intérêts courus | E22: =SUMIF('Balance N'!B:B,536,'Balance N'!O:O) -> 0 | G22: =SUMIF('Balance N-1'!B:B,536,'Balance N-1'!O:O) -> 0 | I22: =(E22-G22) -> 0 | J22: =IF(G22,(E22-G22)/G22,IF(ISBLANK(G22),"",IF(E22,IF( E22 > 0,1,-1),"")))
A23: Instruments de monnaie électronique | E23: =SUMIF('Balance N'!A:A,55,'Balance N'!O:O) -> 0 | G23: =SUMIF('Balance N-1'!A:A,55,'Balance N-1'!O:O) -> 0 | I23: =(E23-G23) -> 0 | J23: =IF(G23,(E23-G23)/G23,IF(ISBLANK(G23),"",IF(E23,IF( E23 > 0,1,-1),"")))
A24: Caisse | E24: =SUMIF('Balance N'!A:A,57,'Balance N'!O:O) -> 0 | G24: =SUMIF('Balance N-1'!A:A,57,'Balance N-1'!O:O) -> 0 | I24: =(E24-G24) -> 0 | J24: =IF(G24,(E24-G24)/G24,IF(ISBLANK(G24),"",IF(E24,IF( E24 > 0,1,-1),"")))
A25: Régies d’avances et virements accréditifs | E25: =SUMIF('Balance N'!A:A,58,'Balance N'!O:O) -> 0 | G25: =SUMIF('Balance N-1'!A:A,58,'Balance N-1'!O:O) -> 0 | I25: =(E25-G25) -> 0 | J25: =IF(G25,(E25-G25)/G25,IF(ISBLANK(G25),"",IF(E25,IF( E25 > 0,1,-1),"")))
A26: TOTAL BANQUES ET CAISSES | E26: =SUM(E15:F25) -> 0 | G26: =SUM(G15:H25) -> 0 | I26: =(E26-G26) -> 0 | J26: =IF(G26,(E26-G26)/G26,IF(ISBLANK(G26),"",IF(E26,IF( E26 > 0,1,-1),"")))
A27: Dépréciations | E27: =SUMIF('Balance N'!B:B,592,'Balance N'!P:P) -> 0 | F27: 0 | G27: =SUMIF('Balance N-1'!B:B,592,'Balance N-1'!P:P) -> 0 | H27: 0 | I27: =(E27-G27) -> 0 | J27: =IF(G27,(E27-G27)/G27,IF(ISBLANK(G27),"",IF(E27,IF( E27 > 0,1,-1),"")))
A28: TOTAL NET DE DEPRECIATIONS | E28: =SUM(E27) -> 0 | G28: =SUM(G27) -> 0 | I28: =(E28-G28) -> 0 | J28: =IF(G28,(E28-G28)/G28,IF(ISBLANK(G28),"",IF(E28,IF( E28 > 0,1,-1),"")))
A29: Commentaire :
A30: ● Indiquer la date de rapprochement des comptes bancaires.
A31: ● Indiquer la date d'inventaire de la caisse et des instruments de monnaie électronique.
A32: ● Justifier toute variation significative.
A33: ● Détailler les instruments de monnaie électronique si le montant est significatif.
A34: ● Indiquer les événements et circonstances qui ont conduit à la dépréciation et à la reprise.
A36: NB : Banques et intérêts courus et Etablissement financiers intérêts courus figurent dans cette rubrique en négatif si le compte principal attaché est débiteur

Sheet NOTE 8
A1: - 21 -
H2: NOTE 8 SYSTEME NORMAL
A3: Dénomination sociale de l'entité : | C3: =+'NOTE 7'!C3 -> DSO Services | K3: NB: Certaines rubriques de cette pages seront, selon les cas, renseignées mannuellement.
A4: Adresse : | C4: =+'NOTE 7'!C4 -> Rue Alphamoi Djénèpo, secteur 01, Bobo-Dioulasso, Burkina Faso | H4: Sigle usuel : | I4: =+'NOTE 7'!I4 -> DSO Services
A5: N° de compte contribuable (NCC) : | C5: =+'NOTE 7'!C5 -> 00000101A | F5: Exercice clos le : | G5: =+'NOTE 7'!F5 -> 45657 | H5: Durée (en mois) : | I5: =+'NOTE 7'!I5 -> 12 | K5: Vous aurez à repartir les montants dans les rubriques adequates
A6: N° de télédéclarant (NTD): | C6: =+'NOTE 7'!C6 -> Néant
A7: NOTE 8 : ECARTS DE CONVERSION
A8: ECARTS DE CONVERSION
A9: Libellés | E9: Devises | F9: Montant en devises | G9: Cours UML Année acquisition | H9: Cours UML 31/12 | I9: Variation en
I10: Valeur | J10: %
A11: Ecarts de conversion actif : détailler les créances et dettes concernées
I12: =(G12-H12)*F12 -> 0 | J12: =IF(H12,(G12-H12)/H12,IF(ISBLANK(H12),"",IF(G12,IF( G12 > 0,1,-1),"")))
I13: =(G13-H13)*F13 -> 0 | J13: =IF(H13,(G13-H13)/H13,IF(ISBLANK(H13),"",IF(G13,IF( G13 > 0,1,-1),"")))
I14: =(G14-H14)*F14 -> 0 | J14: =IF(H14,(G14-H14)/H14,IF(ISBLANK(H14),"",IF(G14,IF( G14 > 0,1,-1),"")))
I15: =(G15-H15)*F15 -> 0 | J15: =IF(H15,(G15-H15)/H15,IF(ISBLANK(H15),"",IF(G15,IF( G15 > 0,1,-1),"")))
I16: =(G16-H16)*F16 -> 0 | J16: =IF(H16,(G16-H16)/H16,IF(ISBLANK(H16),"",IF(G16,IF( G16 > 0,1,-1),"")))
I17: =(G17-H17)*F17 -> 0 | J17: =IF(H17,(G17-H17)/H17,IF(ISBLANK(H17),"",IF(G17,IF( G17 > 0,1,-1),"")))
A18: Ecart de conversion passif : détailler les créances et dettes concernées
I19: =(G19-H19)*F19 -> 0 | J19: =IF(H19,(G19-H19)/H19,IF(ISBLANK(H19),"",IF(G19,IF( G19 > 0,1,-1),"")))
I20: =(G20-H20)*F20 -> 0 | J20: =IF(H20,(G20-H20)/H20,IF(ISBLANK(H20),"",IF(G20,IF( G20 > 0,1,-1),"")))
I21: =(G21-H21)*F21 -> 0 | J21: =IF(H21,(G21-H21)/H21,IF(ISBLANK(H21),"",IF(G21,IF( G21 > 0,1,-1),"")))
I22: =(G22-H22)*F22 -> 0 | J22: =IF(H22,(G22-H22)/H22,IF(ISBLANK(H22),"",IF(G22,IF( G22 > 0,1,-1),"")))
I23: =(G23-H23)*F23 -> 0 | J23: =IF(H23,(G23-H23)/H23,IF(ISBLANK(H23),"",IF(G23,IF( G23 > 0,1,-1),"")))
I24: =(G24-H24)*F24 -> 0 | J24: =IF(H24,(G24-H24)/H24,IF(ISBLANK(H24),"",IF(G24,IF( G24 > 0,1,-1),"")))
I25: =(G25-H25)*F25 -> 0 | J25: =IF(H25,(G25-H25)/H25,IF(ISBLANK(H25),"",IF(G25,IF( G25 > 0,1,-1),"")))
I26: =(G26-H26)*F26 -> 0 | J26: =IF(H26,(G26-H26)/H26,IF(ISBLANK(H26),"",IF(G26,IF( G26 > 0,1,-1),"")))
A27: UML : Unités Monétaires légales Commentaire: Faire un commentaire.
A28: Commentaire: Faire un commentaire.

Sheet NOTE 9
A1: - 22 -
I2: NOTE 9 SYSTEME NORMAL
A3: Dénomination sociale de l'entité : | B3: =+'NOTE 8'!C3 -> DSO Services | C3: 0
A4: Adresse : | B4: =+'NOTE 8'!C4 -> Rue Alphamoi Djénèpo, secteur 01, Bobo-Dioulasso, Burkina Faso | H4: Sigle usuel : | I4: =+'NOTE 8'!I4 -> DSO Services
A5: N° de compte contribuable (NCC) : | B5: =+'NOTE 8'!C5 -> 00000101A | F5: Exercice clos le : | G5: =+'NOTE 8'!G5 -> 45657 | H5: Durée (en mois) : | I5: =+'NOTE 8'!I5 -> 12
A6: N° de télédéclarant (NTD) : | B6: =+'NOTE 8'!C6 -> Néant | C6: 0
A7: NOTE 9 : FONDS DU BAILLEUR
A9: Date des décaissements | B9: BAILLEUR/SOUS PROJET 1 (1) | E9: BAILLEUR/SOUS PROJET 2 (1) | H9: BAILLEUR/SOUS PROJET 3 (1)
B10: Montant décaissé | C10: Montant consommé | D10: Solde restant | E10: Montant décaissé | F10: Montant consommé | G10: Solde restant | H10: Montant décaissé | I10: Montant consommé | J10: Solde restant
A12: Fonds d'investissement (1)
A20: TOTAL FONDS D'INVESTISSEMENT | B20: =SUM(B13:B19) -> 0 | C20: =SUM(C13:C19) -> 0 | D20: =SUM(D13:D19) -> 0 | E20: =SUM(E13:E19) -> 0 | F20: =SUM(F13:F19) -> 0 | G20: =SUM(G13:G19) -> 0 | H20: =SUM(H13:H19) -> 0 | I20: =SUM(I13:I19) -> 0 | J20: =SUM(J13:J19) -> 0
A22: Fonds d'administration (2)
A28: TOTAL FONDS D'ADMINISTRATION | B28: =SUM(B23:B27) -> 0 | C28: =SUM(C23:C27) -> 0 | D28: =SUM(D23:D27) -> 0 | E28: =SUM(E23:E27) -> 0 | F28: =SUM(F23:F27) -> 0 | G28: =SUM(G23:G27) -> 0 | H28: =SUM(H23:H27) -> 0 | I28: =SUM(I23:I27) -> 0 | J28: =SUM(J23:J27) -> 0
A29: TOTAL FONDS DU BAILLEUR | B29: =B20+B28 -> 0 | C29: =C20+C28 -> 0 | D29: =D20+D28 -> 0 | E29: =E20+E28 -> 0 | F29: =F20+F28 -> 0 | G29: =G20+G28 -> 0 | H29: =H20+H28 -> 0 | I29: =I20+I28 -> 0 | J29: =J20+J28 -> 0
A32: (1) Le nombre de colonnes est fonction du nombre de bailleurs et/ou sous projets.
A33: (2) Le montant consommé eu titre d’un exercice représente le solde du compte 702 Quote – part de fonds d’administration transférés qu’il convient de subdiviser par nature de projet.
A34: Commentaire :
A35: · Indiquer pour chaque projet le niveau d’utilisation des fonds affectés en pourcentage par catégorie de fonds (fonds d’investissement et fonds d’administration) et de façon global
A36: · Expliquer les motifs liés aux éventuels retards dans le cadre de l’exécution des projets.

Sheet NOTE 10
A1: - 23 -
G2: NOTE 10 SYSTEME NORMAL
A3: Dénomination sociale de l'entité : | C3: =+'NOTE 9'!B3 -> DSO Services | I3: NB: Certaines rubriques de cette pages seront, selon les cas, renseignées mannuellement.
A4: Adresse : | C4: =+'NOTE 9'!B4 -> Rue Alphamoi Djénèpo, secteur 01, Bobo-Dioulasso, Burkina Faso | G4: Sigle usuel : | H4: =+'NOTE 9'!I4 -> DSO Services
A5: N° d'identification fiscale : | C5: =+'NOTE 9'!B5 -> 00000101A | E5: Exercice clos le : | F5: =+'NOTE 9'!G5 -> 45657 | G5: Durée (en mois) : | H5: =+'NOTE 9'!I5 -> 12 | I5: Vous aurez à repartir les montants dans les rubriques adequates
A6: N° de télédéclarant (NTD): | C6: =+'NOTE 9'!B6 -> Néant
A7: NOTE 10 : SUBVENTIONS | J7: 0
A8: Libellés | D8: Année N | E8: Année N-1 | F8: Variation | H8: Echéances
F9: Valeur | G9: %
A10: État | D10: =SUMIF('Balance N'!C:C,1411,'Balance N'!P:P) -> 0 | E10: =SUMIF('Balance N-1'!C:C,1411,'Balance N-1'!P:P) -> 0 | F10: =(D10-E10) -> 0 | G10: =IF(E10,(D10-E10)/E10,IF(ISBLANK(E10),"",IF(D10,IF( D10 > 0,1,-1),"")))
A11: Régions | D11: =SUMIF('Balance N'!C:C,1412,'Balance N'!P:P) -> 0 | E11: =SUMIF('Balance N-1'!C:C,1412,'Balance N-1'!P:P) -> 0 | F11: =(D11-E11) -> 0 | G11: =IF(E11,(D11-E11)/E11,IF(ISBLANK(E11),"",IF(D11,IF( D11 > 0,1,-1),"")))
A12: Départements | D12: =SUMIF('Balance N'!C:C,1413,'Balance N'!P:P) -> 0 | E12: =SUMIF('Balance N-1'!C:C,1413,'Balance N-1'!P:P) -> 0 | F12: =(D12-E12) -> 0 | G12: =IF(E12,(D12-E12)/E12,IF(ISBLANK(E12),"",IF(D12,IF( D12 > 0,1,-1),"")))
A13: Communes et collectivités publiques décentralisées | D13: =SUMIF('Balance N'!C:C,1414,'Balance N'!P:P) -> 0 | E13: =SUMIF('Balance N-1'!C:C,1414,'Balance N-1'!P:P) -> 0 | F13: =(D13-E13) -> 0 | G13: =IF(E13,(D13-E13)/E13,IF(ISBLANK(E13),"",IF(D13,IF( D13 > 0,1,-1),"")))
A14: Entités publiques ou mixtes | D14: =SUMIF('Balance N'!C:C,1415,'Balance N'!P:P) -> 0 | E14: =SUMIF('Balance N-1'!C:C,1415,'Balance N-1'!P:P) -> 0 | F14: =(D14-E14) -> 0 | G14: =IF(E14,(D14-E14)/E14,IF(ISBLANK(E14),"",IF(D14,IF( D14 > 0,1,-1),"")))
A15: Entités et organismes privés | D15: =SUMIF('Balance N'!C:C,1416,'Balance N'!P:P) -> 0 | E15: =SUMIF('Balance N-1'!C:C,1416,'Balance N-1'!P:P) -> 0 | F15: =(D15-E15) -> 0 | G15: =IF(E15,(D15-E15)/E15,IF(ISBLANK(E15),"",IF(D15,IF( D15 > 0,1,-1),"")))
A16: Organismes internationaux | D16: =SUMIF('Balance N'!C:C,1417,'Balance N'!P:P) -> 0 | E16: =SUMIF('Balance N-1'!C:C,1417,'Balance N-1'!P:P) -> 0 | F16: =(D16-E16) -> 0 | G16: =IF(E16,(D16-E16)/E16,IF(ISBLANK(E16),"",IF(D16,IF( D16 > 0,1,-1),"")))
A17: Autres | D17: =SUMIF('Balance N'!C:C,1418,'Balance N'!P:P)+SUMIF('Balance N'!B:B,148,'Balance N'!P:P) -> 0 | E17: =SUMIF('Balance N-1'!C:C,1418,'Balance N-1'!P:P)+SUMIF('Balance N-1'!B:B,148,'Balance N-1'!P:P) -> 0 | F17: =(D17-E17) -> 0 | G17: =IF(E17,(D17-E17)/E17,IF(ISBLANK(E17),"",IF(D17,IF( D17 > 0,1,-1),"")))
A18: TOTAL SUBVENTIONS | D18: =SUM(D10:D17) -> 0 | E18: =SUM(E10:E17) -> 0 | F18: =SUM(F10:F17) -> 0 | G18: =IF(E18,(D18-E18)/E18,IF(ISBLANK(E18),"",IF(D18,IF( D18 > 0,1,-1),"")))
A19: Commentaire:
A20: ● Indiquer pour la subvention la date d’octroi, la nature, les obligations éventuelles.
A21: ● Commenter toute variation significative.

Sheet NOTE 11
A1: - 24 -
J2: NOTE 11 SYSTEME NORMAL
A3: Dénomination sociale de l'entité : | C3: =+'NOTE 10'!C3 -> DSO Services | L3: NB: Certaines rubriques de cette pages seront, selon les cas, renseignées mannuellement.
A4: Adresse : | C4: =+'NOTE 10'!C4 -> Rue Alphamoi Djénèpo, secteur 01, Bobo-Dioulasso, Burkina Faso | J4: Sigle usuel : | K4: =+'NOTE 10'!H4 -> DSO Services
A5: N° d'identification fiscale : | C5: =+'NOTE 10'!C5 -> 00000101A | F5: Exercice clos le : | G5: =+'NOTE 10'!F5 -> 45657 | J5: Durée (en mois) : | K5: =+'NOTE 10'!H5 -> 12 | L5: Vous aurez à repartir les montants dans les rubriques adequates
A6: N° de télédéclarant (NTD): | C6: =+'NOTE 10'!C6 -> Néant
A7: NOTE 11 : DETTES FINANCIERES ET RESSOURCES ASSIMILES | M7: 1
A8: Libellés | E8: Année N | F8: Année N-1 | G8: Variation en | I8: Dettes à un an au plus | J8: Dettes à plus d'un an et à deux ans au plus | K8: Dettes à plus de deux ans
G9: Valeur | H9: %
A10: Emprunts et dettes auprès des établissements de crédit | B10: Emprunts et dettes auprès des établissements de crédit | C10: Emprunts et dettes auprès des établissements de crédit | D10: Emprunts et dettes auprès des établissements de crédit | E10: =SUMIF('Balance N'!B:B,181,'Balance N'!P:P) -> 0 | F10: =SUMIF('Balance N-1'!B:B,181,'Balance N-1'!P:P) -> 0 | G10: =(E10-F10) -> 0 | H10: =IF(F10,(E10-F10)/F10,IF(ISBLANK(F10),"",IF(E10,IF( E10 > 0,1,-1),"")))
A11: Avances reçues de l'Etat | B11: Avances reçues de l'Etat | C11: Avances reçues de l'Etat | D11: Avances reçues de l'Etat | E11: =SUMIF('Balance N'!B:B,182,'Balance N'!P:P) -> 0 | F11: =SUMIF('Balance N-1'!B:B,182,'Balance N-1'!P:P) -> 0 | G11: =(E11-F11) -> 0 | H11: =IF(F11,(E11-F11)/F11,IF(ISBLANK(F11),"",IF(E11,IF( E11 > 0,1,-1),"")))
A12: Dépôt et cautionnement reçus | B12: Dépôt et cautionnement reçus | C12: Dépôt et cautionnement reçus | D12: Dépôt et cautionnement reçus | E12: =SUMIF('Balance N'!B:B,183,'Balance N'!P:P) -> 0 | F12: =SUMIF('Balance N-1'!B:B,183,'Balance N-1'!P:P) -> 0 | G12: =(E12-F12) -> 0 | H12: =IF(F12,(E12-F12)/F12,IF(ISBLANK(F12),"",IF(E12,IF( E12 > 0,1,-1),"")))
A13: Intérêt courus | B13: Intérêt courus | C13: Intérêt courus | D13: Intérêt courus | E13: =SUMIF('Balance N'!B:B,185,'Balance N'!P:P) -> 0 | F13: =SUMIF('Balance N-1'!B:B,185,'Balance N-1'!P:P) -> 0 | G13: =(E13-F13) -> 0 | H13: =IF(F13,(E13-F13)/F13,IF(ISBLANK(F13),"",IF(E13,IF( E13 > 0,1,-1),"")))
A14: Etat et collectivité publiques | B14: Etat et collectivité publiques | C14: Etat et collectivité publiques | D14: Etat et collectivité publiques | E14: =SUMIF('Balance N'!B:B,186,'Balance N'!P:P) -> 0 | F14: =SUMIF('Balance N-1'!B:B,186,'Balance N-1'!P:P) -> 0 | G14: =(E14-F14) -> 0 | H14: =IF(F14,(E14-F14)/F14,IF(ISBLANK(F14),"",IF(E14,IF( E14 > 0,1,-1),"")))
A15: Autres emprunts et dettes | B15: Autres emprunts et dettes | C15: Autres emprunts et dettes | D15: Autres emprunts et dettes | E15: =SUMIF('Balance N'!C:C,1881,'Balance N'!P:P) -> 0 | F15: =SUMIF('Balance N-1'!C:C,1881,'Balance N-1'!P:P) -> 0 | G15: =(E15-F15) -> 0 | H15: =IF(F15,(E15-F15)/F15,IF(ISBLANK(F15),"",IF(E15,IF( E15 > 0,1,-1),"")))
A16: TOTAL EMPRUNTS ET DETTES FINANCIERES | E16: =SUM(E10:E15) -> 0 | F16: =SUM(F10:F15) -> 0 | G16: =SUM(G10:G15) -> 0 | H16: =IF(F16,(E16-F16)/F16,IF(ISBLANK(F16),"",IF(E16,IF( E16 > 0,1,-1),""))) | I16: =SUM(I10:I15) -> 0 | J16: =SUM(J10:J15) -> 0 | K16: =SUM(K10:K15) -> 0
A17: Crédit - bail immobilier | B17: Crédit - bail immobilier | C17: Crédit - bail immobilier | D17: Crédit - bail immobilier | E17: =SUMIF('Balance N'!C:C,1871,'Balance N'!P:P) -> 0 | F17: =SUMIF('Balance N-1'!C:C,1871,'Balance N-1'!P:P) -> 0 | G17: =(E17-F17) -> 0 | H17: =IF(F17,(E17-F17)/F17,IF(ISBLANK(F17),"",IF(E17,IF( E17 > 0,1,-1),"")))
A18: Crédit - bail mobilier | B18: Crédit - bail mobilier | C18: Crédit - bail mobilier | D18: Crédit - bail mobilier | E18: =SUMIF('Balance N'!C:C,1872,'Balance N'!P:P) -> 0 | F18: =SUMIF('Balance N-1'!C:C,1872,'Balance N-1'!P:P) -> 0 | G18: =(E18-F18) -> 0 | H18: =IF(F18,(E18-F18)/F18,IF(ISBLANK(F18),"",IF(E18,IF( E18 > 0,1,-1),"")))
A19: Location - vente | B19: Location - vente | C19: Location - vente | D19: Location - vente | E19: =SUMIF('Balance N'!C:C,1873,'Balance N'!P:P) -> 0 | F19: =SUMIF('Balance N-1'!C:C,1873,'Balance N-1'!P:P) -> 0 | G19: =(E19-F19) -> 0 | H19: =IF(F19,(E19-F19)/F19,IF(ISBLANK(F19),"",IF(E19,IF( E19 > 0,1,-1),"")))
A20: Intérêts courus | B20: Intérêts courus | C20: Intérêts courus | D20: Intérêts courus | E20: =SUMIF('Balance N'!C:C,1876,'Balance N'!P:P) -> 0 | F20: =SUMIF('Balance N-1'!C:C,1876,'Balance N-1'!P:P) -> 0 | G20: =(E20-F20) -> 0 | H20: =IF(F20,(E20-F20)/F20,IF(ISBLANK(F20),"",IF(E20,IF( E20 > 0,1,-1),"")))
A21: Autres dettes de location - acquisition | B21: Autres dettes de location - acquisition | C21: Autres dettes de location - acquisition | D21: Autres dettes de location - acquisition | E21: =SUMIF('Balance N'!C:C,1882,'Balance N'!P:P) -> 0 | F21: =SUMIF('Balance N-1'!C:C,1882,'Balance N-1'!P:P) -> 0 | G21: =(E21-F21) -> 0 | H21: =IF(F21,(E21-F21)/F21,IF(ISBLANK(F21),"",IF(E21,IF( E21 > 0,1,-1),"")))
A22: TOTAL DETTES DE LOCATION ACQUISITION | E22: =SUM(E17:E21) -> 0 | F22: =SUM(F17:F21) -> 0 | G22: =SUM(G17:G21) -> 0 | H22: =IF(F22,(E22-F22)/F22,IF(ISBLANK(F22),"",IF(E22,IF( E22 > 0,1,-1),""))) | I22: =SUM(I17:I21) -> 0 | J22: =SUM(J17:J21) -> 0 | K22: =SUM(K17:K21) -> 0
A23: Provisions pour litiges | B23: Provisions pour litiges | C23: Provisions pour litiges | D23: Provisions pour litiges | E23: =SUMIF('Balance N'!B:B,191,'Balance N'!P:P) -> 0 | F23: =SUMIF('Balance N-1'!B:B,191,'Balance N-1'!P:P) -> 0 | G23: =(E23-F23) -> 0 | H23: =IF(F23,(E23-F23)/F23,IF(ISBLANK(F23),"",IF(E23,IF( E23 > 0,1,-1),"")))
A24: Provisions pour pertes de change | B24: Provisions pour pertes de change | C24: Provisions pour pertes de change | D24: Provisions pour pertes de change | E24: =SUMIF('Balance N'!B:B,194,'Balance N'!P:P) -> 0 | F24: =SUMIF('Balance N-1'!B:B,194,'Balance N-1'!P:P) -> 0 | G24: =(E24-F24) -> 0 | H24: =IF(F24,(E24-F24)/F24,IF(ISBLANK(F24),"",IF(E24,IF( E24 > 0,1,-1),"")))
A25: Provisions pour pensions et obligations assimiliées | B25: Provisions pour pensions et obligations assimiliées | C25: Provisions pour pensions et obligations assimiliées | D25: Provisions pour pensions et obligations assimiliées | E25: =SUMIF('Balance N'!B:B,195,'Balance N'!P:P) -> 0 | F25: =SUMIF('Balance N-1'!B:B,195,'Balance N-1'!P:P) -> 0 | G25: =(E25-F25) -> 0 | H25: =IF(F25,(E25-F25)/F25,IF(ISBLANK(F25),"",IF(E25,IF( E25 > 0,1,-1),"")))
A26: Provisions pour amendes et pénalités | B26: Provisions pour amendes et pénalités | C26: Provisions pour amendes et pénalités | D26: Provisions pour amendes et pénalités | E26: =SUMIF('Balance N'!B:B,196,'Balance N'!P:P) -> 0 | F26: =SUMIF('Balance N-1'!B:B,196,'Balance N-1'!P:P) -> 0 | G26: =(E26-F26) -> 0 | H26: =IF(F26,(E26-F26)/F26,IF(ISBLANK(F26),"",IF(E26,IF( E26 > 0,1,-1),"")))
A27: Autres provisions | B27: Autres provisions | C27: Autres provisions | D27: Autres provisions | E27: =SUMIF('Balance N'!C:C,1981,'Balance N'!P:P) -> 0 | F27: =SUMIF('Balance N-1'!C:C,1981,'Balance N-1'!P:P) -> 0 | G27: =(E27-F27) -> 0 | H27: =IF(F27,(E27-F27)/F27,IF(ISBLANK(F27),"",IF(E27,IF( E27 > 0,1,-1),"")))
A28: TOTAL PROVISIONS FINANCIERES POUR RISQUES ET CHARGES | E28: =SUM(E23:E27) -> 0 | F28: =SUM(F23:F27) -> 0 | G28: =SUM(G23:G27) -> 0 | H28: =SUM(H23:H27) -> 0
A29: (1): Le solde de ce compte est débiteur
A30: Commentaire:
A31: Pour chaque emprunt et dette de location acquisition: mentionner la date d'octroi, le nom de l'organisme financier, le montant initial de l'emprunt ou de la dette, la durée du crédit, les garanties données par la société.
A32: ● Indiquer les événements et circonstances qui ont conduit à la provision et à la reprise.
A33: ● Pour les pensions et obligations de retraite, indiquer :
A34: - la méthode d'évaluation retenue
A35: - le nom de la compagnie d'assurance ou du fonds de pension, le descriptif de la convention signée avec l'organisme, la périodicité des versements, le montant et la durée de la convention, pour les actifs du régime.

Sheet NOTE 12
A1: - 25 -
K2: NOTE 12 SYSTEME NORMAL
A3: Dénomination sociale de l'entité : | C3: =+'NOTE 11'!C3 -> DSO Services | M3: NB: Certaines rubriques de cette pages seront, selon les cas, renseignées mannuellement.
A4: Adresse : | C4: =+'NOTE 11'!C4 -> Rue Alphamoi Djénèpo, secteur 01, Bobo-Dioulasso, Burkina Faso | K4: Sigle usuel : | L4: =+'NOTE 11'!K4 -> DSO Services
A5: N° d'identification fiscale : | C5: =+'NOTE 11'!C5 -> 00000101A | F5: Exercice clos le : | G5: =+'NOTE 11'!G5 -> 45657 | K5: Durée (en mois) : | L5: =+'NOTE 11'!K5 -> 12 | M5: Vous aurez à repartir les montants dans les rubriques adequates
A6: N° de télédéclarant (NTD): | C6: =+'NOTE 11'!C6 -> Néant
A7: NOTE 12 : DETTES FOURNISSEURS ET ASSIMILEES, FISCALES ET SOCIALES | N7: 1
A8: Libellés | F8: Année N | G8: Année N-1 | H8: Variation en | J8: Dettes à un an au plus | K8: Dettes à plus d'un an et à deux ans au plus | L8: Dettes à plus de deux ans
H9: Valeur | I9: %
A10: Fournisseurs dettes en compte | B10: Fournisseurs | C10: Fournisseurs | D10: Fournisseurs | E10: Fournisseurs | F10: =SUMIF('Balance N'!B:B,401,'Balance N'!P:P)-SUMIF('Balance N'!C:C,4012,'Balance N'!P:P) -> 0 | G10: =SUMIF('Balance N-1'!B:B,401,'Balance N-1'!P:P)-SUMIF('Balance N-1'!C:C,4012,'Balance N-1'!P:P) -> 0 | H10: =IF(G10,(F10-G10),IF(ISBLANK(G10),"",IF(F10,IF( F10 > 0,1,-1),""))) | I10: =IF(G10,(F10-G10)/G10,IF(ISBLANK(G10),"",IF(F10,IF( F10 > 0,1,-1),""))) | K10: =F10-(J10+L10) -> 0
A11: Clients-usagers créditeurs | B11: Clients-usagers créditeurs | C11: Clients-usagers créditeurs | D11: Clients-usagers créditeurs | E11: Clients-usagers créditeurs | F11: =SUMIF('Balance N'!B:B,419,'Balance N'!P:P) -> 0 | G11: =SUMIF('Balance N-1'!B:B,419,'Balance N-1'!P:P) -> 0 | H11: =IF(G11,(F11-G11),IF(ISBLANK(G11),"",IF(F11,IF( F11 > 0,1,-1),""))) | I11: =IF(G11,(F11-G11)/G11,IF(ISBLANK(G11),"",IF(F11,IF( F11 > 0,1,-1),""))) | K11: =F11-(J11+L11) -> 0
A12: DETTES FOURNISSEURS ET ASSIMILEES | F12: =SUM(F10:F11) -> 0 | G12: =SUM(G10:G11) -> 0 | H12: =IF(G12,(F12-G12),IF(ISBLANK(G12),"",IF(F12,IF( F12 > 0,1,-1),""))) | I12: =IF(G12,(F12-G12)/G12,IF(ISBLANK(G12),"",IF(F12,IF( F12 > 0,1,-1),""))) | J12: =SUM(J10:J11) -> 0 | K12: =SUM(K10:K11) -> 0 | L12: =SUM(L10:L11) -> 0
A13: Personnel, rémunérations dues | B13: Personnel, rémunérations dues | C13: Personnel, rémunérations dues | D13: Personnel, rémunérations dues | E13: Personnel, rémunérations dues | F13: =SUMIF('Balance N'!B:B,422,'Balance N'!P:P) -> 0 | G13: =SUMIF('Balance N-1'!B:B,422,'Balance N-1'!P:P) -> 0 | H13: =IF(G13,(F13-G13),IF(ISBLANK(G13),"",IF(F13,IF( F13 > 0,1,-1),""))) | I13: =IF(G13,(F13-G13)/G13,IF(ISBLANK(G13),"",IF(F13,IF( F13 > 0,1,-1),""))) | K13: =F13-(J13+L13) -> 0
A14: Personnel, congés payer | B14: Personnel, congés payer | C14: Personnel, congés payer | D14: Personnel, congés payer | E14: Personnel, congés payer | F14: =SUMIF('Balance N'!C:C,4081,'Balance N'!P:P) -> 0 | G14: =SUMIF('Balance N-1'!C:C,4081,'Balance N-1'!P:P) -> 0 | H14: =IF(G14,(F14-G14),IF(ISBLANK(G14),"",IF(F14,IF( F14 > 0,1,-1),""))) | I14: =IF(G14,(F14-G14)/G14,IF(ISBLANK(G14),"",IF(F14,IF( F14 > 0,1,-1),""))) | K14: =F14-(J14+L14) -> 0
A15: Charges sociales sur congés à payer | B15: Charges sociales sur congés à payer | C15: Charges sociales sur congés à payer | D15: Charges sociales sur congés à payer | E15: Charges sociales sur congés à payer | F15: =SUMIF('Balance N'!C:C,4382,'Balance N'!P:P) -> 0 | G15: =SUMIF('Balance N-1'!C:C,4382,'Balance N-1'!P:P) -> 0 | H15: =IF(G15,(F15-G15),IF(ISBLANK(G15),"",IF(F15,IF( F15 > 0,1,-1),""))) | I15: =IF(G15,(F15-G15)/G15,IF(ISBLANK(G15),"",IF(F15,IF( F15 > 0,1,-1),""))) | K15: =F15-(J15+L15) -> 0
A16: Autres personnels | B16: Autres personnels | C16: Autres personnels | D16: Autres personnels | E16: Autres personnels | F16: =SUMIF('Balance N'!B:B,421,'Balance N'!P:P)+SUMIF('Balance N'!B:B,423,'Balance N'!P:P)+SUMIF('Balance N'!B:B,424,'Balance N'!P:P)+SUMIF('Balance N'!B:B,425,'Balance N'!P:P)+SUMIF('Balance N'!B:B,427,'Balance N'!P:P)+SUMIF('Balance N'!B:B,428,'Balance N'!P:P) -> 0 | G16: =SUMIF('Balance N-1'!B:B,421,'Balance N-1'!P:P)+SUMIF('Balance N-1'!B:B,423,'Balance N-1'!P:P)+SUMIF('Balance N-1'!B:B,424,'Balance N-1'!P:P)+SUMIF('Balance N-1'!B:B,425,'Balance N-1'!P:P)+SUMIF('Balance N-1'!B:B,427,'Balance N-1'!P:P)+SUMIF('Balance N-1'!B:B,428,'Balance N-1'!P:P) -> 0 | H16: =IF(G16,(F16-G16),IF(ISBLANK(G16),"",IF(F16,IF( F16 > 0,1,-1),""))) | I16: =IF(G16,(F16-G16)/G16,IF(ISBLANK(G16),"",IF(F16,IF( F16 > 0,1,-1),""))) | K16: =F16-(J16+L16) -> 0 | L16: =SUM(L10:L15) -> 0
A17: Caisse de sécurités sociales | B17: Caisse de sécurités sociales | C17: Caisse de sécurités sociales | D17: Caisse de sécurités sociales | E17: Caisse de sécurités sociales | F17: =SUMIF('Balance N'!B:B,431,'Balance N'!P:P) -> 0 | G17: =SUMIF('Balance N-1'!B:B,431,'Balance N-1'!P:P) -> 0 | H17: =IF(G17,(F17-G17),IF(ISBLANK(G17),"",IF(F17,IF( F17 > 0,1,-1),""))) | I17: =IF(G17,(F17-G17)/G17,IF(ISBLANK(G17),"",IF(F17,IF( F17 > 0,1,-1),""))) | K17: =F17-(J17+L17) -> 0
A18: Caisse de retraite | B18: Caisse de retraite | C18: Caisse de retraite | D18: Caisse de retraite | E18: Caisse de retraite | F18: =SUMIF('Balance N'!B:B,432,'Balance N'!P:P) -> 0 | G18: =SUMIF('Balance N-1'!B:B,432,'Balance N-1'!P:P) -> 0 | H18: =IF(G18,(F18-G18),IF(ISBLANK(G18),"",IF(F18,IF( F18 > 0,1,-1),""))) | I18: =IF(G18,(F18-G18)/G18,IF(ISBLANK(G18),"",IF(F18,IF( F18 > 0,1,-1),""))) | K18: =F18-(J18+L18) -> 0
A19: Mutuelles de santé | B19: Mutuelles de santé | C19: Mutuelles de santé | D19: Mutuelles de santé | E19: Mutuelles de santé | F19: =SUMIF('Balance N'!C:C,4331,'Balance N'!P:P) -> 0 | G19: =SUMIF('Balance N-1'!C:C,4331,'Balance N-1'!P:P) -> 0 | H19: =IF(G19,(F19-G19),IF(ISBLANK(G19),"",IF(F19,IF( F19 > 0,1,-1),""))) | I19: =IF(G19,(F19-G19)/G19,IF(ISBLANK(G19),"",IF(F19,IF( F19 > 0,1,-1),""))) | K19: =F19-(J19+L19) -> 0
A20: Assurance Retraite | B20: Assurance Retraite | C20: Assurance Retraite | D20: Assurance Retraite | E20: Assurance Retraite | F20: =SUMIF('Balance N'!C:C,4332,'Balance N'!P:P) -> 0 | G20: =SUMIF('Balance N-1'!C:C,4332,'Balance N-1'!P:P) -> 0 | H20: =IF(G20,(F20-G20),IF(ISBLANK(G20),"",IF(F20,IF( F20 > 0,1,-1),""))) | I20: =IF(G20,(F20-G20)/G20,IF(ISBLANK(G20),"",IF(F20,IF( F20 > 0,1,-1),""))) | K20: =F20-(J20+L20) -> 0
A21: Autres charges sociales à payer | B21: Autres charges sociales à payer | C21: Autres charges sociales à payer | D21: Autres charges sociales à payer | E21: Autres charges sociales à payer | F21: =SUMIF('Balance N'!B:B,431,'Balance N'!P:P)-(SUMIF('Balance N'!C:C,4311,'Balance N'!P:P)+SUMIF('Balance N'!C:C,4312,'Balance N'!P:P)+SUMIF('Balance N'!C:C,4318,'Balance N'!P:P))+SUMIF('Balance N'!B:B,432,'Balance N'!P:P)-(SUMIF('Balance N'!C:C,4321,'Balance N'!P:P)+SUMIF('Balance N'!C:C,4322,'Balance N'!P:P)+SUMIF('Balance N'!C:C,4328,'Balance N'!P:P)) -> 0 | G21: =SUMIF('Balance N-1'!B:B,431,'Balance N-1'!P:P)-(SUMIF('Balance N-1'!C:C,4311,'Balance N-1'!P:P)+SUMIF('Balance N-1'!C:C,4312,'Balance N-1'!P:P)+SUMIF('Balance N-1'!C:C,4318,'Balance N-1'!P:P))+SUMIF('Balance N-1'!B:B,432,'Balance N-1'!P:P)-(SUMIF('Balance N-1'!C:C,4321,'Balance N-1'!P:P)+SUMIF('Balance N-1'!C:C,4322,'Balance N-1'!P:P)+SUMIF('Balance N-1'!C:C,4328,'Balance N-1'!P:P)) -> 0 | H21: =IF(G21,(F21-G21),IF(ISBLANK(G21),"",IF(F21,IF( F21 > 0,1,-1),""))) | I21: =IF(G21,(F21-G21)/G21,IF(ISBLANK(G21),"",IF(F21,IF( F21 > 0,1,-1),""))) | K21: =F21-(J21+L21) -> 0
A22: Autres cotisations et organismes sociaux | B22: Autres cotisations et organismes sociaux | C22: Autres cotisations et organismes sociaux | D22: Autres cotisations et organismes sociaux | E22: Autres cotisations et organismes sociaux | F22: =SUMIF('Balance N'!B:B,433,'Balance N'!P:P)-(SUMIF('Balance N'!C:C,4331,'Balance N'!P:P)+SUMIF('Balance N'!C:C,4332,'Balance N'!P:P))+(SUMIF('Balance N'!B:B,438,'Balance N'!P:P))-(SUMIF('Balance N'!C:C,4386,'Balance N'!P:P)) -> 0 | G22: =SUMIF('Balance N-1'!B:B,433,'Balance N-1'!P:P)-(SUMIF('Balance N-1'!C:C,4331,'Balance N-1'!P:P)+SUMIF('Balance N-1'!C:C,4332,'Balance N-1'!P:P))+(SUMIF('Balance N-1'!B:B,438,'Balance N-1'!P:P))-(SUMIF('Balance N-1'!C:C,4386,'Balance N-1'!P:P)) -> 0 | H22: =IF(G22,(F22-G22),IF(ISBLANK(G22),"",IF(F22,IF( F22 > 0,1,-1),""))) | I22: =IF(G22,(F22-G22)/G22,IF(ISBLANK(G22),"",IF(F22,IF( F22 > 0,1,-1),""))) | K22: =F22-(J22+L22) -> 0
A23: TOTAL DETTES SOCIALES | F23: =SUM(F17:F17) -> 0 | G23: =SUM(G17:G17) -> 0 | H23: =IF(G23,(F23-G23),IF(ISBLANK(G23),"",IF(F23,IF( F23 > 0,1,-1),""))) | I23: =IF(G23,(F23-G23)/G23,IF(ISBLANK(G23),"",IF(F23,IF( F23 > 0,1,-1),""))) | J23: =SUM(J17:J17) -> 0 | K23: =SUM(K17:K17) -> 0 | L23: =SUM(L17:L17) -> 0
A24: Etats, impôts sur les bénéfices | B24: Etats, impôts sur les bénéfices | C24: Etats, impôts sur les bénéfices | D24: Etats, impôts sur les bénéfices | E24: Etats, impôts sur les bénéfices | F24: =SUMIF('Balance N'!B:B,441,'Balance N'!P:P) -> 0 | G24: =SUMIF('Balance N-1'!B:B,441,'Balance N-1'!P:P) -> 0 | H24: =(F24-G24) -> 0 | I24: =IF(G24,(F24-G24)/G24,IF(ISBLANK(G24),"",IF(F24,IF( F24 > 0,1,-1),"")))
A25: Etats, autres impôts et taxes | B25: Etats, autres impôts et taxes | C25: Etats, autres impôts et taxes | D25: Etats, autres impôts et taxes | E25: Etats, autres impôts et taxes | F25: =SUMIF('Balance N'!B:B,442,'Balance N'!P:P) -> 0 | G25: =SUMIF('Balance N-1'!B:B,442,'Balance N-1'!P:P) -> 0 | H25: =IF(G25,(F25-G25),IF(ISBLANK(G25),"",IF(F25,IF( F25 > 0,1,-1),""))) | I25: =IF(G25,(F25-G25)/G25,IF(ISBLANK(G25),"",IF(F25,IF( F25 > 0,1,-1),"")))
A26: Etats, TVA | B26: Etats, TVA | C26: Etats, TVA | D26: Etats, TVA | E26: Etats, TVA | F26: =SUMIF('Balance N'!B:B,443,'Balance N'!P:P)+SUMIF('Balance N'!B:B,444,'Balance N'!P:P)+SUMIF('Balance N'!B:B,445,'Balance N'!P:P) -> 0 | G26: =SUMIF('Balance N-1'!B:B,443,'Balance N-1'!P:P)+SUMIF('Balance N-1'!B:B,444,'Balance N-1'!P:P)+SUMIF('Balance N-1'!B:B,445,'Balance N-1'!P:P) -> 0 | H26: =IF(G26,(F26-G26),IF(ISBLANK(G26),"",IF(F26,IF( F26 > 0,1,-1),""))) | I26: =IF(G26,(F26-G26)/G26,IF(ISBLANK(G26),"",IF(F26,IF( F26 > 0,1,-1),"")))
A27: Etat, impôts retenus à la source | B27: Etat, impôts retenus à la source | C27: Etat, impôts retenus à la source | D27: Etat, impôts retenus à la source | E27: Etat, impôts retenus à la source | F27: =SUMIF('Balance N'!B:B,447,'Balance N'!P:P) -> 0 | G27: =SUMIF('Balance N-1'!B:B,447,'Balance N-1'!P:P) -> 0 | H27: =IF(G27,(F27-G27),IF(ISBLANK(G27),"",IF(F27,IF( F27 > 0,1,-1),""))) | I27: =IF(G27,(F27-G27)/G27,IF(ISBLANK(G27),"",IF(F27,IF( F27 > 0,1,-1),"")))
A28: TOTAL DETTES FISCALES | F28: =SUM(F24:F27) -> 0 | G28: =SUM(G24:G27) -> 0 | H28: =IF(G28,(F28-G28),IF(ISBLANK(G28),"",IF(F28,IF( F28 > 0,1,-1),""))) | I28: =IF(G28,(F28-G28)/G28,IF(ISBLANK(G28),"",IF(F28,IF( F28 > 0,1,-1),""))) | J28: =SUM(J24:J27) -> 0 | K28: =SUM(K24:K27) -> 0 | L28: =SUM(L24:L27) -> 0
I29: =IF(G29,(F29-G29)/G29,IF(ISBLANK(G29),"",IF(F29,IF( F29 > 0,1,-1),"")))
A30: TOTAL DETTES FOURNISSEURS ET ASSIMILEES, DETTES FISCALES ET SOCIALES | F30: =F12+F23+F28 -> 0 | G30: =G12+G23+G28 -> 0 | H30: =IF(G30,(F30-G30),IF(ISBLANK(G30),"",IF(F30,IF( F30 > 0,1,-1),""))) | I30: =IF(G30,(F30-G30)/G30,IF(ISBLANK(G30),"",IF(F30,IF( F30 > 0,1,-1),""))) | J30: =J12+J23+J28 -> 0 | K30: =K12+K23+K28 -> 0 | L30: =L12+L23+L28 -> 0
A31: Commentaire:
A32: ● Commenter toutes variations significatives.
A33: ● Commenter les dettes anciennes.

Sheet NOTE 13
A1: - 26 -
H2: NOTE 13 SYSTEME NORMAL
A3: Dénomination sociale de l'entité : | C3: =+'NOTE 12'!C3 -> DSO Services
A4: Adresse : | C4: =+'NOTE 12'!C4 -> Rue Alphamoi Djénèpo, secteur 01, Bobo-Dioulasso, Burkina Faso | H4: Sigle usuel : | I4: =+'NOTE 12'!L4 -> DSO Services
A5: N° de compte contribuable (NCC) : | C5: =+'NOTE 12'!C5 -> 00000101A | F5: Exercice clos le : | G5: =+'NOTE 12'!G5 -> 45657 | H5: Durée (en mois) : | I5: =+'NOTE 12'!L5 -> 12
A6: N° de télédéclarant (NTD): | C6: =+'NOTE 12'!C6 -> Néant
A7: NOTE 13 : BANQUES, CREDIT D'ESCOMPTE ET DE TRESORERIE | K7: 1
A8: Libellés | F8: Année N | G8: Année N-1 | H8: Variation en
H9: Valeur | I9: %
A10: Escomptes de crédit de campagne | F10: =SUMIF('Balance N'!B:B,564,'Balance N'!P:P) -> 0 | G10: =SUMIF('Balance N-1'!B:B,564,'Balance N-1'!P:P) -> 0 | H10: =(F10-G10) -> 0 | I10: =IF(G10,(F10-G10)/G10,IF(ISBLANK(G10),"",IF(F10,IF( F10 > 0,1,-1),"")))
A11: Escomptes de crédit ordinaires | F11: =SUMIF('Balance N'!B:B,565,'Balance N'!P:P) -> 0 | G11: =SUMIF('Balance N-1'!B:B,565,'Balance N-1'!P:P) -> 0 | H11: =(F11-G11) -> 0 | I11: =IF(G11,(F11-G11)/G11,IF(ISBLANK(G11),"",IF(F11,IF( F11 > 0,1,-1),"")))
A12: TOTAL: BANQUES, CREDITS D'ESCOMPTE ET DE TRESORERIE | F12: =SUM(F10:F11) -> 0 | G12: =SUM(G10:G11) -> 0 | H12: =SUM(H10:H11) -> 0 | I12: =IF(G12,(F12-G12)/G12,IF(ISBLANK(G12),"",IF(F12,IF( F12 > 0,1,-1),"")))
A13: Banques locales | F13: =SUMIF('Balance N'!B:B,521,'Balance N'!P:P) -> 0 | G13: =SUMIF('Balance N-1'!B:B,521,'Balance N-1'!P:P) -> 0 | H13: =(F13-G13) -> 0 | I13: =IF(G13,(F13-G13)/G13,IF(ISBLANK(G13),"",IF(F13,IF( F13 > 0,1,-1),"")))
A14: Banques autres états région | F14: =SUMIF('Balance N'!B:B,522,'Balance N'!P:P) -> 0 | G14: =SUMIF('Balance N-1'!B:B,522,'Balance N-1'!P:P) -> 0 | H14: =(F14-G14) -> 0 | I14: =IF(G14,(F14-G14)/G14,IF(ISBLANK(G14),"",IF(F14,IF( F14 > 0,1,-1),"")))
A15: Autres Banques | F15: =SUMIF('Balance N'!A:A,52,'Balance N'!P:P)-(SUMIF('Balance N'!B:B,521,'Balance N'!P:P)+SUMIF('Balance N'!B:B,522,'Balance N'!P:P)) -> 0 | G15: =SUMIF('Balance N-1'!A:A,52,'Balance N-1'!P:P)-(SUMIF('Balance N-1'!B:B,521,'Balance N-1'!P:P)+SUMIF('Balance N-1'!B:B,522,'Balance N-1'!P:P)) -> 0 | H15: =(F15-G15) -> 0 | I15: =IF(G15,(F15-G15)/G15,IF(ISBLANK(G15),"",IF(F15,IF( F15 > 0,1,-1),"")))
A16: Banques intérêts courus | F16: =SUMIF('Balance N'!B:B,526,'Balance N'!P:P)+SUMIF('Balance N'!B:B,566,'Balance N'!P:P) -> 0 | G16: =SUMIF('Balance N-1'!B:B,526,'Balance N-1'!P:P)+SUMIF('Balance N-1'!B:B,566,'Balance N-1'!P:P) -> 0 | H16: =(F16-G16) -> 0 | I16: =IF(G16,(F16-G16)/G16,IF(ISBLANK(G16),"",IF(F16,IF( F16 > 0,1,-1),"")))
A17: Crédit de trésorerie | F17: =SUMIF('Balance N'!B:B,561,'Balance N'!P:P) -> 0 | G17: =SUMIF('Balance N-1'!B:B,561,'Balance N-1'!P:P) -> 0 | H17: =(F17-G17) -> 0 | I17: =IF(G17,(F17-G17)/G17,IF(ISBLANK(G17),"",IF(F17,IF( F17 > 0,1,-1),"")))
A18: TOTAL: BANQUES, CREDITS DE TRESORERIE | F18: =SUM(F13:F17) -> 0 | G18: =SUM(G13:G17) -> 0 | H18: =SUM(H13:H17) -> 0 | I18: =IF(G18,(F18-G18)/G18,IF(ISBLANK(G18),"",IF(F18,IF( F18 > 0,1,-1),"")))
A19: TOTAL GENERAL | F19: =F12+F18 -> 0 | G19: =G12+G18 -> 0 | H19: =H12+H18 -> 0 | I19: =IF(G19,(F19-G19)/G19,IF(ISBLANK(G19),"",IF(F19,IF( F19 > 0,1,-1),"")))
A20: Commentaire:
A21: ● Commenter toute variation significative.
A22: ● Indiquer le nom de l'organisme les conditions de crédit, le taux d'intérêt, la durée du crédit.
A24: NB : Banques et intérêts courus figurent dans cette rubrique si le compte principal attaché est créditeur.

Sheet NOTE 14
A1: - 27 -
H2: NOTE 14 SYSTEME NORMAL
A3: Dénomination sociale de l'entité : | C3: =+'NOTE 13'!C3 -> DSO Services | J3: NB: Certaines rubriques de cette pages seront, selon les cas, renseignées mannuellement.
A4: Adresse : | C4: =+'NOTE 13'!C4 -> Rue Alphamoi Djénèpo, secteur 01, Bobo-Dioulasso, Burkina Faso | H4: Sigle usuel : | I4: =+'NOTE 13'!I4 -> DSO Services
A5: N° de compte contribuable (NCC) : | C5: =+'NOTE 13'!C5 -> 00000101A | F5: Exercice clos le : | G5: =+'NOTE 13'!G5 -> 45657 | H5: Durée (en mois) : | I5: =+'NOTE 13'!I5 -> 12 | J5: Vous aurez à repartir les montants dans les rubriques adequates
A6: N° de télédéclarant (NTD): | C6: =+'NOTE 13'!C6 -> Néant
A7: NOTE 14 : REVENUS ET AUTRES PRODUITS | K7: 1
A8: Libellés | F8: Année N | G8: Année N-1 | H8: Variation en
H9: Valeur | I9: %
A10: Ventes de marchandises, services et produits finis | F10: =SUMIF('Balance N'!B:B,705,'Balance N'!P:P) -> 0 | G10: =SUMIF('Balance N-1'!B:B,705,'Balance N-1'!P:P) -> 0 | H10: =(F10-G10) -> 0 | I10: =IF(G10,(F10-G10)/G10,IF(ISBLANK(G10),"",IF(F10,IF( F10 > 0,1,-1),"")))
A11: Autres revenus | F11: =SUMIF('Balance N'!B:B,702,'Balance N'!P:P)-SUMIF('Balance N'!B:B,702,'Balance N'!O:O) -> 0 | G11: =SUMIF('Balance N-1'!B:B,702,'Balance N-1'!P:P)-SUMIF('Balance N-1'!B:B,702,'Balance N-1'!O:O) -> 0 | H11: =(F11-G11) -> 0 | I11: =IF(G11,(F11-G11)/G11,IF(ISBLANK(G11),"",IF(F11,IF( F11 > 0,1,-1),"")))
A12: Production immobilisée | F12: =SUMIF('Balance N'!A:A,72,'Balance N'!P:P) -> 0 | G12: =SUMIF('Balance N-1'!A:A,72,'Balance N-1'!P:P) -> 0 | H12: =(F12-G12) -> 0 | I12: =IF(G12,(F12-G12)/G12,IF(ISBLANK(G12),"",IF(F12,IF( F12 > 0,1,-1),"")))
A13: Subventions d'exploitation | F13: =SUMIF('Balance N'!A:A,71,'Balance N'!P:P) -> 0 | G13: =SUMIF('Balance N-1'!A:A,71,'Balance N-1'!P:P) -> 0 | H13: =(F13-G13) -> 0 | I13: =IF(G13,(F13-G13)/G13,IF(ISBLANK(G13),"",IF(F13,IF( F13 > 0,1,-1),"")))
A14: Autres produits et transfert de charges d'exploitation | F14: =(SUMIF('Balance N'!B:B,707,'Balance N'!P:P)-(SUMIF('Balance N'!B:B,707,'Balance N'!O:O)))+(SUMIF('Balance N'!A:A,73,'Balance N'!P:P)-SUMIF('Balance N'!A:A,73,'Balance N'!O:O))+(SUMIF('Balance N'!A:A,75,'Balance N'!P:P)-SUMIF('Balance N'!A:A,75,'Balance N'!O:O))+(SUMIF('Balance N'!A:A,77,'Balance N'!P:P)-SUMIF('Balance N'!A:A,77,'Balance N'!O:O))+(SUMIF('Balance N'!A:A,78,'Balance N'!P:P)-SUMIF('Balance N'!A:A,78,'Balance N'!O:O)) -> 0 | G14: =(SUMIF('Balance N-1'!B:B,707,'Balance N-1'!P:P)-(SUMIF('Balance N-1'!B:B,707,'Balance N-1'!O:O)))+(SUMIF('Balance N-1'!A:A,73,'Balance N-1'!P:P)-SUMIF('Balance N-1'!A:A,73,'Balance N-1'!O:O))+(SUMIF('Balance N-1'!A:A,75,'Balance N-1'!P:P)-SUMIF('Balance N-1'!A:A,75,'Balance N-1'!O:O))+(SUMIF('Balance N-1'!A:A,77,'Balance N-1'!P:P)-SUMIF('Balance N-1'!A:A,77,'Balance N-1'!O:O))+(SUMIF('Balance N-1'!A:A,78,'Balance N-1'!P:P)-SUMIF('Balance N-1'!A:A,78,'Balance N-1'!O:O)) -> 0 | H14: =(F14-G14) -> 0 | I14: =IF(G14,(F14-G14)/G14,IF(ISBLANK(G14),"",IF(F14,IF( F14 > 0,1,-1),"")))
A15: TOTAL AUTRES PRODUITS | F15: =SUM(F10:F14) -> 0 | G15: =SUM(G10:G14) -> 0 | H15: =(F15-G15) -> 0 | I15: =IF(G15,(F15-G15)/G15,IF(ISBLANK(G15),"",IF(F15,IF( F15 > 0,1,-1),"")))
A16: Commentaire:
A17: ● Justifier toute variation significative.
A18: ● Détailler: produits intermédiaires, produits résiduels, produits accessoires et autres produits si significatifs.

Sheet NOTE 15
A1: - 28 -
H2: NOTE 15 SYSTEME NORMAL
A3: Dénomination sociale de l'entité : | C3: =+'NOTE 14'!C3 -> DSO Services
A4: Adresse : | C4: =+'NOTE 14'!C4 -> Rue Alphamoi Djénèpo, secteur 01, Bobo-Dioulasso, Burkina Faso | H4: Sigle usuel : | I4: =+'NOTE 14'!I4 -> DSO Services
A5: N° de compte contribuable (NCC) : | C5: =+'NOTE 14'!C5 -> 00000101A | F5: Exercice clos le : | G5: =+'NOTE 14'!G5 -> 45657 | H5: Durée (en mois) : | I5: =+'NOTE 14'!I5 -> 12
A6: N° de télédéclarant (NTD): | C6: =+'NOTE 14'!C6 -> Néant
A7: NOTE 15 : ACHATS | K7: 1
A8: Libellés | F8: Année N | G8: Année N-1 | H8: Variation en
H9: Valeur | I9: %
A10: Achats de biens et services liés à l'activité | F10: =SUMIF('Balance N'!B:B,601,'Balance N'!O:O) -> 0 | G10: =SUMIF('Balance N-1'!B:B,601,'Balance N-1'!O:O) -> 0 | H10: =(F10-G10) -> 0 | I10: =IF(G10,(F10-G10)/G10,IF(ISBLANK(G10),"",IF(F10,IF( F10 > 0,1,-1),"")))
A11: Achats de marchandises, de matières premières et fournitures liées | F11: =SUMIF('Balance N'!B:B,602,'Balance N'!O:O) -> 0 | G11: =SUMIF('Balance N-1'!B:B,602,'Balance N-1'!O:O) -> 0 | H11: =(F11-G11) -> 0 | I11: =IF(G11,(F11-G11)/G11,IF(ISBLANK(G11),"",IF(F11,IF( F11 > 0,1,-1),"")))
A12: Matières consommables | F12: =SUMIF('Balance N'!C:C,6041,'Balance N'!O:O) -> 0 | G12: =SUMIF('Balance N-1'!C:C,6041,'Balance N-1'!O:O) -> 0 | H12: =(F12-G12) -> 0 | I12: =IF(G12,(F12-G12)/G12,IF(ISBLANK(G12),"",IF(F12,IF( F12 > 0,1,-1),"")))
A13: Matières combustibles | F13: =SUMIF('Balance N'!C:C,6042,'Balance N'!O:O) -> 0 | G13: =SUMIF('Balance N-1'!C:C,6042,'Balance N-1'!O:O) -> 0 | H13: =(F13-G13) -> 0 | I13: =IF(G13,(F13-G13)/G13,IF(ISBLANK(G13),"",IF(F13,IF( F13 > 0,1,-1),"")))
A14: Produits d'entretien | F14: =SUMIF('Balance N'!C:C,6043,'Balance N'!O:O) -> 0 | G14: =SUMIF('Balance N-1'!C:C,6043,'Balance N-1'!O:O) -> 0 | H14: =(F14-G14) -> 0 | I14: =IF(G14,(F14-G14)/G14,IF(ISBLANK(G14),"",IF(F14,IF( F14 > 0,1,-1),"")))
A15: Fournitures d'atelier, d'usine et de magasin | F15: =SUMIF('Balance N'!C:C,6044,'Balance N'!O:O)+SUMIF('Balance N'!C:C,6046,'Balance N'!O:O) -> 0 | G15: =SUMIF('Balance N-1'!C:C,6044,'Balance N-1'!O:O)+SUMIF('Balance N-1'!C:C,6046,'Balance N-1'!O:O) -> 0 | H15: =(F15-G15) -> 0 | I15: =IF(G15,(F15-G15)/G15,IF(ISBLANK(G15),"",IF(F15,IF( F15 > 0,1,-1),"")))
A16: Eau | F16: =SUMIF('Balance N'!C:C,6051,'Balance N'!O:O) -> 0 | G16: =SUMIF('Balance N-1'!C:C,6051,'Balance N-1'!O:O) -> 0 | H16: =(F16-G16) -> 0 | I16: =IF(G16,(F16-G16)/G16,IF(ISBLANK(G16),"",IF(F16,IF( F16 > 0,1,-1),"")))
A17: Electricité | F17: =SUMIF('Balance N'!C:C,6052,'Balance N'!O:O) -> 0 | G17: =SUMIF('Balance N-1'!C:C,6052,'Balance N-1'!O:O) -> 0 | H17: =(F17-G17) -> 0 | I17: =IF(G17,(F17-G17)/G17,IF(ISBLANK(G17),"",IF(F17,IF( F17 > 0,1,-1),"")))
A18: Autres énergies | F18: =SUMIF('Balance N'!C:C,6053,'Balance N'!O:O) -> 0 | G18: =SUMIF('Balance N-1'!C:C,6053,'Balance N-1'!O:O) -> 0 | H18: =(F18-G18) -> 0 | I18: =IF(G18,(F18-G18)/G18,IF(ISBLANK(G18),"",IF(F18,IF( F18 > 0,1,-1),"")))
A19: Fourniture d'entretien | F19: =SUMIF('Balance N'!C:C,6054,'Balance N'!O:O) -> 0 | G19: =SUMIF('Balance N-1'!C:C,6054,'Balance N-1'!O:O) -> 0 | H19: =(F19-G19) -> 0 | I19: =IF(G19,(F19-G19)/G19,IF(ISBLANK(G19),"",IF(F19,IF( F19 > 0,1,-1),"")))
A20: Fourniture de bureau | F20: =SUMIF('Balance N'!C:C,6055,'Balance N'!O:O) -> 0 | G20: =SUMIF('Balance N-1'!C:C,6055,'Balance N-1'!O:O) -> 0 | H20: =(F20-G20) -> 0 | I20: =IF(G20,(F20-G20)/G20,IF(ISBLANK(G20),"",IF(F20,IF( F20 > 0,1,-1),"")))
A21: Petit matériel et outillages | F21: =SUMIF('Balance N'!C:C,6056,'Balance N'!O:O) -> 0 | G21: =SUMIF('Balance N-1'!C:C,6056,'Balance N-1'!O:O) -> 0 | H21: =(F21-G21) -> 0 | I21: =IF(G21,(F21-G21)/G21,IF(ISBLANK(G21),"",IF(F21,IF( F21 > 0,1,-1),"")))
A22: Achats études, prestations de services, de travaux matériels et équipements | F22: =SUMIF('Balance N'!C:C,6057,'Balance N'!O:O)+SUMIF('Balance N'!C:C,6058,'Balance N'!O:O) -> 0 | G22: =SUMIF('Balance N-1'!C:C,6057,'Balance N-1'!O:O)+SUMIF('Balance N-1'!C:C,6058,'Balance N-1'!O:O) -> 0 | H22: =(F22-G22) -> 0 | I22: =IF(G22,(F22-G22)/G22,IF(ISBLANK(G22),"",IF(F22,IF( F22 > 0,1,-1),"")))
A23: Achats autres activités | F23: =SUMIF('Balance N'!B:B,606,'Balance N'!O:O) -> 0 | G23: =SUMIF('Balance N-1'!B:B,606,'Balance N-1'!O:O) -> 0 | H23: =(F23-G23) -> 0 | I23: =IF(G23,(F23-G23)/G23,IF(ISBLANK(G23),"",IF(F23,IF( F23 > 0,1,-1),"")))
A24: Achats d'emballages | F24: =SUMIF('Balance N'!B:B,608,'Balance N'!O:O)-(SUMIF('Balance N'!C:C,6085,'Balance N'!O:O)+SUMIF('Balance N'!C:C,6089,'Balance N'!O:O)) -> 0 | G24: =SUMIF('Balance N-1'!B:B,608,'Balance N-1'!O:O)-(SUMIF('Balance N-1'!C:C,6085,'Balance N-1'!O:O)+SUMIF('Balance N-1'!C:C,6089,'Balance N-1'!O:O)) -> 0 | H24: =(F24-G24) -> 0 | I24: =IF(G24,(F24-G24)/G24,IF(ISBLANK(G24),"",IF(F24,IF( F24 > 0,1,-1),"")))
A25: Frais sur achats (1) | F25: =SUMIF('Balance N'!C:C,6085,'Balance N'!O:O)+SUMIF('Balance N'!C:C,6015,'Balance N'!O:O)+SUMIF('Balance N'!C:C,6025,'Balance N'!O:O)+SUMIF('Balance N'!C:C,6045,'Balance N'!O:O) -> 0 | G25: =SUMIF('Balance N-1'!C:C,6085,'Balance N-1'!O:O)+SUMIF('Balance N-1'!C:C,6015,'Balance N-1'!O:O)+SUMIF('Balance N-1'!C:C,6025,'Balance N-1'!O:O)+SUMIF('Balance N-1'!C:C,6045,'Balance N-1'!O:O) -> 0 | H25: =(F25-G25) -> 0 | I25: =IF(G25,(F25-G25)/G25,IF(ISBLANK(G25),"",IF(F25,IF( F25 > 0,1,-1),"")))
A26: Remises rabais, remises et ristournes (non ventilés) | F26: =SUMIF('Balance N'!C:C,6089,'Balance N'!O:O)+SUMIF('Balance N'!C:C,6059,'Balance N'!O:O) -> 0 | G26: =SUMIF('Balance N-1'!C:C,6089,'Balance N-1'!O:O)+SUMIF('Balance N-1'!C:C,6059,'Balance N-1'!O:O) -> 0 | H26: =(F26-G26) -> 0 | I26: =IF(G26,(F26-G26)/G26,IF(ISBLANK(G26),"",IF(F26,IF( F26 > 0,1,-1),"")))
A27: TOTAL : AUTRES ACHATS | F27: =SUM(F12:F26) -> 0 | G27: =SUM(G12:G26) -> 0 | H27: =SUM(H12:H26) -> 0 | I27: =IF(G27,(F27-G27)/G27,IF(ISBLANK(G27),"",IF(F27,IF( F27 > 0,1,-1),"")))
A28: (1) voir la note "SUPPL5"
A29: Commentaire :
A30: ● Commenter toute variation significative.

Sheet NOTE 16
A1: - 29 -
H2: NOTE 16 SYSTEME NORMAL
A3: Dénomination sociale de l'entité : | C3: =+'NOTE 15'!C3 -> DSO Services | J3: NB: Certaines rubriques de cette pages seront, selon les cas, renseignées mannuellement.
A4: Adresse : | C4: =+'NOTE 15'!C4 -> Rue Alphamoi Djénèpo, secteur 01, Bobo-Dioulasso, Burkina Faso | H4: Sigle usuel : | I4: =+'NOTE 15'!I4 -> DSO Services | J4: Vous aurez à repartir les montants dans les rubriques adequates
A5: N° d'identification fiscale : | C5: =+'NOTE 15'!C5 -> 00000101A | F5: Exercice clos le : | G5: =+'NOTE 15'!G5 -> 45657 | H5: Durée (en mois) : | I5: =+'NOTE 15'!I5 -> 12
A6: N° de télédéclarant (NTD): | C6: =+'NOTE 15'!C6 -> Néant
A7: NOTE 16 : TRANSPORTS | K7: 1
A8: Libellés | F8: Année N | G8: Année N-1 | H8: Variation en
H9: Valeur | I9: %
A10: Transports sur ventes | F10: =SUMIF('Balance N'!B:B,612,'Balance N'!O:O) -> 0 | G10: =SUMIF('Balance N-1'!B:B,612,'Balance N-1'!O:O) -> 0 | H10: =(F10-G10) -> 0 | I10: =IF(G10,(F10-G10)/G10,IF(ISBLANK(G10),"",IF(F10,IF( F10 > 0,1,-1),"")))
A11: Transports pour le compte de tiers | F11: =SUMIF('Balance N'!B:B,613,'Balance N'!O:O) -> 0 | G11: =SUMIF('Balance N-1'!B:B,613,'Balance N-1'!O:O) -> 0 | H11: =(F11-G11) -> 0 | I11: =IF(G11,(F11-G11)/G11,IF(ISBLANK(G11),"",IF(F11,IF( F11 > 0,1,-1),"")))
A12: Transport du personnel | F12: =SUMIF('Balance N'!B:B,614,'Balance N'!O:O) -> 0 | G12: =SUMIF('Balance N-1'!B:B,614,'Balance N-1'!O:O) -> 0 | H12: =(F12-G12) -> 0 | I12: =IF(G12,(F12-G12)/G12,IF(ISBLANK(G12),"",IF(F12,IF( F12 > 0,1,-1),"")))
A13: Transports de plis | F13: =SUMIF('Balance N'!B:B,616,'Balance N'!O:O) -> 0 | G13: =SUMIF('Balance N-1'!B:B,616,'Balance N-1'!O:O) -> 0 | H13: =(F13-G13) -> 0 | I13: =IF(G13,(F13-G13)/G13,IF(ISBLANK(G13),"",IF(F13,IF( F13 > 0,1,-1),"")))
A14: Voyages et déplacements (transport) | F14: =SUMIF('Balance N'!C:C,6181,'Balance N'!O:O) -> 0 | G14: =SUMIF('Balance N-1'!C:C,6181,'Balance N-1'!O:O) -> 0 | H14: =(F14-G14) -> 0 | I14: =IF(G14,(F14-G14)/G14,IF(ISBLANK(G14),"",IF(F14,IF( F14 > 0,1,-1),"")))
A15: Transports administratifs | F15: =SUMIF('Balance N'!C:C,6183,'Balance N'!O:O) -> 0 | G15: =SUMIF('Balance N-1'!C:C,6183,'Balance N-1'!O:O) -> 0 | H15: =(F15-G15) -> 0 | I15: =IF(G15,(F15-G15)/G15,IF(ISBLANK(G15),"",IF(F15,IF( F15 > 0,1,-1),"")))
A16: Autres transports | F16: =SUMIF('Balance N'!B:B,618,'Balance N'!O:O)-(SUMIF('Balance N'!C:C,6183,'Balance N'!O:O)+SUMIF('Balance N'!C:C,6181,'Balance N'!O:O)) -> 0 | G16: =SUMIF('Balance N-1'!B:B,618,'Balance N-1'!O:O)-(SUMIF('Balance N-1'!C:C,6183,'Balance N-1'!O:O)+SUMIF('Balance N-1'!C:C,6181,'Balance N-1'!O:O)) -> 0 | H16: =(F16-G16) -> 0 | I16: =IF(G16,(F16-G16)/G16,IF(ISBLANK(G16),"",IF(F16,IF( F16 > 0,1,-1),"")))
A17: TOTAL | F17: =SUM(F10:F16) -> 0 | G17: =SUM(G10:G16) -> 0 | H17: =SUM(H10:H16) -> 0 | I17: =IF(G17,(F17-G17)/G17,IF(ISBLANK(G17),"",IF(F17,IF( F17 > 0,1,-1),"")))
A18: Commentaire :
A19: ● Commenter toute variation significative.

Sheet NOTE 17
A1: - 30 -
H2: NOTE 17 SYSTEME NORMAL
A3: Dénomination sociale de l'entité : | C3: =+'NOTE 16'!C3 -> DSO Services | J3: NB: Certaines rubriques de cette pages seront, selon les cas, renseignées mannuellement.
A4: Adresse : | B4: 0 | C4: =+'NOTE 16'!C4 -> Rue Alphamoi Djénèpo, secteur 01, Bobo-Dioulasso, Burkina Faso | H4: Sigle usuel : | I4: =+'NOTE 16'!I4 -> DSO Services | J4: Vous aurez à repartir les montants dans les rubriques adequates
A5: N° d'identification fiscale : | C5: =+'NOTE 16'!C5 -> 00000101A | F5: Exercice clos le : | G5: =+'NOTE 16'!G5 -> 45657 | H5: Durée (en mois) : | I5: =+'NOTE 16'!I5 -> 12
A6: N° de télédéclarant (NTD): | C6: =+'NOTE 16'!C6 -> Néant
A7: NOTE 17 : SERVICES EXTERIEURS | K7: 1
A8: Libellés | F8: Année N | G8: Année N-1 | H8: Variation en
H9: Valeur | I9: %
A10: Sous-traitance générale | F10: =SUMIF('Balance N'!B:B,621,'Balance N'!O:O) -> 0 | G10: =SUMIF('Balance N-1'!B:B,621,'Balance N-1'!O:O) -> 0 | H10: =(F10-G10) -> 0 | I10: =IF(G10,(F10-G10)/G10,IF(ISBLANK(G10),"",IF(F10,IF( F10 > 0,1,-1),"")))
A11: Locations et charges locatives | F11: =SUMIF('Balance N'!B:B,622,'Balance N'!O:O) -> 0 | G11: =SUMIF('Balance N-1'!B:B,622,'Balance N-1'!O:O) -> 0 | H11: =(F11-G11) -> 0 | I11: =IF(G11,(F11-G11)/G11,IF(ISBLANK(G11),"",IF(F11,IF( F11 > 0,1,-1),"")))
A12: Redevances de location acquisition | F12: =SUMIF('Balance N'!B:B,623,'Balance N'!O:O) -> 0 | G12: =SUMIF('Balance N-1'!B:B,623,'Balance N-1'!O:O) -> 0 | H12: =(F12-G12) -> 0 | I12: =IF(G12,(F12-G12)/G12,IF(ISBLANK(G12),"",IF(F12,IF( F12 > 0,1,-1),"")))
A13: Entretien, réparations et maintenance | F13: =SUMIF('Balance N'!B:B,624,'Balance N'!O:O) -> 0 | G13: =SUMIF('Balance N-1'!B:B,624,'Balance N-1'!O:O) -> 0 | H13: =(F13-G13) -> 0 | I13: =IF(G13,(F13-G13)/G13,IF(ISBLANK(G13),"",IF(F13,IF( F13 > 0,1,-1),"")))
A14: Primes d'assurance | F14: =SUMIF('Balance N'!B:B,625,'Balance N'!O:O) -> 0 | G14: =SUMIF('Balance N-1'!B:B,625,'Balance N-1'!O:O) -> 0 | H14: =(F14-G14) -> 0 | I14: =IF(G14,(F14-G14)/G14,IF(ISBLANK(G14),"",IF(F14,IF( F14 > 0,1,-1),"")))
A15: Etudes, recherches et documentation | F15: =SUMIF('Balance N'!B:B,626,'Balance N'!O:O) -> 0 | G15: =SUMIF('Balance N-1'!B:B,626,'Balance N-1'!O:O) -> 0 | H15: =(F15-G15) -> 0 | I15: =IF(G15,(F15-G15)/G15,IF(ISBLANK(G15),"",IF(F15,IF( F15 > 0,1,-1),"")))
A16: Publicité, publications, relations publiques | F16: =SUMIF('Balance N'!B:B,627,'Balance N'!O:O) -> 0 | G16: =SUMIF('Balance N-1'!B:B,627,'Balance N-1'!O:O) -> 0 | H16: =(F16-G16) -> 0 | I16: =IF(G16,(F16-G16)/G16,IF(ISBLANK(G16),"",IF(F16,IF( F16 > 0,1,-1),"")))
A17: Frais de télécommunications | F17: =SUMIF('Balance N'!B:B,628,'Balance N'!O:O) -> 0 | G17: =SUMIF('Balance N-1'!B:B,628,'Balance N-1'!O:O) -> 0 | H17: =(F17-G17) -> 0 | I17: =IF(G17,(F17-G17)/G17,IF(ISBLANK(G17),"",IF(F17,IF( F17 > 0,1,-1),"")))
A18: Frais bancaires | F18: =SUMIF('Balance N'!B:B,631,'Balance N'!O:O) -> 0 | G18: =SUMIF('Balance N-1'!B:B,631,'Balance N-1'!O:O) -> 0 | H18: =(F18-G18) -> 0 | I18: =IF(G18,(F18-G18)/G18,IF(ISBLANK(G18),"",IF(F18,IF( F18 > 0,1,-1),"")))
A19: Rémunérations d'intermédiaires et de conseils | F19: =SUMIF('Balance N'!B:B,632,'Balance N'!O:O) -> 0 | G19: =SUMIF('Balance N-1'!B:B,632,'Balance N-1'!O:O) -> 0 | H19: =(F19-G19) -> 0 | I19: =IF(G19,(F19-G19)/G19,IF(ISBLANK(G19),"",IF(F19,IF( F19 > 0,1,-1),"")))
A20: Frais de formation du personnel | F20: =SUMIF('Balance N'!B:B,633,'Balance N'!O:O) -> 0 | G20: =SUMIF('Balance N-1'!B:B,633,'Balance N-1'!O:O) -> 0 | H20: =(F20-G20) -> 0 | I20: =IF(G20,(F20-G20)/G20,IF(ISBLANK(G20),"",IF(F20,IF( F20 > 0,1,-1),"")))
A21: Redevances pour brevets, licences, logiciels, concession et droits similaires | F21: =SUMIF('Balance N'!B:B,634,'Balance N'!O:O) -> 0 | G21: =SUMIF('Balance N-1'!B:B,634,'Balance N-1'!O:O) -> 0 | H21: =(F21-G21) -> 0 | I21: =IF(G21,(F21-G21)/G21,IF(ISBLANK(G21),"",IF(F21,IF( F21 > 0,1,-1),"")))
A22: Cotisations | F22: =SUMIF('Balance N'!B:B,635,'Balance N'!O:O) -> 0 | G22: =SUMIF('Balance N-1'!B:B,635,'Balance N-1'!O:O) -> 0 | H22: =(F22-G22) -> 0 | I22: =IF(G22,(F22-G22)/G22,IF(ISBLANK(G22),"",IF(F22,IF( F22 > 0,1,-1),"")))
A23: Frais de recherche de fonds | F23: =SUMIF('Balance N'!B:B,636,'Balance N'!O:O) -> 0 | G23: =SUMIF('Balance N-1'!B:B,636,'Balance N-1'!O:O) -> 0 | H23: =(F23-G23) -> 0 | I23: =IF(G23,(F23-G23)/G23,IF(ISBLANK(G23),"",IF(F23,IF( F23 > 0,1,-1),"")))
A24: Rémunérations de personnel extérieur à l'entité | F24: =SUMIF('Balance N'!B:B,637,'Balance N'!O:O) -> 0 | G24: =SUMIF('Balance N-1'!B:B,637,'Balance N-1'!O:O) -> 0 | H24: =(F24-G24) -> 0 | I24: =IF(G24,(F24-G24)/G24,IF(ISBLANK(G24),"",IF(F24,IF( F24 > 0,1,-1),"")))
A25: Autres charges externes | F25: =SUMIF('Balance N'!B:B,638,'Balance N'!O:O) -> 0 | G25: =SUMIF('Balance N-1'!B:B,638,'Balance N-1'!O:O) -> 0 | H25: =(F25-G25) -> 0 | I25: =IF(G25,(F25-G25)/G25,IF(ISBLANK(G25),"",IF(F25,IF( F25 > 0,1,-1),"")))
A26: TOTAL | F26: =SUM(F10:F25) -> 0 | G26: =SUM(G10:G25) -> 0 | H26: =SUM(H10:H25) -> 0 | I26: =IF(G26,(F26-G26)/G26,IF(ISBLANK(G26),"",IF(F26,IF( F26 > 0,1,-1),"")))
A27: Commentaire :
A28: ● Commenter toute variation significative.

Sheet NOTE 18
A1: - 31 -
H2: NOTE 18 SYSTEME NORMAL
A3: Dénomination sociale de l'entité : | C3: =+'NOTE 17'!C3 -> DSO Services
A4: Adresse : | C4: =+'NOTE 17'!C4 -> Rue Alphamoi Djénèpo, secteur 01, Bobo-Dioulasso, Burkina Faso | H4: Sigle usuel : | I4: =+'NOTE 17'!I4 -> DSO Services
A5: N° d'identification fiscale : | C5: =+'NOTE 17'!C5 -> 00000101A | F5: Exercice clos le : | G5: =+'NOTE 17'!G5 -> 45657 | H5: Durée (en mois) : | I5: =+'NOTE 17'!I5 -> 12
A6: N° de télédéclarant (NTD): | C6: =+'NOTE 17'!C6 -> Néant
A7: NOTE 18 : IMPOTS ET TAXES | K7: 1
A8: Libellés | F8: Année N | G8: Année N-1 | H8: Variation en
H9: Valeur | I9: %
A10: Impôts et taxes directs | F10: =SUMIF('Balance N'!B:B,641,'Balance N'!O:O) -> 0 | G10: =SUMIF('Balance N-1'!B:B,641,'Balance N-1'!O:O) -> 0 | H10: =(F10-G10) -> 0 | I10: =IF(G10,(F10-G10)/G10,IF(ISBLANK(G10),"",IF(F10,IF( F10 > 0,1,-1),"")))
A11: Impôts et taxes indirects | F11: =SUMIF('Balance N'!B:B,645,'Balance N'!O:O) -> 0 | G11: =SUMIF('Balance N-1'!B:B,645,'Balance N-1'!O:O) -> 0 | H11: =(F11-G11) -> 0 | I11: =IF(G11,(F11-G11)/G11,IF(ISBLANK(G11),"",IF(F11,IF( F11 > 0,1,-1),"")))
A12: Droits d'enregistrement | F12: =SUMIF('Balance N'!B:B,646,'Balance N'!O:O) -> 0 | G12: =SUMIF('Balance N-1'!B:B,646,'Balance N-1'!O:O) -> 0 | H12: =(F12-G12) -> 0 | I12: =IF(G12,(F12-G12)/G12,IF(ISBLANK(G12),"",IF(F12,IF( F12 > 0,1,-1),"")))
A13: Pénalités et amendes fiscales | F13: =SUMIF('Balance N'!B:B,647,'Balance N'!O:O) -> 0 | G13: =SUMIF('Balance N-1'!B:B,647,'Balance N-1'!O:O) -> 0 | H13: =(F13-G13) -> 0 | I13: =IF(G13,(F13-G13)/G13,IF(ISBLANK(G13),"",IF(F13,IF( F13 > 0,1,-1),"")))
A14: Autres impôts et taxes | F14: =SUMIF('Balance N'!B:B,648,'Balance N'!O:O) -> 0 | G14: =SUMIF('Balance N-1'!B:B,648,'Balance N-1'!O:O) -> 0 | H14: =(F14-G14) -> 0 | I14: =IF(G14,(F14-G14)/G14,IF(ISBLANK(G14),"",IF(F14,IF( F14 > 0,1,-1),"")))
A15: Dégrèvement et annulations des impôts et taxes (1) | F15: =SUMIF('Balance N'!B:B,649,'Balance N'!P:P) -> 0 | G15: =SUMIF('Balance N-1'!B:B,649,'Balance N-1'!P:P) -> 0 | H15: =(F15-G15) -> 0 | I15: =IF(G15,(F15-G15)/G15,IF(ISBLANK(G15),"",IF(F15,IF( F15 > 0,1,-1),"")))
A16: TOTAL | F16: =SUM(F10:F15) -> 0 | G16: =SUM(G10:G15) -> 0 | H16: =SUM(H10:H15) -> 0 | I16: =IF(G16,(F16-G16)/G16,IF(ISBLANK(G16),"",IF(F16,IF( F16 > 0,1,-1),"")))
A17: Commentaire:
A18: ● Commenter toute variation significative.
A19: ● Détailler les pénalités et amendes et indiquer la cause.
A20: (1) : Ce compte a un solde créditeur, son montant doit être précédé d’un signe (-)

Sheet NOTE 19
A1: - 32 -
H2: NOTE 19 SYSTEME NORMAL
A3: Dénomination sociale de l'entité : | C3: =+'NOTE 18'!C3 -> DSO Services
A4: Adresse : | C4: =+'NOTE 18'!C4 -> Rue Alphamoi Djénèpo, secteur 01, Bobo-Dioulasso, Burkina Faso | H4: Sigle usuel : | I4: =+'NOTE 18'!I4 -> DSO Services
A5: N° d'identification fiscale : | C5: =+'NOTE 18'!C5 -> 00000101A | F5: Exercice clos le : | G5: =+'NOTE 18'!G5 -> 45657 | H5: Durée (en mois) : | I5: =+'NOTE 18'!I5 -> 12
A6: N° de télédéclarant (NTD): | C6: =+'NOTE 18'!C6 -> Néant
A7: NOTE 19 : AUTRES CHARGES | K7: 1
A8: Libellés | F8: Année N | G8: Année N-1 | H8: Variation en
H9: Valeur | I9: %
A10: Pertes sur créances clients-usagers | F10: =SUMIF('Balance N'!C:C,6511,'Balance N'!O:O) -> 0 | G10: =SUMIF('Balance N-1'!C:C,6511,'Balance N-1'!O:O) -> 0 | H10: =(F10-G10) -> 0 | I10: =IF(G10,(F10-G10)/G10,IF(ISBLANK(G10),"",IF(F10,IF( F10 > 0,1,-1),"")))
A11: Pertes sur clients et autres débiteurs | F11: =SUMIF('Balance N'!C:C,6515,'Balance N'!O:O) -> 0 | G11: =SUMIF('Balance N-1'!C:C,6515,'Balance N-1'!O:O) -> 0 | H11: =(F11-G11) -> 0 | I11: =IF(G11,(F11-G11)/G11,IF(ISBLANK(G11),"",IF(F11,IF( F11 > 0,1,-1),"")))
A12: Perte de change sur créances | B12: Perte de change sur créances | C12: Perte de change sur créances | D12: Perte de change sur créances | E12: Perte de change sur créances | F12: =SUMIF('Balance N'!B:B,652,'Balance N'!O:O) -> 0 | G12: =SUMIF('Balance N-1'!B:B,652,'Balance N-1'!O:O) -> 0 | H12: =(F12-G12) -> 0 | I12: =IF(G12,(F12-G12)/G12,IF(ISBLANK(G12),"",IF(F12,IF( F12 > 0,1,-1),"")))
A13: Pénalités et amendes pénales | B13: Pénalités et amendes pénales | C13: Pénalités et amendes pénales | D13: Pénalités et amendes pénales | E13: Pénalités et amendes pénales | F13: =SUMIF('Balance N'!B:B,657,'Balance N'!O:O) -> 0 | G13: =SUMIF('Balance N-1'!B:B,657,'Balance N-1'!O:O) -> 0 | H13: =(F13-G13) -> 0 | I13: =IF(G13,(F13-G13)/G13,IF(ISBLANK(G13),"",IF(F13,IF( F13 > 0,1,-1),"")))
A14: Dons et mécénat | B14: Dons et mécénat | C14: Dons et mécénat | D14: Dons et mécénat | E14: Dons et mécénat | F14: =SUMIF('Balance N'!B:B,654,'Balance N'!O:O) -> 0 | G14: =SUMIF('Balance N-1'!B:B,654,'Balance N-1'!O:O) -> 0 | H14: =(F14-G14) -> 0 | I14: =IF(G14,(F14-G14)/G14,IF(ISBLANK(G14),"",IF(F14,IF( F14 > 0,1,-1),"")))
A15: Autres charges diverses | B15: Autres charges diverses | C15: Autres charges diverses | D15: Autres charges diverses | E15: Autres charges diverses | F15: =SUMIF('Balance N'!B:B,658,'Balance N'!O:O) -> 0 | G15: =SUMIF('Balance N-1'!B:B,658,'Balance N-1'!O:O) -> 0 | H15: =(F15-G15) -> 0 | I15: =IF(G15,(F15-G15)/G15,IF(ISBLANK(G15),"",IF(F15,IF( F15 > 0,1,-1),"")))
A16: Charges pour dépréciations et provisions pour risques à court terme d'exploitation (voir note 20) | F16: =SUMIF('Balance N'!B:B,659,'Balance N'!O:O) -> 0 | G16: =SUMIF('Balance N-1'!B:B,659,'Balance N-1'!O:O) -> 0 | H16: =(F16-G16) -> 0 | I16: =IF(G16,(F16-G16)/G16,IF(ISBLANK(G16),"",IF(F16,IF( F16 > 0,1,-1),"")))
A17: TOTAL | F17: =SUM(F10:F16) -> 0 | G17: =SUM(G10:G16) -> 0 | H17: =SUM(H10:H16) -> 0 | I17: =IF(G17,(F17-G17)/G17,IF(ISBLANK(G17),"",IF(F17,IF( F17 > 0,1,-1),"")))
A18: Commentaire :
A19: ● Commenter toute variation significative.
A20: ● Indiquer les organismes bénéficiaires des dons.

Sheet NOTE 20A
A1: - 33 -
H2: NOTE 20A SYSTEME NORMAL
A3: Dénomination sociale de l'entité : | C3: =+'NOTE 19'!C3 -> DSO Services
A4: Adresse : | C4: =+'NOTE 19'!C4 -> Rue Alphamoi Djénèpo, secteur 01, Bobo-Dioulasso, Burkina Faso | H4: Sigle usuel : | I4: =+'NOTE 19'!I4 -> DSO Services
A5: N° d'identification fiscale : | C5: =+'NOTE 19'!C5 -> 00000101A | F5: Exercice clos le : | G5: =+'NOTE 19'!G5 -> 45657 | H5: Durée (en mois) : | I5: =+'NOTE 19'!I5 -> 12
A6: N° de télédéclarant (NTD): | C6: =+'NOTE 19'!C6 -> Néant
A7: NOTE 20A : CHARGES DE PERSONNEL | K7: 1
A8: Libellés | F8: Année N | G8: Année N-1 | H8: Variation en
H9: Valeur | I9: %
A10: Rémunérations directes versées au personnel national | F10: =SUMIF('Balance N'!B:B,661,'Balance N'!O:O) -> 0 | G10: =SUMIF('Balance N-1'!B:B,661,'Balance N-1'!O:O) -> 0 | H10: =(F10-G10) -> 0 | I10: =IF(G10,(F10-G10)/G10,IF(ISBLANK(G10),"",IF(F10,IF( F10 > 0,1,-1),"")))
A11: Rémunérations directes versées au personnel non national | F11: =SUMIF('Balance N'!B:B,662,'Balance N'!O:O) -> 0 | G11: =SUMIF('Balance N-1'!B:B,662,'Balance N-1'!O:O) -> 0 | H11: =(F11-G11) -> 0 | I11: =IF(G11,(F11-G11)/G11,IF(ISBLANK(G11),"",IF(F11,IF( F11 > 0,1,-1),"")))
A12: Indemnités forfaitaires versées au personnel | F12: =SUMIF('Balance N'!B:B,663,'Balance N'!O:O) -> 0 | G12: =SUMIF('Balance N-1'!B:B,663,'Balance N-1'!O:O) -> 0 | H12: =(F12-G12) -> 0 | I12: =IF(G12,(F12-G12)/G12,IF(ISBLANK(G12),"",IF(F12,IF( F12 > 0,1,-1),"")))
A13: Charges sociales (personnel national) | F13: =SUMIF('Balance N'!C:C,6641,'Balance N'!O:O) -> 0 | G13: =SUMIF('Balance N-1'!C:C,6641,'Balance N-1'!O:O) -> 0 | H13: =(F13-G13) -> 0 | I13: =IF(G13,(F13-G13)/G13,IF(ISBLANK(G13),"",IF(F13,IF( F13 > 0,1,-1),"")))
A14: Charges sociales (personnel non national) | F14: =SUMIF('Balance N'!C:C,6642,'Balance N'!O:O) -> 0 | G14: =SUMIF('Balance N-1'!C:C,6642,'Balance N-1'!O:O) -> 0 | H14: =(F14-G14) -> 0 | I14: =IF(G14,(F14-G14)/G14,IF(ISBLANK(G14),"",IF(F14,IF( F14 > 0,1,-1),"")))
A15: Habillement et équipement du personnel | F15: =SUMIF('Balance N'!B:B,665,'Balance N'!O:O) -> 0 | G15: =SUMIF('Balance N-1'!B:B,665,'Balance N-1'!O:O) -> 0 | H15: =(F15-G15) -> 0 | I15: =IF(G15,(F15-G15)/G15,IF(ISBLANK(G15),"",IF(F15,IF( F15 > 0,1,-1),"")))
A16: Rémunération transférée de personnel extérieur | F16: =SUMIF('Balance N'!B:B,667,'Balance N'!O:O) -> 0 | G16: =SUMIF('Balance N-1'!B:B,667,'Balance N-1'!O:O) -> 0 | H16: =(F16-G16) -> 0 | I16: =IF(G16,(F16-G16)/G16,IF(ISBLANK(G16),"",IF(F16,IF( F16 > 0,1,-1),"")))
A17: Autres charges sociales | F17: =SUMIF('Balance N'!B:B,668,'Balance N'!O:O) -> 0 | G17: =SUMIF('Balance N-1'!B:B,668,'Balance N-1'!O:O) -> 0 | H17: =(F17-G17) -> 0 | I17: =IF(G17,(F17-G17)/G17,IF(ISBLANK(G17),"",IF(F17,IF( F17 > 0,1,-1),"")))
A18: Dégrèvements et annulations des charges sociales (1) | F18: =SUMIF('Balance N'!B:B,669,'Balance N'!P:P) -> 0 | G18: =SUMIF('Balance N-1'!B:B,669,'Balance N-1'!P:P) -> 0 | H18: =(F18-G18) -> 0 | I18: =IF(G18,(F18-G18)/G18,IF(ISBLANK(G18),"",IF(F18,IF( F18 > 0,1,-1),"")))
A19: TOTAL | F19: =SUM(F10:F18) -> 0 | G19: =SUM(G10:G18) -> 0 | H19: =SUM(H10:H18) -> 0 | I19: =IF(G19,(F19-G19)/G19,IF(ISBLANK(G19),"",IF(F19,IF( F19 > 0,1,-1),"")))
A20: Commentaire :
A21: ● Commenter toute variation significative.
A22: ● Indiquer la nature et la durée du contrat du personnel extérieur.
A23: (1) : Ce compte a un solde créditeur, son montant doit être précédé d’un signe (-)

Sheet NOTE 20B
A1: - 34 -
R2: NOTE 20B SYSTEME NORMAL
A3: Dénomination sociale de l'entité : | D3: =+'NOTE 20A'!C3 -> DSO Services | T3: NB: Certaines rubriques de cette pages seront, selon les cas, renseignées mannuellement.
A4: Adresse : | D4: =+'NOTE 20A'!C4 -> Rue Alphamoi Djénèpo, secteur 01, Bobo-Dioulasso, Burkina Faso | R4: Sigle usuel : | S4: =+'NOTE 20A'!I4 -> DSO Services
A5: N° d'identification fiscale : | D5: =+'NOTE 20A'!C5 -> 00000101A | L5: Exercice clos le : | O5: =+'NOTE 20A'!G5 -> 45657 | R5: Durée (en mois) : | S5: =+'NOTE 20A'!I5 -> 12 | T5: Vous aurez à repartir les montants dans les rubriques adequates
A6: N° de télédéclarant (NTD): | D6: =+'NOTE 20A'!C6 -> Néant
A7: NOTE 20B : EFFECTIFS, MASSE SALARIALE ET PERSONNEL EXTERIEUR | U7: 0
B8: EFFECTIF ET MASSE SALARIALE | E8: EFFECTIFS | L8: MASSE SALARIALE
E9: Nationaux | G9: Autres Etats de la Région (3) | I9: Hors Région (3) | K9: TOTAL | L9: Nationaux | O9: Autres Etats de la Région (3) | Q9: Hors Région (3) | S9: TOTAL
B11: QUALIFICATIONS | E11: M | F11: F | G11: M | H11: F | I11: M | J11: F | L11: M | M11: F | O11: M | P11: F | Q11: M | R11: F
A12: YA | B12: 1. Cadres supérieurs | K12: =SUM(E12:J12) -> 0 | S12: =SUM(L12+M12+O12+P12+Q12+R12) -> 0
A13: YB | B13: 2. Techniciens supérieurs et cadres moyens | K13: =SUM(E13:J13) -> 0 | S13: =SUM(L13+M13+O13+P13+Q13+R13) -> 0
A14: YC | B14: 3. Techniciens, agents de maîtrise et ouvriers qualifiés | K14: =SUM(E14:J14) -> 0 | S14: =SUM(L14+M14+O14+P14+Q14+R14) -> 0
A15: YD | B15: 4. Employés, manœuvres, ouvriers, et apprentis | K15: =SUM(E15:J15) -> 0 | S15: =SUM(L15+M15+O15+P15+Q15+R15) -> 0
A16: YE | B16: TOTAL (1) (A) | E16: =SUM(E12:E15) -> 0 | F16: =SUM(F12:F15) -> 0 | G16: =SUM(G12:G15) -> 0 | H16: =SUM(H12:H15) -> 0 | I16: =SUM(I12:I15) -> 0 | J16: =SUM(J12:J15) -> 0 | K16: =SUM(K12:K15) -> 0 | L16: =SUM(L12:L15) -> 0 | M16: =SUM(M12:M15) -> 0 | O16: =SUM(O12:O15) -> 0 | P16: =SUM(P12:P15) -> 0 | Q16: =SUM(Q12:Q15) -> 0 | R16: =SUM(R12:R15) -> 0 | S16: =SUM(S12:S15) -> 0
A17: YF | B17: Permanents | E17: 0 | F17: 0 | G17: 0 | H17: 0 | I17: 0 | J17: 0 | K17: =SUM(E17:J17) -> 0 | L17: 0 | M17: 0 | O17: 0 | P17: 0 | Q17: 0 | R17: 0 | S17: =L17+M17+O17+P17+Q17+R17 -> 0
A18: YG | B18: Saisonniers | K18: =SUM(E18:J18) -> 0 | S18: =L18+M18+O18+P18+Q18+R18 -> 0
L20: Facturation à l'entité
B21: 2. Personnel extérieur et bénévole
A22: YH | B22: 1. Cadres supérieurs | K22: =SUM(E22:J22) -> 0 | P22: M : Masculin
A23: YI | B23: 2. Techniciens supérieurs et cadres moyens | K23: =SUM(E23:J23) -> 0 | P23: F : Féminin
A24: YJ | B24: 3. Techniciens, agents de maîtrise et ouvriers qualifiés | K24: =SUM(E24:J24) -> 0
A25: YK | B25: 4. Employés, manœuvres, ouvriers, et apprentis | K25: =SUM(E25:J25) -> 0
A26: YL | B26: TOTAL (2) | E26: =SUM(E22:E25) -> 0 | F26: =SUM(F22:F25) -> 0 | G26: =SUM(G22:G25) -> 0 | H26: =SUM(H22:H25) -> 0 | I26: =SUM(I22:I25) -> 0 | J26: =SUM(J22:J25) -> 0 | K26: =SUM(K22:K25) -> 0 | L26: =SUM(L22:L25) -> 0 | M26: =SUM(M22:M25) -> 0
A27: YM | B27: Permanents | E27: 0 | F27: 0 | G27: 0 | H27: 0 | I27: 0 | J27: 0 | K27: =SUM(E27:J27) -> 0 | L27: 0 | M27: 0
A28: YN | B28: Saisonniers | K28: =SUM(E28:J28) -> 0
A29: YO | B29: TOTAL (1 + 2) | E29: =E16+E26 -> 0 | F29: =F16+F26 -> 0 | G29: =G16+G26 -> 0 | H29: =H16+H26 -> 0 | I29: =I16+I26 -> 0 | J29: =J16+J26 -> 0 | K29: =K16+K26 -> 0
A30: Commentaire:
A31: ● Faire un commentaire si nécessaire en cas de mouvement significatif du personnel

Sheet NOTE 21
A1: - 35 -
H2: NOTE 21 SYSTEME NORMAL
A3: Dénomination sociale de l'entité : | C3: =+'NOTE 20B'!D3 -> DSO Services
A4: Adresse : | C4: =+'NOTE 20B'!D4 -> Rue Alphamoi Djénèpo, secteur 01, Bobo-Dioulasso, Burkina Faso | G4: Sigle usuel : | H4: =+'NOTE 20B'!S4 -> DSO Services
A5: N° d'identification fiscale : | C5: =+'NOTE 20B'!D5 -> 00000101A | E5: Exercice clos le : | F5: =+'NOTE 20B'!O5 -> 45657 | G5: Durée (en mois) : | H5: =+'NOTE 20B'!S5 -> 12
A6: N° de télédéclarant (NTD): | C6: =+'NOTE 20B'!D6 -> Néant
A7: NOTE 21 : CHARGES ET REVENUS FINANCIERS | K7: 1
A8: Libellés | F8: Année N | G8: Année N-1 | H8: Variation en
H9: Valeur | I9: %
A10: Intérêts des emprunts | F10: =SUMIF('Balance N'!B:B,671,'Balance N'!O:O) -> 0 | G10: =SUMIF('Balance N-1'!B:B,671,'Balance N-1'!O:O) -> 0 | H10: =(F10-G10) -> 0 | I10: =IF(G10,(F10-G10)/G10,IF(ISBLANK(G10),"",IF(F10,IF( F10 > 0,1,-1),"")))
A11: Intérêts dans loyers de locations acquisition | F11: =SUMIF('Balance N'!B:B,672,'Balance N'!O:O) -> 0 | G11: =SUMIF('Balance N-1'!B:B,672,'Balance N-1'!O:O) -> 0 | H11: =(F11-G11) -> 0 | I11: =IF(G11,(F11-G11)/G11,IF(ISBLANK(G11),"",IF(F11,IF( F11 > 0,1,-1),"")))
A12: Escomptes accordés | F12: =SUMIF('Balance N'!B:B,673,'Balance N'!O:O) -> 0 | G12: =SUMIF('Balance N-1'!B:B,673,'Balance N-1'!O:O) -> 0 | H12: =(F12-G12) -> 0 | I12: =IF(G12,(F12-G12)/G12,IF(ISBLANK(G12),"",IF(F12,IF( F12 > 0,1,-1),"")))
A13: Autres intérêts | F13: =SUMIF('Balance N'!B:B,674,'Balance N'!O:O) -> 0 | G13: =SUMIF('Balance N-1'!B:B,674,'Balance N-1'!O:O) -> 0 | H13: =(F13-G13) -> 0 | I13: =IF(G13,(F13-G13)/G13,IF(ISBLANK(G13),"",IF(F13,IF( F13 > 0,1,-1),"")))
A14: Pertes de change financières | F14: =SUMIF('Balance N'!B:B,676,'Balance N'!O:O) -> 0 | G14: =SUMIF('Balance N-1'!B:B,676,'Balance N-1'!O:O) -> 0 | H14: =(F14-G14) -> 0 | I14: =IF(G14,(F14-G14)/G14,IF(ISBLANK(G14),"",IF(F14,IF( F14 > 0,1,-1),"")))
A15: Pertes sur cessions de titres de placement | F15: =SUMIF('Balance N'!B:B,677,'Balance N'!O:O) -> 0 | G15: =SUMIF('Balance N-1'!B:B,677,'Balance N-1'!O:O) -> 0 | H15: =(F15-G15) -> 0 | I15: =IF(G15,(F15-G15)/G15,IF(ISBLANK(G15),"",IF(F15,IF( F15 > 0,1,-1),"")))
A16: Pertes et charges sur risques financiers | F16: =SUMIF('Balance N'!B:B,678,'Balance N'!O:O) -> 0 | G16: =SUMIF('Balance N-1'!B:B,678,'Balance N-1'!O:O) -> 0 | H16: =(F16-G16) -> 0 | I16: =IF(G16,(F16-G16)/G16,IF(ISBLANK(G16),"",IF(F16,IF( F16 > 0,1,-1),"")))
A17: Charges pour dépréciation et provisions à court terme à caractère financier (voir note 20) | F17: =SUMIF('Balance N'!B:B,679,'Balance N'!O:O) -> 0 | G17: =SUMIF('Balance N-1'!B:B,679,'Balance N-1'!O:O) -> 0 | H17: =(F17-G17) -> 0 | I17: =IF(G17,(F17-G17)/G17,IF(ISBLANK(G17),"",IF(F17,IF( F17 > 0,1,-1),"")))
A18: SOUS TOTAL : FRAIS FINANCIERS (A) | F18: =SUM(F10:F17) -> 0 | G18: =SUM(G10:G17) -> 0 | H18: =SUM(H10:H17) -> 0 | I18: =IF(G18,(F18-G18)/G18,IF(ISBLANK(G18),"",IF(F18,IF( F18 > 0,1,-1),"")))
A19: Intérêts de prêts et créances diverses | F19: =SUMIF('Balance N'!B:B,771,'Balance N'!P:P) -> 0 | G19: =SUMIF('Balance N-1'!B:B,771,'Balance N-1'!P:P) -> 0 | H19: =(F19-G19) -> 0 | I19: =IF(G19,(F19-G19)/G19,IF(ISBLANK(G19),"",IF(F19,IF( F19 > 0,1,-1),"")))
A20: Revenus de participations et autres titres immobilisés | F20: =SUMIF('Balance N'!B:B,772,'Balance N'!P:P) -> 0 | G20: =SUMIF('Balance N-1'!B:B,772,'Balance N-1'!P:P) -> 0 | H20: =(F20-G20) -> 0 | I20: =IF(G20,(F20-G20)/G20,IF(ISBLANK(G20),"",IF(F20,IF( F20 > 0,1,-1),"")))
A21: Escomptes obtenus | F21: =SUMIF('Balance N'!B:B,773,'Balance N'!P:P) -> 0 | G21: =SUMIF('Balance N-1'!B:B,773,'Balance N-1'!P:P) -> 0 | H21: =(F21-G21) -> 0 | I21: =IF(G21,(F21-G21)/G21,IF(ISBLANK(G21),"",IF(F21,IF( F21 > 0,1,-1),"")))
A22: Revenus de placement | F22: =SUMIF('Balance N'!B:B,774,'Balance N'!P:P) -> 0 | G22: =SUMIF('Balance N-1'!B:B,774,'Balance N-1'!P:P) -> 0 | H22: =(F22-G22) -> 0 | I22: =IF(G22,(F22-G22)/G22,IF(ISBLANK(G22),"",IF(F22,IF( F22 > 0,1,-1),"")))
A23: Gains de change financiers | F23: =SUMIF('Balance N'!B:B,776,'Balance N'!P:P) -> 0 | G23: =SUMIF('Balance N-1'!B:B,776,'Balance N-1'!P:P) -> 0 | H23: =(F23-G23) -> 0 | I23: =IF(G23,(F23-G23)/G23,IF(ISBLANK(G23),"",IF(F23,IF( F23 > 0,1,-1),"")))
A24: Gains sur cessions de titres de placement | F24: =SUMIF('Balance N'!B:B,777,'Balance N'!P:P) -> 0 | G24: =SUMIF('Balance N-1'!B:B,777,'Balance N-1'!P:P) -> 0 | H24: =(F24-G24) -> 0 | I24: =IF(G24,(F24-G24)/G24,IF(ISBLANK(G24),"",IF(F24,IF( F24 > 0,1,-1),"")))
A25: Gains sur risques financiers | F25: =SUMIF('Balance N'!B:B,778,'Balance N'!P:P) -> 0 | G25: =SUMIF('Balance N-1'!B:B,778,'Balance N-1'!P:P) -> 0 | H25: =(F25-G25) -> 0 | I25: =IF(G25,(F25-G25)/G25,IF(ISBLANK(G25),"",IF(F25,IF( F25 > 0,1,-1),"")))
A26: Reprises de charges pour dépréciation et provisions à court terme à caractère financier (voir note 20) | F26: =SUMIF('Balance N'!B:B,779,'Balance N'!P:P) -> 0 | G26: =SUMIF('Balance N-1'!B:B,779,'Balance N-1'!P:P) -> 0 | H26: =(F26-G26) -> 0 | I26: =IF(G26,(F26-G26)/G26,IF(ISBLANK(G26),"",IF(F26,IF( F26 > 0,1,-1),"")))
A27: SOUS TOTAL : REVENUS FINANCIERS (B) | F27: =SUM(F19:F26) -> 0 | G27: =SUM(G19:G26) -> 0 | H27: =SUM(H19:H26) -> 0 | I27: =IF(G27,(F27-G27)/G27,IF(ISBLANK(G27),"",IF(F27,IF( F27 > 0,1,-1),"")))
A28: SOUS TOTAL (contrôle) : RESULTAT FINANCIER (B) - (A) | F28: =F27-F18 -> 0 | G28: =G27-G18 -> 0 | H28: =H27-H18 -> 0 | I28: =IF(G28,(F28-G28)/G28,IF(ISBLANK(G28),"",IF(F28,IF( F28 > 0,1,-1),"")))
A29: Commentaire :
A30: ● Commenter toute variation significative

Sheet NOTE 22
A1: - 36 -
K2: NOTE 22 SYSTEME NORMAL
A3: Dénomination sociale de l'entité : | D3: =+'NOTE 21'!C3 -> DSO Services | M3: NB: Certaines rubriques de cette pages seront, selon les cas, renseignées mannuellement.
A4: Adresse : | D4: =+'NOTE 21'!C4 -> Rue Alphamoi Djénèpo, secteur 01, Bobo-Dioulasso, Burkina Faso | J4: Sigle usuel : | K4: =+'NOTE 21'!H4 -> DSO Services
A5: N° d'identification fiscale : | D5: =+'NOTE 21'!C5 -> 00000101A | G5: Exercice clos le : | H5: =+'NOTE 21'!F5 -> 45657 | J5: Durée (en mois) : | K5: =+'NOTE 21'!H5 -> 12 | M5: Vous aurez à repartir les montants dans les rubriques adequates
A6: N° de télédéclarant (NTD): | D6: =+'NOTE 21'!C6 -> Néant
A7: NOTE 22 : DOTATIONS ET CHARGES POUR PROVISIONS | N7: 1
A8: SITUATIONS ET MOUVEMENTS | E8: A | F8: B | I8: C | L8: D = A + B - C
E9: PROVISIONS A L'OUVERTURE DE L'EXERCICE | F9: AUGMENTATIONS : DOTATIONS | I9: DIMINUTIONS : REPRISES | L9: PROVISIONS A LA CLOTURE DE L'EXERCICE
A10: NATURE | F10: D'EXPLOITATION | G10: FINANCIERES | H10: HORS ACTIVITES ORDINAIRES | I10: D'EXPLOITATION | J10: FINANCIERES | K10: HORS ACTIVITES ORDINAIRES
A11: Provisions réglementées | E11: =SUMIF('Balance N'!A:A,15,'Balance N'!L:L) -> 0 | H11: =SUMIF('Balance N'!A:A,15,'Balance N'!N:N) -> 0 | K11: =SUMIF('Balance N'!A:A,15,'Balance N'!N:N) -> 0 | L11: =E11+F11+G11+H11-I11-J11-K11 -> 0
A12: Provisions financières pour risques et charges | E12: =SUMIF('Balance N'!A:A,19,'Balance N'!L:L) -> 0 | G12: =SUMIF('Balance N'!A:A,15,'Balance N'!N:N) -> 0 | J12: =SUMIF('Balance N'!A:A,15,'Balance N'!M:M) -> 0 | L12: =E12+F12+G12+H12-I12-J12-K12 -> 0
A13: TOTAL DOTATIONS | E13: =SUM(E11:E12) -> 0 | F13: =SUM(F12:F12) -> 0 | G13: =SUM(G12:G12) -> 0 | H13: =SUM(H11:H12) -> 0 | I13: =SUM(I12:I12) -> 0 | J13: =SUM(J12:J12) -> 0 | K13: =SUM(K11:K12) -> 0 | L13: =SUM(L11:L12) -> 0
A14: Dépréciations des stocks et en cours | E14: =SUMIF('Balance N'!A:A,39,'Balance N'!L:L) -> 0 | F14: =SUMIF('Balance N'!A:A,39,'Balance N'!N:N) -> 0 | I14: =SUMIF('Balance N'!A:A,39,'Balance N'!M:M) -> 0 | L14: =E14+F14+G14+H14-I14-J14-K14 -> 0
A15: Dépréciations des comptes fournisseurs | E15: =SUMIF('Balance N'!B:B,490,'Balance N'!L:L) -> 0 | F15: =SUMIF('Balance N'!B:B,490,'Balance N'!N:N) -> 0 | I15: =SUMIF('Balance N'!B:B,490,'Balance N'!M:M) -> 0 | L15: =E15+F15+G15+H15-I15-J15-K15 -> 0
A16: Dépréciations des comptes adhérents et clients-usagers | E16: =SUMIF('Balance N'!B:B,491,'Balance N'!L:L) -> 0 | F16: =SUMIF('Balance N'!B:B,491,'Balance N'!N:N) -> 0 | I16: =SUMIF('Balance N'!B:B,491,'Balance N'!M:M) -> 0 | L16: =E16+F16+G16+H16-I16-J16-K16 -> 0
A17: Dépréciations autres créances d'exploitation | E17: =SUMIF('Balance N'!B:B,492,'Balance N'!L:L)+SUMIF('Balance N'!B:B,493,'Balance N'!L:L)+SUMIF('Balance N'!B:B,494,'Balance N'!L:L)+SUMIF('Balance N'!B:B,497,'Balance N'!L:L) -> 0 | F17: =SUMIF('Balance N'!B:B,492,'Balance N'!N:N)+SUMIF('Balance N'!B:B,493,'Balance N'!N:N)+SUMIF('Balance N'!B:B,494,'Balance N'!N:N)+SUMIF('Balance N'!B:B,497,'Balance N'!N:N) -> 0 | I17: =SUMIF('Balance N'!B:B,492,'Balance N'!M:M)+SUMIF('Balance N'!B:B,493,'Balance N'!M:M)+SUMIF('Balance N'!B:B,494,'Balance N'!M:M) -> 0 | L17: =E17+F17+G17+H17-I17-J17-K17 -> 0
