Workbook
Name _dFin: 42735
Name _soNumFisc: 3201201523617
Name _soSigle: "PYTHAGORE CONSULTAN"

Sheet COUVERTURE
F4: BURKINA FASO
C6: MINISTERE DE L'ECONOMIE DES FINANCES ET DU DEVELOPPEMENT
F8: DIRECTION GENERALE DES IMPOTS
E31: LIASSE SYSTEME NORMAL

Sheet GARDE
B2: BURKINA FASO
B3: MINISTERE DE L'ECONOMIE DES FINANCES ET DU DEVELOPPEMENT
B4: DIRECTION GENERALE DES IMPOTS
C8: CENTRE DE DEPOT DE
C12: ETATS FINANCIERS NORMALISES SYSTEME COMPTABLE OHADA (SYSCOHADA)
E16: EXERCICE CLOS LE
D20: DESIGNATION DE L'ENTITE
B22: DENOMINATION SOCIALE :
B23: (ou nom et prénoms de l'exploitant)
B26: SIGLE USUEL :
B28: ADRESSE COMPLETE :
B30: N° IFU DU CONTRIBUABLE :
B31: N° DE TELEDECLARANT (NES):
B32: SYSTEME NORMAL
B33: Documents déposés | H33: Réservé à la Direction Générale des Impôts
B35: Fiche d'identification et renseignements divers | H35: Date de dépôt
B36: Bilan
B37: Compte de résultat
B38: Tableau des flux de trésorerie
B39: Notes annexes | H39: Nom de l'agent de la DGI ayant réceptionné le dépôt
B40: Etats supplémentaires DGI
B44: Nombre de pages déposées par exemplaire : | H44: Signature de l'agent et cachet du service
B45: Nombre d'exemplaires déposés :

Sheet RECEVABILITE
A1: - 0 -
A3: CONDITIONS DE RECEVABILITE
B5: Entités utilisant des imprimés:
B7: * N'utilisez que des imprimés normalisés
B9: * Remplir chaque page de façon parfaitement lisible sans décalage de lignes
B11: * Ne créer aucune rubrique
B13: * Eviter toute surcharge et donner les explications sur une feuille séparée
B15: * N'utilisez que des codes indiqués dans les tables
B17: * N'utilisez que des imprimés en noir et blanc
B20: Entités produisant les états financiers à l'aide de l'outil informatique
B22: * Reproduire à l'identique la contexture des imprimés normalisés
B24: * Fournir une liasse comprenant à la fois : la fiche d'identification et renseignements divers et les états financiers correspondant au système comptable
B26: * Ne créer aucune rubrique
B28: * N'utilisez que des codes indiqués dans les tables
... B37: Les Notes annexes non chiffrées doivent êtres supprimées. Cependant, elles devront être indiquées dans la Fiche récapitulative des Notes Annexes.

Sheet NOTE36 (TABLE DES CODES)
A1: - 0 -
H2: NOTE 36 SYSTEME NORMAL
A3: Dénomination sociale de l'entité : | C3: =GARDE!D22 -> 0
A4: Adresse : | B4: =GARDE!C28 -> 0 | H4: Sigle usuel: | I4: =GARDE!C26 -> 0
A5: N° IFU du contribuable : | C5: =GARDE!D30 -> 0 | E5: Exercice clos le : | G5: =GARDE!E17 -> 0 | H5: Durée (en mois) : | I5: ='FICHE R1'!U5 -> 0
A6: N° de télédéclarant (NES): | C6: =GARDE!D31 -> 0
A7: NOTE 36 : TABLE DES CODES
A9: 1- Code forme juridique (1) | F9: 3- Code pays du siège social
A11: Société Anonyme (SA) à participation publique | D11: 0 | E11: 0
F12: Pays UEMOA (2)
A13: Société Anonyme (SA) | D13: 0 | E13: 1
F14: Pays CEMAC (3)
A15: Société par Actions Simplifiée (SAS) | D15: 0 | E15: 2
F16: Autres pays OHADA (4)
A17: Société à Responsabilité Limitée (SARL) | D17: 0 | E17: 3 | F17: Afrique du Sud | I17: 2 | J17: 0
F18: Autres pays africains | I18: 2 | J18: 1
A19: Société en Commandite Simple (SCS) | D19: 0 | E19: 4
F20: Suisse | I20: 2 | J20: 2
A21: Société en Nom Collectif (SNC) | D21: 0 | E21: 5
F22: France | I22: 2 | J22: 3
A23: Société en Participation (SP) | D23: 0 | E23: 6
F24: Autres pays de l'Union Européenne | I24: 3 | J24: 9
A25: Groupement d'Intérêt Economique (GIE) | D25: 0 | E25: 7
F26: U.S.A. | I26: 4 | J26: 0
A27: Association | D27: 0 | E27: 8
F28: Canada | I28: 4 | J28: 1
A29: Autre forme juridique (à préciser) | D29: 0 | E29: 9 | F29: Brésil | I29: 4 | J29: 3
F30: Autres pays américains | I30: 4 | J30: 9
A31: 2 - Code régime fiscal
F32: Chine | I32: 5 | J32: 0
A33: Réel normal | E33: 1 | F33: Inde | I33: 5 | J33: 2
F34: Liban | I34: 5 | J34: 3
A35: Réel simplifié | E35: 2 | F35: Autres pays asiatiques | I35: 5 | J35: 9
F36: Russie | I36: 6 | J36: 0
A37: CME | E37: 3
F38: Autres pays | I38: 9 | J38: 9
A39: AUTRE | E39: 4
F40: (Zone monétaire = Zone franc CFA)
A42: (1) Remplacer le premier 0 par 1 si l'entreprise bénéficie d'un agrément prioritaire
A43: (2) Bénin = 01 ; Burkina = 02 ; Côte d'Ivoire = 03 ; Guinée Bissau = 04 ; Mali = 05 ; Niger = 06 ; Sénégal = 07 ; Togo = 08
A44: (3) Cameroun = 09 ; Centrafrique = 10 ; Congo = 11 ; Gabon = 12 ; Guinée Equatoriale = 13 ; Tchad = 14
A45: (4) Comores = 15 ; Guinée Conakry = 16

Sheet NOTE36 Suite(nomenclature)
A1: NOTE 36 (suite Nomenclature)
A2: Sélectionner la ou les codes activités selon le découpage de votre chiffre d'affaires pour le renseignement de la fiche R2
A6: CODES ACTIVITES ECONOMIQUES
A7: Agriculture vivrière | H7: Industries du caoutchouc et des plastiques
A8: 001 001 Culture céréalière | H8: 022 001 Fabrication du caoutchouc naturel
A9: 001 002 Culture de tubercules et plantains | H9: 022 002 Industries du caoutchouc
A10: 001 003 Culture de légumes | H10: 022 003 Fabrication de matières plastiques
A11: 001 004 Culture de condiments | H11: Fabrication d’autres produits minéraux non métalliques et de matériaux
A12: 001 005 Culture de fruits | H12: de construction
A13: 001 006 Culture d’autres produits de l’Agriculture vivrière | H13: 023 001 Industrie du verre
A14: Agriculture industrielle et d’exportation | H14: 023 002 Fabrication de produits minéraux pour la construction
A15: 002 001 Culture de canne à sucre | H15: 023 003 Fabrication d’autres produits minéraux non métalliques
A16: 002 002 Culture d’arachide d’huilerie | H16: Métallurgie et travail des métaux
A17: 002 003 Culture d’arachide de bouche | H17: 024 001 Métallurgie
A18: 002 004 Culture de tabac | H18: 024 002 Travail des métaux
... A56: 012 000 Industries laitières | H56: Postes, télécommunications

Sheet FICHE R1
A1: - 0 -
R2: FICHE R1
A3: Dénomination sociale de l'entité : | E3: =GARDE!D22 -> 0
A4: Adresse : | D4: =GARDE!C28 -> 0 | P4: Sigle usuel : | S4: =GARDE!C26 -> 0
A5: N° IFU du contribuable : | E5: =GARDE!D30 -> 0 | H5: Exercice clos le : | Q5: Durée (en mois) :
A6: N° de télédéclarant (NES) : | E6: =GARDE!D31 -> 0
A7: FICHE R1 : FICHE D'IDENTIFICATION ET RENSEIGNEMENTS DIVERS 1
A8: ZA | C8: EXERCICE COMPTABLE : | M8: DU: | R8: AU:
A10: ZB | C10: DATE D'ARRETE EFFECTIF DES COMPTES : | T10: ZD
A12: ZC | C12: EXERCICE PRECEDENT CLOS LE : | K12: DUREE EXERCICE PRECEDENT EN MOIS :
A14: ZE | J14: ZF
C15: Greffe | D15: N°Registre du Commerce | K15: N° Répertoire des entités
A17: ZG | E17: ZH | P17: ZI
C18: N° de caisse sociale | F18: N° Code Importateur | Q18: Code activité principale
A20: ZJ
C21: Désignation de l'entité | Q21: Sigle
A23: ZK
C24: N° de téléphone | E24: Adresse e-mail | K24: Code | N24: Boîte Postale | Q24: Ville
A26: ZL
C27: Adresse géographique complète (Immeuble, rue, quartier, ville, pays)
P28: ZN
A29: ZM
C30: Désignation précise de l'activité principale exercée par l'entité | P30: % Capacité production utile
A32: ZO
C33: Nom, adresse, téléphone, adresse e-mail et qualité de la personne à contacter en cas de demande
A35: ZP
C36: Nom, adresse, téléphone et e-mail du salarié de l'entité ou
C37: du professionnel comptable inscrit à l'Ordre des Experts-comptables ayant établi les états financiers
A39: ZQ
A43: ZR
C44: Nom, adresse, téléphone, e-mail et numéro d'inscription à l'Ordre des Experts-comptables
C45: de l'Expert comptablble ayant délivré l'attestation d'exécution de la mission du commissariat aux comptes
A47: ZS | O47: Non | T47: Oui
N48: Etats financiers approuvés par l'Assemblée Générale (cocher la case)
J49: ZW
A50: ZT | J50: Domiciliations bancaires
C51: Nom du signataire des états financiers | J51: Banque | Q51: Numéro de compte
A53: ZU
C54: Qualité du signataire des états financiers
A56: ZV
C57: Date de signature
C63: Signature

Sheet FICHE R2
A1: - 0 -
AG2: FICHE R2
A3: Dénomination sociale de l'entité : | I3: ='FICHE R1'!E3 -> 0
A4: Adresse : | E4: ='FICHE R1'!D4 -> 0 | AC4: Sigle usuel : | AI4: ='FICHE R1'!S4 -> 0
A5: N° IFU du contribuable : | I5: ='FICHE R1'!E5 -> 0 | Q5: Exercice clos le : | W5: ='FICHE R1'!J5 -> 0 | AC5: Durée (en mois) : | AI5: ='FICHE R1'!U5 -> 0
A6: N° de télédéclarant (NES) : | I6: ='FICHE R1'!E6 -> 0
A7: FICHE R2 : FICHE D'IDENTIFICATION ET RENSEIGNEMENTS DIVERS 2
V8: Contrôle de l'Entité (cocher la case)
A9: ZX | D9: Forme juridique (1) : | V9: ZZ5 | X9: Entité sous contrôle public
A11: ZY | D11: Régime fiscal (1) : | V11: ZZ6 | X11: Entité sous contrôle privé national
A13: ZZ1 | D13: Pays du siège social (1) : | V13: ZZ7 | X13: Entité sous contrôle privé étranger
A15: ZZ2 | D15: Nombre d'établissements dans le pays :
A17: ZZ3 | D17: Nombre d'établissements hors du pays pour
D18: lesquels une comptabilité distincte est tenue :
A20: ZZ4 | D20: Première année d'exercice dans le pays :
A23: ACTIVITE DE L'ENTITE
A25: Désignation de l'activité (2) | P25: Code nomenclature d'activité (1) | Y25: Chiffre d'affaires HT (CA HT) ou Valeur ajoutée (VA) (3) (4) | AI25: % activité dans le CA HT ou la VA
AJ35: 0
AJ38: 0
AJ41: 0
AJ44: 0
AJ47: 0
AJ50: 0
A52: Divers (4)
P54: TOTAL | Z54: =Z29+Z32+Z35+Z38+Z41+Z44+Z47+Z50+Z52 -> 0 | AI54: =AI29+AI32+AI35+AI38+AI41+AI44+AI47+AI50+AI52 -> 0
A57: (1) Note 36 Suite (Nomenclature)
A58: (2) Lister de manière précise les activités dans l'ordre décroissant du C.A.HT ou de la valeur ajoutée (V.A).
A59: (3) Rayer la mention inutile - Au Burkina Faso, pour les besoins de l'INSD, on préfèrera le chiffre d'affaires.
A60: (4) Indiquer dans la note annexe n°21 "Chiffre d'affaires et autres produits", la liste détaillée des activités classées dans la rubrique "Divers"

Sheet FICHE R3
A1: - 0 -
I2: FICHE R3
A3: Dénomination sociale de l'entité : | C3: ='FICHE R1'!E3 -> 0
A4: Adresse : | B4: ='FICHE R1'!D4 -> 0 | H4: Sigle usuel : | J4: ='FICHE R1'!S4 -> 0
A5: N° IFU du contribuable : | C5: ='FICHE R1'!E5 -> 0 | E5: Exercice clos le : | F5: ='FICHE R1'!J5 -> 0 | H5: Durée (en mois) : | J5: ='FICHE R1'!U5 -> 0
A6: N° de télédéclarant (NES) : | C6: ='FICHE R1'!E6 -> 0
A7: FICHE R3 : FICHE D'IDENTIFICATION ET RENSEIGNEMENTS DIVERS 3
A8: DIRIGEANTS (1)
A10: Nom et Prénoms | C10: Nationalité | D10: Autres nationalités (à préciser) (2) | E10: Qualité | F10: N° d'identification fiscale | H10: Adresse (BP, ville, pays, adresse géographique et adresse email)
A22: (1) Dirigeants = Président Directeur Général, Directeur Général, Administrateur Général, Gérant, Autres.
A23: (2) En cas de double nationalité
A24: MEMBRES DU CONSEIL D'ADMINISTRATION
A26: Nom et Prénoms | C26: Structure représentée | E26: Qualité | G26: Adresse (BP, ville, pays, adresse géographique et adresse email)

Sheet BILAN
A1: - 0 -
L2: BILAN SYSTEME NORMAL PAGE 1/1
A3: Dénomination sociale de l'entité :
A4: Adresse : | L4: Sigle usuel :
A5: N° IFU du contribuable : | I5: Exercice clos le : | L5: Durée (en mois) :
A6: N° de télédéclarant (NES):
A7: BILAN
A8: REF | B8: ACTIF | E8: NOTE | F8: EXERCICE au 31/12/ N | I8: EXERCICE AU 31/12/N-1 | J8: REF | K8: PASSIF | L8: NOTE | M8: EXERCICE AU 31/12/N | N8: EXERCICE AU 31/12/N-1
F10: BRUT | G10: AMORT et DEPREC. | H10: NET | I10: NET | M10: NET | N10: NET
A11: AD | B11: IMMOBILISATIONS INCORPORELLES | E11: 3 | F11: =SUM(F12:F15) -> 0 | G11: =SUM(G12:G15) -> 0 | H11: =SUM(H12:H15) -> 0 | I11: =SUM(I12:I15) -> 0 | J11: CA | K11: Capital | L11: 13
A12: AE | B12: Frais de développement et de prospection | H12: =F12-G12 -> 0 | J12: CB | K12: Apporteurs capital non appelé (-) | L12: 13
A13: AF | B13: Brevets, licences, logiciels et droits similaires | H13: =F13-G13 -> 0 | J13: CD | K13: Primes liées au capital social | L13: 14
A14: AG | B14: Fonds commercial et droit au bail | H14: =F14-G14 -> 0 | J14: CE | K14: Ecarts de réévaluation | L14: 3e
A15: AH | B15: Autres immobilisations incorporelles | H15: =F15-G15 -> 0 | J15: CF | K15: Réserves indisponibles | L15: 14
A16: AI | B16: IMMOBILISATIONS CORPORELLES | E16: 3 | F16: =SUM(F17:F21) -> 0 | G16: =SUM(G17:G21) -> 0 | H16: =SUM(H17:H21) -> 0 | I16: =SUM(I17:I21) -> 0 | J16: CG | K16: Réserves libres | L16: 14
A17: AJ | B17: Terrains (1) dont Placement Net : | H17: =F17-G17 -> 0 | J17: CH | K17: Report à nouveau (+ ou -) | L17: 14
A18: AK | B18: Bâtiments(1) dont Placement Net : | H18: =F18-G18 -> 0 | J18: CJ | K18: Résultat net de l'exercice (bénéfice + ou perte -)
A19: AL | B19: Aménagements, agencements et installations | H19: =F19-G19 -> 0 | J19: CL | K19: Subventions d'investissement | L19: 15
A20: AM | B20: Matériel, mobilier et actifs biologiques | H20: =F20-G20 -> 0 | J20: CM | K20: Provisions réglementées | L20: 15
A21: AN | B21: Matériel de transport | H21: =F21-G21 -> 0 | J21: CP | K21: TOTAL CAPITAUX PROPRES ET RESSOURCES ASSIMILEES | M21: =SUM(M11:M20) -> 0 | N21: =SUM(N11:N20) -> 0
A22: AP | B22: AVANCES ET ACOMPTES VERSES SUR IMMOBILISATIONS | E22: 3 | H22: =F22-G22 -> 0 | J22: DA | K22: Emprunts et dettes financières diverses | L22: 16
A23: AQ | B23: IMMOBILISATIONS FINANCIERES | E23: 4 | F23: =SUM(F24:F25) -> 0 | G23: =SUM(G24:G25) -> 0 | H23: =SUM(H24:H25) -> 0 | I23: =SUM(I24:I25) -> 0 | J23: DB | K23: Dettes de location-acquisition | L23: 16
A24: AR | B24: Titres de participation | H24: =F24-G24 -> 0 | J24: DC | K24: Provisions pour risques et charges | L24: 16
A25: AS | B25: Autres immobilisations financières | H25: =F25-G25 -> 0 | J25: DD | K25: TOTAL DETTES FINANCIERES ET RESSOURCES ASSIMILEES | M25: =SUM(M22:M24) -> 0 | N25: =SUM(N22:N24) -> 0
A26: AZ | B26: TOTAL ACTIF IMMOBILISE | F26: =F11+F16+F22+F23 -> 0 | G26: =G11+G16+G22+G23 -> 0 | H26: =H11+H16+H22+H23 -> 0 | I26: =I11+I16+I22+I23 -> 0 | J26: DF | K26: TOTAL RESSOURCES STABLES | M26: =M21+M25 -> 0 | N26: =N21+N25 -> 0
A27: BA | B27: ACTIF CIRCULANT HAO | E27: 5 | H27: =F27-G27 -> 0 | J27: DH | K27: Dettes circulantes HAO | L27: 5
A28: BB | B28: STOCKS ET ENCOURS | E28: 6 | H28: =F28-G28 -> 0 | J28: DI | K28: Clients, avances reçues | L28: 7
A29: BG | B29: CREANCES ET EMPLOIS ASSIMILES | F29: =F30+F31+F32 -> 0 | G29: =G30+G31+G32 -> 0 | H29: =H30+H31+H32 -> 0 | I29: =I30+I31+I32 -> 0 | J29: DJ | K29: Fournisseurs d'exploitation | L29: 17
A30: BH | B30: Fournisseurs avances versées | E30: 17 | H30: =F30-G30 -> 0 | J30: DK | K30: Dettes fiscales et sociales | L30: 18
A31: BI | B31: Clients | E31: 7 | H31: =F31-G31 -> 0 | J31: DM | K31: Autres dettes | L31: 19
A32: BJ | B32: Autres créances | E32: 8 | H32: =F32-G32 -> 0 | J32: DN | K32: Provisions pour risques et charges à court terme | L32: 19
A33: BK | B33: TOTAL ACTIF CIRCULANT | F33: =F27+F28+F29 -> 0 | G33: =G27+G28+G29 -> 0 | H33: =H27+H28+H29 -> 0 | I33: =I27+I28+I29 -> 0 | J33: DP | K33: TOTAL PASSIF CIRCULANT | M33: =SUM(M27:M32) -> 0 | N33: =SUM(N27:N32) -> 0
A34: BQ | B34: Titres de placement | E34: 9 | H34: =F34-G34 -> 0
A35: BR | B35: Valeurs à encaisser | E35: 10 | H35: =F35-G35 -> 0 | J35: DQ | K35: Banques, crédits d'escompte | L35: 20
A36: BS | B36: Banques, chèques postaux, caisse et assimilés | E36: 11 | H36: =F36-G36 -> 0 | J36: DR | K36: Banques, établissements financiers et crédits de trésorerie | L36: 20
A37: BT | B37: TOTAL TRESORERIE-ACTIF | F37: =SUM(F34:F36) -> 0 | G37: =SUM(G34:G36) -> 0 | H37: =SUM(H34:H36) -> 0 | I37: =SUM(I34:I36) -> 0 | J37: DT | K37: TOTAL TRESORERIE-PASSIF | M37: =SUM(M35:M36) -> 0 | N37: =SUM(N35:N36) -> 0
A38: BU | B38: Ecart de conversion-Actif | E38: 12 | H38: =F38-G38 -> 0 | J38: DV | K38: Ecart de conversion-Passif | L38: 12
A39: BZ | B39: TOTAL GENERAL | F39: =F26+F33+F37+F38 -> 0 | G39: =G26+G33+G37+G38 -> 0 | H39: =H26+H33+H37+H38 -> 0 | I39: =I26+I33+I37+I38 -> 0 | J39: DZ | K39: TOTAL GENERAL | M39: =M26+M33+M37+M38 -> 0 | N39: =N26+N33+N37+N38 -> 0

Sheet RESULTAT
A1: - 0 -
H2: COMPTE DE RESULTAT SYSTEME NORMAL PAGE 1/1
A3: Dénomination sociale de l'entité : | C3: =BILAN!C3 -> 0
A4: Adresse : | C4: =BILAN!C4 -> 0 | I4: Sigle usuel : | J4: =BILAN!N4 -> 0
A5: N° IFU du contribuable : | C5: =BILAN!C6 -> 0 | E5: Exercice clos le : | F5: =BILAN!K5 -> 0 | I5: Durée (en mois) : | J5: =BILAN!N5 -> 0
A6: N° de télédéclarant (NES): | C6: ='FICHE R1'!E6 -> 0
A7: COMPTE DE RESULTAT
A8: REF | B8: LIBELLES | G8: (1) | H8: NOTE | I8: EXERCICE AU 31/12/N | J8: EXERCICE AU 31/12/N-1
I10: NET | J10: NET
A11: TA | B11: Ventes de marchandises | F11: A | G11: + | H11: 21
A12: RA | B12: Achats de marchandises | G12: - | H12: 22
A13: RB | B13: Variation de stocks de marchandises | G13: -/+ | H13: 6
A14: XA | B14: MARGE COMMERCIALE (Somme TA à RB) | I14: =SUM(I11:I13) -> 0 | J14: =IFERROR(SUM(J11:J13),"") -> 0
A15: TB | B15: Ventes de produits fabriqués | F15: B | G15: + | H15: 21
A16: TC | B16: Travaux, services vendus | F16: C | G16: + | H16: 21
A17: TD | B17: Produits accessoires | F17: D | G17: + | H17: 21
A18: XB | B18: CHIFFRE D'AFFAIRES (A + B + C + D) | I18: =I11+I15+I16+I17 -> 0 | J18: =IFERROR(J11+J15+J16+J17,"") -> 0
A19: TE | B19: Production stockée (ou déstockage) | G19: -/+ | H19: 6
A20: TF | B20: Production immobilisée | H20: 21
A21: TG | B21: Subventions d’exploitation | H21: 21
A22: TH | B22: Autres produits | G22: + | H22: 21
A23: TI | B23: Transferts de charges d'exploitation | G23: + | H23: 12
A24: RC | B24: Achats de matières premières et fournitures liées | G24: - | H24: 22
A25: RD | B25: Variation de stocks de matières premières et fournitures liées | G25: -/+ | H25: 6
A26: RE | B26: Autres achats | G26: - | H26: 22
A27: RF | B27: Variation de stocks d’autres approvisionnements | G27: -/+ | H27: 6
A28: RG | B28: Transports | G28: - | H28: 23
A29: RH | B29: Services extérieurs | G29: - | H29: 24
A30: RI | B30: Impôts et taxes | G30: - | H30: 25
A31: RJ | B31: Autres charges | G31: - | H31: 26
A32: XC | B32: VALEUR AJOUTEE (XB +RA+RB) + (somme TE à RJ) | I32: =SUM(I19:I31) +I12+I13+I18 -> 0 | J32: =IFERROR(SUM(J19:J31) +J12+J13+J18,"") -> 0
A33: RK | B33: Charges de personnel | G33: - | H33: 27
A34: XD | B34: EXCEDENT BRUT D'EXPLOITATION (XC+RK) | I34: =I32+I33 -> 0 | J34: =IFERROR(J32+J33,"") -> 0
A35: TJ | B35: Reprises d’amortissements, provisions et dépréciations | G35: + | H35: 28
A36: RL | B36: Dotations aux amortissements, aux provisions et dépréciations | G36: - | H36: 3C&28
A37: XE | B37: RESULTAT D'EXPLOITATION (XD+TJ+ RL) | I37: =I34+I35+I36 -> 0 | J37: =IFERROR(J34+J35+J36,"") -> 0
A38: TK | B38: Revenus financiers et assimilés | G38: + | H38: 29
A39: TL | B39: Reprises de provisions et dépréciations financières | G39: + | H39: 28
A40: TM | B40: Transferts de charges financières | G40: + | H40: 12
A41: RM | B41: Frais financiers et charges assimilées | G41: - | H41: 29
A42: RN | B42: Dotations aux provisions et aux dépréciations financières | G42: - | H42: 3C&28
A43: XF | B43: RESULTAT FINANCIER (somme TK à RN) | I43: =SUM(I38:I42) -> 0 | J43: =IFERROR(SUM(J38:J42),"") -> 0
A44: XG | B44: RESULTAT DES ACTIVITES ORDINAIRES (XE+XF) | I44: =I37+I43 -> 0 | J44: =IFERROR(J37+J43,"") -> 0
A45: TN | B45: Produits des cessions d'immobilisations | G45: + | H45: 3D
A46: TO | B46: Autres Produits HAO | G46: + | H46: 30
A47: RO | B47: Valeurs comptables des cessions d'immobilisations | G47: - | H47: 3D
A48: RP | B48: Autres Charges HAO | G48: - | H48: 30
A49: XH | B49: RESULTAT HORS ACTIVITES ORDINAIRES (somme TN à RP) | I49: =SUM(I45:I48) -> 0 | J49: =IFERROR(SUM(J45:J48),"") -> 0
A50: RQ | B50: Participation des travailleurs | G50: - | H50: 30
A51: RS | B51: Impôts sur le résultat | G51: - | H51: 37
A52: XI | B52: RESULTAT NET (XG+XH+RQ+RS) | I52: =I44+I49+I50+I51 -> 0 | J52: =IFERROR(J44+J49+J50+J51,"") -> 0
A53: (1) (+/-) : Solde débiteur "(-)", solde créditeur "(+)"

Sheet TFT
A1: - 0 -
H2: FLUX DE TRESORERIE SYSTEME NORMAL PAGE 1/1
A3: Dénomination sociale de l'entité : | C3: =BILAN!C3 -> 0
A4: Adresse : | C4: =BILAN!C4 -> 0 | I4: Sigle usuel : | J4: =BILAN!N4 -> 0
A5: N° IFU du contribuable : | C5: =BILAN!C5 -> 0 | E5: Exercice clos le : | F5: =BILAN!K5 -> 0 | I5: Durée (en mois) : | J5: =BILAN!N5 -> 0
A6: N° de télédéclarant (NES): | C6: =BILAN!C6 -> 0
A7: TABLEAU DES FLUX DE TRESORERIE
A8: REF | B8: LIBELLES | H8: NOTE | I8: EXERCICE | J8: EXERCICE
I9: N | J9: N-1
A10: ZA | B10: Trésorerie nette au 1er janvier (Trésorerie actif N-1 - Trésorerie passif N-1) | G10: A
B11: Flux de trésorerie provenant des activités opérationnelles
A12: FA | B12: Capacité d'Autofinancement Globale (CAFG)
A13: FB | B13: - Variation d'actif circulant HAO (1)
A14: FC | B14: - Variation des stocks
A15: FD | B15: - Variation des créances
A16: FE | B16: + Variation du passif circulant (1)
B17: Variation du BF lié aux activités opérationnelles
B18: FB+FC+FD+FE : | C18: =I13+I14+I15+I16 -> 0 | E18: =IFERROR(J13+J14+J15+J16,"") -> 0
A19: ZB | B19: Flux de trésorerie provenant des activités opérationnelles (Somme FA à FE) | G19: B | I19: =SUM(I12:I16) -> 0 | J19: =IFERROR(SUM(J12:J16),"") -> 0
B20: Flux de trésorerie provenant des activités d’investissements
A21: FF | B21: - Décaissements liés aux acquisitions d'immobilisations incorporelles
A22: FG | B22: - Décaissements liés aux acquisitions d'immobilisations corporelles
A23: FH | B23: - Décaissements liés aux acquisitions d'immobilisations financières
A24: FI | B24: + Encaissements liés aux cessions d’immobilisations incorporelles et corporelles
A25: FJ | B25: + Encaissements liés aux cessions d’immobilisations financières
A26: ZC | B26: Flux de trésorerie provenant des activités d’investissement (somme FF à FJ) | G26: C | I26: =SUM(I21:I25) -> 0 | J26: =IFERROR(SUM(J21:J25),"") -> 0
B27: Flux de trésorerie provenant du financement par les capitaux propres
A28: FK | B28: + Augmentations de capital par apports nouveaux
A29: FL | B29: + Subventions d'investissement reçues
A30: FM | B30: - Prélèvements sur le capital
A31: FN | B31: - Dividendes versés
A32: ZD | B32: Flux de trésorerie provenant des capitaux propres (somme FK à FN) | G32: D | I32: =SUM(I28:I31) -> 0 | J32: =IFERROR(SUM(J28:J31),"") -> 0
B33: Trésorerie provenant du financement par les capitaux étrangers
A34: FO | B34: + Emprunts
A35: FP | B35: + Autres dettes financières diverses
A36: FQ | B36: - Remboursements des emprunts et autres dettes financières
A37: ZE | B37: Flux de trésorerie provenant des capitaux étrangers (somme FO à FQ) | G37: E | I37: =SUM(I34:I36) -> 0 | J37: =IFERROR(SUM(J34:J36),"") -> 0
A38: ZF | B38: Flux de trésorerie provenant des activités de financement (D+E) | G38: F | I38: =I32+I37 -> 0 | J38: =IFERROR(J32+J37,"") -> 0
A39: ZG | B39: VARIATION DE LA TRÉSORERIE NETTE DE LA PÉRIODE (B+C+F) | G39: G | I39: =I19+I26+I38 -> 0 | J39: =J19+J26+J38 -> 0
A40: ZH | B40: Trésorerie nette au 31 Décembre (G+A) | G40: H | I40: =I10+I39 -> 0 | J40: =IFERROR(J10+J39,"") -> 0
B41: Contrôle : Trésorerie actif N - Trésorerie passif N
A42: [1] à l’exclusion des variations des créances et dettes liées aux activités d’investissement (variation des créances sur cession d’immobilisation et des dettes sur acquisition ou production d’immobilisation) et de financement (par exemple variation des créances sur subventions d’investissements reçues).

Sheet FICHE R4
A1: - 0 -
I2: FICHE R4
A3: Dénomination sociale de l'entité :
A4: Adresse : | H4: Sigle usuel :
A5: N° IFU du contribuable : | E5: Exercice clos le : | H5: Durée (en mois) :
A6: N° de télédéclarant (NES):
A7: FICHE R4 : FICHE RECAPITULATIVE DES NOTES ANNEXES PRESENTEES (1)
A8: NOTES | B8: INTITULES | I8: A | J8: N/A
A9: NOTE 1 | B9: DETTES GARANTIES PAR DES SURETES REELLES ET LES ENGAGEMENTS FINANCIERS
A10: NOTE 2 | B10: INFORMATIONS OBLIGATOIRES
A11: NOTE 3A | B11: IMMOBILISATIONS BRUTES
A12: NOTE 3B | B12: BIENS PRIS EN LOCATION-ACQUISITION
A13: NOTE 3C | B13: IMMOBILISATIONS : AMORTISSEMENTS
A14: NOTE 3C bis | B14: IMMOBILISATIONS : DEPRECIATIONS
A15: NOTE 3D | B15: IMMOBILISATIONS : PLUS-VALUES ET MOINS VALUE DE CESSION
A16: NOTE 3E | B16: INFORMATIONS SUR LES REEVALUATIONS EFFECTUEES PAR L'ENTITE
A17: NOTE 4 | B17: IMMOBILISATIONS FINANCIERES
A18: NOTE 5 | B18: ACTIF CIRCULANT ET DETTES CIRCULANTES HAO
A19: NOTE 6 | B19: STOCKS ET ENCOURS
A20: NOTE 7 | B20: CLIENTS
... A61: ETATS DGI | B61: ETATS SUPPLEMENTAIRES DGI
A63: (1) les Notes non documentées ne doivent pas être jointes aux états financiers. Leur contenu peut être amélioré par les entités Par ailleurs, dans une note, les lignes non chiffrées doivent être supprimées. Par exemple, dans la note 24 Services Extérieurs, lorsque la ligne sous-traitance générale n'est pas chiffrée, elle ne doit pas figurer dans les notes.
A64: (2) A : Applicable A/N : Non applicable.
A65: Par exemple pour une entité qui n'a pas de stocks et en-cours, elle doit cocher à l'intersection ('ligne NOTE 6' & 'colonne N/A')

Sheet NOTE 1
A1: - 0 -
H2: NOTE 1 SYSTEME NORMAL
A3: Dénomination sociale de l'entité : | C3: ='FICHE R4'!C3 -> 0
A4: Adresse : | B4: ='FICHE R4'!B4 -> 0 | H4: Sigle usuel : | I4: ='FICHE R4'!I4 -> 0
A5: N° IFU du contribuable : | C5: ='FICHE R4'!C5 -> 0 | F5: Exercice clos le : | G5: ='FICHE R4'!F5 -> 0 | H5: Durée (en mois) : | I5: ='FICHE R4'!I5 -> 0
A6: N° de télédéclarant (NES): | C6: ='FICHE R4'!C6 -> 0
A7: NOTE 1: DETTES GARANTIES PAR DES SURETES REELLES ET LES ENGAGEMENTS FINANCIERS
A8: LIBELLES | E8: Note | F8: Montant brut (1) | G8: SURETES REELLES (2)
G9: Hypothèques | H9: Nantissements | I9: Gages/autres
A10: Emprunts et dettes financières diverses : | E10: 16
A11: Emprunts obligataires convertibles
A12: Autres emprunts obligataires
A13: Emprunts et dettes des établissements de crédit
A14: Autres dettes financières
A15: SOUS TOTAL (1) | F15: =SUM(F11:F14) -> 0
A16: Dettes de location-acquisition : | E16: 16
A17: Dettes de crédit-bail immobilier
A18: Dettes de crédit-bail mobilier
A19: Dettes sur contrats de location-vente
A20: Autres dettes sur contrats de location-acquisition
A21: SOUS TOTAL (2) | F21: =SUM(F17:F20) -> 0
A22: Dettes du passif circulant :
A23: Fournisseurs et comptes rattachés | E23: 17
A24: Clients | E24: 7
A25: Personnel | E25: 18
A26: Sécurité sociale et organismes sociaux | E26: 18
A27: Etat | E27: 18
A28: Organismes internationaux | E28: 19
A29: Associés et groupe | E29: 19
A30: Créditeurs divers | E30: 19
A31: SOUS TOTAL (3) | F31: =SUM(F23:F30) -> 0
A32: TOTAL (1) + (2) + (3) | F32: =F15+F21+F31 -> 0
A33: ENGAGEMENTS FINANCIERS | G33: Engagements réciproques | H33: Engagements donnés | I33: Engagements reçus
A34: Engagements consentis à des entités liées
A35: Primes de remboursement des obligations non échues
A36: Avals, cautions, garanties
A37: Hypothèques, nantissements, gages, autres
A38: Effets escomptés non échus
A39: Créances commerciales et professionnelles cédées
A40: Abandons de créances conditionnels
A41: Achats de marchandises à terme
A42: Achats à terme de devises non couverts
A43: Commandes fermes des clients
A44: Autres engagements réciproques
A45: TOTAL | G45: =SUM(G34:G44) -> 0 | H45: =SUM(H34:H40) -> 0 | I45: =SUM(I34:I40) -> 0
A46: (1) indiquer le montant de la garantie
A47: (2) indiquer les références de la sûreté
A48: Commentaire :
A49: ● Indiquer la raison d'être des suretés.
A50: ● Pour les actifs et passifs externes frappés de réserve de propriété(R/P), indiquer les informations prévues dans le chapitre Opérations et problèmes spécifiques.
A51: ● Pour les transactions entre les parties liées, indiquer :
A52: - la nature et le montant des transactions effectuées avec chaque partie liée (entité mère,autres filiales du groupe,etc.)
A53: - les transactions avec les principaux dirigeants (prêts aux dirigeants,salaires bruts et avantages en nature,atribution gratuite d'actions etc.).

Sheet NOTE 2
A1: - 0 -
H2: NOTE 2 SYSTEME NORMAL
A3: Dénomination sociale de l'entité : | C3: ='NOTE 1'!C3 -> 0
A4: Adresse : | B4: ='NOTE 1'!B4 -> 0 | H4: Sigle usuel : | I4: ='NOTE 1'!I4 -> 0
A5: N° IFU du contribuable : | C5: ='NOTE 1'!C5 -> 0 | F5: Exercice clos le : | G5: ='NOTE 1'!G5 -> 0 | H5: Durée (en mois) : | I5: ='NOTE 1'!I5 -> 0
A6: N° de télédéclarant (NES): | C6: ='NOTE 1'!C6 -> 0
A7: NOTE 2: INFORMATIONS OBLIGATOIRES
A8: A - DECLARATION DE CONFORMITE AU SYSCOHADA ET FAITS MARQUANTS DE L'EXERCICE
A10: B - REGLES ET METHODES COMPTABLES
A12: C- DEROGATION AUX POSTULATS ET CONVENTIONS COMPTABLES
A14: D - INFORMATIONS COMPLEMENTAIRES RELATIVES AU BILAN, AU COMPTE DE RESULTAT ET AU TABLEAU DES FLUX DE TRESORERIE
A17: Commentaire :
A18: ● Mentionner les faits marquants après la déclaration de conformité.
A19: Seuls les éléments ayant une incidence comptable significative ou qui misent à la comparabilité des exercices doivent être mentionnés. Par exemple, le lancement d'un produit sur le marché, ou la perte du principal client de l'entité.
A20: ● Décrire les régles et méthodes utilisées pour l'établissement des états financiers et celles utilisées dans le cas de contrat pluri- exercices, de contrats de concession, de l'établissement de comptes intermédiaires, de fusion et opérations assimilées comme indiquées dans les opérations et problèmes spécifiques.

Sheet NOTE 3A
A1: - 0 -
I2: NOTE 3A SYSTEME NORMAL
A3: Dénomination sociale de l'entité : | C3: ='NOTE 1'!C3 -> 0
A4: Adresse : | B4: ='NOTE 1'!B4 -> 0 | I4: Sigle usuel : | J4: ='NOTE 1'!I4 -> 0
A5: N° IFU : | C5: ='NOTE 1'!C5 -> 0 | F5: Exercice clos le : | G5: ='NOTE 1'!G5 -> 0 | I5: Durée (en mois) : | J5: ='NOTE 1'!I5 -> 0
A6: N° de télédéclarant (NES): | C6: ='NOTE 1'!C6 -> 0
A7: NOTE 3A : IMMOBILISATIONS (BRUTES)
A8: SITUATIONS ET MOUVEMENTS | D8: A | E8: AUGMENTATIONS B | H8: DIMINUTIONS C | J8: D = A + B - C
D9: MONTANT BRUT A L'OUVERTURE DE L'EXERCICE | E9: Acquisitions Apports Créations | F9: Virements de poste à poste | G9: Suite à une réévaluation pratiquée au cours de l'exercice | H9: Cessions Scissions Hors service | I9: Virements de poste à poste | J9: MONTANT BRUT A LA CLOTURE DE L'EXERCICE
A10: RUBRIQUES
A11: IMMOBILISATIONS INCORPORELLES | D11: =SUM(D12:D15) -> 0 | E11: =SUM(E12:E15) -> 0 | F11: =SUM(F12:F15) -> 0 | G11: =SUM(G12:G15) -> 0 | H11: =SUM(H12:H15) -> 0 | I11: =SUM(I12:I15) -> 0 | J11: =D11+E11+F11+G11-H11-I11 -> 0
A12: Frais de développement et de prospection | J12: =D12+E12+F12+G12-H12-I12 -> 0
A13: Brevets, licences, logiciels, et droits similaires | J13: =D13+E13+F13+G13-H13-I13 -> 0
A14: Fonds commercial et droit au bail | J14: =D14+E14+F14+G14-H14-I14 -> 0
A15: Autres immobilisations incorporelles | J15: =D15+E15+F15+G15-H15-I15 -> 0
A16: IMMOBILISATIONS CORPORELLES | D16: =SUM(D17:D23) -> 0 | E16: =SUM(E17:E23) -> 0 | F16: =SUM(F17:F23) -> 0 | G16: =SUM(G17:G23) -> 0 | H16: =SUM(H17:H23) -> 0 | I16: =SUM(I17:I23) -> 0 | J16: =D16+E16+F16+G16-H16-I16 -> 0
A17: Terrains hors immeuble de placement | J17: =D17+E17+F17+G17-H17-I17 -> 0
A18: Terrains - immeuble de placement | J18: =D18+E18+F18+G18-H18-I18 -> 0
A19: Bâtiments hors immeuble de placement | J19: =D19+E19+F19+G19-H19-I19 -> 0
A20: Bâtiments - immeuble de placement | J20: =D20+E20+F20+G20-H20-I20 -> 0
A21: Aménagements, agencements et installations | J21: =D21+E21+F21+G21-H21-I21 -> 0
A22: Matériel, mobilier et actifs biologiques | I22: 0 | J22: =D22+E22+F22+G22-H22-I22 -> 0
A23: Matériel de transport | J23: =D23+E23+F23+G23-H23-I23 -> 0
A24: AVANCES ET ACOMPTES VERSES SUR IMMOBILISATIONS | J24: =D24+E24+F24+G24-H24-I24 -> 0
A25: Avances et acomptes sur immobilisations incorporelles | J25: =D25+E25+F25+G25-H25-I25 -> 0
A26: Avances et acomptes sur immobilisations corporelles | J26: =D26+E26+F26+G26-H26-I26 -> 0
A27: IMMOBILISATIONS FINANCIERES | D27: =SUM(D28:D29) -> 0 | E27: =SUM(E28:E29) -> 0 | F27: =SUM(F28:F29) -> 0 | G27: =SUM(G28:G29) -> 0 | H27: =SUM(H28:H29) -> 0 | I27: =SUM(I28:I29) -> 0 | J27: =D27+E27+F27+G27-H27-I27 -> 0
A28: Titres de participation | J28: =D28+E28+F28+G28-H28-I28 -> 0
A29: Autres immobilisations financières | J29: =D29+E29+F29+G29-H29-I29 -> 0
A30: TOTAL GENERAL | D30: =D11+D16+ D24 +D27 -> 0 | E30: =E11+E16+ E24 +E27 -> 0 | F30: =F11+F16+ F24 +F27 -> 0 | G30: =G11+G16+ G24 +G27 -> 0 | H30: =H11+H16+ H24 +H27 -> 0 | I30: =I11+I16+ I24 +I27 -> 0 | J30: =J11+J16+ J24 +J27 -> 0
A31: Commentaire :
A32: ● Toute variation significative doit être commentée. | E32: ● Indiquer les créances du groupe avec nature et date d'échéance.
A33: ● Détailler les éléments constitutifs du fonds commercial et indiquer la date d'acquisition. | E33: ● Pour les banques, DAT indiquer le nom de la banque le montant et la date d'échéance.
A34: ● Pour l'immobilisation incorporelle relative à la concession faire un descriptif de l'accord. | E34: ● Pour les frais de développement, donner toutes les informations mentionnées dans la partie Opérations et problèmes spécifiques.
A35: ● Indiquer : | E35: ● Donner le détail des produits et charges liés aux immeubles de placement.
A36: - la nature de la créance ;
A37: - la durée de la concession ;
A38: - l'échéance.

Sheet NOTE 3B
A1: - 0 -
K2: NOTE 3B SYSTEME NORMAL
A3: Dénomination sociale de l'entité : | C3: ='NOTE 1'!C3 -> 0
A4: Adresse : | B4: ='NOTE 1'!B4 -> 0 | K4: Sigle usuel : | L4: ='NOTE 1'!I4 -> 0
A5: N° IFU : | C5: ='NOTE 1'!C5 -> 0 | H5: Exercice clos le : | I5: ='NOTE 1'!G5 -> 0 | K5: Durée (en mois) : | L5: ='NOTE 1'!I5 -> 0
A6: N° de télédéclarant (NES): | C6: ='NOTE 1'!C6 -> 0
A7: NOTE 3B : BIENS PRIS EN LOCATION ACQUISITION
A8: SITUATIONS ET MOUVEMENTS | F8: A | G8: AUGMENTATIONS B | J8: DIMINUTIONS C | L8: D = A + B - C
E9: NATURE DU CONTRAT (I ; M ; A) [1] | F9: MONTANT BRUT A L'OUVERTURE DE L'EXERCICE | G9: Acquisitions Apports Créations | H9: Virements de poste à poste | I9: Suite à une réévaluation pratiquée au cours de l'exercice | J9: Cessions Scissions Hors service | K9: Virements de poste à poste | L9: MONTANT BRUT A LA CLOTURE DE L'EXERCICE
A10: RUBRIQUES
A11: Terrains | L11: =F11+G11+H11+I11-J11-K11 -> 0
A12: Bâtiments | L12: =F12+G12+H12+I12-J12-K12 -> 0
A13: Matériel, mobilier | L13: =F13+G13+H13+I13-J13-K13 -> 0
A14: Matériel de transport | L14: =F14+G14+H14+I14-J14-K14 -> 0
A15: TOTAL IMMOBILISATIONS EN LOCATION-ACQUISITION | F15: =SUM(F11:F14) -> 0 | G15: =SUM(G11:G14) -> 0 | H15: =SUM(H11:H14) -> 0 | I15: =SUM(I11:I14) -> 0 | J15: =SUM(J11:J14) -> 0 | K15: =SUM(K11:K14) -> 0 | L15: =SUM(L11:L14) -> 0
A16: [1] I : Crédit-bail immobilier ; M : Crédit-bail mobilier ; A : Autres contrats (dédoubler le poste si montants
A17: Commentaire:
A18: ● Indiquer la nature du bien, le nom du bailleur et la durée du bail.

Sheet NOTE 3C
A1: - 0 -
N2: NOTE 3C SYSTEME NORMAL
A3: Dénomination sociale de l'entité : | C3: ='NOTE 1'!C3 -> 0
A4: Adresse : | B4: ='NOTE 1'!B4 -> 0 | L4: Sigle usuel : | N4: ='NOTE 1'!I4 -> 0
A5: N° IFU : | C5: ='NOTE 1'!C5 -> 0 | H5: Exercice clos le : | J5: ='NOTE 1'!G5 -> 0 | L5: Durée (en mois) : | N5: ='NOTE 1'!I5 -> 0
A6: N° de télédéclarant (NES): | C6: ='NOTE 1'!C6 -> 0
A7: NOTE 3C : IMMOBILISATIONS (AMORTISSEMENTS)
A8: SITUATIONS ET MOUVEMENTS | D8: A | F8: B | H8: C | L8: D | N8: E = A + B - C - D
D9: AMORTISSEMENTS CUMULES A L'OUVERTURE DE L'EXERCICE | F9: AUGMENTATIONS: | H9: DIMINUTIONS : | L9: Virements de poste à poste | N9: CUMUL DES AMORTISSEMENTS A LA CLOTURE DE L'EXERCICE
A10: RUBRIQUES | F10: DOTATIONS DE L'EXERCICE | H10: Amortissements relatifs aux éléments sortis de l'actif | J10: Reprises d'amortissements
A11: Frais de développement et de prospection | N11: =D11+F11-H11-J11-L11 -> 0
A12: Brevets, licences, logiciels et droits similaires | N12: =D12+F12-H12-J12-L12 -> 0
A13: Fonds commercial et droit au bail | N13: =D13+F13-H13-J13-L13 -> 0
A14: Autres immobilisations incorporelles | N14: =D14+F14-H14-J14-L14 -> 0
A15: IMMOBILISATIONS INCORPORELLES | D15: =SUM(D11:E14) -> 0 | F15: =SUM(F11:G14) -> 0 | H15: =SUM(H11:I14) -> 0 | J15: =SUM(J11:K14) -> 0 | L15: =SUM(L11:M14) -> 0 | N15: =SUM(N11:O14) -> 0
A16: Terrains hors immeuble de placement | N16: =D16+F16-H16-J16-L16 -> 0
A17: Terrains - immeuble de placement | N17: =D17+F17-H17-J17-L17 -> 0
A18: Bâtiments hors immeuble de placement | N18: =D18+F18-H18-J18-L18 -> 0
A19: Bâtiments - immeuble de placement | N19: =D19+F19-H19-J19-L19 -> 0
A20: Aménagements, agencements et installations | N20: =D20+F20-H20-J20-L20 -> 0
A21: Matériel, mobilier et actifs biologiques | N21: =D21+F21-H21-J21-L21 -> 0
A22: Matériel de transport | N22: =D22+F22-H22-J22-L22 -> 0
A23: IMMOBILISATIONS CORPORELLES | D23: =SUM(D16:E22) -> 0 | F23: =SUM(F16:G22) -> 0 | H23: =SUM(H16:I22) -> 0 | J23: =SUM(J16:K22) -> 0 | L23: =SUM(L16:M22) -> 0 | N23: =SUM(N16:O22) -> 0
A24: TOTAL GENERAL | D24: =D15+D23 -> 0 | F24: =F15+F23 -> 0 | H24: =H15+H23 -> 0 | J24: =J15+J23 -> 0 | L24: =L15+L23 -> 0 | N24: =N15+N23 -> 0
A25: Commentaire :
A26: ● Indiquer
A27: - les modes d'amortissement utilisés ;
A28: - la durée d'utilité ou les taux d'amortissements utilisés.

Sheet NOTE 3C BIS
A1: - 0 -
J2: NOTE 3C BIS SYSTEME NORMAL
A3: Dénomination sociale de l'entité : | C3: ='NOTE 1'!C3 -> 0
A4: Adresse : | B4: ='NOTE 1'!B4 -> 0 | J4: Sigle usuel : | K4: ='NOTE 1'!I4 -> 0
A5: N° IFU : | C5: ='NOTE 1'!C5 -> 0 | E5: Exercice clos le : | G5: ='NOTE 1'!G5 -> 0 | J5: Durée (mois) : | K5: ='NOTE 1'!I5 -> 0
A6: N° de télédéclarant (NES): | C6: ='NOTE 1'!C6 -> 0
A7: NOTE 3C BIS : IMMOBILISATIONS (DEPRECIATIONS)
A8: SITUATIONS ET MOUVEMENTS | D8: A | F8: B | H8: C | J8: D = A + B - C
D9: DEPRECIATIONS CUMULES A L'OUVERTURE DE L'EXERCICE | F9: AUGMENTATIONS: DOTATIONS DE L'EXERCICE | H9: DIMINUTIONS : REPRISES DE L'EXERCICE | J9: CUMUL DES DEPRECIATIONS A LA CLOTURE DE L'EXERCICE
A10: RUBRIQUES
A11: Frais de développement et de prospection | J11: =D11+F11-H11 -> 0
A12: Brevets, licences, logiciels et droits similaires | J12: =D12+F12-H12 -> 0
A13: Fonds commercial et droit au bail | J13: =D13+F13-H13 -> 0
A14: Autres immobilisations incorporelles | J14: =D14+F14-H14 -> 0
A15: IMMOBILISATIONS INCORPORELLES | D15: =SUM(D11:E14) -> 0 | F15: =SUM(F11:G14) -> 0 | H15: =SUM(H11:I14) -> 0 | J15: =SUM(J11:K14) -> 0
A16: Terrains hors immeuble de placement | J16: =D16+F16-H16 -> 0
A17: Terrains - immeuble de placement | J17: =D17+F17-H17 -> 0
A18: Bâtiments hors immeuble de placement | J18: =D18+F18-H18 -> 0
A19: Bâtiments - immeuble de placement | J19: =D19+F19-H19 -> 0
A20: Aménagements, agencements et installations | J20: =D20+F20-H20 -> 0
A21: Matériel, mobilier et actifs biologiques | J21: =D21+F21-H21 -> 0
A22: Matériel de transport | J22: =D22+F22-H22 -> 0
A23: IMMOBILISATIONS CORPORELLES | D23: =SUM(D16:E22) -> 0 | F23: =SUM(F16:G22) -> 0 | H23: =SUM(H16:I22) -> 0 | J23: =SUM(J16:K22) -> 0
A24: TOTAL GENERAL | D24: =D15+D23 -> 0 | F24: =F15+F23 -> 0 | H24: =H15+H23 -> 0 | J24: =J15+J23 -> 0
A25: Commentaire :
A26: ● Indiquer les événements et circonstances qui ont conduit à la dépréciation et à la reprise.

Sheet NOTE 3D
A1: - 0 -
G2: NOTE 3D SYSTEME NORMAL
A3: Dénomination sociale de l'entité : | C3: ='NOTE 1'!C3 -> 0
A4: Adresse : | B4: ='NOTE 1'!B4 -> 0 | G4: Sigle usuel : | H4: ='NOTE 1'!I4 -> 0
A5: N° IFU : | C5: ='NOTE 1'!C5 -> 0 | D5: Exercice clos le : | E5: ='NOTE 1'!G5 -> 0 | G5: Durée (en mois) : | H5: ='NOTE 1'!I5 -> 0
A6: N° de télédéclarant (NES): | C6: ='NOTE 1'!C6 -> 0
A7: NOTE 3D : IMMOBILISATIONS (PLUS-VALUES ET MOINS- VALUES DE CESSION)
A8: SITUATIONS ET MOUVEMENTS | D8: MONTANT BRUT | E8: AMORTISSEMENTS PRATIQUES | F8: VALEUR COMPTABLE NETTE | G8: PRIX DE CESSION | H8: PLUS-VALUE OU MOINS-VALUE
A9: RUBRIQUES | D9: A | E9: B | F9: C = A - B | G9: D | H9: E = D - C
A10: Frais de développement et de prospection | F10: =D10-E10 -> 0 | H10: =G10-F10 -> 0
A11: Brevets, licences, logiciels et droits similaires | F11: =D11-E11 -> 0 | H11: =G11-F11 -> 0
A12: Fonds commercial et droit au bail | F12: =D12-E12 -> 0 | H12: =G12-F12 -> 0
A13: Autres immobilisations incorporelles | F13: =D13-E13 -> 0 | H13: =G13-F13 -> 0
A14: IMMOBILISATIONS INCORPORELLES | D14: =SUM(D10:D13) -> 0 | E14: =SUM(E10:E13) -> 0 | F14: =SUM(F10:F13) -> 0 | G14: =SUM(G10:G13) -> 0 | H14: =SUM(H10:H13) -> 0
A15: Terrains | F15: =D15-E15 -> 0 | H15: =G15-F15 -> 0
A16: Bâtiments | F16: =D16-E16 -> 0 | H16: =G16-F16 -> 0
A17: Aménagements, agencements et installations | F17: =D17-E17 -> 0 | H17: =G17-F17 -> 0
A18: Matériel, mobilier et actifs biologiques | F18: =D18-E18 -> 0 | H18: =G18-F18 -> 0
A19: Matériel de transport | F19: =D19-E19 -> 0 | H19: =G19-F19 -> 0
A20: IMMOBILISATIONS CORPORELLES | D20: =SUM(D15:D19) -> 0 | E20: =SUM(E15:E19) -> 0 | F20: =SUM(F15:F19) -> 0 | G20: =SUM(G15:G19) -> 0 | H20: =SUM(H15:H19) -> 0
A21: Titres de participations | F21: =D21-E21 -> 0 | H21: =G21-F21 -> 0
A22: Autres immobilisations financières | F22: =D22-E22 -> 0 | H22: =G22-F22 -> 0
A23: IMMOBILISATIONS FINANCIERES | D23: =SUM(D21:D22) -> 0 | E23: =SUM(E21:E22) -> 0 | F23: =SUM(F21:F22) -> 0 | G23: =SUM(G21:G22) -> 0 | H23: =SUM(H21:H22) -> 0
A24: TOTAL GENERAL | D24: =D14+D20+D23 -> 0 | E24: =E14+E20+E23 -> 0 | F24: =F14+F20+F23 -> 0 | G24: =G14+G20+G23 -> 0 | H24: =H14+H20+H23 -> 0
A25: Commentaire :
A26: ● Mentionner la justification de la cession ainsi que la date d'acquisition et la date de sortie.

Sheet NOTE 3E
A1: - 0 -
H2: NOTE 3E SYSTEME NORMAL
A3: Dénomination sociale de l'entité : | C3: ='NOTE 1'!C3 -> 0
A4: Adresse : | B4: ='NOTE 1'!B4 -> 0 | H4: Sigle usuel : | I4: ='NOTE 1'!I4 -> 0
A5: N° IFU : | C5: ='NOTE 1'!C5 -> 0 | D5: Exercice clos le : | E5: ='NOTE 1'!G5 -> 0 | H5: Durée (en mois) : | I5: ='NOTE 1'!I5 -> 0
A6: N° de télédéclarant (NES): | C6: ='NOTE 1'!C6 -> 0
A7: NOTE 3E : INFORMATIONS SUR LES REEVALUATIONS EFFECTUEES PAR L'ENTITE
A8: Nature et date des réévaluations :
A10: Eléments réévalués par postes du bilan | F10: Montants en coûts historiques | G10: Montant réévalués | H10: Ecarts de réévaluation | I10: Amortissements supplémentaires
A18: TOTAL GENERAL | F18: =SUM(F11:F17) -> 0 | G18: =SUM(G11:G17) -> 0 | H18: =SUM(H11:H17) -> 0 | I18: =SUM(I11:I17) -> 0
A19: Méthode de réévaluation utilisée :
A21: Traitement fiscal de l'écart de réévaluation et des amortissements supplémentaires :
A23: Montant de l'écart incorporé au capital :

Sheet NOTE 4
A1: - 0 -
J2: NOTE 4 SYSTEME NORMAL
A3: Dénomination sociale de l'entité : | C3: ='NOTE 1'!C3 -> 0
A4: Adresse : | B4: ='NOTE 1'!B4 -> 0 | I4: Sigle usuel : | J4: ='NOTE 1'!I4 -> 0
A5: N° IFU : | C5: ='NOTE 1'!C5 -> 0 | F5: Exercice clos le : | G5: ='NOTE 1'!G5 -> 0 | I5: Durée (en mois) : | J5: ='NOTE 1'!I5 -> 0
A6: N° de télédéclarant (NES): | C6: ='NOTE 1'!C6 -> 0
A7: NOTE 4 : IMMOBILISATIONS FINANCIERES
A8: Libellés | F8: Année N | G8: Année N-1 | H8: Variation en % | I8: Créances à un an au plus | J8: Créances à plus d'un an et à deux ans au plus | K8: Créances à plus de deux ans
A9: Titres de participation | H9: =IF(G9,(F9-G9)/ABS(G9),IF(ISBLANK(G9),"",IF(F9,IF( F9 > 0,1,-1),"")))
A10: Prêts et créances | H10: =IF(G10,(F10-G10)/ABS(G10),IF(ISBLANK(G10),"",IF(F10,IF( F10 > 0,1,-1),"")))
A11: Prêt au personnel | H11: =IF(G11,(F11-G11)/ABS(G11),IF(ISBLANK(G11),"",IF(F11,IF( F11 > 0,1,-1),"")))
A12: Créances sur l'état | H12: =IF(G12,(F12-G12)/ABS(G12),IF(ISBLANK(G12),"",IF(F12,IF( F12 > 0,1,-1),"")))
A13: Titres immobilisés | H13: =IF(G13,(F13-G13)/ABS(G13),IF(ISBLANK(G13),"",IF(F13,IF( F13 > 0,1,-1),"")))
A14: Dépôts et cautionnements | H14: =IF(G14,(F14-G14)/ABS(G14),IF(ISBLANK(G14),"",IF(F14,IF( F14 > 0,1,-1),"")))
A15: Intérêts courus | H15: =IF(G15,(F15-G15)/ABS(G15),IF(ISBLANK(G15),"",IF(F15,IF( F15 > 0,1,-1),"")))
A16: Créances rattachées à des avances et participations à des GIE | H16: =IF(G16,(F16-G16)/ABS(G16),IF(ISBLANK(G16),"",IF(F16,IF( F16 > 0,1,-1),"")))
A17: Immobilisations financières diverses | H17: =IF(G17,(F17-G17)/ABS(G17),IF(ISBLANK(G17),"",IF(F17,IF( F17 > 0,1,-1),"")))
A18: TOTAL BRUT | F18: =SUM(F9:F15) -> 0 | G18: =SUM(G9:G15) -> 0 | H18: =IF(G18,(F18-G18)/G18,IF(ISBLANK(G18),"",IF(F18,1,""))) | I18: =SUM(I9:I15) -> 0 | J18: =SUM(J9:J15) -> 0 | K18: =SUM(K9:K15) -> 0
A19: Dépréciations des titres de participation | H19: =IF(G19,(F19-G19)/ABS(G19),IF(ISBLANK(G19),"",IF(F19,IF( F19 > 0,1,-1),"")))
A20: Dépréciations des autres immobilisations financières | H20: =IF(G20,(F20-G20)/ABS(G20),IF(ISBLANK(G20),"",IF(F20,IF( F20 > 0,1,-1),"")))
A21: TOTAL NET DE DEPRECIATION | F21: =F18+F19+F20 -> 0 | G21: =G18+G19+G20 -> 0 | H21: =IF(G21,(F21-G21)/G21,IF(ISBLANK(G21),"",IF(F21,1,"")))
A23: Liste des filiales et participations :
A24: Dénomination sociale | E24: Localisation (ville / pays) | G24: Valeur d'acquisition | H24: % Détenu | I24: Montant des capitaux propres filiale | J24: Résultat dernier exercice filiale (1) | K24: Part de bénéfice reçue de la filiale (2)
A31: (1): Préciser s'il s'agit du résultat de l'exercice N ou du résultat de l'exercice N-1 | E31: (2): S'il s'agit du résultat de l'exercice n-1, renseigner la colonne "part du bénéfice reçue de la filiale"
A32: Commentaire :
A33: ● Justifier toute variation significative. | F33: ● Indiquer le nombre et la date d'acquisition des actions ou parts propres.
A34: ● Commenter toutes les créances anciennes. | F34: ● Dépréciation : indiquer les évènements et les circonstances qui ont motivé la dépréciation ou la reprise.
A35: ● Pour les créances relatives à la concession, faire un descriptif de l'accord.
A36: ● Indiquer :
A37: - la nature de la créance ;
A38: - la durée de la concession ;
A39: - l'échéance.

Sheet NOTE 5
A1: - 0 -
H2: NOTE 5 SYSTEME NORMAL
A3: Dénomination sociale de l'entité : | C3: ='NOTE 1'!C3 -> 0
A4: Adresse : | B4: ='NOTE 1'!B4 -> 0 | H4: Sigle usuel : | I4: ='NOTE 1'!I4 -> 0
A5: N° IFU : | C5: ='NOTE 1'!C5 -> 0 | E5: Exercice clos le : | F5: ='NOTE 1'!G5 -> 0 | H5: Durée (en mois) : | I5: ='NOTE 1'!I5 -> 0
A6: N° de télédéclarant (NES): | C6: ='NOTE 1'!C6 -> 0
A7: NOTE 5 : ACTIF CIRCULANT ET DETTES CIRCULANTES HAO
A8: ACTIF CIRCULANT HAO
A9: Libellés | E9: Année N | G9: Année N-1 | I9: Variation en %
A10: Créances sur cessions d'immobilisations | I10: =IF(G10,(E10-G10)/G10,IF(ISBLANK(G10),"",IF(E10,IF( E10 > 0,1,-1),"")))
A11: Autres créances hors activités ordinaires | I11: =IF(G11,(E11-G11)/G11,IF(ISBLANK(G11),"",IF(E11,IF( E11 > 0,1,-1),"")))
A12: TOTAL BRUT | E12: =SUM(E10:F11) -> 0 | G12: =SUM(G10:H11) -> 0 | I12: =IF(G12,(E12-G12)/G12,IF(ISBLANK(G12),"",IF(E12,IF( E12 > 0,1,-1),"")))
A13: Dépréciations des créances HAO | I13: =IF(G13,(E13-G13)/G13,IF(ISBLANK(G13),"",IF(E13,IF( E13 > 0,1,-1),"")))
A14: TOTAL NET DE DEPRECIATIONS | E14: =E12+E13 -> 0 | G14: =G12+G13 -> 0 | I14: =IF(G14,(E14-G14)/G14,IF(ISBLANK(G14),"",IF(E14,IF( E14 > 0,1,-1),"")))
A15: Commentaire:
A16: • Commenter toute variation significative.
A17: • Dépréciation : indiquer les évènements et les circonstances qui ont motivé la dépréciation ou la reprise.
A19: DETTES CIRCULANTES HAO
A21: Libellés | E21: Année N | G21: Année N-1 | I21: Variation en %
A22: Fournisseurs d'investissements | I22: =IF(G22,(E22-G22)/G22,IF(ISBLANK(G22),"",IF(E22,IF( E22 > 0,1,-1),"")))
A23: Fournisseurs d'investissements effets à payer | I23: =IF(G23,(E23-G23)/G23,IF(ISBLANK(G23),"",IF(E23,IF( E23 > 0,1,-1),"")))
A24: Versements restant à effectuer sur titres de participation et titres immobilisés non libérés | I24: =IF(G24,(E24-G24)/G24,IF(ISBLANK(G24),"",IF(E24,IF( E24 > 0,1,-1),"")))
A25: Autres dettes hors activités ordinaires | I25: =IF(G25,(E25-G25)/G25,IF(ISBLANK(G25),"",IF(E25,IF( E25 > 0,1,-1),"")))
A26: TOTAL | E26: =SUM(E22:F25) -> 0 | G26: =SUM(G22:H25) -> 0 | I26: =IF(G26,(E26-G26)/G26,IF(ISBLANK(G26),"",IF(E26,IF( E26 > 0,1,-1),"")))
A27: Commentaire:
A28: ● Indiquer la date de cession et la nature de l'immobilisation achetée et/ou cédée.
A29: ● Expliciter toute variation significative.

Sheet NOTE 6
A1: - 0 -
I2: NOTE 6 SYSTEME NORMAL
A3: Dénomination sociale de l'entité : | C3: ='NOTE 1'!C3 -> 0
A4: Adresse : | B4: ='NOTE 1'!B4 -> 0 | I4: Sigle usuel : | J4: ='NOTE 1'!I4 -> 0
A5: N° IFU : | C5: ='NOTE 1'!C5 -> 0 | E5: Exercice clos le : | F5: ='NOTE 1'!G5 -> 0 | I5: Durée (en mois) : | J5: ='NOTE 1'!I5 -> 0
A6: N° de télédéclarant (NES): | C6: ='NOTE 1'!C6 -> 0
A7: NOTE 6 : STOCKS ET EN COURS (1)
A8: Libellés | E8: Année N | G8: Année N-1 | I8: Variation de stock en valeur absolue | J8: Variation en %
A9: Marchandises | I9: =ABS(E9-G9) -> 0 | J9: =IF(G9,(E9-G9)/G9,IF(ISBLANK(G9),"",IF(E9,IF( E9 > 0,1,-1),"")))
A10: Matières premières et fournitures liées | I10: =ABS(E10-G10) -> 0 | J10: =IF(G10,(E10-G10)/G10,IF(ISBLANK(G10),"",IF(E10,IF( E10 > 0,1,-1),"")))
A11: Autres approvisionnements | I11: =ABS(E11-G11) -> 0 | J11: =IF(G11,(E11-G11)/G11,IF(ISBLANK(G11),"",IF(E11,IF( E11 > 0,1,-1),"")))
A12: Produits en cours | I12: =ABS(E12-G12) -> 0 | J12: =IF(G12,(E12-G12)/G12,IF(ISBLANK(G12),"",IF(E12,IF( E12 > 0,1,-1),"")))
A13: Services en cours | I13: =ABS(E13-G13) -> 0 | J13: =IF(G13,(E13-G13)/G13,IF(ISBLANK(G13),"",IF(E13,IF( E13 > 0,1,-1),"")))
A14: Produits finis | I14: =ABS(E14-G14) -> 0 | J14: =IF(G14,(E14-G14)/G14,IF(ISBLANK(G14),"",IF(E14,IF( E14 > 0,1,-1),"")))
A15: Produits intermédiaires | I15: =ABS(E15-G15) -> 0 | J15: =IF(G15,(E15-G15)/G15,IF(ISBLANK(G15),"",IF(E15,IF( E15 > 0,1,-1),"")))
A16: Stocks en cours de route, en consignation ou en dépôt | I16: =ABS(E16-G16) -> 0 | J16: =IF(G16,(E16-G16)/G16,IF(ISBLANK(G16),"",IF(E16,IF( E16 > 0,1,-1),"")))
A17: TOTAL BRUT STOCKS ET EN COURS | E17: =SUM(E9:F16) -> 0 | G17: =SUM(G9:H16) -> 0 | I17: =ABS(E17-G17) -> 0 | J17: =IF(G17,(E17-G17)/G17,IF(ISBLANK(G17),"",IF(E17,IF( E17 > 0,1,-1),"")))
A18: Dépréciations des stocks | I18: =ABS(E18-G18) -> 0 | J18: =IF(G18,(E18-G18)/G18,IF(ISBLANK(G18),"",IF(E18,IF( E18 > 0,1,-1),"")))
A19: TOTAL NET DE DEPRECIATIONS | E19: =E17+E18 -> 0 | G19: =G17+G18 -> 0 | I19: =ABS(E19-G19) -> 0 | J19: =IF(G19,(E19-G19)/G19,IF(ISBLANK(G19),"",IF(E19,IF( E19 > 0,1,-1),"")))
A20: (1) Les stocks H.A.O. seront inscrits dans l'actif circulant H.A.O. que lorsque leur montant total est significatif (supérieur à 5 % du total de l'actif circulant).
A21: Commentaire :
A22: ● Indiquer la date de prise d'inventaire et décrire brièvement la procédure, les méthodes comptables adoptées pour évaluer le stock.
A23: ● Commenter toute variation significative des stocks.
A24: ● Indiquer le détail des stocks dépréciés et les évènements et circonstances qui ont conduit à la dépréciation et à la reprise.

Sheet NOTE 7
A1: - 0 -
I2: NOTE 7 SYSTEME NORMAL
A3: Dénomination sociale de l'entité : | C3: ='NOTE 1'!C3 -> 0
A4: Adresse : | B4: ='NOTE 1'!B4 -> 0 | I4: Sigle usuel : | J4: ='NOTE 1'!I4 -> 0
A5: N° IFU : | C5: ='NOTE 1'!C5 -> 0 | F5: Exercice clos le : | G5: ='NOTE 1'!G5 -> 0 | I5: Durée (en mois) : | J5: ='NOTE 1'!I5 -> 0
A6: N° de télédéclarant (NES): | C6: ='NOTE 1'!C6 -> 0
A7: NOTE 7 : CLIENTS
A8: Libellés | E8: Année N | F8: Année N-1 | G8: Variation en % | H8: Créances à un an au plus | I8: Créances à plus d'un an et à deux ans au plus | J8: Créances à plus de deux ans
A9: Clients (hors réserves de propriété et Groupe) | G9: =IF(F9,(E9-F9)/F9,IF(ISBLANK(F9),"",IF(E9,IF( E9 > 0,1,-1),"")))
A10: Clients effets à recevoir (hors réserves de propriété et groupe) | G10: =IF(F10,(E10-F10)/F10,IF(ISBLANK(F10),"",IF(E10,IF( E10 > 0,1,-1),"")))
A11: Clients avec réserves de propriété | G11: =IF(F11,(E11-F11)/F11,IF(ISBLANK(F11),"",IF(E11,IF( E11 > 0,1,-1),"")))
A12: Clients et effets à recevoir Groupe | G12: =IF(F12,(E12-F12)/F12,IF(ISBLANK(F12),"",IF(E12,IF( E12 > 0,1,-1),"")))
A13: Créances sur cession d'immobilisations | G13: =IF(F13,(E13-F13)/F13,IF(ISBLANK(F13),"",IF(E13,IF( E13 > 0,1,-1),"")))
A14: Clients effets escomptés et non échus | G14: =IF(F14,(E14-F14)/F14,IF(ISBLANK(F14),"",IF(E14,IF( E14 > 0,1,-1),"")))
A15: Créances litigieuses ou douteuses | G15: =IF(F15,(E15-F15)/F15,IF(ISBLANK(F15),"",IF(E15,IF( E15 > 0,1,-1),"")))
A16: Clients produits à recevoir | G16: =IF(F16,(E16-F16)/F16,IF(ISBLANK(F16),"",IF(E16,IF( E16 > 0,1,-1),"")))
A17: TOTAL BRUT CLIENTS | E17: =SUM(E9:E16) -> 0 | F17: =SUM(F9:F16) -> 0 | G17: =IF(F17,(E17-F17)/F17,IF(ISBLANK(F17),"",IF(E17,IF( E17 > 0,1,-1),""))) | H17: =SUM(H9:H16) -> 0 | I17: =SUM(I9:I16) -> 0 | J17: =SUM(J9:J16) -> 0
A18: Dépréciations des comptes clients | G18: =IF(F18,(E18-F18)/F18,IF(ISBLANK(F18),"",IF(E18,IF( E18 > 0,1,-1),"")))
A19: TOTAL NET DE DEPRECIATIONS | E19: =E17-E18 -> 0 | F19: =F17-F18 -> 0 | G19: =IF(F19,(E19-F19)/F19,IF(ISBLANK(F19),"",IF(E19,IF( E19 > 0,1,-1),"")))
A20: Clients, avances reçues hors groupe | G20: =IF(F20,(E20-F20)/F20,IF(ISBLANK(F20),"",IF(E20,IF( E20 > 0,1,-1),"")))
A21: Clients, avances reçues groupe | G21: =IF(F21,(E21-F21)/F21,IF(ISBLANK(F21),"",IF(E21,IF( E21 > 0,1,-1),"")))
A22: Autres clients créditeurs | G22: =IF(F22,(E22-F22)/F22,IF(ISBLANK(F22),"",IF(E22,IF( E22 > 0,1,-1),"")))
A23: TOTAL CLIENTS CREDITEURS | E23: =SUM(E20:E22) -> 0 | F23: =SUM(F20:F22) -> 0 | G23: =IF(F23,(E23-F23)/F23,IF(ISBLANK(F23),"",IF(E23,IF( E23 > 0,1,-1),""))) | H23: =SUM(H20:H22) -> 0 | I23: =SUM(I20:I22) -> 0 | J23: =SUM(J20:J22) -> 0
A24: Commentaire :
A25: ● Commenter toutes variations significatives.
A26: ● Indiquer pour les créances du groupe, le nom de la société du groupe et le % de titres détenues.
A27: ● Commenter les créances anciennes.
A28: ● Indiquer les événements et circonstances qui ont conduit à la dépréciation et à la reprise.

Sheet NOTE 8
A1: - 0 -
I2: NOTE 8 SYSTEME NORMAL
A3: Dénomination sociale de l'entité : | C3: ='NOTE 1'!C3 -> 0
A4: Adresse : | B4: ='NOTE 1'!B4 -> 0 | I4: Sigle usuel : | J4: ='NOTE 1'!I4 -> 0
A5: N° IFU : | C5: ='NOTE 1'!C5 -> 0 | F5: Exercice clos le : | G5: ='NOTE 1'!G5 -> 0 | I5: Durée (en mois) : | J5: ='NOTE 1'!I5 -> 0
A6: N° de télédéclarant (NES): | C6: ='NOTE 1'!C6 -> 0
A7: NOTE 8 : AUTRES CREANCES
A8: Libellés | E8: Année N | F8: Année N-1 | G8: Variation en % | H8: Créances à un an au plus | I8: Créances à plus d'un an et à deux ans au plus | J8: Créances à plus de deux ans
A9: Personnel | G9: =IF(F9,(E9-F9)/F9,IF(ISBLANK(F9),"",IF(E9,IF( E9 > 0,1,-1),"")))
A10: Organismes sociaux | G10: =IF(F10,(E10-F10)/F10,IF(ISBLANK(F10),"",IF(E10,IF( E10 > 0,1,-1),"")))
A11: Etat et Collectivités publiques | G11: =IF(F11,(E11-F11)/F11,IF(ISBLANK(F11),"",IF(E11,IF( E11 > 0,1,-1),"")))
A12: Organismes internationaux | G12: =IF(F12,(E12-F12)/F12,IF(ISBLANK(F12),"",IF(E12,IF( E12 > 0,1,-1),"")))
A13: Apporteurs, associés et groupe | G13: =IF(F13,(E13-F13)/F13,IF(ISBLANK(F13),"",IF(E13,IF( E13 > 0,1,-1),"")))
A14: Compte transitoire ajustement spécial lié à la révision du SYSCOHADA (Voir Notes 8A & 8C) | G14: =IF(F14,(E14-F14)/F14,IF(ISBLANK(F14),"",IF(E14,IF( E14 > 0,1,-1),"")))
A15: Autres débiteurs divers | G15: =IF(F15,(E15-F15)/F15,IF(ISBLANK(F15),"",IF(E15,IF( E15 > 0,1,-1),"")))
A16: Comptes permanents non bloqués des établissements et des succursales | G16: =IF(F16,(E16-F16)/F16,IF(ISBLANK(F16),"",IF(E16,IF( E16 > 0,1,-1),"")))
A17: Comptes de liaison charges et produits | G17: =IF(F17,(E17-F17)/F17,IF(ISBLANK(F17),"",IF(E17,IF( E17 > 0,1,-1),"")))
A18: Comptes de liaison des sociétés en participation | G18: =IF(F18,(E18-F18)/F18,IF(ISBLANK(F18),"",IF(E18,IF( E18 > 0,1,-1),"")))
A19: TOTAL BRUT AUTRES CREANCES | E19: =SUM(E9:E18) -> 0 | F19: =SUM(F9:F18) -> 0 | G19: =IF(F19,(E19-F19)/F19,IF(ISBLANK(F19),"",IF(E19,IF( E19 > 0,1,-1),""))) | H19: =SUM(H9:H18) -> 0 | I19: =SUM(I9:I18) -> 0 | J19: =SUM(J9:J18) -> 0
A20: Dépréciations des autres créances | G20: =IF(F20,(E20-F20)/F20,IF(ISBLANK(F20),"",IF(E20,IF( E20 > 0,1,-1),"")))
A21: TOTAL NET DE DEPRECIATIONS | E21: =E19-E20 -> 0 | F21: =F19-F20 -> 0 | G21: =IF(F21,(E21-F21)/F21,IF(ISBLANK(F21),"",IF(E21,IF( E21 > 0,1,-1),"")))
A22: Commentaire :
A23: ● Justifier toute variation significative.
A24: ● Détailler les créances dont le montant est significatif.
A25: ● Justifier les créances anciennes.
A26: ● Indiquer les événements et circonstances qui ont conduit à la dépréciation et à la reprise.
A27: ● Compte transitoire ajustement spécial, indiquer le détail du compte et la durée restant pour l'apurement.

Sheet NOTE 8A
A1: - 0 -
I2: NOTE 8A SYSTEME NORMAL
A3: Dénomination sociale de l'entité : | C3: ='NOTE 1'!C3 -> 0
A4: Adresse : | B4: ='NOTE 1'!B4 -> 0 | I4: Sigle usuel : | J4: ='NOTE 1'!I4 -> 0
A5: N° d'identification fiscale : | C5: ='NOTE 1'!C5 -> 0 | F5: Exercice clos le : | G5: ='NOTE 1'!G5 -> 0 | I5: Durée (en mois) : | J5: ='NOTE 1'!I5 -> 0
A6: N° de télédéclarant (NTD): | C6: ='NOTE 1'!C6 -> 0
A7: NOTE 8A : TABLEAU D’ETALEMENT DES CHARGES IMMOBILISEES
A8: Libellés | E8: Frais d'établissement | G8: Charges à repartir sur plusieurs exercices | I8: Primes de remboursement des obligations
A9: Compte transitoire à solder: 4751 compte transitoire, ajustement lié à la révision du SYSCOHADA, compte-actif
A10: Montant global à étaler au 1er janvier 2018
A11: Durée d'étalement retenue
A12: Exercice 2018 | E12: Comptes | F12: Montants | G12: Comptes | H12: Montants | I12: Comptes | J12: Montants
E13: 60... | G13: 60... | I13: 6714
E14: 61... | G14: 61...
E15: 62... | G15: 62...
E16: 63... | G16: 63...
E22: ... | G22: ...
A23: Total exercice 2018
A24: Total exercice 2019
A25: Total exercice 2020
A26: Total exercice 2021
A27: Total exercice 2022
A28: TOTAL GENERAL | F28: =SUM(F23:F27) -> 0 | H28: =SUM(H23:H27) -> 0 | J28: =SUM(J23:J27) -> 0

Sheet NOTE 8B
A1: - 0 -
H2: NOTE 8B SYSTEME NORMAL
A3: Dénomination sociale de l'entité : | C3: ='NOTE 1'!C3 -> 0
A4: Adresse : | B4: ='NOTE 1'!B4 -> 0 | H4: Sigle usuel : | I4: ='NOTE 1'!I4 -> 0
A5: N° d'identification fiscale : | C5: ='NOTE 1'!C5 -> 0 | E5: Exercice clos le : | F5: ='NOTE 1'!G5 -> 0 | H5: Durée (en mois) : | I5: ='NOTE 1'!I5 -> 0
A6: N° de télédéclarant (NTD): | C6: ='NOTE 1'!C6 -> 0
A7: NOTE 8B : TABLEAU D’ETALEMENT DE PROVISIONS POUR CHARGES A REPARTIR
A8: LIBELLES | E8: PROVISIONS POUR CHARGES A REPARTIR
A9: Compte transitoire à solder: 4752 compte transitoire ajustement spécial lié à la révision du SYSCOHADA, compte-passif
A10: Montant global à étaler au 1er janvier 2018
A11: Durée d'étalement retenue
E12: Comptes | H12: Montants
E13: 791 Reprises de provisions et dépréciations d'exploitation
A14: Total exercice 2018
A15: Total exercice 2019
A16: Total exercice 2020
A17: Total exercice 2021
A18: Total exercice 2022
A19: TOTAL GENERAL | H19: =SUM(H14:I18) -> 0

Sheet NOTE 8C
A1: - 0 -
H2: NOTE 8C SYSTEME NORMAL
A3: Dénomination sociale de l'entité : | C3: ='NOTE 1'!C3 -> 0
A4: Adresse : | B4: ='NOTE 1'!B4 -> 0 | H4: Sigle usuel : | I4: ='NOTE 1'!I4 -> 0
A5: N° d'identification fiscale : | C5: ='NOTE 1'!C5 -> 0 | E5: Exercice clos le : | F5: ='NOTE 1'!G5 -> 0 | H5: Durée (en mois) : | I5: ='NOTE 1'!I5 -> 0
A6: N° de télédéclarant (NTD): | C6: ='NOTE 1'!C6 -> 0
A7: NOTE 8C : TABLEAU D’ETALEMENT DE PROVISIONS POUR ENGAGEMENTS DE RETAITE
A8: Libellés | E8: PROVISIONS POUR PENSIONS ET OBLIGATIONS SIMILAIRES
A9: Compte transitoire à solder: 4752 compte transitoire ajustement spécial lié à la révision du SYSCOHADA, compte-passif
A10: Montant global à étaler au 1er janvier 2018
A11: Durée d'étalement retenue
E12: Comptes | H12: Montants
E13: 6911 Dotation aux provisions pour risques et charges
A14: Total exercice 2018
A15: Total exercice 2019
A16: Total exercice 2020
A17: Total exercice 2021
A18: Total exercice 2022
A19: TOTAL GENERAL | H19: =SUM(H14:I18) -> 0

Sheet NOTE 9
A1: - 0 -
H2: NOTE 9 SYSTEME NORMAL
A3: Dénomination sociale de l'entité : | C3: ='NOTE 1'!C3 -> 0
A4: Adresse : | B4: ='NOTE 1'!B4 -> 0 | H4: Sigle usuel : | I4: ='NOTE 1'!I4 -> 0
A5: N° IFU : | C5: ='NOTE 1'!C5 -> 0 | E5: Exercice clos le : | F5: ='NOTE 1'!G5 -> 0 | H5: Durée (en mois) : | I5: ='NOTE 1'!I5 -> 0
A6: N° de télédéclarant (NES): | C6: ='NOTE 1'!C6 -> 0
A7: NOTE 9 : TITRES DE PLACEMENT
A8: Libellés | E8: Année N | G8: Année N-1 | I8: Variation en %
A9: Titres de trésor et bons de caisse à court terme | I9: =IF(G9,(E9-G9)/G9,IF(ISBLANK(G9),"",IF(E9,IF( E9 > 0,1,-1),"")))
A10: Actions | I10: =IF(G10,(E10-G10)/G10,IF(ISBLANK(G10),"",IF(E10,IF( E10 > 0,1,-1),"")))
A11: Obligations | I11: =IF(G11,(E11-G11)/G11,IF(ISBLANK(G11),"",IF(E11,IF( E11 > 0,1,-1),"")))
A12: Bons de souscription | I12: =IF(G12,(E12-G12)/G12,IF(ISBLANK(G12),"",IF(E12,IF( E12 > 0,1,-1),"")))
A13: Titres négociables hors régions | I13: =IF(G13,(E13-G13)/G13,IF(ISBLANK(G13),"",IF(E13,IF( E13 > 0,1,-1),"")))
A14: Intérêts courus | I14: =IF(G14,(E14-G14)/G14,IF(ISBLANK(G14),"",IF(E14,IF( E14 > 0,1,-1),"")))
A15: Autres valeurs assimilées | I15: =IF(G15,(E15-G15)/G15,IF(ISBLANK(G15),"",IF(E15,IF( E15 > 0,1,-1),"")))
A16: TOTAL BRUT TITRES | E16: =SUM(E9:F15) -> 0 | G16: =SUM(G9:H15) -> 0 | I16: =IF(G16,(E16-G16)/G16,IF(ISBLANK(G16),"",IF(E16,IF( E16 > 0,1,-1),"")))
A17: Dépréciations des titres | I17: =IF(G17,(E17-G17)/G17,IF(ISBLANK(G17),"",IF(E17,IF( E17 > 0,1,-1),"")))
A18: TOTAL NET DE DEPRECIATIONS | E18: =E16-E17 -> 0 | G18: =G16-G17 -> 0 | I18: =IF(G18,(E18-G18)/G18,IF(ISBLANK(G18),"",IF(E18,IF( E18 > 0,1,-1),"")))
A19: Commentaire:
A20: ● Justifier toute variation significative.
A21: ● Pour les titres cotés à une bourse de valeur : indiquer le nombre, le prix unitaire d'acquisition et le cours de la bourse au 31 décembre.
A22: ● Faire ressortir les actions ou parts propres et indiquer la date d'acquisition et le nombre de titres détenus.
A23: ● Indiquer les événements et circonstances qui ont conduit à la dépréciation et à la reprise.

Sheet NOTE 10
A1: - 0 -
H2: NOTE 10 SYSTEME NORMAL
A3: Dénomination sociale de l'entité : | C3: ='NOTE 1'!C3 -> 0
A4: Adresse : | B4: ='NOTE 1'!B4 -> 0 | H4: Sigle usuel : | I4: ='NOTE 1'!I4 -> 0
A5: N° IFU : | C5: ='NOTE 1'!C5 -> 0 | E5: Exercice clos le : | F5: ='NOTE 1'!G5 -> 0 | H5: Durée (en mois) : | I5: ='NOTE 1'!I5 -> 0
A6: N° de télédéclarant (NES): | C6: ='NOTE 1'!C6 -> 0
A7: NOTE 10 : VALEURS A ENCAISSER
A8: Libellés | E8: Année N | G8: Année N-1 | I8: Variation en %
A9: Effets à encaisser | I9: =IF(G9,(E9-G9)/G9,IF(ISBLANK(G9),"",IF(E9,IF( E9 > 0,1,-1),"")))
A10: Effets à l'encaissement | I10: =IF(G10,(E10-G10)/G10,IF(ISBLANK(G10),"",IF(E10,IF( E10 > 0,1,-1),"")))
A11: Chèques à encaisser | I11: =IF(G11,(E11-G11)/G11,IF(ISBLANK(G11),"",IF(E11,IF( E11 > 0,1,-1),"")))
A12: Chèques à l'encaissement | I12: =IF(G12,(E12-G12)/G12,IF(ISBLANK(G12),"",IF(E12,IF( E12 > 0,1,-1),"")))
A13: Cartes de crédit à encaisser | I13: =IF(G13,(E13-G13)/G13,IF(ISBLANK(G13),"",IF(E13,IF( E13 > 0,1,-1),"")))
A14: Autres valeurs à encaisser | I14: =IF(G14,(E14-G14)/G14,IF(ISBLANK(G14),"",IF(E14,IF( E14 > 0,1,-1),"")))
A15: TOTAL BRUT VALEURS A ENCAISSER | E15: =SUM(E9:F14) -> 0 | G15: =SUM(G9:H14) -> 0 | I15: =IF(G15,(E15-G15)/G15,IF(ISBLANK(G15),"",IF(E15,IF( E15 > 0,1,-1),"")))
A16: Dépréciations des valeurs à encaisser | I16: =IF(G16,(E16-G16)/G16,IF(ISBLANK(G16),"",IF(E16,IF( E16 > 0,1,-1),"")))
A17: TOTAL NET DE DEPRECIATIONS | E17: =E15-E16 -> 0 | G17: =G15-G16 -> 0 | I17: =IF(G17,(E17-G17)/G17,IF(ISBLANK(G17),"",IF(E17,IF( E17 > 0,1,-1),"")))
A18: Commentaire :
A19: ● Commenter toute variation significative ;
A20: ● Indiquer les événements et circonstances qui ont conduit à la dépréciation et à la reprise.

Sheet NOTE 11
A1: - 0 -
H2: NOTE 11 SYSTEME NORMAL
A3: Dénomination sociale de l'entité :
A4: Adresse : | H4: Sigle usuel :
A5: N° IFU du contribuable : | E5: Exercice clos le : | H5: Durée (en mois) :
A6: N° de télédéclarant (NES):
A7: NOTE 11 : DISPONIBILITES
A8: Libellés | E8: Année N | G8: Année N-1 | I8: Variation en %
A9: Banques locales | I9: =IF(G9,(E9-G9)/G9,IF(ISBLANK(G9),"",IF(E9,IF( E9 > 0,1,-1),"")))
A10: Banques autres états région | I10: =IF(G10,(E10-G10)/G10,IF(ISBLANK(G10),"",IF(E10,IF( E10 > 0,1,-1),"")))
A11: Banques, dépôt à terme | I11: =IF(G11,(E11-G11)/G11,IF(ISBLANK(G11),"",IF(E11,IF( E11 > 0,1,-1),"")))
A12: Autres Banques | I12: =IF(G12,(E12-G12)/G12,IF(ISBLANK(G12),"",IF(E12,IF( E12 > 0,1,-1),"")))
A13: Banques intérêts courus | I13: =IF(G13,(E13-G13)/G13,IF(ISBLANK(G13),"",IF(E13,IF( E13 > 0,1,-1),"")))
A14: Chèques postaux | I14: =IF(G14,(E14-G14)/G14,IF(ISBLANK(G14),"",IF(E14,IF( E14 > 0,1,-1),"")))
A15: Autres établissement financiers | I15: =IF(G15,(E15-G15)/G15,IF(ISBLANK(G15),"",IF(E15,IF( E15 > 0,1,-1),"")))
A16: Etablissement financiers intérêts courus | I16: =IF(G16,(E16-G16)/G16,IF(ISBLANK(G16),"",IF(E16,IF( E16 > 0,1,-1),"")))
A17: Instruments de trésorerie | I17: =IF(G17,(E17-G17)/G17,IF(ISBLANK(G17),"",IF(E17,IF( E17 > 0,1,-1),"")))
A18: Instruments de monnaie électronique | I18: =IF(G18,(E18-G18)/G18,IF(ISBLANK(G18),"",IF(E18,IF( E18 > 0,1,-1),"")))
A19: Caisse | I19: =IF(G19,(E19-G19)/G19,IF(ISBLANK(G19),"",IF(E19,IF( E19 > 0,1,-1),"")))
A20: Régies d'avances et virements accréditifs | I20: =IF(G20,(E20-G20)/G20,IF(ISBLANK(G20),"",IF(E20,IF( E20 > 0,1,-1),"")))
A21: TOTAL BRUT DISPONIBILITES | E21: =SUM(E9:F20) -> 0 | G21: =SUM(G9:H20) -> 0 | I21: =IF(G21,(E21-G21)/G21,IF(ISBLANK(G21),"",IF(E21,IF( E21 > 0,1,-1),"")))
A22: Dépréciations | I22: =IF(G22,(E22-G22)/G22,IF(ISBLANK(G22),"",IF(E22,IF( E22 > 0,1,-1),"")))
A23: TOTAL NET DE DEPRECIATIONS | E23: =E21-E22 -> 0 | G23: =G21-G22 -> 0 | I23: =IF(G23,(E23-G23)/G23,IF(ISBLANK(G23),"",IF(E23,IF( E23 > 0,1,-1),"")))
A24: Commentaire :
A25: ● Indiquer la date de rapprochement des comptes bancaires.
A26: ● Indiquer la date d'inventaire de la caisse et des instruments de monnaie électronique.
A27: ● Justifier toute variation significative.
A28: ● Détailler les instruments de monnaie électronique si le montant est significatif.
A29: ● Indiquer les événements et circonstances qui ont conduit à la dépréciation et à la reprise.
A31: NB : Banques et intérêts courus et Etablissement financiers intérêts courus figurent dans cette rubrique en négatif si le compte principal attaché est débiteur

Sheet NOTE 12
A1: - 0 -
H2: NOTE 12 SYSTEME NORMAL
A3: Dénomination sociale de l'entité : | C3: ='NOTE 11'!C3 -> 0
A4: Adresse : | B4: ='NOTE 11'!B4 -> 0 | H4: Sigle usuel : | I4: ='NOTE 11'!I4 -> 0
A5: N° IFU du contribuable : | C5: ='NOTE 11'!C5 -> 0 | F5: Exercice clos le : | G5: ='NOTE 11'!F5 -> 0 | H5: Durée (en mois) : | I5: ='NOTE 11'!I5 -> 0
A6: N° de télédéclarant (NES): | C6: ='NOTE 11'!C6 -> 0
A7: NOTE 12 : ECARTS DE CONVERSION ET TRANSFERTS DE CHARGES
A8: ECARTS DE CONVERSION
A9: Libellés | E9: Devises | F9: Montant en devises | G9: Cours UML Année acquisition | H9: Cours UML 31/12 | I9: Variation en valeur absolue
A10: Ecarts de conversion actif : détailler les créances et dettes concernées
I11: =ABS(F11*G11-F11*H11) -> 0
I12: =ABS(F12*G12-F12*H12) -> 0
I13: =ABS(F13*G13-F13*H13) -> 0
I14: =ABS(F14*G14-F14*H14) -> 0
I15: =ABS(F15*G15-F15*H15) -> 0
I16: =ABS(F16*G16-F16*H16) -> 0
A17: Ecart de conversion passif : détailler les créances et dettes concernées
I18: =ABS(F18*G18-F18*H18) -> 0
I19: =ABS(F19*G19-F19*H19) -> 0
I20: =ABS(F20*G20-F20*H20) -> 0
I21: =ABS(F21*G21-F21*H21) -> 0
I22: =ABS(F22*G22-F22*H22) -> 0
I23: =ABS(F23*G23-F23*H23) -> 0
I24: =ABS(F24*G24-F24*H24) -> 0
A25: UML : Unités Monétaires légales Commentaire: Faire un commentaire.
A26: TRANSFERTS DE CHARGES
A27: Libellés | G27: Année N | H27: Année N-1 | I27: Variation en %
A28: Transferts de charges d'exploitation : détailler la nature des charges transférées et leurs comptes de provenance (1)
I29: =IFERROR((G29-H29)/H29,"")
I30: =IFERROR((G30-H30)/H30,"")
I31: =IFERROR((G31-H31)/H31,"")
I32: =IFERROR((G32-H32)/H32,"")
I33: =IFERROR((G33-H33)/H33,"")
I34: =IFERROR((G34-H34)/H34,"")
A35: Transferts de charges financières : détailler la nature des charges transférées et leurs comptes de provenance (2)
I36: =IFERROR((G36-H36)/H36,"")
I37: =IFERROR((G37-H37)/H37,"")
I38: =IFERROR((G38-H38)/H38,"")
I39: =IFERROR((G39-H39)/H39,"")
I40: =IFERROR((G40-H40)/H40,"")
I41: =IFERROR((G41-H41)/H41,"")
I42: =IFERROR((G42-H42)/H42,"")
A43: (1): Leurs comptes d'origine: autrement dit indiquerles numéros de comptes d'où le transfert est effectué.
A44: Commentaire: Faire un commentaire.

Sheet NOTE 13
A1: - 0 -
K2: NOTE 13 SYSTEME NORMAL
A3: Dénomination sociale de l'entité : | C3: ='NOTE 11'!C3 -> 0
A4: Adresse : | B4: ='NOTE 11'!B4 -> 0 | K4: Sigle usuel : | L4: ='NOTE 11'!I4 -> 0
A5: N° IFU : | C5: ='NOTE 11'!C5 -> 0 | I5: Exercice clos le : | J5: ='NOTE 11'!F5 -> 0 | K5: Durée (en mois) : | L5: ='NOTE 11'!I5 -> 0
A6: N° de télédéclarant (NES): | C6: ='NOTE 11'!C6 -> 0
A7: NOTE 13 : CAPITAL
I8: Valeur nominale des actions ou parts :
A9: Nom et prénoms ou raison sociale | E9: N° de compte contribuable | F9: Nationalité | G9: Autres nationalités à préciser | H9: Pays de résidence | I9: Nature des actions ou parts (Ordinaires ou préférences) | J9: Nombre | K9: Montant total | L9: Cessions ou remboursements en cours d'exercice
K10: =L8*J10 -> 0
K11: =L8*J11 -> 0
K12: =L8*J12 -> 0
K13: =L8*J13 -> 0
K14: =L8*J14 -> 0
K15: =L8*J15 -> 0
K16: =L8*J16 -> 0
K17: =L8*J17 -> 0
K18: =L8*J18 -> 0
K19: =L8*J19 -> 0
K20: =L8*J20 -> 0
K21: =L8*J21 -> 0
K22: =L8*J22 -> 0
K23: =L8*J23 -> 0
K24: =L8*J24 -> 0
A25: Apporteurs, capital non appelé
A26: TOTAL | K26: =SUM(K10:K25) -> 0
A27: Commentaire :
A28: ● Indiquer si possible le montant du capital à la constitution. | I28: ● Pour les attributions gratuites d'actions indiquer :
A29: ● Indiquer si possible les dates des AGE et le montant du capital augmenté en cas d'augmentation de capital. | I29: - Date de délibération de l’AGE qui décide de l’attribution des actions
A30: ● Indiquer si possible les dates des AGE et le montant du capital diminué en cas de réduction de capital. | I30: - Pourcentage maximum du capital social à attribuer au personnel salarié
A31: ● Indiquer les avantages accordés aux actions de préférence. | I31: - Pourcentage maximum du capital social à attribuer aux dirigeants
A32: ● Apporteurs, capital non appelé : indiquer le délai restant pour appeler le capital. | I32: - Nombre d’actions à attribuer gratuitement
I33: - Délai de conservation des actions par les bénéficiaires
I34: - Nombre de ses actions propres que la société détient

Sheet NOTE 14
A1: - 0 -
G2: NOTE 14 SYSTEME NORMAL
A3: Dénomination sociale de l'entité : | C3: ='NOTE 11'!C3 -> 0
A4: Adresse : | B4: ='NOTE 11'!B4 -> 0 | G4: Sigle usuel : | H4: ='NOTE 11'!I4 -> 0
A5: N° IFU : | C5: ='NOTE 11'!C5 -> 0 | E5: Exercice clos le : | F5: ='NOTE 11'!F5 -> 0 | G5: Durée (en mois) : | H5: ='NOTE 11'!I5 -> 0
A6: N° de télédéclarant (NES): | C6: ='NOTE 11'!C6 -> 0
A7: NOTE 14 : PRIMES ET RESERVES
A8: Libellés | F8: Année N | G8: Année N-1 | H8: Variation en valeur absolue
A9: Primes d'émission | H9: =ABS(F9-G9) -> 0
A10: Prime d'apport | H10: =ABS(F10-G10) -> 0
A11: Prime de fusion | H11: =ABS(F11-G11) -> 0
A12: Prime de conversion | H12: =ABS(F12-G12) -> 0
A13: Autres primes | H13: =ABS(F13-G13) -> 0
A14: TOTAL PRIMES | F14: =SUM(F9:F13) -> 0 | G14: =SUM(G9:G13) -> 0 | H14: =ABS(F14-G14) -> 0
A15: Réserves légales | H15: =ABS(F15-G15) -> 0
A16: Réserves statutaires | H16: =ABS(F16-G16) -> 0
A17: Réserves de plus-values nettes à long terme | H17: =ABS(F17-G17) -> 0
A18: Réserves d’attribution gratuite d’actions au personnel salarié et aux dirigeants | H18: =ABS(F18-G18) -> 0
A19: Autres réserves réglementées | H19: =ABS(F19-G19) -> 0
A20: TOTAL RESERVES INDISPONIBLES | F20: =SUM(F15:F19) -> 0 | G20: =SUM(G15:G19) -> 0 | H20: =ABS(F20-G20) -> 0
A21: Réserves libres | H21: =ABS(F21-G21) -> 0
A22: Report à nouveau | H22: =ABS(F22-G22) -> 0
A23: Commentaire:
A24: ● Indiquer les dates de l'AGE qui a décidé des primes d'apport, d'émission de fusion.
A25: ● Indiquer le détail des réserves libres.
A26: ● Indiquer le montant restant à doter et le taux de dotation de la réserve légale.
A27: ● Indiquer la date de l'AGO qui justifie la variation des réserves et du report à nouveau.

Sheet NOTE 15A
A1: - 0 -
I2: NOTE 15A SYSTEME NORMAL
A3: Dénomination sociale de l'entité : | C3: ='NOTE 11'!C3 -> 0
A4: Adresse : | B4: ='NOTE 11'!B4 -> 0 | I4: Sigle usuel : | J4: ='NOTE 11'!I4 -> 0
A5: N° IFU : | C5: ='NOTE 11'!C5 -> 0 | F5: Exercice clos le : | G5: ='NOTE 11'!F5 -> 0 | I5: Durée (en mois) : | J5: ='NOTE 11'!I5 -> 0
A6: N° de télédéclarant (NES): | C6: ='NOTE 11'!C6 -> 0
A7: NOTE 15A : SUBVENTIONS D'INVESTISSEMENT ET PROVISIONS REGLEMENTEES
A8: Libellés | D8: NOTE | E8: Année N | F8: Année N-1 | G8: Variation en valeur absolue | H8: Variation en % | I8: Régime fiscal | J8: Echéances
A9: État | G9: =ABS(E9-F9) -> 0 | H9: =IF(F9,(E9-F9)/F9,IF(ISBLANK(F9),"",IF(E9,IF( E9 > 0,1,-1),"")))
A10: Régions | G10: =ABS(E10-F10) -> 0 | H10: =IF(F10,(E10-F10)/F10,IF(ISBLANK(F10),"",IF(E10,IF( E10 > 0,1,-1),"")))
A11: Départements | G11: =ABS(E11-F11) -> 0 | H11: =IF(F11,(E11-F11)/F11,IF(ISBLANK(F11),"",IF(E11,IF( E11 > 0,1,-1),"")))
A12: Communes et collectivités publiques décentralisées | G12: =ABS(E12-F12) -> 0 | H12: =IF(F12,(E12-F12)/F12,IF(ISBLANK(F12),"",IF(E12,IF( E12 > 0,1,-1),"")))
A13: Entités publiques ou mixtes | G13: =ABS(E13-F13) -> 0 | H13: =IF(F13,(E13-F13)/F13,IF(ISBLANK(F13),"",IF(E13,IF( E13 > 0,1,-1),"")))
A14: Entités et organismes privés | G14: =ABS(E14-F14) -> 0 | H14: =IF(F14,(E14-F14)/F14,IF(ISBLANK(F14),"",IF(E14,IF( E14 > 0,1,-1),"")))
A15: Organismes internationaux | G15: =ABS(E15-F15) -> 0 | H15: =IF(F15,(E15-F15)/F15,IF(ISBLANK(F15),"",IF(E15,IF( E15 > 0,1,-1),"")))
A16: Autres | G16: =ABS(E16-F16) -> 0 | H16: =IF(F16,(E16-F16)/F16,IF(ISBLANK(F16),"",IF(E16,IF( E16 > 0,1,-1),"")))
A17: TOTAL SUBVENTIONS | E17: =SUM(E9:E16) -> 0 | F17: =SUM(F9:F16) -> 0 | G17: =ABS(E17-F17) -> 0 | H17: =IF(F17,(E17-F17)/F17,IF(ISBLANK(F17),"",IF(E17,IF( E17 > 0,1,-1),"")))
A18: Amortissements dérogatoires | G18: =ABS(E18-F18) -> 0 | H18: =IF(F18,(E18-F18)/F18,IF(ISBLANK(F18),"",IF(E18,IF( E18 > 0,1,-1),"")))
A19: Plus-value de cession à réinvestir | G19: =ABS(E19-F19) -> 0 | H19: =IF(F19,(E19-F19)/F19,IF(ISBLANK(F19),"",IF(E19,IF( E19 > 0,1,-1),"")))
A20: Provisions spéciales de réévaluation | D20: 3E | G20: =ABS(E20-F20) -> 0 | H20: =IF(F20,(E20-F20)/F20,IF(ISBLANK(F20),"",IF(E20,IF( E20 > 0,1,-1),"")))
A21: Provisions réglementées relatives aux immobilisations | G21: =ABS(E21-F21) -> 0 | H21: =IF(F21,(E21-F21)/F21,IF(ISBLANK(F21),"",IF(E21,IF( E21 > 0,1,-1),"")))
A22: Provisions réglementés relatives aux stocks | G22: =ABS(E22-F22) -> 0 | H22: =IF(F22,(E22-F22)/F22,IF(ISBLANK(F22),"",IF(E22,IF( E22 > 0,1,-1),"")))
A23: Provisions pour investissement | G23: =ABS(E23-F23) -> 0 | H23: =IF(F23,(E23-F23)/F23,IF(ISBLANK(F23),"",IF(E23,IF( E23 > 0,1,-1),"")))
A24: Autres provisions et fonds réglementées | G24: =ABS(E24-F24) -> 0 | H24: =IF(F24,(E24-F24)/F24,IF(ISBLANK(F24),"",IF(E24,IF( E24 > 0,1,-1),"")))
A25: TOTAL PROVISIONS REGLEMENTEES | E25: =SUM(E18:E24) -> 0 | F25: =SUM(F18:F24) -> 0 | G25: =ABS(E25-F25) -> 0 | H25: =IF(F25,(E25-F25)/F25,IF(ISBLANK(F25),"",IF(E25,IF( E25 > 0,1,-1),"")))
A26: TOTAL SUBVENTIONS ET PROVISIONS REGLEMENTEES | E26: =E17+E25 -> 0 | F26: =F17+F25 -> 0 | G26: =ABS(E26-F26) -> 0 | H26: =IF(F26,(E26-F26)/F26,IF(ISBLANK(F26),"",IF(E26,IF( E26 > 0,1,-1),"")))
A27: Commentaire:
A28: ● Indiquer pour la subvention la date d’octroi, la nature, les obligations éventuelles.
A29: ● Pour les provisions réglementées, indiquer le texte de référence, les obligations. Commenter toute variation significative.
A30: ● Commenter toute variation significative.

Sheet NOTE 15B
A1: - 0 -
J2: NOTE 15B SYSTEME NORMAL
A3: Dénomination sociale de l'entité : | C3: ='NOTE 11'!C3 -> 0
A4: Adresse : | B4: ='NOTE 11'!B4 -> 0 | J4: Sigle usuel : | K4: ='NOTE 11'!I4 -> 0
A5: N° IFU : | C5: ='NOTE 11'!C5 -> 0 | G5: Exercice clos le : | H5: ='NOTE 11'!F5 -> 0 | J5: Durée (en mois) : | K5: ='NOTE 11'!I5 -> 0
A6: N° de télédéclarant (NES): | C6: ='NOTE 11'!C6 -> 0
A7: NOTE 15B : AUTRES FONDS PROPRES (1)
A8: Libellés | F8: NOTE | G8: Année N | H8: Année N-1 | I8: Variation en valeur absolue | J8: Variation en % | K8: Echéances
A9: Titres participatifs | I9: =ABS(G9-H9) -> 0 | J9: =IF(H9,(G9-H9)/H9,IF(ISBLANK(H9),"",IF(G9,IF( G9 > 0,1,-1),"")))
A10: Avances conditionnées | I10: =ABS(G10-H10) -> 0 | J10: =IF(H10,(G10-H10)/H10,IF(ISBLANK(H10),"",IF(G10,IF( G10 > 0,1,-1),"")))
A11: Titres subordonnés à durée indéterminée (T.S.D.I.) | I11: =ABS(G11-H11) -> 0 | J11: =IF(H11,(G11-H11)/H11,IF(ISBLANK(H11),"",IF(G11,IF( G11 > 0,1,-1),"")))
A12: Obligations remboursables en actions (O.R.A.) | I12: =ABS(G12-H12) -> 0 | J12: =IF(H12,(G12-H12)/H12,IF(ISBLANK(H12),"",IF(G12,IF( G12 > 0,1,-1),"")))
A13: Autres avances et dettes assorties de conditions particulières | I13: =ABS(G13-H13) -> 0 | J13: =IF(H13,(G13-H13)/H13,IF(ISBLANK(H13),"",IF(G13,IF( G13 > 0,1,-1),"")))
A14: TOTAL AUTRES FONDS PROPRES | G14: =SUM(G9:G13) -> 0 | H14: =SUM(H9:H13) -> 0 | I14: =ABS(G14-H14) -> 0 | J14: =IF(H14,(G14-H14)/H14,IF(ISBLANK(H14),"",IF(G14,IF( G14 > 0,1,-1),"")))
A16: (1) Le cas échéant, une rubrique "Autres fonds propres" (montant des émissions de titres participatifs, avances conditionnées, ...) sur une ligne séparée est intercalée entre les rubriques "Total capitaux propres et ressources assimilées " et "Emprunts et dettes financières" si le montant des autres fonds propres est significatif.
A17: Commentaire:
A18: ● Justifier l'inscription de ces dettes dans une rubrique spécifique du passif du bilan "autres fonds propres"(faible probabilité de remboursement, absence d’échéancier...)
A19: ● Justifier le caractère significatif du montant total de cette rubrique
A20: ● Commenter toute variation significative

Sheet NOTE 16A
A1: - 0 -
J2: NOTE 16A SYSTEME NORMAL
A3: Dénomination sociale de l'entité : | C3: ='NOTE 11'!C3 -> 0
A4: Adresse : | B4: ='NOTE 11'!B4 -> 0 | J4: Sigle usuel : | K4: ='NOTE 11'!I4 -> 0
A5: N° IFU : | C5: ='NOTE 11'!C5 -> 0 | G5: Exercice clos le : | I5: ='NOTE 11'!F5 -> 0 | J5: Durée (en mois) : | K5: ='NOTE 11'!I5 -> 0
A6: N° de télédéclarant (NES): | C6: ='NOTE 11'!C6 -> 0
A7: NOTE 16A : DETTES FINANCIERES ET RESSOURCES ASSIMILES
A8: Libellés | E8: Année N | F8: Année N-1 | G8: Variation en valeur absolue | H8: Variation en % | I8: Dettes à un an au plus | J8: Dettes à plus d'un an et à deux ans au plus | K8: Dettes à plus de deux ans
A9: Emprunts obligataires | G9: =ABS(E9-F9) -> 0 | H9: =IF(F9,(E9-F9)/F9,IF(ISBLANK(F9),"",IF(E9,IF( E9 > 0,1,-1),"")))
A10: Emprunts et dettes auprès des établissements de crédit | G10: =ABS(E10-F10) -> 0 | H10: =IF(F10,(E10-F10)/F10,IF(ISBLANK(F10),"",IF(E10,IF( E10 > 0,1,-1),"")))
A11: Avances reçues de l'Etat | G11: =ABS(E11-F11) -> 0 | H11: =IF(F11,(E11-F11)/F11,IF(ISBLANK(F11),"",IF(E11,IF( E11 > 0,1,-1),"")))
A12: Avances reçues et comptes courants bloqués | G12: =ABS(E12-F12) -> 0 | H12: =IF(F12,(E12-F12)/F12,IF(ISBLANK(F12),"",IF(E12,IF( E12 > 0,1,-1),"")))
A13: Dépôts et cautionnements reçus | G13: =ABS(E13-F13) -> 0 | H13: =IF(F13,(E13-F13)/F13,IF(ISBLANK(F13),"",IF(E13,IF( E13 > 0,1,-1),"")))
A14: Intérêts courus | G14: =ABS(E14-F14) -> 0 | H14: =IF(F14,(E14-F14)/F14,IF(ISBLANK(F14),"",IF(E14,IF( E14 > 0,1,-1),"")))
A15: Avances et dettes assorties de conditions particulières | G15: =ABS(E15-F15) -> 0 | H15: =IF(F15,(E15-F15)/F15,IF(ISBLANK(F15),"",IF(E15,IF( E15 > 0,1,-1),"")))
A16: Autres emprunts et dettes | G16: =ABS(E16-F16) -> 0 | H16: =IF(F16,(E16-F16)/F16,IF(ISBLANK(F16),"",IF(E16,IF( E16 > 0,1,-1),"")))
A17: Dettes liées à des participations et sociétés en participation | G17: =ABS(E17-F17) -> 0 | H17: =IF(F17,(E17-F17)/F17,IF(ISBLANK(F17),"",IF(E17,IF( E17 > 0,1,-1),"")))
A18: Comptes permanents bloqués des établissements et succursales | G18: =ABS(E18-F18) -> 0 | H18: =IF(F18,(E18-F18)/F18,IF(ISBLANK(F18),"",IF(E18,IF( E18 > 0,1,-1),"")))
A19: TOTAL EMPRUNTS ET DETTES FINANCIERES | E19: =SUM(E9:E18) -> 0 | F19: =SUM(F9:F18) -> 0 | G19: =ABS(E19-F19) -> 0 | H19: =IF(F19,(E19-F19)/F19,IF(ISBLANK(F19),"",IF(E19,IF( E19 > 0,1,-1),""))) | I19: =SUM(I9:I18) -> 0 | J19: =SUM(J9:J18) -> 0 | K19: =SUM(K9:K18) -> 0
A20: Crédit bail immobilier | G20: =ABS(E20-F20) -> 0 | H20: =IF(F20,(E20-F20)/F20,IF(ISBLANK(F20),"",IF(E20,IF( E20 > 0,1,-1),"")))
A21: Crédit bail mobilier | G21: =ABS(E21-F21) -> 0 | H21: =IF(F21,(E21-F21)/F21,IF(ISBLANK(F21),"",IF(E21,IF( E21 > 0,1,-1),"")))
A22: Location vente | G22: =ABS(E22-F22) -> 0 | H22: =IF(F22,(E22-F22)/F22,IF(ISBLANK(F22),"",IF(E22,IF( E22 > 0,1,-1),"")))
A23: Intérêts courus | G23: =ABS(E23-F23) -> 0 | H23: =IF(F23,(E23-F23)/F23,IF(ISBLANK(F23),"",IF(E23,IF( E23 > 0,1,-1),"")))
A24: Autres dettes de location acquisition | G24: =ABS(E24-F24) -> 0 | H24: =IF(F24,(E24-F24)/F24,IF(ISBLANK(F24),"",IF(E24,IF( E24 > 0,1,-1),"")))
A25: TOTAL DETTES DE LOCATION ACQUISITION | E25: =SUM(E20:E24) -> 0 | F25: =SUM(F20:F24) -> 0 | G25: =ABS(E25-F25) -> 0 | H25: =IF(F25,(E25-F25)/F25,IF(ISBLANK(F25),"",IF(E25,IF( E25 > 0,1,-1),""))) | I25: =SUM(I20:I24) -> 0 | J25: =SUM(J20:J24) -> 0 | K25: =SUM(K20:K24) -> 0
A26: Provisions pour litiges | G26: =ABS(E26-F26) -> 0 | H26: =IF(F26,(E26-F26)/F26,IF(ISBLANK(F26),"",IF(E26,IF( E26 > 0,1,-1),"")))
A27: Provisions pour garantie donnés aux clients | G27: =ABS(E27-F27) -> 0 | H27: =IF(F27,(E27-F27)/F27,IF(ISBLANK(F27),"",IF(E27,IF( E27 > 0,1,-1),"")))
A28: Provisions pour pertes sur marchés à achèvement futur | G28: =ABS(E28-F28) -> 0 | H28: =IF(F28,(E28-F28)/F28,IF(ISBLANK(F28),"",IF(E28,IF( E28 > 0,1,-1),"")))
A29: Provisions pour pertes de change | G29: =ABS(E29-F29) -> 0 | H29: =IF(F29,(E29-F29)/F29,IF(ISBLANK(F29),"",IF(E29,IF( E29 > 0,1,-1),"")))
A30: Provisions pour impôts | G30: =ABS(E30-F30) -> 0 | H30: =IF(F30,(E30-F30)/F30,IF(ISBLANK(F30),"",IF(E30,IF( E30 > 0,1,-1),"")))
A31: Provisions pour pensions et obligations assimilées - engagements de retraite | G31: =ABS(E31-F31) -> 0 | H31: =IF(F31,(E31-F31)/F31,IF(ISBLANK(F31),"",IF(E31,IF( E31 > 0,1,-1),"")))
A32: Actif du régime de retraite (1) | G32: =ABS(E32-F32) -> 0 | H32: =IF(F32,(E32-F32)/F32,IF(ISBLANK(F32),"",IF(E32,IF( E32 > 0,1,-1),"")))
A33: Provisions pour restructuration | G33: =ABS(E33-F33) -> 0 | H33: =IF(F33,(E33-F33)/F33,IF(ISBLANK(F33),"",IF(E33,IF( E33 > 0,1,-1),"")))
A34: Provisions pour amendes et pénalités | G34: =ABS(E34-F34) -> 0 | H34: =IF(F34,(E34-F34)/F34,IF(ISBLANK(F34),"",IF(E34,IF( E34 > 0,1,-1),"")))
A35: Provisions pour propre assureur | G35: =ABS(E35-F35) -> 0 | H35: =IF(F35,(E35-F35)/F35,IF(ISBLANK(F35),"",IF(E35,IF( E35 > 0,1,-1),"")))
A36: Provisions pour démantèlement et remise en état | G36: =ABS(E36-F36) -> 0 | H36: =IF(F36,(E36-F36)/F36,IF(ISBLANK(F36),"",IF(E36,IF( E36 > 0,1,-1),"")))
A37: Provisions de droits à réduction ou avantage en nature | G37: =ABS(E37-F37) -> 0 | H37: =IF(F37,(E37-F37)/F37,IF(ISBLANK(F37),"",IF(E37,IF( E37 > 0,1,-1),"")))
A38: Autres provisions | G38: =ABS(E38-F38) -> 0 | H38: =IF(F38,(E38-F38)/F38,IF(ISBLANK(F38),"",IF(E38,IF( E38 > 0,1,-1),"")))
A39: TOTAL PROVISIONS POUR RISQUES ET CHARGES | E39: =SUM(E26:E38) -> 0 | F39: =SUM(F26:F38) -> 0 | G39: =ABS(E39-F39) -> 0 | H39: =IF(F39,(E39-F39)/F39,IF(ISBLANK(F39),"",IF(E39,IF( E39 > 0,1,-1),"")))
A40: (1): Le solde de ce compte est débiteur
A41: Commentaire:
A42: Pour chaque emprunt et dette de location acquisition: mentionner la date d'octroi, le nom de l'organisme financier, le montant initial de l'emprunt ou de la dette, la durée du crédit, les garanties données par la société.
A43: ● Indiquer les événements et circonstances qui ont conduit à la provision et à la reprise.
A44: ● Pour les pensions et obligations de retraite, indiquer :
A45: - la méthode d'évaluation retenue
A46: - le nom de la compagnie d'assurance ou du fonds de pension, le descriptif de la convention signée avec l'organisme, la périodicité des versements, le montant et la durée de la convention, pour les actifs du régime.

Sheet NOTE 16B
A1: - 0 -
H2: NOTE 16B SYSTEME NORMAL
A3: Dénomination sociale de l'entité : | C3: ='NOTE 11'!C3 -> 0
A4: Adresse : | B4: ='NOTE 11'!B4 -> 0 | H4: Sigle usuel : | I4: ='NOTE 11'!I4 -> 0
A5: N° IFU : | C5: ='NOTE 11'!C5 -> 0 | F5: Exercice clos le : | G5: ='NOTE 11'!F5 -> 0 | H5: Durée (en mois) : | I5: ='NOTE 11'!I5 -> 0
A6: N° de télédéclarant (NES): | C6: ='NOTE 11'!C6 -> 0
A7: NOTE 16B : ENGAGEMENTS DE RETRAITE ET AVANTAGES ASSIMILES : (METHODE ACTUARIELLE)
A8: HYPOTHESES ACTUARIELLES
A9: Libellés | H9: Année N | I9: Année N-1
A10: Taux d'augmentation des salaires
A11: Taux d'actualisation
A12: Taux d'inflation
A13: Probabilité d'être présent dans l'entité à la date de départ à la retraite (expérience passée)
A14: Probabilité d'être en vie à l'âge de départ à la retraite (table de mortalité)
A15: Taux de rendement effectif des actifs du régime
A16: Commentaire :
A17: ● Commenter les variations d'hypothèses actuarielles utilisées pour le calcul des engagements de retraite et avantages assimilés.
A19: VARIATION DE LA VALEUR DE L'ENGAGEMENT DE RETRAITE AU COURS DE L'EXERCICE
A20: Libellés | H20: Année N | I20: Année N-1
A21: Obligation au titre des engagements de retraite à l'ouverture
A22: Coût des services rendus au cours de l'exercice
A23: Coût financier
A24: Pertes actuarielles / (gain)
A25: Prestations payées au cours de l'exercice
A26: Coût des services passés
A27: Obligation au titre des engagements de retraite à la clôture
A28: Commentaire :
A29: ● Indiquer le montant de la charge par nature comptabilisée au cours de exercice
A31: ANALYSE DE SENSIBILITE DES HYPOTHESES ACTUARIELLES
A32: Libellés | F32: Année N | H32: Année N-1
F33: Augmentation | G33: Diminution | H33: Augmentation | I33: Diminution
A34: Taux d'actualisation (variation de ...%)
A35: Taux de progression des salaires (variation de ...%)
A36: Taux de départ du personnel (variation de ...%)
A37: Commentaire :
A38: ● Indiquer l’impact des variations obtenues sur le montant des engagements de retraite.

Sheet NOTE 16B BIS
A1: - 0 -
H2: NOTE 16B BIS SYSTEME NORMAL
A3: Dénomination sociale de l'entité : | C3: ='NOTE 11'!C3 -> 0
A4: Adresse : | B4: ='NOTE 11'!B4 -> 0 | H4: Sigle usuel : | I4: ='NOTE 11'!I4 -> 0
A5: N° IFU : | C5: ='NOTE 11'!C5 -> 0 | F5: Exercice clos le : | G5: ='NOTE 11'!F5 -> 0 | H5: Durée (en mois) : | I5: ='NOTE 11'!I5 -> 0
A6: N° de télédéclarant (NES): | C6: ='NOTE 11'!C6 -> 0
A7: NOTE 16B BIS : ENGAGEMENTS DE RETRAITE ET AVANTAGES ASSIMILES : (METHODE ACTUARIELLE SUITE)
A8: ACTIF/PASSIF NET COMPTABILISE AU TITRE DES REGIMES FINANCES
A9: Libellés | H9: Année N | I9: Année N-1
A10: Valeur actuelle de l'obligation résultant de régimes financés
A11: Valeur actuelle des actifs affectés aux plans de retraite
A12: Excédent / Déficit de régime
A13: Commentaire :
A14: ● Indiquer le montant comptabilisé au passif (ou actif) à la clôture de l'exercice.
A16: VALEUR ACTUELLE DES ACTIFS DU REGIME
A17: Libellés | F17: Année N | H17: Année N-1
F18: Rendement attendu | G18: Juste valeur des actifs | H18: Rendement attendu | I18: Juste valeur des actifs
A19: Actions
A20: Obligations
A21: Autres
A22: Total | F22: =SUM(F19:F21) -> 0 | G22: =SUM(G19:G21) -> 0 | H22: =SUM(H19:H21) -> 0 | I22: =SUM(I19:I21) -> 0
A23: Commentaire :
A24: ● Expliquer comment les taux de rendement par catégorie d’actifs et global ont été déterminés
A25: ● Indiquer le montant des rendements réels des actifs affectés aux plans en N et N-1

Sheet NOTE 16C
A1: - 0 -
G2: NOTE 16C SYSTEME NORMAL
A3: Dénomination sociale de l'entité : | C3: ='NOTE 11'!C3 -> 0
A4: Adresse : | B4: ='NOTE 11'!B4 -> 0 | G4: Sigle usuel : | H4: ='NOTE 11'!I4 -> 0
A5: N° IFU : | C5: ='NOTE 11'!C5 -> 0 | E5: Exercice clos le : | F5: ='NOTE 11'!F5 -> 0 | G5: Durée (en mois) : | H5: ='NOTE 11'!I5 -> 0
A6: N° de télédéclarant (NES): | C6: ='NOTE 11'!C6 -> 0
A7: NOTE 16C : ACTIFS ET PASSIFS EVENTUELS
A8: Libellés | G8: Année N | H8: Année N-1
A9: Actif éventuel | G9: =SUM(G11:G18) -> 0 | H9: =SUM(H11:H18) -> 0
A10: Litiges
A19: Passif éventuel | G19: =SUM(G21:G28) -> 0 | H19: =SUM(H21:H28) -> 0
A20: Litiges
A29: Commentaire :
A30: ● Décrire les principales caractéristiques des actifs / passifs éventuels, l’horizon de temps auquel les encaissements / décaissements sont attendus et les éventuels remboursements à percevoir.

Sheet NOTE 17
A1: - 0 -
J2: NOTE 17 SYSTEME NORMAL
A3: Dénomination sociale de l'entité : | C3: ='NOTE 11'!C3 -> 0
A4: Adresse : | B4: ='NOTE 11'!B4 -> 0 | J4: Sigle usuel : | K4: ='NOTE 11'!I4 -> 0
A5: N° IFU : | C5: ='NOTE 11'!C5 -> 0 | F5: Exercice clos le : | G5: ='NOTE 11'!F5 -> 0 | J5: Durée (en mois) : | K5: ='NOTE 11'!I5 -> 0
A6: N° de télédéclarant (NES): | C6: ='NOTE 11'!C6 -> 0
A7: NOTE 17 : FOURNISSEURS D'EXPLOITATION
A8: Libellés | F8: Année N | G8: Année N-1 | H8: Variation en % | I8: Dettes à un an au plus | J8: Dettes à plus d'un an et à deux ans au plus | K8: Dettes à plus de deux ans
A9: Fournisseurs dettes en compte (hors groupe) | H9: =IF(G9,(F9-G9)/G9,IF(ISBLANK(G9),"",IF(F9,IF( F9 > 0,1,-1),"")))
A10: Fournisseurs effets à payer (hors groupe) | H10: =IF(G10,(F10-G10)/G10,IF(ISBLANK(G10),"",IF(F10,IF( F10 > 0,1,-1),"")))
A11: Fournisseurs, dettes et effets à payer groupe | H11: =IF(G11,(F11-G11)/G11,IF(ISBLANK(G11),"",IF(F11,IF( F11 > 0,1,-1),"")))
A12: Fournisseurs factures non parvenues (hors groupe) | H12: =IF(G12,(F12-G12)/G12,IF(ISBLANK(G12),"",IF(F12,IF( F12 > 0,1,-1),"")))
A13: Fournisseurs factures non parvenues groupe | H13: =IF(G13,(F13-G13)/G13,IF(ISBLANK(G13),"",IF(F13,IF( F13 > 0,1,-1),"")))
A14: TOTAL FOURNISSEURS | F14: =SUM(F9:F13) -> 0 | G14: =SUM(G9:G13) -> 0 | H14: =IF(G14,(F14-G14)/G14,IF(ISBLANK(G14),"",IF(F14,IF( F14 > 0,1,-1),""))) | I14: =SUM(I9:I13) -> 0 | J14: =SUM(J9:J13) -> 0 | K14: =SUM(K9:K13) -> 0
A15: Fournisseurs, avances et acomptes (hors groupe) | H15: =IF(G15,(F15-G15)/G15,IF(ISBLANK(G15),"",IF(F15,IF( F15 > 0,1,-1),"")))
A16: Fournisseurs, avances et acomptes groupe | H16: =IF(G16,(F16-G16)/G16,IF(ISBLANK(G16),"",IF(F16,IF( F16 > 0,1,-1),"")))
A17: Autres fournisseurs débiteurs | H17: =IF(G17,(F17-G17)/G17,IF(ISBLANK(G17),"",IF(F17,IF( F17 > 0,1,-1),"")))
A18: TOTAL FOURNISSEURS DEBITEURS | F18: =SUM(F15:F17) -> 0 | G18: =SUM(G15:G17) -> 0 | H18: =IF(G18,(F18-G18)/G18,IF(ISBLANK(G18),"",IF(F18,IF( F18 > 0,1,-1),""))) | I18: =SUM(I15:I17) -> 0 | J18: =SUM(J15:J17) -> 0 | K18: =SUM(K15:K17) -> 0
A19: Commentaire:
A20: ● Commenter toutes variations significatives.
A21: ● Indiquer pour les dettes du groupe le nom de la société du groupe et le % de titres détenus.
A22: ● Commenter les dettes anciennes.

Sheet NOTE 18
A1: - 0 -
J2: NOTE 18 SYSTEME NORMAL
A3: Dénomination sociale de l'entité : | C3: ='NOTE 11'!C3 -> 0
A4: Adresse : | B4: ='NOTE 11'!B4 -> 0 | J4: Sigle usuel : | K4: ='NOTE 11'!I4 -> 0
A5: N° IFU : | C5: ='NOTE 11'!C5 -> 0 | G5: Exercice clos le : | H5: ='NOTE 11'!F5 -> 0 | J5: Durée (en mois) : | K5: ='NOTE 11'!I5 -> 0
A6: N° de télédéclarant (NES): | C6: ='NOTE 11'!C6 -> 0
A7: NOTE 18 : DETTES FISCALES ET SOCIALES
A8: Libellés | E8: Année N | F8: Année N-1 | G8: Variation en valeur absolue | H8: Variation en % | I8: Dettes à un an au plus | J8: Dettes à plus d'un an et à deux ans au plus | K8: Dettes à plus de deux ans
A9: Personnel avances et acomptes | G9: =ABS(E9-F9) -> 0 | H9: =IF(F9,(E9-F9)/F9,IF(ISBLANK(F9),"",IF(E9,IF( E9 > 0,1,-1),"")))
A10: Personnel rémunérations dues | G10: =ABS(E10-F10) -> 0 | H10: =IF(F10,(E10-F10)/F10,IF(ISBLANK(F10),"",IF(E10,IF( E10 > 0,1,-1),"")))
A11: Autres personnel | G11: =ABS(E11-F11) -> 0 | H11: =IF(F11,(E11-F11)/F11,IF(ISBLANK(F11),"",IF(E11,IF( E11 > 0,1,-1),"")))
A12: Caisse de sécurité sociale | G12: =ABS(E12-F12) -> 0 | H12: =IF(F12,(E12-F12)/F12,IF(ISBLANK(F12),"",IF(E12,IF( E12 > 0,1,-1),"")))
A13: Caisse de retraite | G13: =ABS(E13-F13) -> 0 | H13: =IF(F13,(E13-F13)/F13,IF(ISBLANK(F13),"",IF(E13,IF( E13 > 0,1,-1),"")))
A14: Autres organismes sociaux | G14: =ABS(E14-F14) -> 0 | H14: =IF(F14,(E14-F14)/F14,IF(ISBLANK(F14),"",IF(E14,IF( E14 > 0,1,-1),"")))
A15: TOTAL DETTES SOCIALES | E15: =SUM(E9:E14) -> 0 | F15: =SUM(F9:F14) -> 0 | G15: =SUM(G9:G14) -> 0 | H15: =IF(F15,(E15-F15)/F15,IF(ISBLANK(F15),"",IF(E15,IF( E15 > 0,1,-1),""))) | I15: =SUM(I9:I14) -> 0 | J15: =SUM(J9:J14) -> 0 | K15: =SUM(K9:K14) -> 0
A16: Etat, impôts sur les bénéfices | G16: =ABS(E16-F16) -> 0 | H16: =IF(F16,(E16-F16)/F16,IF(ISBLANK(F16),"",IF(E16,IF( E16 > 0,1,-1),"")))
A17: Etat, impôts et taxes | G17: =ABS(E17-F17) -> 0 | H17: =IF(F17,(E17-F17)/F17,IF(ISBLANK(F17),"",IF(E17,IF( E17 > 0,1,-1),"")))
A18: Etat, TVA | G18: =ABS(E18-F18) -> 0 | H18: =IF(F18,(E18-F18)/F18,IF(ISBLANK(F18),"",IF(E18,IF( E18 > 0,1,-1),"")))
A19: Etat, impôts retenus à la source | G19: =ABS(E19-F19) -> 0 | H19: =IF(F19,(E19-F19)/F19,IF(ISBLANK(F19),"",IF(E19,IF( E19 > 0,1,-1),"")))
A20: Autres dettes Etat | G20: =ABS(E20-F20) -> 0 | H20: =IF(F20,(E20-F20)/F20,IF(ISBLANK(F20),"",IF(E20,IF( E20 > 0,1,-1),"")))
A21: TOTAL DETTES FISCALES | E21: =SUM(E16:E20) -> 0 | F21: =SUM(F16:F20) -> 0 | G21: =SUM(G16:G20) -> 0 | H21: =IF(F21,(E21-F21)/F21,IF(ISBLANK(F21),"",IF(E21,IF( E21 > 0,1,-1),""))) | I21: =SUM(I16:I20) -> 0 | J21: =SUM(J16:J20) -> 0 | K21: =SUM(K16:K20) -> 0
A22: TOTAL DETTES SOCIALES ET FISCALES | E22: =E15+E21 -> 0 | F22: =F15+F21 -> 0 | G22: =G15+G21 -> 0 | H22: =IF(F22,(E22-F22)/F22,IF(ISBLANK(F22),"",IF(E22,IF( E22 > 0,1,-1),""))) | I22: =I15+I21 -> 0 | J22: =J15+J21 -> 0 | K22: =K15+K21 -> 0
A23: Commentaire:
A24: ● Commenter toute variation significative.
A25: ● Commenter les dettes anciennes

Sheet NOTE 19
A1: - 0 -
J2: NOTE 19 SYSTEME NORMAL
A3: Dénomination sociale de l'entité : | C3: ='NOTE 11'!C3 -> 0
A4: Adresse : | B4: ='NOTE 11'!B4 -> 0 | J4: Sigle usuel : | K4: ='NOTE 11'!I4 -> 0
A5: N° IFU : | C5: ='NOTE 11'!C5 -> 0 | G5: Exercice clos le : | I5: ='NOTE 11'!F5 -> 0 | J5: Durée (en mois) : | K5: ='NOTE 11'!I5 -> 0
A6: N° de télédéclarant (NES): | C6: ='NOTE 11'!C6 -> 0
A7: NOTE 19 : AUTRES DETTES ET PROVISIONS POUR RISQUES ET CHARGES A COURT TERME
A8: Libellés | E8: Année N | F8: Année N-1 | G8: Variation en valeur absolue | H8: Variation en % | I8: Dettes à un an au plus | J8: Dettes à plus d'un an et à deux ans au plus | K8: Dettes à plus de deux ans
A9: Organismes internationaux | G9: =ABS(E9-F9) -> 0 | H9: =IF(F9,(E9-F9)/F9,IF(ISBLANK(F9),"",IF(E9,IF( E9 > 0,1,-1),"")))
A10: Apporteurs, opérations sur le capital | G10: =ABS(E10-F10) -> 0 | H10: =IF(F10,(E10-F10)/F10,IF(ISBLANK(F10),"",IF(E10,IF( E10 > 0,1,-1),"")))
A11: Associés, compte courant | G11: =ABS(E11-F11) -> 0 | H11: =IF(F11,(E11-F11)/F11,IF(ISBLANK(F11),"",IF(E11,IF( E11 > 0,1,-1),"")))
A12: Associés dividendes à payer | G12: =ABS(E12-F12) -> 0 | H12: =IF(F12,(E12-F12)/F12,IF(ISBLANK(F12),"",IF(E12,IF( E12 > 0,1,-1),"")))
A13: Groupe, comptes courants | G13: =ABS(E13-F13) -> 0 | H13: =IF(F13,(E13-F13)/F13,IF(ISBLANK(F13),"",IF(E13,IF( E13 > 0,1,-1),"")))
A14: Autres dettes associés | G14: =ABS(E14-F14) -> 0 | H14: =IF(F14,(E14-F14)/F14,IF(ISBLANK(F14),"",IF(E14,IF( E14 > 0,1,-1),"")))
A15: TOTAL DETTES ASSOCIES | E15: =SUM(E9:E14) -> 0 | F15: =SUM(F9:F14) -> 0 | G15: =SUM(G9:G14) -> 0 | H15: =IF(F15,(E15-F15)/F15,IF(ISBLANK(F15),"",IF(E15,IF( E15 > 0,1,-1),""))) | I15: =SUM(I9:I14) -> 0 | J15: =SUM(J9:J14) -> 0 | K15: =SUM(K9:K14) -> 0
A16: Créditeurs divers | G16: =ABS(E16-F16) -> 0 | H16: =IF(F16,(E16-F16)/F16,IF(ISBLANK(F16),"",IF(E16,IF( E16 > 0,1,-1),"")))
A17: Obligataires | G17: =ABS(E17-F17) -> 0 | H17: =IF(F17,(E17-F17)/F17,IF(ISBLANK(F17),"",IF(E17,IF( E17 > 0,1,-1),"")))
A18: Rémunérations d'administrateurs | G18: =ABS(E18-F18) -> 0 | H18: =IF(F18,(E18-F18)/F18,IF(ISBLANK(F18),"",IF(E18,IF( E18 > 0,1,-1),"")))
A19: Compte d'affacturage et de titrisation | G19: =ABS(E19-F19) -> 0 | H19: =IF(F19,(E19-F19)/F19,IF(ISBLANK(F19),"",IF(E19,IF( E19 > 0,1,-1),"")))
A20: Versements restant à effectuer sur titres de placement non libérés | G20: =ABS(E20-F20) -> 0 | H20: =IF(F20,(E20-F20)/F20,IF(ISBLANK(F20),"",IF(E20,IF( E20 > 0,1,-1),"")))
A21: Compte transitoire ajustement spécial lié à la révision du SYSCOHADA (Voir Note 8B) | G21: =ABS(E21-F21) -> 0 | H21: =IF(F21,(E21-F21)/F21,IF(ISBLANK(F21),"",IF(E21,IF( E21 > 0,1,-1),"")))
A22: Autres créditeurs divers | G22: =ABS(E22-F22) -> 0 | H22: =IF(F22,(E22-F22)/F22,IF(ISBLANK(F22),"",IF(E22,IF( E22 > 0,1,-1),"")))
A23: TOTAL CREDITEURS DIVERS | E23: =SUM(E16:E22) -> 0 | F23: =SUM(F16:F22) -> 0 | G23: =SUM(G16:G22) -> 0 | H23: =IF(F23,(E23-F23)/F23,IF(ISBLANK(F23),"",IF(E23,IF( E23 > 0,1,-1),""))) | I23: =SUM(I16:I22) -> 0 | J23: =SUM(J16:J22) -> 0 | K23: =SUM(K16:K22) -> 0
A24: Comptes permanents non bloqués des établissements et des succursales | G24: =ABS(E24-F24) -> 0 | H24: =IF(F24,(E24-F24)/F24,IF(ISBLANK(F24),"",IF(E24,IF( E24 > 0,1,-1),"")))
A25: Comptes de liaison charges et produits | G25: =ABS(E25-F25) -> 0 | H25: =IF(F25,(E25-F25)/F25,IF(ISBLANK(F25),"",IF(E25,IF( E25 > 0,1,-1),"")))
A26: Comptes de liaison des sociétés en participation | G26: =ABS(E26-F26) -> 0 | H26: =IF(F26,(E26-F26)/F26,IF(ISBLANK(F26),"",IF(E26,IF( E26 > 0,1,-1),"")))
A27: TOTAL COMPTES DE LIAISON | E27: =SUM(E24:E26) -> 0 | F27: =SUM(F24:F26) -> 0 | G27: =SUM(G24:G26) -> 0 | H27: =IF(F27,(E27-F27)/F27,IF(ISBLANK(F27),"",IF(E27,IF( E27 > 0,1,-1),""))) | I27: =SUM(I24:I26) -> 0 | J27: =SUM(J24:J26) -> 0 | K27: =SUM(K24:K26) -> 0
A28: TOTAL AUTRES DETTES | E28: =E15+E23+E27 -> 0 | F28: =F15+F23+F27 -> 0 | G28: =G15+G23+G27 -> 0 | H28: =IF(F28,(E28-F28)/F28,IF(ISBLANK(F28),"",IF(E28,IF( E28 > 0,1,-1),""))) | I28: =I15+I23+I27 -> 0 | J28: =J15+J23+J27 -> 0 | K28: =K15+K23+K27 -> 0
A29: Provisions pour risques et charges à court terme (voir note 28) | G29: =ABS(E29-F29) -> 0 | H29: =IF(F29,(E29-F29)/F29,IF(ISBLANK(F29),"",IF(E29,IF( E29 > 0,1,-1),"")))
A30: Commentaire:
A31: ● Commenter toute variation significative.
A32: ● Indiquer le taux de rémunération si compte courant rémunéré.
A33: ● Commenter les dettes anciennes.
A34: ● Compte transitoire ajustement spécial, indiquer le détail du compte et la durée restant pour l'apurement.

Sheet NOTE 20
A1: - 0 -
G2: NOTE 20 SYSTEME NORMAL
A3: Dénomination sociale de l'entité : | C3: ='NOTE 11'!C3 -> 0
A4: Adresse : | B4: ='NOTE 11'!B4 -> 0 | G4: Sigle usuel : | H4: ='NOTE 11'!I4 -> 0
A5: N° IFU : | C5: ='NOTE 11'!C5 -> 0 | E5: Exercice clos le : | F5: ='NOTE 11'!F5 -> 0 | G5: Durée (en mois) : | H5: ='NOTE 11'!I5 -> 0
A6: N° de télédéclarant (NES): | C6: ='NOTE 11'!C6 -> 0
A7: NOTE 20 : BANQUES, CREDIT D'ESCOMPTE ET DE TRESORERIE
A8: Libellés | F8: Année N | G8: Année N-1 | H8: Variation en %
A9: Escomptes de crédit de campagne | H9: =IF(G9,(F9-G9)/G9,IF(ISBLANK(G9),"",IF(F9,IF( F9 > 0,1,-1),"")))
A10: Escomptes de crédit ordinaires | H10: =IF(G10,(F10-G10)/G10,IF(ISBLANK(G10),"",IF(F10,IF( F10 > 0,1,-1),"")))
A11: TOTAL: BANQUES, CREDITS D'ESCOMPTE ET DE TRESORERIE | F11: =SUM(F9:F10) -> 0 | G11: =SUM(G9:G10) -> 0 | H11: =IF(G11,(F11-G11)/G11,IF(ISBLANK(G11),"",IF(F11,IF( F11 > 0,1,-1),"")))
A12: Banques locales | H12: =IF(G12,(F12-G12)/G12,IF(ISBLANK(G12),"",IF(F12,IF( F12 > 0,1,-1),"")))
A13: Banques autres états région | H13: =IF(G13,(F13-G13)/G13,IF(ISBLANK(G13),"",IF(F13,IF( F13 > 0,1,-1),"")))
A14: Autres Banques | H14: =IF(G14,(F14-G14)/G14,IF(ISBLANK(G14),"",IF(F14,IF( F14 > 0,1,-1),"")))
A15: Banques intérêts courus | H15: =IF(G15,(F15-G15)/G15,IF(ISBLANK(G15),"",IF(F15,IF( F15 > 0,1,-1),"")))
A16: Crédit de trésorerie
A17: TOTAL: BANQUES, CREDITS DE TRESORERIE | F17: =SUM(F12:F15) -> 0 | G17: =SUM(G12:G15) -> 0 | H17: =IF(G17,(F17-G17)/G17,IF(ISBLANK(G17),"",IF(F17,IF( F17 > 0,1,-1),"")))
A18: TOTAL GENERAL | F18: =F11+F17 -> 0 | G18: =G11+G17 -> 0 | H18: =IF(G18,(F18-G18)/G18,IF(ISBLANK(G18),"",IF(F18,IF( F18 > 0,1,-1),"")))
A19: Commentaire:
A20: ● Commenter toute variation significative.
A21: ● Indiquer le nom de l'organisme les conditions de crédit, le taux d'intérêt, la durée du crédit.
A23: NB : Banques et intérêts courus figurent dans cette rubrique si le compte principal attaché est créditeur.

Sheet NOTE 21
A1: - 0 -
G2: NOTE 21 SYSTEME NORMAL
A3: Dénomination sociale de l'entité :
A4: Adresse : | G4: Sigle usuel :
A5: N° IFU : | E5: Exercice clos le : | G5: Durée (en mois) :
A6: N° de télédéclarant (NES):
A7: NOTE 21 : CHIFFRE D’AFFAIRES ET AUTRES PRODUITS
A8: Libellés | F8: Année N | G8: Année N-1 | H8: Variation en %
A9: Ventes de marchandises dans l'Etat partie | H9: =IF(G9,(F9-G9)/G9,IF(ISBLANK(G9),"",IF(F9,IF( F9 > 0,1,-1),"")))
A10: Ventes de marchandises dans les autres Etats parties de la Région | H10: =IF(G10,(F10-G10)/G10,IF(ISBLANK(G10),"",IF(F10,IF( F10 > 0,1,-1),"")))
A11: Ventes de marchandises hors Région | H11: =IF(G11,(F11-G11)/G11,IF(ISBLANK(G11),"",IF(F11,IF( F11 > 0,1,-1),"")))
A12: Ventes de marchandises groupe | H12: =IF(G12,(F12-G12)/G12,IF(ISBLANK(G12),"",IF(F12,IF( F12 > 0,1,-1),"")))
A13: Ventes de marchandises sur internet | H13: =IF(G13,(F13-G13)/G13,IF(ISBLANK(G13),"",IF(F13,IF( F13 > 0,1,-1),"")))
A14: TOTAL : VENTES MARCHANDISES | F14: =SUM(F9:F13) -> 0 | G14: =SUM(G9:G13) -> 0 | H14: =IF(G14,(F14-G14)/G14,IF(ISBLANK(G14),"",IF(F14,IF( F14 > 0,1,-1),"")))
A15: Ventes de produits fabriqués dans l'Etat partie | H15: =IF(G15,(F15-G15)/G15,IF(ISBLANK(G15),"",IF(F15,IF( F15 > 0,1,-1),"")))
A16: Ventes de produits fabriqués dans les autres Etats parties de la Région | H16: =IF(G16,(F16-G16)/G16,IF(ISBLANK(G16),"",IF(F16,IF( F16 > 0,1,-1),"")))
A17: Ventes de produits fabriqués hors Région | H17: =IF(G17,(F17-G17)/G17,IF(ISBLANK(G17),"",IF(F17,IF( F17 > 0,1,-1),"")))
A18: Ventes de produits fabriqués groupe | H18: =IF(G18,(F18-G18)/G18,IF(ISBLANK(G18),"",IF(F18,IF( F18 > 0,1,-1),"")))
A19: Ventes de produits fabriqués sur internet | H19: =IF(G19,(F19-G19)/G19,IF(ISBLANK(G19),"",IF(F19,IF( F19 > 0,1,-1),"")))
A20: TOTAL : VENTES DE PRODUITS FABRIQUES | F20: =SUM(F15:F19) -> 0 | G20: =SUM(G15:G19) -> 0 | H20: =IF(G20,(F20-G20)/G20,IF(ISBLANK(G20),"",IF(F20,IF( F20 > 0,1,-1),"")))
A21: Ventes de travaux et services dans l'Etat partie | H21: =IF(G21,(F21-G21)/G21,IF(ISBLANK(G21),"",IF(F21,IF( F21 > 0,1,-1),"")))
A22: Ventes de travaux et services dans les autres Etats parties de la Région | H22: =IF(G22,(F22-G22)/G22,IF(ISBLANK(G22),"",IF(F22,IF( F22 > 0,1,-1),"")))
A23: Ventes de travaux et services hors Région | H23: =IF(G23,(F23-G23)/G23,IF(ISBLANK(G23),"",IF(F23,IF( F23 > 0,1,-1),"")))
A24: Ventes de travaux et services groupe | H24: =IF(G24,(F24-G24)/G24,IF(ISBLANK(G24),"",IF(F24,IF( F24 > 0,1,-1),"")))
A25: Ventes de travaux et services sur internet | H25: =IF(G25,(F25-G25)/G25,IF(ISBLANK(G25),"",IF(F25,IF( F25 > 0,1,-1),"")))
A26: TOTAL : VENTES DE TRAVAUX ET SERVICES VENDUS | F26: =SUM(F21:F25) -> 0 | G26: =SUM(G21:G25) -> 0 | H26: =IF(G26,(F26-G26)/G26,IF(ISBLANK(G26),"",IF(F26,IF( F26 > 0,1,-1),"")))
A27: Produits accessoires à détailler par nature d'activité économique : dont le détail de la rubrique "Divers" de la FIRD 2 | F27: =SUM(F28:F35) -> 0 | G27: =SUM(G28:G35) -> 0 | H27: =IF(G27,(F27-G27)/G27,IF(ISBLANK(G27),"",IF(F27,IF( F27 > 0,1,-1),"")))
H28: =IF(G28,(F28-G28)/G28,IF(ISBLANK(G28),"",IF(F28,IF( F28 > 0,1,-1),"")))
H29: =IF(G29,(F29-G29)/G29,IF(ISBLANK(G29),"",IF(F29,IF( F29 > 0,1,-1),"")))
H30: =IF(G30,(F30-G30)/G30,IF(ISBLANK(G30),"",IF(F30,IF( F30 > 0,1,-1),"")))
H31: =IF(G31,(F31-G31)/G31,IF(ISBLANK(G31),"",IF(F31,IF( F31 > 0,1,-1),"")))
H32: =IF(G32,(F32-G32)/G32,IF(ISBLANK(G32),"",IF(F32,IF( F32 > 0,1,-1),"")))
H33: =IF(G33,(F33-G33)/G33,IF(ISBLANK(G33),"",IF(F33,IF( F33 > 0,1,-1),"")))
H34: =IF(G34,(F34-G34)/G34,IF(ISBLANK(G34),"",IF(F34,IF( F34 > 0,1,-1),"")))
H35: =IF(G35,(F35-G35)/G35,IF(ISBLANK(G35),"",IF(F35,IF( F35 > 0,1,-1),"")))
A36: TOTAL : CHIFFRES D'AFFAIRES | F36: =F14+F20+F26+F27 -> 0 | G36: =G14+G20+G26+G27 -> 0 | H36: =IF(G36,(F36-G36)/G36,IF(ISBLANK(G36),"",IF(F36,IF( F36 > 0,1,-1),"")))
A37: Production immobilisée | H37: =IF(G37,(F37-G37)/G37,IF(ISBLANK(G37),"",IF(F37,IF( F37 > 0,1,-1),"")))
A38: Subventions d'exploitation | H38: =IF(G38,(F38-G38)/G38,IF(ISBLANK(G38),"",IF(F38,IF( F38 > 0,1,-1),"")))
A39: Autres produits (1) | H39: =IF(G39,(F39-G39)/G39,IF(ISBLANK(G39),"",IF(F39,IF( F39 > 0,1,-1),"")))
A40: TOTAL : AUTRES PRODUITS | F40: =F38+F39 -> 0 | G40: =G38+G39 -> 0 | H40: =IF(G40,(F40-G40)/G40,IF(ISBLANK(G40),"",IF(F40,IF( F40 > 0,1,-1),"")))
A41: TOTAL | F41: =F36+F37+F40 -> 0 | G41: =G36+G37+G40 -> 0 | H41: =IF(G41,(F41-G41)/G41,IF(ISBLANK(G41),"",IF(F41,IF( F41 > 0,1,-1),"")))
A42: (1): Sous cette rubrique, les "Divers" de la FIRD 2 ne doivent pas figurer. Il s'agit ici des comptes 75…
A43: Commentaire:
A44: ● Justifier toute variation significative.
A45: ● Détailler: produits intermédiaires, produits résiduels, produits accessoires et autres produits si significatifs.
A46: ● Dans le cas de location-financement fournir les informations suivantes :
A47: - Résultat de la vente
A48: - Produits financiers sur l’investissement net
A49: - Revenus locatifs liés aux loyers variables non inclus dans l’investissement net
A50: - Echéances des loyers à recevoir :
A51: • jusqu’à 1 an • de 1 an à 5 ans • à plus de 5 ans

Sheet NOTE 22
A1: - 0 -
G2: NOTE 22 SYSTEME NORMAL
A3: Dénomination sociale de l'entité : | C3: ='NOTE 21'!C3 -> 0
A4: Adresse : | B4: ='NOTE 21'!B4 -> 0 | G4: Sigle usuel : | H4: ='NOTE 21'!H4 -> 0
A5: N° IFU : | C5: ='NOTE 21'!C5 -> 0 | E5: Exercice clos le : | F5: ='NOTE 21'!F5 -> 0 | G5: Durée (en mois) : | H5: ='NOTE 21'!H5 -> 0
A6: N° de télédéclarant (NES): | C6: ='NOTE 21'!C6 -> 0
A7: NOTE 22 : ACHATS
A8: Libellés | F8: Année N | G8: Année N-1 | H8: Variation en %
A9: Achats de marchandises dans l'Etat partie | H9: =IF(G9,(F9-G9)/G9,IF(ISBLANK(G9),"",IF(F9,IF( F9 > 0,1,-1),"")))
A10: Achats de marchandises dans les autres Etats parties de la Région | H10: =IF(G10,(F10-G10)/G10,IF(ISBLANK(G10),"",IF(F10,IF( F10 > 0,1,-1),"")))
A11: Achats de marchandises hors Région | H11: =IF(G11,(F11-G11)/G11,IF(ISBLANK(G11),"",IF(F11,IF( F11 > 0,1,-1),"")))
A12: Achats de marchandises groupe | H12: =IF(G12,(F12-G12)/G12,IF(ISBLANK(G12),"",IF(F12,IF( F12 > 0,1,-1),"")))
A13: TOTAL : ACHATS DE MARCHANDISES | F13: =SUM(F9:F12) -> 0 | G13: =SUM(G9:G12) -> 0 | H13: =IF(G13,(F13-G13)/G13,IF(ISBLANK(G13),"",IF(F13,IF( F13 > 0,1,-1),"")))
A14: Achats de matières premières et fournitures liées dans l'Etat partie | H14: =IF(G14,(F14-G14)/G14,IF(ISBLANK(G14),"",IF(F14,IF( F14 > 0,1,-1),"")))
A15: Achats de matères premières et fournitures liées dans les autres Etats parties de la Région | H15: =IF(G15,(F15-G15)/G15,IF(ISBLANK(G15),"",IF(F15,IF( F15 > 0,1,-1),"")))
A16: Achats matières premières et fournitures liées hors Région | H16: =IF(G16,(F16-G16)/G16,IF(ISBLANK(G16),"",IF(F16,IF( F16 > 0,1,-1),"")))
A17: Achats matières premières et fournitures liées groupe | H17: =IF(G17,(F17-G17)/G17,IF(ISBLANK(G17),"",IF(F17,IF( F17 > 0,1,-1),"")))
A18: TOTAL : ACHATS MATIERES PREMIERES ET FOURNITURES LIEES | F18: =SUM(F14:F17) -> 0 | G18: =SUM(G14:G17) -> 0 | H18: =IF(G18,(F18-G18)/G18,IF(ISBLANK(G18),"",IF(F18,IF( F18 > 0,1,-1),"")))
A19: Matières consommables | H19: =IF(G19,(F19-G19)/G19,IF(ISBLANK(G19),"",IF(F19,IF( F19 > 0,1,-1),"")))
A20: Matières combustibles | H20: =IF(G20,(F20-G20)/G20,IF(ISBLANK(G20),"",IF(F20,IF( F20 > 0,1,-1),"")))
A21: Produits d'entretien | H21: =IF(G21,(F21-G21)/G21,IF(ISBLANK(G21),"",IF(F21,IF( F21 > 0,1,-1),"")))
A22: Fournitures d'atelier, d'usine et de magasin | H22: =IF(G22,(F22-G22)/G22,IF(ISBLANK(G22),"",IF(F22,IF( F22 > 0,1,-1),"")))
A23: Eau | H23: =IF(G23,(F23-G23)/G23,IF(ISBLANK(G23),"",IF(F23,IF( F23 > 0,1,-1),"")))
A24: Electricité | H24: =IF(G24,(F24-G24)/G24,IF(ISBLANK(G24),"",IF(F24,IF( F24 > 0,1,-1),"")))
A25: Autres énergies | H25: =IF(G25,(F25-G25)/G25,IF(ISBLANK(G25),"",IF(F25,IF( F25 > 0,1,-1),"")))
A26: Fourniture d'entretien | H26: =IF(G26,(F26-G26)/G26,IF(ISBLANK(G26),"",IF(F26,IF( F26 > 0,1,-1),"")))
A27: Fourniture de bureau | H27: =IF(G27,(F27-G27)/G27,IF(ISBLANK(G27),"",IF(F27,IF( F27 > 0,1,-1),"")))
A28: Petit matériel et outillages | H28: =IF(G28,(F28-G28)/G28,IF(ISBLANK(G28),"",IF(F28,IF( F28 > 0,1,-1),"")))
A29: Achats études, prestations de services, de travaux matériels et équipements | H29: =IF(G29,(F29-G29)/G29,IF(ISBLANK(G29),"",IF(F29,IF( F29 > 0,1,-1),"")))
A30: Achats d'emballages | H30: =IF(G30,(F30-G30)/G30,IF(ISBLANK(G30),"",IF(F30,IF( F30 > 0,1,-1),"")))
... A32: Remises rabais, remises et ristournes (non ventilés) | H32: =IF(G32,(F32-G32)/G32,IF(ISBLANK(G32),"",IF(F32,IF( F32 > 0,1,-1),"")))
A33: TOTAL : AUTRES ACHATS | F33: =SUM(F19:F32) -> 0 | G33: =SUM(G19:G32) -> 0 | H33: =IF(G33,(F33-G33)/G33,IF(ISBLANK(G33),"",IF(F33,IF( F33 > 0,1,-1),"")))
A34: (1) voir la note "SUPPL5"
A35: Commentaire :
A36: ● Commenter toute variation significative.

Sheet NOTE 23
A1: - 0 -
G2: NOTE 23 SYSTEME NORMAL
A3: Dénomination sociale de l'entité : | C3: ='NOTE 21'!C3 -> 0
A4: Adresse : | B4: ='NOTE 21'!B4 -> 0 | G4: Sigle usuel : | H4: ='NOTE 21'!H4 -> 0
A5: N° IFU : | C5: ='NOTE 21'!C5 -> 0 | E5: Exercice clos le : | F5: ='NOTE 21'!F5 -> 0 | G5: Durée (en mois) : | H5: ='NOTE 21'!H5 -> 0
A6: N° de télédéclarant (NES): | C6: ='NOTE 21'!C6 -> 0
A7: NOTE 23 : TRANSPORTS
A8: Libellés | F8: Année N | G8: Année N-1 | H8: Variation en %
A9: Transports sur ventes | H9: =IF(G9,(F9-G9)/G9,IF(ISBLANK(G9),"",IF(F9,IF( F9 > 0,1,-1),"")))
A10: Transports pour le compte de tiers | H10: =IF(G10,(F10-G10)/G10,IF(ISBLANK(G10),"",IF(F10,IF( F10 > 0,1,-1),"")))
A11: Transport du personnel | H11: =IF(G11,(F11-G11)/G11,IF(ISBLANK(G11),"",IF(F11,IF( F11 > 0,1,-1),"")))
A12: Transports de plis | H12: =IF(G12,(F12-G12)/G12,IF(ISBLANK(G12),"",IF(F12,IF( F12 > 0,1,-1),"")))
A13: Voyage déplacement (transport) | H13: =IF(G13,(F13-G13)/G13,IF(ISBLANK(G13),"",IF(F13,IF( F13 > 0,1,-1),"")))
A14: Transport entre établissements ou chantiers | H14: =IF(G14,(F14-G14)/G14,IF(ISBLANK(G14),"",IF(F14,IF( F14 > 0,1,-1),"")))
A15: Transports administratifs | H15: =IF(G15,(F15-G15)/G15,IF(ISBLANK(G15),"",IF(F15,IF( F15 > 0,1,-1),"")))
A16: TOTAL | F16: =SUM(F9:F15) -> 0 | G16: =SUM(G9:G15) -> 0 | H16: =IF(G16,(F16-G16)/G16,IF(ISBLANK(G16),"",IF(F16,IF( F16 > 0,1,-1),"")))
A17: Commentaire :
A18: ● Commenter toute variation significative.

Sheet NOTE 24
A1: - 0 -
G2: NOTE 24 SYSTEME NORMAL
A3: Dénomination sociale de l'entité : | C3: ='NOTE 21'!C3 -> 0
A4: Adresse : | B4: ='NOTE 21'!B4 -> 0 | G4: Sigle usuel : | H4: ='NOTE 21'!H4 -> 0
A5: N° IFU : | C5: ='NOTE 21'!C5 -> 0 | E5: Exercice clos le : | F5: ='NOTE 21'!F5 -> 0 | G5: Durée (en mois) : | H5: ='NOTE 21'!H5 -> 0
A6: N° de télédéclarant (NES): | C6: ='NOTE 21'!C6 -> 0
A7: NOTE 24 : SERVICES EXTERIEURS
A8: Libellés | F8: Année N | G8: Année N-1 | H8: Variation en %
A9: Sous-traitance générale | H9: =IF(G9,(F9-G9)/G9,IF(ISBLANK(G9),"",IF(F9,IF( F9 > 0,1,-1),"")))
A10: Locations et charges locatives | H10: =IF(G10,(F10-G10)/G10,IF(ISBLANK(G10),"",IF(F10,IF( F10 > 0,1,-1),"")))
A11: Redevances de location acquisition | H11: =IF(G11,(F11-G11)/G11,IF(ISBLANK(G11),"",IF(F11,IF( F11 > 0,1,-1),"")))
A12: Entretien, réparations et maintenance | H12: =IF(G12,(F12-G12)/G12,IF(ISBLANK(G12),"",IF(F12,IF( F12 > 0,1,-1),"")))
A13: Primes d'assurance | H13: =IF(G13,(F13-G13)/G13,IF(ISBLANK(G13),"",IF(F13,IF( F13 > 0,1,-1),"")))
A14: Etudes, recherches et documentation | H14: =IF(G14,(F14-G14)/G14,IF(ISBLANK(G14),"",IF(F14,IF( F14 > 0,1,-1),"")))
A15: Publicité, publications, relations publiques | H15: =IF(G15,(F15-G15)/G15,IF(ISBLANK(G15),"",IF(F15,IF( F15 > 0,1,-1),"")))
A16: Frais de télécommunications | H16: =IF(G16,(F16-G16)/G16,IF(ISBLANK(G16),"",IF(F16,IF( F16 > 0,1,-1),"")))
A17: Frais bancaires | H17: =IF(G17,(F17-G17)/G17,IF(ISBLANK(G17),"",IF(F17,IF( F17 > 0,1,-1),"")))
A18: Rémunérations d'intermédiaires et de conseils | H18: =IF(G18,(F18-G18)/G18,IF(ISBLANK(G18),"",IF(F18,IF( F18 > 0,1,-1),"")))
A19: Frais de formation du personnel | H19: =IF(G19,(F19-G19)/G19,IF(ISBLANK(G19),"",IF(F19,IF( F19 > 0,1,-1),"")))
A20: Redevances pour brevets, licences, logiciels, concession et droits similaires | H20: =IF(G20,(F20-G20)/G20,IF(ISBLANK(G20),"",IF(F20,IF( F20 > 0,1,-1),"")))
A21: Cotisations | H21: =IF(G21,(F21-G21)/G21,IF(ISBLANK(G21),"",IF(F21,IF( F21 > 0,1,-1),"")))
A22: Rémunérations de personnel extérieur à l'entité
A23: Autres charges externes | H23: =IF(G23,(F23-G23)/G23,IF(ISBLANK(G23),"",IF(F23,IF( F23 > 0,1,-1),"")))
A24: TOTAL | F24: =SUM(F9:F23) -> 0 | G24: =SUM(G9:G23) -> 0 | H24: =IF(G24,(F24-G24)/G24,IF(ISBLANK(G24),"",IF(F24,IF( F24 > 0,1,-1),"")))
A25: Commentaire :
A26: ● Commenter toute variation significative.

Sheet NOTE 25
A1: - 0 -
G2: NOTE 25 SYSTEME NORMAL
A3: Dénomination sociale de l'entité : | C3: ='NOTE 21'!C3 -> 0
A4: Adresse : | B4: ='NOTE 21'!B4 -> 0 | G4: Sigle usuel : | H4: ='NOTE 21'!H4 -> 0
A5: N° IFU : | C5: ='NOTE 21'!C5 -> 0 | E5: Exercice clos le : | F5: ='NOTE 21'!F5 -> 0 | G5: Durée (en mois) : | H5: ='NOTE 21'!H5 -> 0
A6: N° de télédéclarant (NES): | C6: ='NOTE 21'!C6 -> 0
A7: NOTE 25 : IMPOTS ET TAXES
A8: Libellés | F8: Année N | G8: Année N-1 | H8: Variation en %
A9: Impôts et taxes directs | H9: =IF(G9,(F9-G9)/G9,IF(ISBLANK(G9),"",IF(F9,IF( F9 > 0,1,-1),"")))
A10: Impôts et taxes indirects | H10: =IF(G10,(F10-G10)/G10,IF(ISBLANK(G10),"",IF(F10,IF( F10 > 0,1,-1),"")))
A11: Droits d'enregistrement | H11: =IF(G11,(F11-G11)/G11,IF(ISBLANK(G11),"",IF(F11,IF( F11 > 0,1,-1),"")))
A12: Pénalités et amendes fiscales | H12: =IF(G12,(F12-G12)/G12,IF(ISBLANK(G12),"",IF(F12,IF( F12 > 0,1,-1),"")))
A13: Autres impôts et taxes | H13: =IF(G13,(F13-G13)/G13,IF(ISBLANK(G13),"",IF(F13,IF( F13 > 0,1,-1),"")))
A14: TOTAL | F14: =SUM(F9:F13) -> 0 | G14: =SUM(G9:G13) -> 0 | H14: =IF(G14,(F14-G14)/G14,IF(ISBLANK(G14),"",IF(F14,IF( F14 > 0,1,-1),"")))
A15: Commentaire:
A16: ● Commenter toute variation significative.
A17: ● Détailler les pénalités et amendes et indiquer la cause.

Sheet NOTE 26
A1: - 0 -
G2: NOTE 26 SYSTEME NORMAL
A3: Dénomination sociale de l'entité : | C3: ='NOTE 21'!C3 -> 0
A4: Adresse : | B4: ='NOTE 21'!B4 -> 0 | G4: Sigle usuel : | H4: ='NOTE 21'!H4 -> 0
A5: N° IFU : | C5: ='NOTE 21'!C5 -> 0 | E5: Exercice clos le : | F5: ='NOTE 21'!F5 -> 0 | G5: Durée (en mois) : | H5: ='NOTE 21'!H5 -> 0
A6: N° de télédéclarant (NES): | C6: ='NOTE 21'!C6 -> 0
A7: NOTE 26 : AUTRES CHARGES
A8: Libellés | F8: Année N | G8: Année N-1 | H8: Variation en %
A9: Pertes sur créances clients | H9: =IF(G9,(F9-G9)/G9,IF(ISBLANK(G9),"",IF(F9,IF( F9 > 0,1,-1),"")))
A10: Pertes sur autres débiteurs | H10: =IF(G10,(F10-G10)/G10,IF(ISBLANK(G10),"",IF(F10,IF( F10 > 0,1,-1),"")))
A11: Quote-part de résultat sur opérations faites en commun | H11: =IF(G11,(F11-G11)/G11,IF(ISBLANK(G11),"",IF(F11,IF( F11 > 0,1,-1),"")))
A12: Valeur comptable des cessions courantes d'immobilisations | H12: =IF(G12,(F12-G12)/G12,IF(ISBLANK(G12),"",IF(F12,IF( F12 > 0,1,-1),"")))
A13: Perte de change sur créances et dettes commerciales | H13: =IF(G13,(F13-G13)/G13,IF(ISBLANK(G13),"",IF(F13,IF( F13 > 0,1,-1),"")))
A14: Pénalités et amendes pénales | H14: =IF(G14,(F14-G14)/G14,IF(ISBLANK(G14),"",IF(F14,IF( F14 > 0,1,-1),"")))
A15: Indemnités de fonction et autres rémunérations d'administrateurs | H15: =IF(G15,(F15-G15)/G15,IF(ISBLANK(G15),"",IF(F15,IF( F15 > 0,1,-1),"")))
A16: Dons et mécénat | H16: =IF(G16,(F16-G16)/G16,IF(ISBLANK(G16),"",IF(F16,IF( F16 > 0,1,-1),"")))
A17: Autres charges diverses | H17: =IF(G17,(F17-G17)/G17,IF(ISBLANK(G17),"",IF(F17,IF( F17 > 0,1,-1),"")))
A18: Charges pour dépréciations et provisions pour risques à court terme d'exploitation (voir note 28) | H18: =IF(G18,(F18-G18)/G18,IF(ISBLANK(G18),"",IF(F18,IF( F18 > 0,1,-1),"")))
A19: TOTAL | F19: =SUM(F9:F18) -> 0 | G19: =SUM(G9:G18) -> 0 | H19: =IF(G19,(F19-G19)/G19,IF(ISBLANK(G19),"",IF(F19,IF( F19 > 0,1,-1),"")))
A20: Commentaire :
A21: ● Commenter toute variation significative.
A22: ● Indiquer la date du PV de l'AGO ou du CA qui fixe les rémunérations des administrateurs.
A23: ● Indiquer les organismes bénéficiaires des dons.

Sheet NOTE 27A
A1: - 0 -
G2: NOTE 27A SYSTEME NORMAL
A3: Dénomination sociale de l'entité : | C3: ='NOTE 20'!C3 -> 0
A4: Adresse : | B4: ='NOTE 21'!B4 -> 0 | G4: Sigle usuel : | H4: ='NOTE 21'!H4 -> 0
A5: N° IFU : | C5: ='NOTE 21'!C5 -> 0 | E5: Exercice clos le : | F5: ='NOTE 21'!F5 -> 0 | G5: Durée (en mois) : | H5: ='NOTE 21'!H5 -> 0
A6: N° de télédéclarant (NES): | C6: ='NOTE 21'!C6 -> 0
A7: NOTE 27A : CHARGES DE PERSONNEL
A8: Libellés | F8: Année N | G8: Année N-1 | H8: Variation en %
A9: Rémunérations directes versées au personnel national | H9: =IF(G9,(F9-G9)/G9,IF(ISBLANK(G9),"",IF(F9,IF( F9 > 0,1,-1),"")))
A10: Rémunérations directes versées au personnel non national | H10: =IF(G10,(F10-G10)/G10,IF(ISBLANK(G10),"",IF(F10,IF( F10 > 0,1,-1),"")))
A11: Indemnités forfaitaires versées au personnel | H11: =IF(G11,(F11-G11)/G11,IF(ISBLANK(G11),"",IF(F11,IF( F11 > 0,1,-1),"")))
A12: Charges de sécurité sociale (personnel national) | H12: =IF(G12,(F12-G12)/G12,IF(ISBLANK(G12),"",IF(F12,IF( F12 > 0,1,-1),"")))
A13: Charges de sécurité sociale (personnel non national) | H13: =IF(G13,(F13-G13)/G13,IF(ISBLANK(G13),"",IF(F13,IF( F13 > 0,1,-1),"")))
A14: Rémunérations et charges sociales de l'exploitant individuel | H14: =IF(G14,(F14-G14)/G14,IF(ISBLANK(G14),"",IF(F14,IF( F14 > 0,1,-1),"")))
A15: Rémunération transférée de personnel extérieur | H15: =IF(G15,(F15-G15)/G15,IF(ISBLANK(G15),"",IF(F15,IF( F15 > 0,1,-1),"")))
A16: Autres charges sociales | H16: =IF(G16,(F16-G16)/G16,IF(ISBLANK(G16),"",IF(F16,IF( F16 > 0,1,-1),"")))
A17: TOTAL | F17: =SUM(F9:F16) -> 0 | G17: =SUM(G9:G16) -> 0 | H17: =IF(G17,(F17-G17)/G17,IF(ISBLANK(G17),"",IF(F17,IF( F17 > 0,1,-1),"")))
A18: Commentaire :
A19: ● Commenter toute variation significative.
A20: ● Indiquer la nature et la durée du contrat du personnel extérieur.

Sheet NOTE 27B
A1: - 0 -
R2: NOTE 27B SYSTEME NORMAL
A3: Dénomination sociale de l'entité : | D3: ='NOTE 21'!C3 -> 0
A4: Adresse : | C4: ='NOTE 21'!B4 -> 0 | Q4: Sigle usuel : | R4: ='NOTE 21'!H4 -> 0
A5: N° IFU : | D5: ='NOTE 21'!C5 -> 0 | L5: Exercice clos le : | O5: ='NOTE 21'!F5 -> 0 | R5: Durée (en mois) : | S5: ='NOTE 21'!H5 -> 0
A6: N° de télédéclarant (NES): | D6: ='NOTE 21'!C6 -> 0
A7: NOTE 27B : EFFECTIFS, MASSE SALARIALE ET PERSONNEL EXTERIEUR
B8: EFFECTIF ET MASSE SALARIALE | E8: EFFECTIFS | L8: MASSE SALARIALE
E9: Nationaux | G9: Autres Etats de l'OHADA | I9: Hors OHADA | K9: TOTAL | L9: Nationaux | O9: Autres Etats de l'OHADA | Q9: Hors OHADA | S9: TOTAL
B11: QUALIFICATIONS | E11: M | F11: F | G11: M | H11: F | I11: M | J11: F | L11: M | M11: F | O11: M | P11: F | Q11: M | R11: F
A12: YA | B12: 1. Cadres supérieurs | K12: =SUM(E12:J12) -> 0 | S12: =L12+M12+O12+P12+Q12+R12 -> 0
A13: YB | B13: 2. Techniciens supérieurs et cadres moyens | K13: =SUM(E13:J13) -> 0 | S13: =L13+M13+O13+P13+Q13+R13 -> 0
A14: YC | B14: 3. Techniciens, agents de maîtrise et ouvriers qualifiés | K14: =SUM(E14:J14) -> 0 | S14: =L14+M14+O14+P14+Q14+R14 -> 0
A15: YD | B15: 4. Employés, manœuvres, ouvriers, et apprentis | K15: =SUM(E15:J15) -> 0 | S15: =L15+M15+O15+P15+Q15+R15 -> 0
A16: YE | B16: TOTAL (1) (A) | E16: =SUM(E12:E15) -> 0 | F16: =SUM(F12:F15) -> 0 | G16: =SUM(G12:G15) -> 0 | H16: =SUM(H12:H15) -> 0 | I16: =SUM(I12:I15) -> 0 | J16: =SUM(J12:J15) -> 0 | K16: =SUM(K12:K15) -> 0 | L16: =SUM(L12:L15) -> 0 | M16: =SUM(M12:M15) -> 0 | O16: =SUM(O12:O15) -> 0 | P16: =SUM(P12:P15) -> 0 | Q16: =SUM(Q12:Q15) -> 0 | R16: =SUM(R12:R15) -> 0 | S16: =L16+M16+O16+P16+Q16+R16 -> 0
A17: YF | B17: Permanents | K17: =SUM(E17:J17) -> 0 | S17: =L17+M17+O17+P17+Q17+R17 -> 0
A18: YG | B18: Saisonniers | K18: =SUM(E18:J18) -> 0 | S18: =L18+M18+O18+P18+Q18+R18 -> 0
L20: Facturation à l'entité | S20: Note n°/référence aus autres parties des états financiers
B21: 2. Personnel extérieur
A22: YH | B22: 1. Cadres supérieurs | K22: =SUM(E22:J22) -> 0 | O22: B - Montants comptabilisés non rapportés dans l'état 301 (2)
A23: YI | B23: 2. Techniciens supérieurs et cadres moyens | K23: =SUM(E23:J23) -> 0
A24: YJ | B24: 3. Techniciens, agents de maîtrise et ouvriers qualifiés | K24: =SUM(E24:J24) -> 0 | O24: C - Montants des avantages en nature et en espèces comptabilisés en comptes decharges de personnel
A25: YK | B25: 4. Employés, manœuvres, ouvriers, et apprentis | K25: =SUM(E25:J25) -> 0 | O25: Total frais de personnel ligne RK ( A + B + C) | R25: =S16+R22+R24 -> 0
A26: YL | B26: TOTAL (2) | E26: =SUM(E22:E25) -> 0 | F26: =SUM(F22:F25) -> 0 | G26: =SUM(G22:G25) -> 0 | H26: =SUM(H22:H25) -> 0 | I26: =SUM(I22:I25) -> 0 | J26: =SUM(J22:J25) -> 0 | K26: =SUM(K22:K25) -> 0 | L26: =SUM(L22:L25) -> 0 | M26: =SUM(M22:M25) -> 0 | O26: (1): Montants indiqués dans l'état 301 hors avantages en nature et en espèces
A27: YM | B27: Permanents | K27: =SUM(E27:J27) -> 0 | O27: (2): dont provisions pour congés payés
A28: YN | B28: Saisonniers | K28: =SUM(E28:J28) -> 0 | O28: M : Masculin
A29: YO | B29: TOTAL (1 + 2) | E29: =E16+E26 -> 0 | F29: =F16+F26 -> 0 | G29: =G16+G26 -> 0 | H29: =H16+H26 -> 0 | I29: =I16+I26 -> 0 | J29: =J16+J26 -> 0 | K29: =K16+K26 -> 0 | O29: F: Féminin
A30: Commentaire:
A31: ● Faire un commentaire si nécessaire en cas de mouvement significatif du personnel

Sheet NOTE 28
A1: - 0 -
K2: NOTE 28 SYSTEME NORMAL
A3: Dénomination sociale de l'entité : | D3: ='NOTE 21'!C3 -> 0
A4: Adresse : | B4: ='NOTE 21'!B4 -> 0 | J4: Sigle usuel : | K4: ='NOTE 21'!H4 -> 0
A5: N° IFU : | C5: ='NOTE 21'!C5 -> 0 | G5: Exercice clos le : | H5: ='NOTE 21'!F5 -> 0 | J5: Durée (en mois) : | K5: ='NOTE 21'!H5 -> 0
A6: N° de télédéclarant (NES): | C6: ='NOTE 21'!C6 -> 0
A7: NOTE 28 : DOTATIONS ET CHARGES POUR PROVISIONS ET DEPRECIATIONS
A8: SITUATIONS ET MOUVEMENTS | E8: A | F8: B | I8: C | L8: D = A + B - C
E9: PROVISIONS A L'OUVERTURE DE L'EXERCICE | F9: AUGMENTATIONS : DOTATIONS | I9: DIMINUTIONS : REPRISES | L9: PROVISIONS A LA CLOTURE DE L'EXERCICE
A10: NATURE | F10: D'EXPLOITATION | G10: FINANCIERES | H10: HORS ACTIVITES ORDINAIRES | I10: D'EXPLOITATION | J10: FINANCIERES | K10: HORS ACTIVITES ORDINAIRES
A11: Provisions réglementées | L11: =E11+F11+G11+H11-I11-J11-K11 -> 0
A12: Provisions financières pour risques et charges | L12: =E12+F12+G12+H12-I12-J12-K12 -> 0
A13: Dépréciations des immobilisations | L13: =E13+F13+G13+H13-I13-J13-K13 -> 0
A14: TOTAL DOTATIONS | E14: =SUM(E11:E13) -> 0 | F14: =SUM(F11:F13) -> 0 | G14: =SUM(G11:G13) -> 0 | H14: =SUM(H11:H13) -> 0 | I14: =SUM(I11:I13) -> 0 | J14: =SUM(J11:J13) -> 0 | K14: =SUM(K11:K13) -> 0 | L14: =E14+F14+G14+H14-I14-J14-K14 -> 0
A15: Dépréciations des stocks et en cours | L15: =E15+F15+G15+H15-I15-J15-K15 -> 0
A16: Dépréciations des comptes fournisseurs | L16: =E16+F16+G16+H16-I16-J16-K16 -> 0
A17: Dépréciations des comptes clients | L17: =E17+F17+G17+H17-I17-J17-K17 -> 0
A18: Dépréciations autres créances d'exploitation | L18: =E18+F18+G18+H18-I18-J18-K18 -> 0
A19: Dépréciations des comptes de créances HAO | L19: =E19+F19+G19+H19-I19-J19-K19 -> 0
A20: Dépréciations des titres de placement | L20: =E20+F20+G20+H20-I20-J20-K20 -> 0
A21: Dépréciations des titres et valeurs à encaisser | L21: =E21+F21+G21+H21-I21-J21-K21 -> 0
A22: Dépréciations des comptes banques | L22: =E22+F22+G22+H22-I22-J22-K22 -> 0
A23: Dépréciations des comptes établissements financiers et assimilés | L23: =E23+F23+G23+H23-I23-J23-K23 -> 0
A24: Dépréciations des comptes d'instruments de trésorerie | L24: =E24+F24+G24+H24-I24-J24-K24 -> 0
A25: Provisions pour risques à court terme d'exploitation | L25: =E25+F25+G25+H25-I25-J25-K25 -> 0
A26: Provisions pour risques à court terme HAO | L26: =E26+F26+G26+H26-I26-J26-K26 -> 0
A27: Provisions pour risques à court terme à caractère financier | L27: =E27+F27+G27+H27-I27-J27-K27 -> 0
A28: TOTAL CHARGES POUR DEPRECIATIONS ET PROVISIONS A COURT TERME | E28: =SUM(E15:E27) -> 0 | F28: =SUM(F15:F27) -> 0 | G28: =SUM(G15:G27) -> 0 | H28: =SUM(H15:H27) -> 0 | I28: =SUM(I15:I27) -> 0 | J28: =SUM(J15:J27) -> 0 | K28: =SUM(K15:K27) -> 0 | L28: =E28+F28+G28+H28-I28-J28-K28 -> 0
A29: TOTAL | E29: =E14+E28 -> 0 | F29: =F14+F28 -> 0 | G29: =G14+G28 -> 0 | H29: =H14+H28 -> 0 | I29: =I14+I28 -> 0 | J29: =J14+J28 -> 0 | K29: =K14+K28 -> 0 | L29: =E29+F29+G29+H29-I29-J29-K29 -> 0
A30: Commentaire:
A31: ● Indiquer les événements et circonstances qui ont conduit à la constitution et à la reprise de la provision.

Sheet NOTE 29
A1: - 0 -
G2: NOTE 29 SYSTEME NORMAL
A3: Dénomination sociale de l'entité : | C3: ='NOTE 21'!C3 -> 0
A4: Adresse : | B4: ='NOTE 21'!B4 -> 0 | G4: Sigle usuel : | H4: ='NOTE 21'!H4 -> 0
A5: N° IFU : | C5: ='NOTE 21'!C5 -> 0 | E5: Exercice clos le : | F5: ='NOTE 21'!F5 -> 0 | G5: Durée (en mois) : | H5: ='NOTE 21'!H5 -> 0
A6: N° de télédéclarant (NES): | C6: ='NOTE 21'!C6 -> 0
A7: NOTE 29 : CHARGES ET REVENUS FINANCIERS
A8: Libellés | F8: Année N | G8: Année N-1 | H8: Variation en %
A9: Intérêts des emprunts | H9: =IF(G9,(F9-G9)/G9,IF(ISBLANK(G9),"",IF(F9,IF( F9 > 0,1,-1),"")))
A10: Intérêts dans loyers de locations acquisition | H10: =IF(G10,(F10-G10)/G10,IF(ISBLANK(G10),"",IF(F10,IF( F10 > 0,1,-1),"")))
A11: Escomptes accordés | H11: =IF(G11,(F11-G11)/G11,IF(ISBLANK(G11),"",IF(F11,IF( F11 > 0,1,-1),"")))
A12: Autres intérêts | H12: =IF(G12,(F12-G12)/G12,IF(ISBLANK(G12),"",IF(F12,IF( F12 > 0,1,-1),"")))
A13: Escomptes des effets de commerce | H13: =IF(G13,(F13-G13)/G13,IF(ISBLANK(G13),"",IF(F13,IF( F13 > 0,1,-1),"")))
A14: Pertes de change financières | H14: =IF(G14,(F14-G14)/G14,IF(ISBLANK(G14),"",IF(F14,IF( F14 > 0,1,-1),"")))
A15: Pertes sur cessions de titres de placement | H15: =IF(G15,(F15-G15)/G15,IF(ISBLANK(G15),"",IF(F15,IF( F15 > 0,1,-1),"")))
A16: Malis provenant d’attribution gratuite d’actions au personnel salarié et aux dirigeants | H16: =IF(G16,(F16-G16)/G16,IF(ISBLANK(G16),"",IF(F16,IF( F16 > 0,1,-1),"")))
A17: Pertes et charges sur risques financiers | H17: =IF(G17,(F17-G17)/G17,IF(ISBLANK(G17),"",IF(F17,IF( F17 > 0,1,-1),"")))
A18: Charges pour dépréciation et provisions à court terme à caractère financier (voir note 28) | H18: =IF(G18,(F18-G18)/G18,IF(ISBLANK(G18),"",IF(F18,IF( F18 > 0,1,-1),"")))
A19: SOUS TOTAL : FRAIS FINANCIERS (A) | F19: =SUM(F9:F18) -> 0 | G19: =SUM(G9:G18) -> 0 | H19: =IF(G19,(F19-G19)/G19,IF(ISBLANK(G19),"",IF(F19,IF( F19 > 0,1,-1),"")))
A20: Intérêts de prêts et créances diverses | H20: =IF(G20,(F20-G20)/G20,IF(ISBLANK(G20),"",IF(F20,IF( F20 > 0,1,-1),"")))
A21: Revenus de participations et autres titres immobilisés | H21: =IF(G21,(F21-G21)/G21,IF(ISBLANK(G21),"",IF(F21,IF( F21 > 0,1,-1),"")))
A22: Escomptes obtenus | H22: =IF(G22,(F22-G22)/G22,IF(ISBLANK(G22),"",IF(F22,IF( F22 > 0,1,-1),"")))
A23: Revenus de placement | H23: =IF(G23,(F23-G23)/G23,IF(ISBLANK(G23),"",IF(F23,IF( F23 > 0,1,-1),"")))
A24: Intérêts dans loyers de location-financement | H24: =IF(G24,(F24-G24)/G24,IF(ISBLANK(G24),"",IF(F24,IF( F24 > 0,1,-1),"")))
A25: Gains de change financiers | H25: =IF(G25,(F25-G25)/G25,IF(ISBLANK(G25),"",IF(F25,IF( F25 > 0,1,-1),"")))
A26: Gains sur cessions de titres de placement | H26: =IF(G26,(F26-G26)/G26,IF(ISBLANK(G26),"",IF(F26,IF( F26 > 0,1,-1),"")))
A27: Gains sur risques financiers | H27: =IF(G27,(F27-G27)/G27,IF(ISBLANK(G27),"",IF(F27,IF( F27 > 0,1,-1),"")))
A28: Reprises de charges pour dépréciation et provisions à court terme à caractère financier (voir note 28) | H28: =IF(G28,(F28-G28)/G28,IF(ISBLANK(G28),"",IF(F28,IF( F28 > 0,1,-1),"")))
A29: SOUS TOTAL : REVENUS FINANCIERS (B) | F29: =SUM(F20:F28) -> 0 | G29: =SUM(G20:G28) -> 0 | H29: =IF(G29,(F29-G29)/G29,IF(ISBLANK(G29),"",IF(F29,IF( F29 > 0,1,-1),"")))
A30: SOUS TOTAL (contrôle) : RESULTAT FINANCIER (B) - (A) | F30: =F29-F19 -> 0 | G30: =G29-G19 -> 0 | H30: =IF(G30,(F30-G30)/G30,IF(ISBLANK(G30),"",IF(F30,IF( F30 > 0,1,-1),"")))
A31: Commentaire :
A32: ● Commenter toute variation significative
A33: ● En cas de paiement à terme, indiquer :
A34: -la différence entre le total non actualisé des paiements futurs et la valeur actualisée de ces paiements si celle-ci est significative,
A35: - le taux d'actualisation
A36: ● En cas d'incorporation du coût d'emprunt, indiquer :
A37: -le montant des coûts d'emprunt incorporés dans le coût d'actifs au cours de l'exercice; et,
A38: - le taux de capitalisation utilisé pour déterminer le montant des coûts d'emprunt pouvant être incorporés dans le coût d'actifs.

Sheet NOTE 30
A1: - 0 -
G2: NOTE 30 SYSTEME NORMAL
A3: Dénomination sociale de l'entité : | C3: ='NOTE 21'!C3 -> 0
A4: Adresse : | B4: ='NOTE 21'!B4 -> 0 | G4: Sigle usuel : | H4: ='NOTE 21'!H4 -> 0
A5: N° IFU : | C5: ='NOTE 21'!C5 -> 0 | E5: Exercice clos le : | F5: ='NOTE 21'!F5 -> 0 | G5: Durée (en mois) : | H5: ='NOTE 21'!H5 -> 0
A6: N° de télédéclarant (NES): | C6: ='NOTE 21'!C6 -> 0
A7: NOTE 30 : AUTRES CHARGES ET PRODUITS HAO
A8: Libellés | F8: Année N | G8: Année N-1 | H8: Variation en %
A9: Charges HAO constatées (compte 831) à détailler (1) : | H9: =IF(G9,(F9-G9)/G9,IF(ISBLANK(G9),"",IF(F9,IF( F9 > 0,1,-1),"")))
H10: =IF(G10,(F10-G10)/G10,IF(ISBLANK(G10),"",IF(F10,IF( F10 > 0,1,-1),"")))
H11: =IF(G11,(F11-G11)/G11,IF(ISBLANK(G11),"",IF(F11,IF( F11 > 0,1,-1),"")))
H12: =IF(G12,(F12-G12)/G12,IF(ISBLANK(G12),"",IF(F12,IF( F12 > 0,1,-1),"")))
H13: =IF(G13,(F13-G13)/G13,IF(ISBLANK(G13),"",IF(F13,IF( F13 > 0,1,-1),"")))
H14: =IF(G14,(F14-G14)/G14,IF(ISBLANK(G14),"",IF(F14,IF( F14 > 0,1,-1),"")))
H15: =IF(G15,(F15-G15)/G15,IF(ISBLANK(G15),"",IF(F15,IF( F15 > 0,1,-1),"")))
A16: Charges liées aux opéations de restructuration | H16: =IF(G16,(F16-G16)/G16,IF(ISBLANK(G16),"",IF(F16,IF( F16 > 0,1,-1),"")))
A17: Pertes sur créances HAO | H17: =IF(G17,(F17-G17)/G17,IF(ISBLANK(G17),"",IF(F17,IF( F17 > 0,1,-1),"")))
A18: Dons et libéralités accordés | H18: =IF(G18,(F18-G18)/G18,IF(ISBLANK(G18),"",IF(F18,IF( F18 > 0,1,-1),"")))
A19: Abandons de créances consentis | H19: =IF(G19,(F19-G19)/G19,IF(ISBLANK(G19),"",IF(F19,IF( F19 > 0,1,-1),"")))
A20: Charges pour dépréciations et provisions pour risques à court terme HAO | H20: =IF(G20,(F20-G20)/G20,IF(ISBLANK(G20),"",IF(F20,IF( F20 > 0,1,-1),"")))
A21: Dotations hors activités ordinaires | H21: =IF(G21,(F21-G21)/G21,IF(ISBLANK(G21),"",IF(F21,IF( F21 > 0,1,-1),"")))
A22: Participation des travailleurs | H22: =IF(G22,(F22-G22)/G22,IF(ISBLANK(G22),"",IF(F22,IF( F22 > 0,1,-1),"")))
A23: SOUS TOTAL : AUTRES CHARGES HAO (ligne RP du CR) | F23: =SUM(F10:F22) -> 0 | G23: =SUM(G10:G22) -> 0 | H23: =IF(G23,(F23-G23)/G23,IF(ISBLANK(G23),"",IF(F23,IF( F23 > 0,1,-1),"")))
A24: Produits HAO constatés (compte 841) à détailler(1) : | H24: =IF(G24,(F24-G24)/G24,IF(ISBLANK(G24),"",IF(F24,IF( F24 > 0,1,-1),"")))
H25: =IF(G25,(F25-G25)/G25,IF(ISBLANK(G25),"",IF(F25,IF( F25 > 0,1,-1),"")))
H26: =IF(G26,(F26-G26)/G26,IF(ISBLANK(G26),"",IF(F26,IF( F26 > 0,1,-1),"")))
H27: =IF(G27,(F27-G27)/G27,IF(ISBLANK(G27),"",IF(F27,IF( F27 > 0,1,-1),"")))
H28: =IF(G28,(F28-G28)/G28,IF(ISBLANK(G28),"",IF(F28,IF( F28 > 0,1,-1),"")))
H29: =IF(G29,(F29-G29)/G29,IF(ISBLANK(G29),"",IF(F29,IF( F29 > 0,1,-1),"")))
H30: =IF(G30,(F30-G30)/G30,IF(ISBLANK(G30),"",IF(F30,IF( F30 > 0,1,-1),"")))
A31: Produits liés aux opéations de restructuration | H31: =IF(G31,(F31-G31)/G31,IF(ISBLANK(G31),"",IF(F31,IF( F31 > 0,1,-1),"")))
A32: Indemnités et subventions HAO (entité agricole) | H32: =IF(G32,(F32-G32)/G32,IF(ISBLANK(G32),"",IF(F32,IF( F32 > 0,1,-1),"")))
A33: Dons et libéralités obtenus | H33: =IF(G33,(F33-G33)/G33,IF(ISBLANK(G33),"",IF(F33,IF( F33 > 0,1,-1),"")))
A34: Abandons de créances obtenus | H34: =IF(G34,(F34-G34)/G34,IF(ISBLANK(G34),"",IF(F34,IF( F34 > 0,1,-1),"")))
A35: Transfert de charges H.A.O | H35: =IF(G35,(F35-G35)/G35,IF(ISBLANK(G35),"",IF(F35,IF( F35 > 0,1,-1),"")))
A36: Reprises de charges pour dépréciations et provisions pour risques à court terme HAO | H36: =IF(G36,(F36-G36)/G36,IF(ISBLANK(G36),"",IF(F36,IF( F36 > 0,1,-1),"")))
A37: Reprises des charges, provisions et dépréciations H.A.O | H37: =IF(G37,(F37-G37)/G37,IF(ISBLANK(G37),"",IF(F37,IF( F37 > 0,1,-1),"")))
A38: Subventions d'équilibre | H38: =IF(G38,(F38-G38)/G38,IF(ISBLANK(G38),"",IF(F38,IF( F38 > 0,1,-1),"")))
A39: SOUS TOTAL : AUTRES PRODUITS HAO (ligne TO du CR) | F39: =SUM(F25:F38) -> 0 | G39: =SUM(G25:G38) -> 0 | H39: =IF(G39,(F39-G39)/G39,IF(ISBLANK(G39),"",IF(F39,IF( F39 > 0,1,-1),"")))
A40: (CR): Compte de résultat
A41: Commentaire :
A42: ● Commenter toute variation significative.

Sheet NOTE 31
A1: - 0 -
J2: NOTE 31 SYSTEME NORMAL
A3: Dénomination sociale de l'entité :
A4: Adresse : | J4: Sigle usuel :
A5: N° IFU : | G5: Exercice clos le : | J5: Durée (en mois) :
A6: N° de télédéclarant (NES):
A7: NOTE 31 : REPARTITION DU RESULTAT ET AUTRES ELEMENTS CARACTERISTIQUES DES CINQ DERNIERS EXERCICES
A8: EXERCICES CONCERNES (1) | G8: N | H8: N-1 | I8: N - 2 | J8: N - 3 | K8: N - 4
A9: NATURE DES INDICATIONS
A10: STRUCTURE DU CAPITAL A LA CLOTURE DE L'EXERCICE (2) | G10: =SUM(G11:G16) -> 0 | H10: =SUM(H11:H16) -> 0 | I10: =SUM(I11:I16) -> 0 | J10: =SUM(J11:J16) -> 0 | K10: =SUM(K11:K16) -> 0
A11: Capital social
A12: Actions ordinaires
A13: Actions à dividendes prioritaires (A.D.P) sans droit de vote
A14: Actions nouvelles à émettre :
A15: - par conversion d'obligations
A16: - par exercice de droits de souscription
A17: OPERATIONS ET RESULTATS DE L'EXERCICE (3) | G17: =SUM(G18:G22) -> 0 | H17: =SUM(H18:H22) -> 0 | I17: =SUM(I18:I22) -> 0 | J17: =SUM(J18:J22) -> 0 | K17: =SUM(K18:K22) -> 0
A18: Chiffre d'affaires hors taxes
A19: Résultat des activités ordinaires (R.A.O) hors dotations et reprises (exploitation et financières)
A20: Participation des travailleurs aux bénéfices
A21: Impôt sur le résultat
A22: Résultat net (4)
A23: RESULTAT ET DIVIDENDE DISTRIBUES | G23: =SUM(G24:G25) -> 0 | H23: =SUM(H24:H25) -> 0 | I23: =SUM(I24:I25) -> 0 | J23: =SUM(J24:J25) -> 0 | K23: =SUM(K24:K25) -> 0
A24: Résultat distribué (5)
A25: Dividende attribué à chaque action
A26: PERSONNEL ET POLITIQUE SALARIALE | G26: =SUM(G27:G31) -> 0 | H26: =SUM(H27:H31) -> 0 | I26: =SUM(I27:I31) -> 0 | J26: =SUM(J27:J31) -> 0 | K26: =SUM(K27:K31) -> 0
A27: Effectif moyen des travailleurs au cours de l'exercice (6)
A28: Effectif moyen de personnel extérieur
A29: Masse salariale distribuée au cours de l'exercice (7)
A30: Avantages sociaux versés au cours de l'exercice (8) [Sécurité sociale, œuvres sociales]
A31: Personnel extérieur facturé à l'entité (9)
A33: (1) Y compris l'exercice dont les états financiers sont soumis à l'approbation de l'Assemblée | G33: (6) Personnel propre
A34: (2) Indication, en cas de libération partielle du capital, du montant du capital non appelé | G34: (7) Total des comptes 661, 662, 663
A35: (3) Les éléments de cette rubrique sont ceux figurant au compte de résultat | G35: (8) Total des comptes 664, 668
A36: (4) Le résultat, lorsqu'il est négatif, doit être mis entre parenthèses | G36: (9) Compte 667
A37: (5) L'exercice N correspond au dividende proposé du dernier exercice

Sheet NOTE 32
A1: - 0 -
O2: NOTE 32 SYSTEME NORMAL
A3: Dénomination sociale de l'entité : | C3: ='NOTE 31'!C3 -> 0
A4: Adresse : | B4: ='NOTE 31'!B4 -> 0 | N4: Sigle usuel : | O4: ='NOTE 31'!K4 -> 0
A5: N° IFU : | C5: ='NOTE 31'!C5 -> 0 | H5: Exercice clos le : | J5: ='NOTE 31'!H5 -> 0 | N5: Durée (en mois) : | O5: ='NOTE 31'!K5 -> 0
A6: N° de télédéclarant (NES): | C6: ='NOTE 31'!C6 -> 0
A7: NOTE 32 : PRODUCTION DE L'EXERCICE
A8: DESIGNATION DU PRODUIT | D8: UNITE DE QUANTITE CHOISIE | E8: PRODUCTION VENDUE DANS LE PAYS | G8: PRODUCTION VENDUE DANS LES AUTRES PAYS DE L'OHADA | I8: PRODUCTION VENDUE HORS OHADA | K8: PRODUCTION IMMOBILISEE | M8: STOCK OUVERTURE DE L'EXERCICE | O8: STOCK CLOTURE DE L'EXERCICE
E10: Quantité | F10: Valeur | G10: Quantité | H10: Valeur | I10: Quantité | J10: Valeur | K10: Quantité | L10: Valeur | M10: Quantité | N10: Valeur | O10: Quantité | P10: Valeur
A29: NON VENTILE (1)
A30: TOTAL | E30: =SUM(E11:E29) -> 0 | F30: =SUM(F11:F29) -> 0 | G30: =SUM(G11:G29) -> 0 | H30: =SUM(H11:H29) -> 0 | I30: =SUM(I11:I29) -> 0 | J30: =SUM(J11:J29) -> 0 | K30: =SUM(K11:K29) -> 0 | L30: =SUM(L11:L29) -> 0 | ... P30: =SUM(P11:P29) -> 0
A31: (1) Le montant doit être inférieur ou égal à 1% du total des produits

Sheet NOTE 33
A1: - 0 -
K2: NOTE 33 SYSTEME NORMAL
A3: Dénomination sociale de l'entité : | C3: ='NOTE 31'!C3 -> 0
A4: Adresse : | B4: ='NOTE 31'!B4 -> 0 | J4: Sigle usuel : | K4: ='NOTE 31'!K4 -> 0
A5: N° IFU : | C5: ='NOTE 31'!C5 -> 0 | E5: Exercice clos le : | G5: ='NOTE 31'!H5 -> 0 | I5: Durée (en mois) : | K5: ='NOTE 31'!K5 -> 0
A6: N° de télédéclarant (NES): | C6: ='NOTE 31'!C6 -> 0
A7: NOTE 33 : ACHATS DESTINES A LA PRODUCTION
A8: DESIGNATION DES MATIERES ET PRODUITS | E8: UNITE DE QUANTITE CHOISIE | F8: ACHATS EFFECTUES AU COURS DE L'EXERCICE | L8: VARIATION DES STOCKS (en valeur)
F9: PRODUITS DE L'ETAT | H9: PRODUITS IMPORTES
H10: ACHETES DANS L'ETAT | J10: ACHETES HORS DE L'ETAT
F11: Quantité | G11: Valeur | H11: Quantité | I11: Valeur | J11: Quantité | K11: Valeur
A30: NON VENTILES (1)
A31: TOTAL | F31: =SUM(F12:F30) -> 0 | G31: =SUM(G12:G30) -> 0 | H31: =SUM(H12:H30) -> 0 | I31: =SUM(I12:I30) -> 0 | J31: =SUM(J12:J30) -> 0 | K31: =SUM(K12:K30) -> 0 | L31: =SUM(L12:L30) -> 0
A32: (1) Le montant doit être inférieur ou égal à 1% du total des achats

Sheet NOTE 34
A1: - 0 -
G2: NOTE 34 SYSTEME NORMAL
A3: Dénomination sociale de l'entité : | C3: ='NOTE 31'!C3 -> 0
A4: Adresse : | B4: ='NOTE 31'!B4 -> 0 | F4: Sigle usuel : | G4: ='NOTE 31'!K4 -> 0
A5: N° IFU : | C5: ='NOTE 31'!C5 -> 0 | E5: Exercice clos le : | F5: ='NOTE 31'!H5 -> 0 | G5: Durée (en mois) : | H5: ='NOTE 31'!K5 -> 0
A6: N° de télédéclarant (NES): | C6: ='NOTE 31'!C6 -> 0
A7: NOTE 34 : FICHE DE SYNTHESE DES PRINCIPAUX INDICATEURS FINANCIERS
A8: ( EN MILLIERS DE FRANCS) | F8: Année N | G8: Année N-1 | H8: Variation en %
A9: ANALYSE DE L'ACTIVITE
A10: SOLDES INTERMEDIAIRES DE GESTION
A11: CHIFFRE D'AFFAIRES | H11: =IF(G11,(F11-G11)/G11,IF(ISBLANK(G11),"",IF(F11,IF( F11 > 0,1,-1),"")))
A12: MARGE COMMERCIALE | H12: =IF(G12,(F12-G12)/G12,IF(ISBLANK(G12),"",IF(F12,IF( F12 > 0,1,-1),"")))
A13: VALEUR AJOUTEE | H13: =IF(G13,(F13-G13)/G13,IF(ISBLANK(G13),"",IF(F13,IF( F13 > 0,1,-1),"")))
A14: EXCEDENT BRUT D'EXPLOITATION (EBE) | H14: =IF(G14,(F14-G14)/G14,IF(ISBLANK(G14),"",IF(F14,IF( F14 > 0,1,-1),"")))
A15: RESULTAT D'EXPLOITATION | H15: =IF(G15,(F15-G15)/G15,IF(ISBLANK(G15),"",IF(F15,IF( F15 > 0,1,-1),"")))
A16: RESULTAT FINANCIER | H16: =IF(G16,(F16-G16)/G16,IF(ISBLANK(G16),"",IF(F16,IF( F16 > 0,1,-1),"")))
A17: RESULTAT DES ACTIVITES ORDINAIRES | H17: =IF(G17,(F17-G17)/G17,IF(ISBLANK(G17),"",IF(F17,IF( F17 > 0,1,-1),"")))
A18: RESULTAT HORS ACTIVITES ORDINAIRES | H18: =IF(G18,(F18-G18)/G18,IF(ISBLANK(G18),"",IF(F18,IF( F18 > 0,1,-1),"")))
A19: RESULTAT NET | H19: =IF(G19,(F19-G19)/G19,IF(ISBLANK(G19),"",IF(F19,IF( F19 > 0,1,-1),"")))
A20: DETERMINATION DE LA CAPACITE D'AUTOFINANCEMENT
A21: Excédent brut d'exploitation (EBE) | F21: =F14 -> 0 | G21: =G14 -> 0
A22: + Valeurs comptables des cessions courantes d’immobilisation (compte 654)
A23: - Produits des cessions courantes d’immobilisation (compte 754)
A24: = CAPACITE D'AUTOFINANCEMENT D'EXPLOITATION | F24: =F21+F22-F23 -> 0 | G24: =G21+G22-G23 -> 0 | H24: =IF(G24,(F24-G24)/G24,IF(ISBLANK(G24),"",IF(F24,IF( F24 > 0,1,-1),"")))
A25: + Revenus financiers
A26: + Gains de change financiers
A27: + Transferts de charges financières
A28: + Produits HAO
A29: + Transferts de charges HAO
A30: - Frais financiers
A31: - Pertes de change financières
A32: - Charges HAO
A33: - Participations
A34: - Impôts sur les résultats
A35: = CAPACITE D'AUTOFINANCEMENT GLOBALE (C.A.F.G.) | F35: =SUM(F24:F34) -> 0 | G35: =SUM(G24:G34) -> 0 | H35: =IF(G35,(F35-G35)/G35,IF(ISBLANK(G35),"",IF(F35,IF( F35 > 0,1,-1),"")))
A36: - Distributions de dividendes opérées durant l'exercice | H36: =IF(G36,(F36-G36)/G36,IF(ISBLANK(G36),"",IF(F36,IF( F36 > 0,1,-1),"")))
A37: = AUTOFINANCEMENT | F37: =F35+F36 -> 0 | G37: =G35+G36 -> 0 | H37: =IF(G37,(F37-G37)/G37,IF(ISBLANK(G37),"",IF(F37,IF( F37 > 0,1,-1),"")))
A38: ANALYSE DE LA RENTABILITE
A39: Rentabilité économique = Résultat d’exploitation (a)/Capitaux propres + dettes financières | H39: =TEXT(100*(F39-G39),"0") & " points" -> 0 points
A40: Rentabilité financière = Résultat net/Capitaux propres | H40: =TEXT(100*(F40-G40),"0") & " points" -> 0 points
A41: ANALYSE DE LA STRUCTURE FINANCIERE
A42: + Capitaux propres et ressources assimilées | H42: =IF(G42,(F42-G42)/G42,IF(ISBLANK(G42),"",IF(F42,IF( F42 > 0,1,-1),"")))
A43: + Dettes financières* et autres ressources assimilées (b) | H43: =IF(G43,(F43-G43)/G43,IF(ISBLANK(G43),"",IF(F43,IF( F43 > 0,1,-1),"")))
A44: = ressources stables | F44: =F42+F43 -> 0 | G44: =G42+G43 -> 0 | H44: =IF(G44,(F44-G44)/G44,IF(ISBLANK(G44),"",IF(F44,IF( F44 > 0,1,-1),"")))
A45: - Actif immobilisé (b) | H45: =IF(G45,(F45-G45)/G45,IF(ISBLANK(G45),"",IF(F45,IF( F45 > 0,1,-1),"")))
A46: = FONDS DE ROULEMENT (1) | F46: =F44+F45 -> 0 | G46: =G44+G45 -> 0 | H46: =IF(G46,(F46-G46)/G46,IF(ISBLANK(G46),"",IF(F46,IF( F46 > 0,1,-1),"")))
A47: + Actif circulant d'exploitation (b) | H47: =IF(G47,(F47-G47)/G47,IF(ISBLANK(G47),"",IF(F47,IF( F47 > 0,1,-1),"")))
A48: - Passif circulant d'exploitation (b) | H48: =IF(G48,(F48-G48)/G48,IF(ISBLANK(G48),"",IF(F48,IF( F48 > 0,1,-1),"")))
A49: = BESOIN DE FINANCEMENT D'EXPLOITATION (2) | F49: =F47+F48 -> 0 | G49: =G47+G48 -> 0 | H49: =IF(G49,(F49-G49)/G49,IF(ISBLANK(G49),"",IF(F49,IF( F49 > 0,1,-1),"")))
A50: + Actif circulant HAO (b) | H50: =IF(G50,(F50-G50)/G50,IF(ISBLANK(G50),"",IF(F50,IF( F50 > 0,1,-1),"")))
A51: - Passif circulant HAO (b) | H51: =IF(G51,(F51-G51)/G51,IF(ISBLANK(G51),"",IF(F51,IF( F51 > 0,1,-1),"")))
A52: = BESOIN DE FINANCEMENT HAO (3) | F52: =F50+F51 -> 0 | G52: =G50+G51 -> 0 | H52: =IF(G52,(F52-G52)/G52,IF(ISBLANK(G52),"",IF(F52,IF( F52 > 0,1,-1),"")))
A53: BESOIN DE FINANCEMENT GLOBAL (4) = (2) + (3) | F53: =F49+F52 -> 0 | G53: =G49+G52 -> 0 | H53: =IF(G53,(F53-G53)/G53,IF(ISBLANK(G53),"",IF(F53,IF( F53 > 0,1,-1),"")))
A54: TRESORERIE NETTE (5) = (1) - (4) | F54: =F46-F53 -> 0 | G54: =G46-G53 -> 0 | H54: =IF(G54,(F54-G54)/G54,IF(ISBLANK(G54),"",IF(F54,IF( F54 > 0,1,-1),"")))
A55: CONTRÔLE : TRESORERIE NETTE = (TRESORERIE - ACTIF) - (TRESORERIE - PASSIF) | H55: =IF(G55,(F55-G55)/G55,IF(ISBLANK(G55),"",IF(F55,IF( F55 > 0,1,-1),"")))
A56: ANALYSE DE LA VARIATION DE LA TRESORERIE
A57: + Flux de trésorerie des activités opérationnelles | H57: =IF(G57,(F57-G57)/G57,IF(ISBLANK(G57),"",IF(F57,IF( F57 > 0,1,-1),"")))
A58: - Flux de trésorerie des activités d'investissement | H58: =IF(G58,(F58-G58)/G58,IF(ISBLANK(G58),"",IF(F58,IF( F58 > 0,1,-1),"")))
A59: + Flux de trésorerie des activités de financement | H59: =IF(G59,(F59-G59)/G59,IF(ISBLANK(G59),"",IF(F59,IF( F59 > 0,1,-1),"")))
A60: = VARIATION de LA TRESORERIE NETTE de LA PERIODE | F60: =F57+F58+F59 -> 0 | G60: =G57+G58+G59 -> 0 | H60: =IF(G60,(F60-G60)/G60,IF(ISBLANK(G60),"",IF(F60,IF( F60 > 0,1,-1),"")))
A61: ANALYSE DE LA VARIATION DE L’ENDETTEMENT FINANCIER NET
A62: Endettement financier brut (Dettes financières* + Trésorerie – passif) | H62: =IF(G62,(F62-G62)/G62,IF(ISBLANK(G62),"",IF(F62,IF( F62 > 0,1,-1),"")))
A63: - Trésorerie - actif | H63: =IF(G63,(F63-G63)/G63,IF(ISBLANK(G63),"",IF(F63,IF( F63 > 0,1,-1),"")))
A64: = ENDETTEMENT FINANCIER NET | F64: =F62+F63 -> 0 | G64: =G62+G63 -> 0 | H64: =IF(G64,(F64-G64)/G64,IF(ISBLANK(G64),"",IF(F64,IF( F64 > 0,1,-1),"")))
A65: (a) Résultat d’exploitation après impôt théorique sur le bénéfice. (b) Les écarts de conversion doivent être éliminés afin de ramener les créances et les dettes concernées à leur valeur initiale. Dettes financières* = emprunts et dettes financières diverses + dettes de location acquisition.

Sheet NOTE 35
A1: - 0 -
H2: NOTE 35 SYSTEME NORMAL
A3: Dénomination sociale de l'entité : | C3: ='NOTE 31'!C3 -> 0
A4: Adresse : | B4: ='NOTE 31'!B4 -> 0 | H4: Sigle usuel : | I4: ='NOTE 31'!K4 -> 0
A5: N° IFU : | C5: ='NOTE 31'!C5 -> 0 | E5: Exercice clos le : | G5: ='NOTE 31'!H5 -> 0 | H5: Durée (en mois) : | I5: ='NOTE 31'!K5 -> 0
A6: N° de télédéclarant (NES): | C6: ='NOTE 31'!C6 -> 0
A7: NOTE 35 : LISTE DES INFORMATIONS SOCIALES, ENVIRONNEMENTALES ET SOCIETALES A FOURNIR
A8: Note obligatoire pour les entités ayant un effectif de plus de 250 salariés
A9: Liste des informations sociales, environnementales et sociétales à fournir
A10: INFORMATIONS SOCIALES
A11: Emplois :
A12: • l'effectif total et la répartition des salariés par sexe, âge et zone géographique ;
A13: • les embauches et les licenciements ;
A14: • les rémunérations et leur évolution.
A15: Relations sociales :
A16: • l'organisation du dialogue social ;
A17: • le bilan des accords collectifs.
A18: Santé et sécurité :
... A52: • la prise en compte dans la politique d'achat des enjeux sociaux et environnementaux.

Sheet NOTE 37
A1: - 0 -
H2: NOTE 37 SYSTEME NORMAL
A3: Dénomination sociale de l'entité : | C3: ='NOTE 31'!C3 -> 0
A4: Adresse : | B4: ='NOTE 31'!B4 -> 0 | H4: Sigle usuel : | I4: ='NOTE 31'!K4 -> 0
A5: N° IFU : | C5: ='NOTE 31'!C5 -> 0 | E5: Exercice clos le : | F5: ='NOTE 31'!H5 -> 0 | H5: Durée (en mois) : | I5: ='NOTE 31'!K5 -> 0
A6: N° de télédéclarant (NES): | C6: ='NOTE 31'!C6 -> 0
A7: NOTE 37 : EVENEMENTS POSTERIEURS A LA CLOTURE DE L'EXERCICE
A8: Date d'arrêté des états financiers :
A10: Organe ayant autorisé la publication des comptes :
A12: A - EVENEMENTS POSTERIEURS A LA DATE DE CLOTURE DONNANT LIEU A DES AJUSTEMENTS DES ETATS FINANCIERS
A14: Commentaire :
A16: Indiquer la nature des événements postérieurs à la date de clôture donnant lieu à des ajustements des états financiers.
A17: Pour chaque événement, donnez des précisions sur les comptes qui ont fait l'objet d'un ajustement.
A19: B - EVENEMENTS POSTERIEURS A LA DATE DE CLOTURE NE DONNANT LIEU A DES AJUSTEMENTS DES ETATS FINANCIERS
A21: Commentaire :
A23: Procéder à une estimation de l'impact financier de chaque événement ou l'indication que cette estimation ne peut être fournie.
A25: C - EVENEMENTS REMETTANT EN CAUSE L'HYPOTHESE DE BASE DE CONTINUITE D'EXPLOITATION
A27: Commentaire :
... A30: Donner des précisions sur les valeurs liquidatives retenues

Sheet NOTE 38
A1: - 0 -
H2: NOTE 38 SYSTEME NORMAL
A3: Dénomination sociale de l'entité : | C3: ='NOTE 31'!C3 -> 0
A4: Adresse : | B4: ='NOTE 31'!B4 -> 0 | H4: Sigle usuel : | I4: ='NOTE 31'!K4 -> 0
A5: N° IFU : | C5: ='NOTE 31'!C5 -> 0 | E5: Exercice clos le : | F5: ='NOTE 31'!H5 -> 0 | H5: Durée (en mois) : | I5: ='NOTE 31'!K5 -> 0
A6: N° de télédéclarant (NES): | C6: ='NOTE 31'!C6 -> 0
A7: NOTE 38 : CHANGEMENTS DE METHODES COMPTABLES, D'ESTIMATIONS ET CORRECTIONS D'ERREURS
A9: A – CHANGEMENTS DE METHODES COMPTABLES
A11: 1. Changement de réglementation comptable
A12: Commentaire :
A13: • l’entité doit indiquer l’impact du changement de réglementation comptable (par exemple lors du passage
A14: au SYSCOHADA révisé) déterminé à l’ouverture en précisant les postes concernés ;
A16: • l’entité doit présenter les principaux postes des exercices antérieurs présentés, retraités selon la
A17: nouvelle méthode en cas de changement de réglementation comptable appliqué de manière rétrospective,
A19: • l’entité doit indiquer l’impact du changement sur les principaux postes concernés de l’exercice en cas
A20: de changement de réglementation comptable appliqué de manière prospective.
A22: 2. Changement de méthode à l’initiative de l’entité
A23: Commentaire :
... A46: d’un exercice antérieur.

Sheet PAGE GARDE COMMENTAIRES
E26: NOTE 39 : COMMENTAIRES

Sheet NOTE 39 COMMENTAIRES
A1: NOTE 39 | D1: TABLE DES COMMENTAIRES | G1: COMMENTAIRES PAGE 1/9
A2: Dénomination sociale de l'entité :
A3: Adresse : | F3: Sigle usuel :
A4: N° IFU : | E4: Exercice clos le : | G4: Durée (en mois) :
A5: N° de télédéclarant (NES):
A6: NOTE 1 | B6: DETTES GARANTIES PAR DES SURETES REELLES
A8: NOTE 3A | B8: IMMOBILISATIONS (BRUTES)
A10: NOTE 3B | B10: BIENS PRIS EN LOCATION-ACQUISITION
A12: NOTE 3C | B12: IMMOBILISATIONS (AMORTISSEMENTS)
A14: NOTE 3D | B14: IMMOBILISATIONS (PLUS-VALUES ET MOINS- VALUES DE CESSION)
A16: TABLE DES COMMENTAIRES | G16: COMMENTAIRES PAGE 2/9
A17: Dénomination sociale de l'entité : | C17: =C2 -> 0
A18: Adresse : | B18: =B3 -> 0 | F18: Sigle usuel : | G18: =G3 -> 0
A19: N° IFU : | C19: =C4 -> 0 | E19: Exercice clos le : | F19: =F4 -> 0 | G19: Durée (en mois) : | H19: =H4 -> 0
A20: N° de télédéclarant (NES): | C20: =C5 -> 0
A21: NOTE 4 | B21: IMMOBILISATIONS FINANCIERES
A23: NOTE 5 | B23: ACTIF CIRCULANT ET DETTES CIRCULANTES HAO
A24: ACTIF CIRCULANT HAO
A26: DETTES CIRCULANTES HAO
A28: NOTE 6 | B28: STOCKS ET EN COURS (1)
A30: NOTE 7 | B30: CLIENTS
A32: TABLE DES COMMENTAIRES | G32: COMMENTAIRES PAGE 3/9
A33: Dénomination sociale de l'entité : | C33: =C17 -> 0
A34: Adresse : | B34: =B18 -> 0 | F34: Sigle usuel : | G34: =G18 -> 0
A35: N° IFU : | C35: =C19 -> 0 | E35: Exercice clos le : | F35: =F19 -> 0 | G35: Durée (en mois) : | H35: =H19 -> 0
A36: N° de télédéclarant (NES): | C36: =C20 -> 0
A37: NOTE 8 | B37: AUTRES CREANCES
A39: NOTE 9 | B39: TITRES DE PLACEMENT
A41: NOTE 10 | B41: VALEURS A ENCAISSER
A43: NOTE 11 | B43: DISPONIBILITES
A45: TABLE DES COMMENTAIRES | G45: COMMENTAIRES PAGE 4/9
A46: Dénomination sociale de l'entité : | C46: =C33 -> 0
A47: Adresse : | B47: =B34 -> 0 | F47: Sigle usuel : | G47: =G34 -> 0
A48: N° de compte contribuable (NCC) : | C48: =C35 -> 0 | E48: Exercice clos le : | F48: =F35 -> 0 | G48: Durée (en mois) : | H48: =H35 -> 0
A49: N° de télédéclarant (NTD) : | C49: =C36 -> 0
A50: NOTE 12 | B50: ECARTS DE CONVERSION ET TRANSFERTS DE CHARGES
A51: ECARTS DE CONVERSION
A53: TRANSFERTS DE CHARGES
A55: NOTE 13 | B55: CAPITAL
A57: NOTE 14 | B57: PRIMES ET RESERVES
A59: NOTE 15A | B59: TOTAL SUBVENTIONS D'INVESTISSEMENT ET PROVISIONS REGLEMENTEES
A61: TABLE DES COMMENTAIRES | G61: COMMENTAIRES PAGE 5/9
A62: Dénomination sociale de l'entité : | C62: =C46 -> 0
A63: Adresse : | B63: =B47 -> 0 | F63: Sigle usuel : | G63: =G47 -> 0
A64: N° IFU : | C64: =C48 -> 0 | E64: Exercice clos le : | F64: =F48 -> 0 | G64: Durée (en mois) : | H64: =H48 -> 0
A65: N° de télédéclarant (NES): | C65: =C49 -> 0
A66: NOTE 15B | B66: AUTRES FONDS PROPRES
A68: NOTE 16A | B68: DETTES FINANCIERES ET RESSOURCES ASSIMILEES
A70: NOTE 16B | B70: ENGAGEMENTS DE RETRAITE ET AVANTAGES ASSIMILES : PARTIE 1 (METHODE ACTUARIELLE)
A71: HYPOTHESES ACTUARIELLES
A73: VARIATION DE LA VALEUR DE L'ENGAGEM ENT DE RETRAITE AU COURS DE L'EXERCICE
A75: ANALYSE DE SENSIBILITE DES HY POTHESES ACTUA R IELLES
A77: TABLE DES COMMENTAIRES | G77: COMMENTAIRES PAGE 6/9
A78: Dénomination sociale de l'entité : | C78: =C62 -> 0
A79: Adresse : | B79: =B63 -> 0 | F79: Sigle usuel : | G79: =G63 -> 0
A80: N° IFU : | C80: =C64 -> 0 | E80: Exercice clos le : | F80: =F64 -> 0 | G80: Durée (en mois) : | H80: =H64 -> 0
A81: N° de télédéclarant (NES): | C81: =C65 -> 0
A82: NOTE 16B bis | B82: ENGAGEMENTS DE RETRAITE ET AVANTAGES ASSIMILES : PARTIE 2 (METHODE ACTUARIELLE)
A83: ACTIF/PASSIF NET COMPTABILISE AU TITRE DES REGIMES FINANCES
A85: VALEUR ACTUELLE DES ACTI FS DU REGIME
A87: NOTE 16C | B87: ACTIFS ET PASSIFS EVENTUELS
A89: NOTE 17 | B89: FOURNISSEURS D'EXPLOITATION
A91: NOTE 18 | B91: DETTES FISCALES ET SOCIALES
A93: TABLE DES COMMENTAIRES | G93: COMMENTAIRES PAGE 7/9
A94: Dénomination sociale de l'entité : | C94: =C78 -> 0
A95: Adresse : | B95: =B79 -> 0 | F95: Sigle usuel : | G95: =G79 -> 0
A96: N° IFU : | C96: =C80 -> 0 | E96: Exercice clos le : | F96: =F80 -> 0 | G96: Durée (en mois) : | H96: =H80 -> 0
A97: N° de télédéclarant (NES): | C97: =C81 -> 0
A98: NOTE 19 | B98: AUTRES DETTES ET PROVISIONS POUR RISQUES A COURT TERME
A100: NOTE 20 | B100: BANQUES, CREDIT D'ESCOMPTE ET DE TRESORERIE
A102: NOTE 21 | B102: CHIFFRE D'AFFAIRES ET AUTRES PRODUITS
A104: NOTE 22 | B104: ACHATS
A106: NOTE 23 | B106: TRANSPORTS
A108: TABLE DES COMMENTAIRES | G108: COMMENTAIRES PAGE 8/9
A109: Dénomination sociale de l'entité : | C109: =C94 -> 0
A110: Adresse : | B110: =B95 -> 0 | F110: Sigle usuel : | G110: =G95 -> 0
A111: N° IFU : | C111: =C96 -> 0 | E111: Exercice clos le : | F111: =F96 -> 0 | G111: Durée (en mois) : | H111: =H96 -> 0
A112: N° de télédéclarant (NES): | C112: =C97 -> 0
A113: NOTE 24 | B113: SERVICES EXTERIEURS
A115: NOTE 25 | B115: IMPOTS ET TAXES
A117: NOTE 26 | B117: AUTRES CHARGES
A119: NOTE 27A | B119: CHARGES DE PERSONNEL
A121: NOTE 27B | B121: EFFECTIFS, MASSE SALARIALE ET PERSONNEL EXTERIEUR
A123: TABLE DES COMMENTAIRES | G123: COMMENTAIRES PAGE 9/9
A124: Dénomination sociale de l'entité : | C124: =C109 -> 0
A125: Adresse : | B125: =B110 -> 0 | F125: Sigle usuel : | G125: =G110 -> 0
A126: N° IFU : | C126: =C111 -> 0 | E126: Exercice clos le : | F126: =F111 -> 0 | G126: Durée (en mois) : | H126: =H111 -> 0
A127: N° de télédéclarant (NES): | C127: =C112 -> 0
A128: NOTE 28A | B128: PROVISIONS ET DEPRECIATIONS INSCRITES AU BILAN
A130: NOTE 28B | B130: DEPRECIATIONS DES IMMOBILISATIONS
A132: NOTE 28C | B132: AUTRES DEPRECIATIONS
A134: NOTE 29 | B134: CHARGES ET REVENUS FINANCIERS
A136: NOTE 30 | B136: AUTRES CHARGES ET PRODUITS HAO

Sheet GARDE (DGI)
E23: ETATS SUPPLEMENTAIRES DIRECTION GENERALE DES IMPOTS

Sheet Liste ETATS SUPPL DGI
A1: - 0 -
I2: LISTE ETATS DGI
A3: Dénomination sociale de l'entité :
A4: Adresse : | H4: Sigle usuel :
A5: N° IFU : | E5: Exercice clos le : | H5: Durée (en mois) :
A6: N° de télédéclarant (NES):
A7: FICHE RECAPITULATIVE DES ETATS SUPPLEMENTAIRES DGI PRESENTES (1)
A8: ETATS | B8: INTITULES | I8: A | J8: N/A
A9: Etat supplémentaire 1 | B9: DETAIL DES CHARGES
A10: Etat supplémentaire 2 | B10: DETAIL DES PRODUITS
A11: Etat supplémentaire 3 | B11: TVA
A12: Etat supplémentaire 4 | B12: ETAT COMPLEMENTAIRE POUR l'INSD: TVA SUPPORTEE NON DEDUCTIBLE
A13: Etat supplémentaire 5 | B13: ELEMENTS STATISTIQUES UEMOA
A14: Etat supplémentaire 6 | B14: REPARTITION DU RESULTAT FISCAL DES SOCIETES DE PERSONNES
A15: Etat supplémentaire 7 | B15: COMPLEMENT INFORMATIONS ENTITES INDIVIDUELLES
A16: Etat supplémentaire 8 | B16: TABLEAU DES IMMOBILISATIONS ET DES AMORTISSEMENTS
A17: Etat supplémentaire 9 | B17: DETAIL DES FRAIS ACCESSOIRES SUR ACHATS
A18: Etat supplémentaire 10 | B18: DETAIL DES AVANTAGES EN NATURE ALLOUES AU PERSONNEL
A19: Etat supplémentaire 11 | B19: CREANCES ET DETTES ECHUES DE L'EXERCICE
A20: Etat supplémentaire 12 | B20: ETAT ANNUEL DES SALAIRES
... A29: A INSERER AUX PAGES APPROPRIEES | B29: PAGE de garde Détermination du réultat fiscal et de l'IS
B30: PAGE de garde Détermination du réultat fiscal et de l'IBICA
B31: PAGE de garde Détermination du réultat fiscal et de l'IBNC
A34: (1) les Notes non documentées ne doivent pas être jointes aux états financiers. Leur contenu peut être amélioré par les entités
A35: (2) Bénéfice industriel ou commercial pour le calcul de l'IS ou de l'IBICA
A36: (3): Le contribuable peut insérer autant de déclarations fiscales supplémentaires qu'il le souhaite.
A37: A : Applicable N/A : Non applicable.

Sheet SUPPL1-CHARGES
A1: SYSTEME NORMAL | D1: - 2 - | H1: ETAT SUPPLEMENTAIRE N°1
A2: Dénomination sociale de l'entité : | C2: ='Liste ETATS SUPPL DGI'!C3 -> 0
A3: Adresse : | B3: ='Liste ETATS SUPPL DGI'!B4 -> 0 | I3: Sigle usuel : | J3: ='Liste ETATS SUPPL DGI'!I4 -> 0
A4: N° IFU : | C4: ='Liste ETATS SUPPL DGI'!C5 -> 0 | G4: Exercice clos le : | H4: ='Liste ETATS SUPPL DGI'!F5 -> 0 | I4: Durée (en mois) : | J4: ='Liste ETATS SUPPL DGI'!I5 -> 0
A5: N° de télédéclarant (NES): | C5: ='Liste ETATS SUPPL DGI'!C6 -> 0
A7: ETAT SUPPLEMENTAIRE DIRECTION GENERALE DES IMPOTS/COMPTABILITE NATIONALE
A9: DETAIL DES CHARGES EN FCFA | G9: Exercice N | H9: Exercice N-1 | I9: Variation N/N-1
I10: En valeur | J10: En %
A11: 6011 | B11: Achats de marchandises dans la région | I11: =G11-H11 -> 0 | J11: =IF(H11,(G11-H11)/H11,IF(ISBLANK(H11),"",IF(G11,IF( G11 > 0,1,-1),"")))
A12: 6012 | B12: Achats de marchandises hors région | I12: =G12-H12 -> 0 | J12: =IF(H12,(G12-H12)/H12,IF(ISBLANK(H12),"",IF(G12,IF( G12 > 0,1,-1),"")))
A13: 6013 | B13: Achats de marchandises aux entités du groupe dans la région | I13: =G13-H13 -> 0 | J13: =IF(H13,(G13-H13)/H13,IF(ISBLANK(H13),"",IF(G13,IF( G13 > 0,1,-1),"")))
A14: 6014 | B14: Achats de marchandises aux entités du groupe hors région | I14: =G14-H14 -> 0 | J14: =IF(H14,(G14-H14)/H14,IF(ISBLANK(H14),"",IF(G14,IF( G14 > 0,1,-1),"")))
A15: 6015 | B15: Frais sur achats | I15: =G15-H15 -> 0 | J15: =IF(H15,(G15-H15)/H15,IF(ISBLANK(H15),"",IF(G15,IF( G15 > 0,1,-1),"")))
A16: 6019 | B16: Rabais, remises et ristournes obtenus (non ventilés) | I16: =G16-H16 -> 0 | J16: =IF(H16,(G16-H16)/H16,IF(ISBLANK(H16),"",IF(G16,IF( G16 > 0,1,-1),"")))
A17: RA | C17: Achats de marchandises | G17: =SUM(G11:G16) -> 0 | H17: =SUM(H11:H16) -> 0 | I17: =G17-H17 -> 0 | J17: =IF(H17,(G17-H17)/H17,IF(ISBLANK(H17),"",IF(G17,IF( G17 > 0,1,-1),"")))
A18: 6031 | B18: Variation des stocks de marchandises | I18: =G18-H18 -> 0 | J18: =IF(H18,(G18-H18)/H18,IF(ISBLANK(H18),"",IF(G18,IF( G18 > 0,1,-1),"")))
A19: RB | C19: Variation de stocks | G19: =G18 -> 0 | H19: =H18 -> 0 | I19: =G19-H19 -> 0 | J19: =IF(H19,(G19-H19)/H19,IF(ISBLANK(H19),"",IF(G19,IF( G19 > 0,1,-1),"")))
A20: 6021 | B20: Achats de matières premières et fournitures liées dans la région | I20: =G20-H20 -> 0 | J20: =IF(H20,(G20-H20)/H20,IF(ISBLANK(H20),"",IF(G20,IF( G20 > 0,1,-1),"")))
A21: 6022 | B21: Achats de matières premières et fournitures liées hors région | I21: =G21-H21 -> 0 | J21: =IF(H21,(G21-H21)/H21,IF(ISBLANK(H21),"",IF(G21,IF( G21 > 0,1,-1),"")))
A22: 6023 | B22: Achats de matières premières et fournitures liées aux entités du groupe dans la région | I22: =G22-H22 -> 0 | J22: =IF(H22,(G22-H22)/H22,IF(ISBLANK(H22),"",IF(G22,IF( G22 > 0,1,-1),"")))
A23: 6024 | B23: Achats de matières premières et fournitures liées aux entités du groupe hors région | I23: =G23-H23 -> 0 | J23: =IF(H23,(G23-H23)/H23,IF(ISBLANK(H23),"",IF(G23,IF( G23 > 0,1,-1),"")))
A24: 6025 | B24: Frais sur achats | I24: =G24-H24 -> 0 | J24: =IF(H24,(G24-H24)/H24,IF(ISBLANK(H24),"",IF(G24,IF( G24 > 0,1,-1),"")))
A25: 6029 | B25: Rabais, remises et ristournes obtenus (non ventilés) | I25: =G25-H25 -> 0 | J25: =IF(H25,(G25-H25)/H25,IF(ISBLANK(H25),"",IF(G25,IF( G25 > 0,1,-1),"")))
A26: RC | C26: Achats de matières premières et fournitures liées | G26: =SUM(G20:G25) -> 0 | H26: =SUM(H20:H25) -> 0 | I26: =G26-H26 -> 0 | J26: =IF(H26,(G26-H26)/H26,IF(ISBLANK(H26),"",IF(G26,IF( G26 > 0,1,-1),"")))
A27: 6032 | B27: Variation des stocks de matières premières et fournitures liées | I27: =G27-H27 -> 0 | J27: =IF(H27,(G27-H27)/H27,IF(ISBLANK(H27),"",IF(G27,IF( G27 > 0,1,-1),"")))
A28: RD | C28: Variation de stocks de matières premières | G28: =G27 -> 0 | H28: =H27 -> 0 | I28: =G28-H28 -> 0 | J28: =IF(H28,(G28-H28)/H28,IF(ISBLANK(H28),"",IF(G28,IF( G28 > 0,1,-1),"")))
A29: 6041 | B29: Matières consommables | I29: =G29-H29 -> 0 | J29: =IF(H29,(G29-H29)/H29,IF(ISBLANK(H29),"",IF(G29,IF( G29 > 0,1,-1),"")))
A30: 6042 | B30: Matières combustibles | I30: =G30-H30 -> 0 | J30: =IF(H30,(G30-H30)/H30,IF(ISBLANK(H30),"",IF(G30,IF( G30 > 0,1,-1),"")))
A31: 6043 | B31: Produits d'entretien | I31: =G31-H31 -> 0 | J31: =IF(H31,(G31-H31)/H31,IF(ISBLANK(H31),"",IF(G31,IF( G31 > 0,1,-1),"")))
A32: 6044 | B32: Fournitures d'atelier et d'usine | I32: =G32-H32 -> 0 | J32: =IF(H32,(G32-H32)/H32,IF(ISBLANK(H32),"",IF(G32,IF( G32 > 0,1,-1),"")))
A33: 6045 | B33: Frais sur achats | I33: =G33-H33 -> 0 | J33: =IF(H33,(G33-H33)/H33,IF(ISBLANK(H33),"",IF(G33,IF( G33 > 0,1,-1),"")))
A34: 6046 | B34: Fournitures de magasin | I34: =G34-H34 -> 0 | J34: =IF(H34,(G34-H34)/H34,IF(ISBLANK(H34),"",IF(G34,IF( G34 > 0,1,-1),"")))
A35: 6047 | B35: Fournitures de bureau | I35: =G35-H35 -> 0 | J35: =IF(H35,(G35-H35)/H35,IF(ISBLANK(H35),"",IF(G35,IF( G35 > 0,1,-1),"")))
A36: 6049 | B36: Rabais, remises et ristournes obtenus (non ventilés) | I36: =G36-H36 -> 0 | J36: =IF(H36,(G36-H36)/H36,IF(ISBLANK(H36),"",IF(G36,IF( G36 > 0,1,-1),"")))
A37: 6051 | B37: Fournitures non stockables-Eau | I37: =G37-H37 -> 0 | J37: =IF(H37,(G37-H37)/H37,IF(ISBLANK(H37),"",IF(G37,IF( G37 > 0,1,-1),"")))
A38: 6052 | B38: Fournitures non stockables-Electricité | I38: =G38-H38 -> 0 | J38: =IF(H38,(G38-H38)/H38,IF(ISBLANK(H38),"",IF(G38,IF( G38 > 0,1,-1),"")))
A39: 6053 | B39: Fournitures non stockables-Autres énergies | I39: =G39-H39 -> 0 | J39: =IF(H39,(G39-H39)/H39,IF(ISBLANK(H39),"",IF(G39,IF( G39 > 0,1,-1),"")))
A40: 6054 | B40: Fournitures d'entretien non stockables | I40: =G40-H40 -> 0 | J40: =IF(H40,(G40-H40)/H40,IF(ISBLANK(H40),"",IF(G40,IF( G40 > 0,1,-1),"")))
... A50: 6089 | B50: Rabais, remises et ristournes obtenus (non ventilés) | I50: =G50-H50 -> 0 | J50: =IF(H50,(G50-H50)/H50,IF(ISBLANK(H50),"",IF(G50,IF( G50 > 0,1,-1),"")))
A51: RE | C51: Autres achats | G51: =SUM(G29:G50) -> 0 | H51: =SUM(H29:H50) -> 0 | I51: =G51-H51 -> 0 | J51: =IF(H51,(G51-H51)/H51,IF(ISBLANK(H51),"",IF(G51,IF( G51 > 0,1,-1),"")))
A52: 6033 | B52: Variation des stocks d'autres approvisionnements | I52: =G52-H52 -> 0 | J52: =IF(H52,(G52-H52)/H52,IF(ISBLANK(H52),"",IF(G52,IF( G52 > 0,1,-1),"")))
A53: RF | C53: Variation de stocks d'autres approvisionnements | G53: =G52 -> 0 | H53: =H52 -> 0 | I53: =G53-H53 -> 0 | J53: =IF(H53,(G53-H53)/H53,IF(ISBLANK(H53),"",IF(G53,IF( G53 > 0,1,-1),"")))
A54: 612 | B54: Transports sur ventes | I54: =G54-H54 -> 0 | J54: =IF(H54,(G54-H54)/H54,IF(ISBLANK(H54),"",IF(G54,IF( G54 > 0,1,-1),"")))
A55: 613 | B55: Transports pour le compte de tiers | I55: =G55-H55 -> 0 | J55: =IF(H55,(G55-H55)/H55,IF(ISBLANK(H55),"",IF(G55,IF( G55 > 0,1,-1),"")))
A56: 614 | B56: Transports du personnel | I56: =G56-H56 -> 0 | J56: =IF(H56,(G56-H56)/H56,IF(ISBLANK(H56),"",IF(G56,IF( G56 > 0,1,-1),"")))
A57: 616 | B57: Transports de plis | I57: =G57-H57 -> 0 | J57: =IF(H57,(G57-H57)/H57,IF(ISBLANK(H57),"",IF(G57,IF( G57 > 0,1,-1),"")))
A58: 6181 | B58: Voyages et déplacements | I58: =G58-H58 -> 0 | J58: =IF(H58,(G58-H58)/H58,IF(ISBLANK(H58),"",IF(G58,IF( G58 > 0,1,-1),"")))
A59: 6182 | B59: Transports entre établissements et chantiers | I59: =G59-H59 -> 0 | J59: =IF(H59,(G59-H59)/H59,IF(ISBLANK(H59),"",IF(G59,IF( G59 > 0,1,-1),"")))
A60: 6183 | B60: Transports administratifs | I60: =G60-H60 -> 0 | J60: =IF(H60,(G60-H60)/H60,IF(ISBLANK(H60),"",IF(G60,IF( G60 > 0,1,-1),"")))
A61: 619 | B61: Rabais, remises et ristournes obtenus (non ventilés) | I61: =G61-H61 -> 0 | J61: =IF(H61,(G61-H61)/H61,IF(ISBLANK(H61),"",IF(G61,IF( G61 > 0,1,-1),"")))
A62: RG | C62: Transports | G62: =SUM(G54:G60) -> 0 | H62: =SUM(H54:H60) -> 0 | I62: =G62-H62 -> 0 | J62: =IF(H62,(G62-H62)/H62,IF(ISBLANK(H62),"",IF(G62,IF( G62 > 0,1,-1),"")))
A63: 621 | B63: Sous-traitance générale | I63: =G63-H63 -> 0 | J63: =IF(H63,(G63-H63)/H63,IF(ISBLANK(H63),"",IF(G63,IF( G63 > 0,1,-1),"")))
A64: 6221 | B64: Location de terrains | I64: =G64-H64 -> 0 | J64: =IF(H64,(G64-H64)/H64,IF(ISBLANK(H64),"",IF(G64,IF( G64 > 0,1,-1),"")))
A65: 6222 | B65: Location de bâtiments | I65: =G65-H65 -> 0 | J65: =IF(H65,(G65-H65)/H65,IF(ISBLANK(H65),"",IF(G65,IF( G65 > 0,1,-1),"")))
A66: 6223 | B66: Location de matériels et outillages | I66: =G66-H66 -> 0 | J66: =IF(H66,(G66-H66)/H66,IF(ISBLANK(H66),"",IF(G66,IF( G66 > 0,1,-1),"")))
A67: 6224 | B67: Malis sur emballages | I67: =G67-H67 -> 0 | J67: =IF(H67,(G67-H67)/H67,IF(ISBLANK(H67),"",IF(G67,IF( G67 > 0,1,-1),"")))
A68: 6225 | B68: Locations d'emballages | I68: =G68-H68 -> 0 | J68: =IF(H68,(G68-H68)/H68,IF(ISBLANK(H68),"",IF(G68,IF( G68 > 0,1,-1),"")))
A69: 6226 | B69: Fermages et loyers du foncier | I69: =G69-H69 -> 0 | J69: =IF(H69,(G69-H69)/H69,IF(ISBLANK(H69),"",IF(G69,IF( G69 > 0,1,-1),"")))
A70: 6228 | B70: Locations et charges locatives diverses | I70: =G70-H70 -> 0 | J70: =IF(H70,(G70-H70)/H70,IF(ISBLANK(H70),"",IF(G70,IF( G70 > 0,1,-1),"")))
A71: 6232 | B71: Crédit-bail immobilier | I71: =G71-H71 -> 0 | J71: =IF(H71,(G71-H71)/H71,IF(ISBLANK(H71),"",IF(G71,IF( G71 > 0,1,-1),"")))
A72: 6233 | B72: Crédit-bail mobilier | I72: =G72-H72 -> 0 | J72: =IF(H72,(G72-H72)/H72,IF(ISBLANK(H72),"",IF(G72,IF( G72 > 0,1,-1),"")))
A73: 6234 | B73: Location-vente | I73: =G73-H73 -> 0 | J73: =IF(H73,(G73-H73)/H73,IF(ISBLANK(H73),"",IF(G73,IF( G73 > 0,1,-1),"")))
A75: SYSTEME NORMAL | D75: - 3 - | H75: ETAT SUPPLEMENTAIRE N°1
A76: Dénomination sociale de l'entité : | C76: =C2 -> 0
A77: Adresse : | B77: =B3 -> 0 | I77: Sigle usuel : | J77: =J3 -> 0
A78: N° IFU : | C78: =C4 -> 0 | G78: Exercice clos le : | H78: =H4 -> 0 | I78: Durée (en mois) : | J78: =J4 -> 0
A79: N° de télédéclarant (NES): | C79: =C5 -> 0
A81: ETAT COMPLEMENTAIRE DIRECTION GENERALE DES IMPOTS/COMPTABILITE NATIONALE
A83: DETAIL DES CHARGES EN FCFA | G83: Exercice N | H83: Exercice N-1 | I83: Variation N/N-1
I84: En valeur | J84: En %
A85: 6238 | B85: Autres contrats de location-acquisition | I85: =G85-H85 -> 0 | J85: =IF(H85,(G85-H85)/H85,IF(ISBLANK(H85),"",IF(G85,IF( G85 > 0,1,-1),"")))
A86: 6241 | B86: Entretien et réparation des biens immobiliers | I86: =G86-H86 -> 0 | J86: =IF(H86,(G86-H86)/H86,IF(ISBLANK(H86),"",IF(G86,IF( G86 > 0,1,-1),"")))
A87: 6242 | B87: Entretien et réparation des biens mobiliers | I87: =G87-H87 -> 0 | J87: =IF(H87,(G87-H87)/H87,IF(ISBLANK(H87),"",IF(G87,IF( G87 > 0,1,-1),"")))
A88: 6243 | B88: Maintenance | I88: =G88-H88 -> 0 | J88: =IF(H88,(G88-H88)/H88,IF(ISBLANK(H88),"",IF(G88,IF( G88 > 0,1,-1),"")))
A89: 6244 | B89: Charges de démentellement et remise en état | I89: =G89-H89 -> 0 | J89: =IF(H89,(G89-H89)/H89,IF(ISBLANK(H89),"",IF(G89,IF( G89 > 0,1,-1),"")))
A90: 6248 | B90: Autre entretiens et réparation | I90: =G90-H90 -> 0 | J90: =IF(H90,(G90-H90)/H90,IF(ISBLANK(H90),"",IF(G90,IF( G90 > 0,1,-1),"")))
A91: 6251 | B91: Assurances multirisques | I91: =G91-H91 -> 0 | J91: =IF(H91,(G91-H91)/H91,IF(ISBLANK(H91),"",IF(G91,IF( G91 > 0,1,-1),"")))
A92: 6252 | B92: Assurances matériels de transport | I92: =G92-H92 -> 0 | J92: =IF(H92,(G92-H92)/H92,IF(ISBLANK(H92),"",IF(G92,IF( G92 > 0,1,-1),"")))
A93: 6253 | B93: Assurances risques d'exploitation | I93: =G93-H93 -> 0 | J93: =IF(H93,(G93-H93)/H93,IF(ISBLANK(H93),"",IF(G93,IF( G93 > 0,1,-1),"")))
A94: 6254 | B94: Assurances responsabilité du producteur | I94: =G94-H94 -> 0 | J94: =IF(H94,(G94-H94)/H94,IF(ISBLANK(H94),"",IF(G94,IF( G94 > 0,1,-1),"")))
A95: 6255 | B95: Assurances insolvabilité clients | I95: =G95-H95 -> 0 | J95: =IF(H95,(G95-H95)/H95,IF(ISBLANK(H95),"",IF(G95,IF( G95 > 0,1,-1),"")))
A96: 6257 | B96: Assurances transport sur ventes | I96: =G96-H96 -> 0 | J96: =IF(H96,(G96-H96)/H96,IF(ISBLANK(H96),"",IF(G96,IF( G96 > 0,1,-1),"")))
... A111: 6283 | B111: Frais de télécopie | I111: =G111-H111 -> 0 | J111: =IF(H111,(G111-H111)/H111,IF(ISBLANK(H111),"",IF(G111,IF( G111 > 0,1,-1),"")))
A112: 6284 | B112: Frais d'internet | I112: =G112-H112 -> 0
A113: 6288 | B113: Autres frais de télécommunications | I113: =G113-H113 -> 0 | J113: =IF(H113,(G113-H113)/H113,IF(ISBLANK(H113),"",IF(G113,IF( G113 > 0,1,-1),"")))
A114: 6311 | B114: Frais sur titres (vente, garde) | I114: =G114-H114 -> 0 | J114: =IF(H114,(G114-H114)/H114,IF(ISBLANK(H114),"",IF(G114,IF( G114 > 0,1,-1),"")))
A115: 6312 | B115: Frais sur effets | I115: =G115-H115 -> 0 | J115: =IF(H115,(G115-H115)/H115,IF(ISBLANK(H115),"",IF(G115,IF( G115 > 0,1,-1),"")))
A116: 6313 | B116: Location de coffres | I116: =G116-H116 -> 0 | J116: =IF(H116,(G116-H116)/H116,IF(ISBLANK(H116),"",IF(G116,IF( G116 > 0,1,-1),"")))
A117: 6314 | B117: Commissions d'affacturage et de titrisation | I117: =G117-H117 -> 0 | J117: =IF(H117,(G117-H117)/H117,IF(ISBLANK(H117),"",IF(G117,IF( G117 > 0,1,-1),"")))
A118: 6315 | B118: Commissions sur cartes de crédit | I118: =G118-H118 -> 0 | J118: =IF(H118,(G118-H118)/H118,IF(ISBLANK(H118),"",IF(G118,IF( G118 > 0,1,-1),"")))
A119: 6316 | B119: Frais d'émission d'emprunts | I119: =G119-H119 -> 0 | J119: =IF(H119,(G119-H119)/H119,IF(ISBLANK(H119),"",IF(G119,IF( G119 > 0,1,-1),"")))
A120: 6317 | B120: Frais sur instruments monnaie électronique | I120: =G120-H120 -> 0 | J120: =IF(H120,(G120-H120)/H120,IF(ISBLANK(H120),"",IF(G120,IF( G120 > 0,1,-1),"")))
A121: 6318 | B121: Autres frais bancaires | I121: =G121-H121 -> 0 | J121: =IF(H121,(G121-H121)/H121,IF(ISBLANK(H121),"",IF(G121,IF( G121 > 0,1,-1),"")))
A122: 6322 | B122: Commissions et courtages sur ventes | I122: =G122-H122 -> 0 | J122: =IF(H122,(G122-H122)/H122,IF(ISBLANK(H122),"",IF(G122,IF( G122 > 0,1,-1),"")))
A123: 6324 | B123: Honoraires des professions règlementées | I123: =G123-H123 -> 0 | J123: =IF(H123,(G123-H123)/H123,IF(ISBLANK(H123),"",IF(G123,IF( G123 > 0,1,-1),"")))
A124: 6325 | B124: Frais d'actes et de contentieux | I124: =G124-H124 -> 0 | J124: =IF(H124,(G124-H124)/H124,IF(ISBLANK(H124),"",IF(G124,IF( G124 > 0,1,-1),"")))
... A143: 6388 | B143: Charges externes diverses | I143: =G143-H143 -> 0 | J143: =IF(H143,(G143-H143)/H143,IF(ISBLANK(H143),"",IF(G143,IF( G143 > 0,1,-1),"")))
A144: RH | C144: Services extérieurs | G144: =SUM(G63:G73,G85:G142) -> 0 | H144: =SUM(H63:H73,H85:H142) -> 0 | I144: =G144-H144 -> 0 | J144: =IF(H144,(G144-H144)/H144,IF(ISBLANK(H144),"",IF(G144,IF( G144 > 0,1,-1),"")))
A145: 6411 | B145: Impôts fonciers et taxes annexes | I145: =G145-H145 -> 0 | J145: =IF(H145,(G145-H145)/H145,IF(ISBLANK(H145),"",IF(G145,IF( G145 > 0,1,-1),"")))
A146: 6412 | B146: Patentes, licences et taxes annexes | I146: =G146-H146 -> 0 | J146: =IF(H146,(G146-H146)/H146,IF(ISBLANK(H146),"",IF(G146,IF( G146 > 0,1,-1),"")))
...

Sheet SUPPL2-PRODUITS
A1: SYSTEME NORMAL | D1: - 2 - | H1: ETAT SUPPLEMENTAIRE N°2
A2: Dénomination sociale de l'entité : | C2: ='Liste ETATS SUPPL DGI'!C3 -> 0
A3: Adresse : | B3: ='Liste ETATS SUPPL DGI'!B4 -> 0 | I3: Sigle usuel : | J3: ='Liste ETATS SUPPL DGI'!I4 -> 0
A4: N° IFU : | C4: ='Liste ETATS SUPPL DGI'!C5 -> 0 | G4: Exercice clos le : | H4: ='Liste ETATS SUPPL DGI'!F5 -> 0 | I4: Durée (en mois) : | J4: ='Liste ETATS SUPPL DGI'!I5 -> 0
A5: N° de télédéclarant (NES): | C5: ='Liste ETATS SUPPL DGI'!C6 -> 0
A7: ETAT SUPPLEMENTAIRE DIRECTION GENERALE DES IMPOTS/COMPTABILITE NATIONALE
A9: DETAIL DES PRODUITS EN FCFA | G9: Exercice N | H9: Exercice N-1 | I9: Variation N/N-1
I10: En valeur | J10: En %
A11: 70 | B11: VENTES | I11: =G11-H11 -> 0 | J11: =IF(H11,(G11-H11)/H11,IF(ISBLANK(H11),"",IF(G11,IF( G11 > 0,1,-1),"")))
A12: 71 | B12: SUBVENTIONS D'EXPLOITATION | I12: =G12-H12 -> 0 | J12: =IF(H12,(G12-H12)/H12,IF(ISBLANK(H12),"",IF(G12,IF( G12 > 0,1,-1),"")))
A13: 72 | B13: PRODUCTION IMMOBILISEE | I13: =G13-H13 -> 0 | J13: =IF(H13,(G13-H13)/H13,IF(ISBLANK(H13),"",IF(G13,IF( G13 > 0,1,-1),"")))
A14: 73 | B14: VARIATIONS DE STOCKS DE BIENS ET DE SERVICES PRODUITS | I14: =G14-H14 -> 0 | J14: =IF(H14,(G14-H14)/H14,IF(ISBLANK(H14),"",IF(G14,IF( G14 > 0,1,-1),"")))
A15: 75 | B15: AUTRES PRODUITS | I15: =G15-H15 -> 0 | J15: =IF(H15,(G15-H15)/H15,IF(ISBLANK(H15),"",IF(G15,IF( G15 > 0,1,-1),"")))
A16: 77 | B16: REVENUS FINANCIERS ET ASSIMILES | I16: =G16-H16 -> 0 | J16: =IF(H16,(G16-H16)/H16,IF(ISBLANK(H16),"",IF(G16,IF( G16 > 0,1,-1),"")))
A17: 78 | B17: TRANSFERTS DE CHARGES | I17: =G17-H17 -> 0 | J17: =IF(H17,(G17-H17)/H17,IF(ISBLANK(H17),"",IF(G17,IF( G17 > 0,1,-1),"")))
A18: 79 | B18: REPRISES DE PROVISIONS DE DEPRECIATIONS ET AUTRES | I18: =G18-H18 -> 0 | J18: =IF(H18,(G18-H18)/H18,IF(ISBLANK(H18),"",IF(G18,IF( G18 > 0,1,-1),"")))
J22: =IF(H22,(G22-H22)/H22,IF(ISBLANK(H22),"",IF(G22,1,"")))
A23: TOTAL DES PRODUITS | G23: =SUM(G11:G22) -> 0 | H23: =SUM(H11:H22) -> 0 | I23: =SUM(I11:I22) -> 0 | J23: =SUM(J11:J22) -> 0
A24: NB: tous les sous-comptes utilisés devront être indiqués en détail

Sheet SUPPL3-TVA (1)
A1: SYSTEME NORMAL | E1: - 0 - | G1: ETAT SUPPLEMENTAIRE N°3
A2: Dénomination sociale de l'entité : | C2: ='Liste ETATS SUPPL DGI'!C3 -> 0
A3: Adresse : | B3: ='Liste ETATS SUPPL DGI'!B4 -> 0 | G3: Sigle usuel : | H3: ='Liste ETATS SUPPL DGI'!I4 -> 0
A4: N° IFU : | C4: ='Liste ETATS SUPPL DGI'!C5 -> 0 | E4: Exercice clos le : | F4: ='Liste ETATS SUPPL DGI'!F5 -> 0 | G4: Durée (en mois) : | H4: ='Liste ETATS SUPPL DGI'!I5 -> 0
A5: N° de télédéclarant (NES): | C5: ='Liste ETATS SUPPL DGI'!C6 -> 0
A7: ETAT SUPPLEMENTAIRE DIRECTION GENERALE DES IMPOTS/COMPTABILITE NATIONALE
A9: ETAT TVA (Inscrire les mouvements de la période et non les soldes des comptes) | G9: Exercice N | H9: Exercice N-1
B10: T.V.A. facturée sur ventes de la période
B11: T.V.A. facturée sur prestations de services de la période
B12: T.V.A. facturée sur travaux de la période
B13: T.V.A. facturée sur production livrée à soi-même de la période
B14: T.V.A. sur factures à établir de la période
C15: T.V.A. facturée de la période | G15: =SUM(G10:G14) -> 0 | H15: =SUM(H10:H14) -> 0
C16: T.V.A. exigible de la période
B17: T.V.A. récupérable sur immobilisations de la période
B18: T.V.A. récupérable sur achats de la période
B19: T.V.A. récupérable sur transport de la période
B20: T.V.A. récupérable sur services extérieurs et autres charges de la période
B21: T.V.A. récupérable sur factures non parvenues de la période
B22: T.V.A. transférée par d'autres entités de la période
C23: T.V.A. Récupérable de la période | G23: =SUM(G17:G22) -> 0 | H23: =SUM(H17:H22) -> 0
C24: T.V.A. Récupérée de la période
C25: Prorata de déduction
B26: État, T.V.A. due
B27: État, crédit de T.V.A. à reporter
C28: T.V.A. Due ou crédit de T.V.A. | G28: =SUM(G26:G27) -> 0 | H28: =SUM(H26:H27) -> 0

Sheet SUPPL4-TVA (2)
A1: SYSTEME NORMAL | E1: - 0 - | G1: ETAT SUPPLEMENTAIRE N°4
A2: Dénomination sociale de l'entité : | C2: ='Liste ETATS SUPPL DGI'!C3 -> 0
A3: Adresse : | B3: ='Liste ETATS SUPPL DGI'!B4 -> 0 | G3: Sigle usuel : | H3: ='Liste ETATS SUPPL DGI'!I4 -> 0
A4: N° IFU : | C4: ='Liste ETATS SUPPL DGI'!C5 -> 0 | E4: Exercice clos le : | F4: ='Liste ETATS SUPPL DGI'!F5 -> 0 | G4: Durée (en mois) : | H4: ='Liste ETATS SUPPL DGI'!I5 -> 0
A5: N° de télédéclarant (NES): | C5: ='Liste ETATS SUPPL DGI'!C6 -> 0
A7: ETAT SUPPLEMENTAIRE COMPTABILITE NATIONALE
A9: ETAT TVA SUPPORTEE NON DEDUCTIBLE (Inscrire les mouvements de la période et non les soldes des comptes) | G9: Exercice N | H9: Exercice N-1
B10: T.V.A. supportée non déductible sur les immobilisations
B11: T.V.A. supportée non déductible sur les achats de biens et de services
C12: Total T.V.A. supportée non déductible de la période | G12: =SUM(G10:G11) -> 0 | H12: =SUM(H10:H11) -> 0

Sheet SUPPL5
A1: - 0 -
L2: ETAT SUPPLEMENTAIRE N°5
A3: Dénomination sociale de l'entité : | B3: ='Liste ETATS SUPPL DGI'!C3 -> 0
A4: Adresse : | B4: ='Liste ETATS SUPPL DGI'!B4 -> 0 | L4: Sigle usuel : | M4: ='Liste ETATS SUPPL DGI'!I4 -> 0
A5: N° IFU : | B5: ='Liste ETATS SUPPL DGI'!C5 -> 0 | I5: Exercice clos le : | J5: ='Liste ETATS SUPPL DGI'!F5 -> 0 | M5: Durée (en mois) : | N5: ='Liste ETATS SUPPL DGI'!I5 -> 0
A6: N° de télédéclarant (NES): | B6: ='Liste ETATS SUPPL DGI'!C6 -> 0
A7: ETAT SUPPLEMENTAIRE : ELEMENTS STATISTIQUES UEMOA
A8: COMPLEMENT NOTE ANNEXE (Valeur en francs CFA) | I8: COMPLEMENT NOTE 32 (Valeurs en francs CFA)
A9: COMPLEMENT ETAT ANNEXE | D9: Montant autres Etats de l'UEMOA | F9: Montant autres Etats de la Région hors de l'UEMOA | I9: DESIGNATION DU PRODUIT | J9: UNITE DE QUANTITE CHOISIE | K9: PRODUCTION VENDUE DANS LES AUTRES ETATS DE L'UEMOA | M9: PRODUCTION VENDUE AUTRES ETATS DE LA REGION HORS DE L'UEMOA
K12: Quantité | L12: Valeur | M12: Quantité | N12: Valeur
A14: I - B12 - 1 DETAIL DE PRODUITS :
A17: Redevances pour brevets, concessions,
A18: licences, marques et droits similaires :
A19: Redevances pour location de terrains agricoles :
A21: I - C1 - BIENS ACQUIS D'OCCASION :
I30: NON VENTILE
I31: TOTAL | K31: =SUM(K13:K30) -> 0 | L31: =SUM(L13:L30) -> 0 | M31: =SUM(M13:M30) -> 0 | N31: =SUM(N13:N30) -> 0
A33: COMPLEMENT NOTE 27 B | B33: AUTRE ETATS DE L'UEMOA | I33: COMPLEMENT NOTE 33 ACHATS DESTINES A LA PRODUCTION EN F CFA | M33: Exercice N
A34: PERSONNEL PROPRE | B34: EFFECTIFS | D34: MASSE SALARIALE | I34: Achats de marchandises dans l'UEMOA
B35: M | C35: F | D35: M | F35: F | I35: Achats de marchandises au groupe dans
A36: 1. CADRE SUPERIEURS | I36: l'UEMOA
A37: 2. TECHNICIENS SUPERIEURS ET CADRES MOYENS | I37: Achats de marchandises | M37: =SUM(M34:N36) -> 0
A38: 3. TECHNICIENS, AGENTS DE MAITRISE ET OUVRIERS QUALIFIES | I38: Achats de matières premières dans l'UEMOA
A39: 4. EMPLOYES, MANŒUVRES, OUVRIERS ET APPRENTIS | I39: Achats de matières premières au groupe dans l'UEMOA
A40: TOTAL | B40: =SUM(B36:B39) -> 0 | C40: =SUM(C36:C39) -> 0 | D40: =SUM(D36:E39) -> 0 | F40: =SUM(F36:G39) -> 0
A41: PERMANENTS
A42: SAISONNIERS | I42: Achats de matières premières | M42: =SUM(M38:N41) -> 0

Sheet SUPPL6
A1: - 0 -
I2: ETAT SUPPLEMENTAIRE N°6
A3: Dénomination sociale de l'entité : | C3: ='Liste ETATS SUPPL DGI'!C3 -> 0
A4: Adresse : | B4: ='Liste ETATS SUPPL DGI'!B4 -> 0 | I4: Sigle usuel : | J4: ='Liste ETATS SUPPL DGI'!I4 -> 0
A5: N° IFU : | C5: ='Liste ETATS SUPPL DGI'!C5 -> 0 | G5: Exercice clos le : | H5: ='Liste ETATS SUPPL DGI'!F5 -> 0 | I5: Durée (en mois) : | J5: ='Liste ETATS SUPPL DGI'!I5 -> 0
A6: N° de télédéclarant (NES): | C6: ='Liste ETATS SUPPL DGI'!C6 -> 0
A7: REPARTITION DU RESULTAT FISCAL DES SOCIETES DE PERSONNES
A8: Nom et Prénoms des Associés | C8: Adresse du Domicile Fiscal | F8: N° de Compte Contribuable | G8: Part des résultats avant réintégration de leurs rémunération et AN et part de l'IMF | H8: Rémunération et avantages en nature et part de l'IMF leur revenant | I8: Total imposable au nom de chaque associé | J8: N° note / ref autres parties états financiers
A31: TOTAL | G31: =SUM(G9:G30) -> 0 | H31: =SUM(H9:H30) -> 0 | I31: =SUM(I9:I30) -> 0 | J31: =SUM(J9:J30) -> 0

Sheet SUPPL7
A1: - 0 -
J2: ETAT SUPPLEMENTAIRE N°7
A3: Dénomination sociale de l'entité : | C3: ='Liste ETATS SUPPL DGI'!C3 -> 0
A4: Adresse : | B4: ='Liste ETATS SUPPL DGI'!B4 -> 0 | J4: Sigle usuel : | K4: ='Liste ETATS SUPPL DGI'!I4 -> 0
A5: N° IFU : | C5: ='Liste ETATS SUPPL DGI'!C5 -> 0 | G5: Exercice clos le : | H5: ='Liste ETATS SUPPL DGI'!F5 -> 0 | J5: Durée (en mois) : | K5: ='Liste ETATS SUPPL DGI'!I5 -> 0
A6: N° de télédéclarant (NES): | C6: ='Liste ETATS SUPPL DGI'!C6 -> 0
A7: COMPLEMENT INFORMATIONS ENTITES INDIVIDUELLES
E8: EXPLOITANTS INDIVIDUELS | K8: N° note / ref autres parties des états financiers
A9: APPORTS FINANCIERS AU COURS EXERCICE
A10: PRELEVEMENTS FINANCIERS AU COURS EXERCICE
A11: AVANTAGES EN NATURE VALEUR REELLE
A12: REMUNERATIONS CONJOINT EXPLOITANT

Sheet SUPPL8
A1: - 0 -
M2: ETAT SUPPLEMENTAIRE N°8
A3: Dénomination sociale de l'entité : | C3: ='Liste ETATS SUPPL DGI'!C3 -> 0
A4: Adresse : | B4: ='Liste ETATS SUPPL DGI'!B4 -> 0 | L4: Sigle usuel : | M4: ='Liste ETATS SUPPL DGI'!I4 -> 0
A5: N° IFU : | C5: ='Liste ETATS SUPPL DGI'!C5 -> 0 | G5: Exercice clos le : | I5: ='Liste ETATS SUPPL DGI'!F5 -> 0 | L5: Durée (en mois) : | M5: ='Liste ETATS SUPPL DGI'!I5 -> 0
A6: N° de télédéclarant (NES): | C6: ='Liste ETATS SUPPL DGI'!C6 -> 0
A7: TABLEAU DES IMMOBILISATIONS ET DES AMORTISSEMENTS
A8: NUMERO DE COMPTE | B8: DESIGNATION DES IMMOBILISATIONS | E8: TAUX AMORT. % | F8: DATE MISE SERVICE | G8: VALEUR D'ACQUISITION | H8: AMORTISSEMENTS | K8: VALEUR RESIDUELLE | L8: PRIX CESSION | M8: PLUES-VALUE | N8: MOINS-VALUES
H9: ANTERIEURS | I9: DE L'EXERCICE | J9: TOTAL
J10: =H10+I10 -> 0
J11: =H11+I11 -> 0
J12: =H12+I12 -> 0
J13: =H13+I13 -> 0
J14: =H14+I14 -> 0
J15: =H15+I15 -> 0
J16: =H16+I16 -> 0
J17: =H17+I17 -> 0
J18: =H18+I18 -> 0
J19: =H19+I19 -> 0
J20: =H20+I20 -> 0
J21: =H21+I21 -> 0
... J39: =H39+I39 -> 0
A40: TOTAL | G40: =SUM(G10:G39) -> 0 | H40: =SUM(H10:H39) -> 0 | I40: =SUM(I10:I39) -> 0 | J40: =SUM(J10:J39) -> 0 | K40: =SUM(K10:K39) -> 0 | L40: =SUM(L10:L39) -> 0 | M40: =SUM(M10:M39) -> 0 | N40: =SUM(N10:N39) -> 0

Sheet SUPPL9
A1: - 0 -
O2: ETAT SUPPLEMENTAIRE N°9
A3: Dénomination sociale de l'entité : | C3: ='Liste ETATS SUPPL DGI'!C3 -> 0
A4: Adresse : | B4: ='Liste ETATS SUPPL DGI'!B4 -> 0 | N4: Sigle usuel : | P4: ='Liste ETATS SUPPL DGI'!I4 -> 0
A5: N° IFU : | C5: ='Liste ETATS SUPPL DGI'!C5 -> 0 | I5: Exercice clos le : | K5: ='Liste ETATS SUPPL DGI'!F5 -> 0 | N5: Durée (en mois) : | P5: ='Liste ETATS SUPPL DGI'!I5 -> 0
A6: N° de télédéclarant (NES): | C6: ='Liste ETATS SUPPL DGI'!C6 -> 0
A7: DETAIL DES FRAIS ACCESSOIRES SUR ACHATS
D8: Achats de marchandises | F8: Achats de matières premières et fournitures liées | H8: Achats stockés de matières et fournitures consommables | J8: Achats d'emballages | L8: Autres achats | N8: Total rubriques | P8: Immobilisations
A9: Droits de douane | N9: =SUM(D9:M9) -> 0
A10: Frets et transports sur achats | N10: =SUM(D10:M10) -> 0
A11: Assurances transport sur achats | N11: =SUM(D11:M11) -> 0
A12: Commissions et courtages sur achats | N12: =SUM(D12:M12) -> 0
A13: Rémunération du transitaire | N13: =SUM(D13:M13) -> 0
A14: Autres frais accessoires d'achat | N14: =SUM(D14:M14) -> 0
A15: Total frais accessoires d'achats | D15: =SUM(D9:E14) -> 0 | F15: =SUM(F9:G14) -> 0 | H15: =SUM(H9:I14) -> 0 | J15: =SUM(J9:K14) -> 0 | L15: =SUM(L9:M14) -> 0 | N15: =SUM(N9:O14) -> 0 | P15: =SUM(P9:Q14) -> 0

Sheet SUPPL10
A1: - 0 -
G2: ETAT SUPPLEMENTAIRE N°10
A3: Dénomination sociale de l'entité : | C3: ='Liste ETATS SUPPL DGI'!C3 -> 0
A4: Adresse : | B4: ='Liste ETATS SUPPL DGI'!B4 -> 0 | G4: Sigle usuel : | H4: ='Liste ETATS SUPPL DGI'!I4 -> 0
A5: N° IFU : | C5: ='Liste ETATS SUPPL DGI'!C5 -> 0 | E5: Exercice clos le : | F5: ='Liste ETATS SUPPL DGI'!F5 -> 0 | G5: Durée (en mois) : | H5: ='Liste ETATS SUPPL DGI'!I5 -> 0
A6: N° de télédéclarant (NES): | C6: ='Liste ETATS SUPPL DGI'!C6 -> 0
A7: DETAIL DES AVANTAGES EN NATURE ALLOUES AU PERSONNEL
G8: Forfait (Barème) F.CFA | H8: Montant réel F.CFA
A9: Loyers de logement du personnel
A10: Bâtiment de logement mis à la disposition du personnel
A11: Eau logement du personnel
A12: Electricité logement du personnel
A13: Télécommunication logement du personnel
A14: Frais de téléphone mobile
A15: Gardiennage logement du personnel
A16: Voyages congés personnel
A17: Matériels de transport mis à disposition du personnel
A18: Autres à préciser
A24: TOTAL (1) | G24: =SUM(G9:G23) -> 0 | H24: =SUM(H9:H23) -> 0

Sheet SUPPL  11
A1: - 0 -
H2: ETAT SUPPLEMENTAIRE N°11
A3: Dénomination sociale de l'entité : | C3: ='Liste ETATS SUPPL DGI'!C3 -> 0
A4: Adresse : | B4: ='Liste ETATS SUPPL DGI'!B4 -> 0 | H4: Sigle usuel : | I4: ='Liste ETATS SUPPL DGI'!I4 -> 0
A5: N° IFU : | C5: ='Liste ETATS SUPPL DGI'!C5 -> 0 | E5: Exercice clos le : | F5: ='Liste ETATS SUPPL DGI'!F5 -> 0 | H5: Durée (en mois) : | I5: ='Liste ETATS SUPPL DGI'!I5 -> 0
A6: N° de télédéclarant (NES): | C6: ='Liste ETATS SUPPL DGI'!C6 -> 0
A7: CREANCES & DETTES ECHUES DE L'EXERCICE
A8: CREANCES ECHUES DE L'EXERCICE | H8: PRINCIPAL | I8: INTERETS
A19: DETTES ECHUES DE L'EXERCICE | H19: PRINCIPAL | I19: INTERETS

Sheet SUPPL12
A1: - 0 -
I2: ETAT SUPPLEMENTAIRE N°12
A3: Dénomination sociale de l'entité : | C3: ='Liste ETATS SUPPL DGI'!C3 -> 0
A4: Adresse : | B4: ='Liste ETATS SUPPL DGI'!B4 -> 0 | I4: Sigle usuel : | J4: ='Liste ETATS SUPPL DGI'!I4 -> 0
A5: N° IFU : | B5: ='Liste ETATS SUPPL DGI'!C5 -> 0 | E5: Exercice clos le : | G5: ='Liste ETATS SUPPL DGI'!F5 -> 0 | I5: Durée (en mois) : | J5: ='Liste ETATS SUPPL DGI'!I5 -> 0
A6: N° de télédéclarant (NES): | C6: ='Liste ETATS SUPPL DGI'!C6 -> 0
A7: ETAT ANNUEL DES SALAIRES
A8: DESIGNATION DES SALARIES | D8: MONTANT des traitements ou Salaires bruts 4 | E8: NOMBRE de personnes à charge 5 | F8: PERIODE 6 | G8: MONTANT des allocations à la fonction 7 | H8: INDEMNITE de logement 8 | I8: INDEMNITE de transport 9 | J8: RETENUES pour pension 11 | K8: RETENUES IUTS 12
A9: NOM ET PRENOMS 1 | B9: EMPLOI 2 | C9: ADRESSE AU 1er JANVIER ou dernière adresse 3
A20: TOTAL | D20: =SUM(D10:D19) -> 0 | J20: =SUM(J10:J19) -> 0 | K20: =SUM(K10:K19) -> 0

Sheet SUPPL13
I1: ETAT SUPPLEMENTAIRE N°13
A2: Dénomination sociale de l'entité : | C2: ='Liste ETATS SUPPL DGI'!C2 -> 0
A3: Adresse : | C3: ='Liste ETATS SUPPL DGI'!B3 -> 0 | I3: Sigle usuel : | J3: ='Liste ETATS SUPPL DGI'!I3 -> 0
A4: N° IFU : | C4: ='Liste ETATS SUPPL DGI'!C4 -> 0 | E4: Exercice clos le : | G4: ='Liste ETATS SUPPL DGI'!F4 -> 0 | I4: Durée (en mois) : | J4: ='Liste ETATS SUPPL DGI'!I4 -> 0
A5: N° de télédéclarant (NES): | C5: ='Liste ETATS SUPPL DGI'!C5 -> 0
A6: ETAT ANNUEL DES COMMISSIONS, VACATIONS, COURTAGES, RISTOURNES, HONORAIRES ET DROITS D'AUTEUR
A7: N° IFU | B7: NOM, RAISON SOCIALE | E7: TELEPHONE | G7: NATURE DE L'OPERATION | I7: Montant annuel HTVA | J7: TVA | K7: TOTAL TTC
A19: TOTAL | B19: =SUM(C9:C18) -> 0 | J19: =SUM(J9:J18) -> 0 | K19: =SUM(K9:K18) -> 0

Sheet SUPPL14
G1: ETAT SUPPLEMENTAIRE N°14
A3: Dénomination sociale de l'entité : | C3: ='Liste ETATS SUPPL DGI'!C3 -> 0
A4: Adresse : | C4: ='Liste ETATS SUPPL DGI'!B4 -> 0 | H4: Sigle usuel : | I4: ='Liste ETATS SUPPL DGI'!I4 -> 0
A5: N° IFU : | C5: ='Liste ETATS SUPPL DGI'!C5 -> 0 | E5: Exercice clos le : | G5: ='Liste ETATS SUPPL DGI'!F5 -> 0 | H5: Durée (en mois) : | I5: ='Liste ETATS SUPPL DGI'!I5 -> 0
A6: N° de télédéclarant (NES): | C6: ='Liste ETATS SUPPL DGI'!C6 -> 0
A8: ETAT ANNUEL DES REMUNERATIONS VERSEES AUX ASSOCIES ET DES PARTS DE BENEFICES SOCIAUX
A10: N° IFU | B10: NOM, RAISON SOCIALE | E10: TELEPHONE | G10: Type de rémunération | I10: Montant perçu
A22: TOTAL

Sheet SUPPL15
F1: ETAT SUPPLEMENTAIRE N°15
A2: Dénomination sociale de l'entité : | C2: ='[1]Liste ETATS SUPPL DGI'!C2 -> 0
A3: Adresse : | C3: ='[1]Liste ETATS SUPPL DGI'!B3 -> 0 | H3: Sigle usuel : | I3: ='[1]Liste ETATS SUPPL DGI'!I3 -> 0
A4: N° IFU : | C4: ='[1]Liste ETATS SUPPL DGI'!C4 -> 0 | E4: Exercice clos le : | F4: ='[1]Liste ETATS SUPPL DGI'!F4 -> 0 | H4: Durée (en mois) : | I4: ='[1]Liste ETATS SUPPL DGI'!I4 -> 0
A5: N° de télédéclarant (NES): | C5: ='[1]Liste ETATS SUPPL DGI'!C5 -> 0
A7: ETAT DES LOYERS PASSES EN CHARGES
A8: N° IFU du bailleur (éventuellement) | B8: NOM DU BAILLEUR | E8: Adresse, Téléphone | F8: Lieu de situation de l'immeuble loué | H8: Loyer mensuel | I8: Montant total loyers passés en charges
A20: TOTAL | I20: =SUM(I10:I19) -> 0

Sheet SUPPL16
I1: ETAT SUPPLEMENTAIRE N°16
A2: Dénomination sociale de l'entité : | E2: ='[1]Liste ETATS SUPPL DGI'!C2 -> 0
A3: Adresse : | E3: ='[1]Liste ETATS SUPPL DGI'!B3 -> 0 | I3: Sigle usuel : | J3: ='[1]Liste ETATS SUPPL DGI'!I3 -> 0
A4: N° IFU : | E4: ='[1]Liste ETATS SUPPL DGI'!C4 -> 0 | G4: Exercice clos le : | H4: ='[1]Liste ETATS SUPPL DGI'!F4 -> 0 | I4: Durée (en mois) : | K4: ='[1]Liste ETATS SUPPL DGI'!I4 -> 0
A5: N° de télédéclarant (NES): | E5: ='[1]Liste ETATS SUPPL DGI'!C5 -> 0
A6: ETAT ANNUEL DES HONORAIRES RETROCEDES POUR DETERMINATION DE L'IBNC
A7: N° IFU du bénéficiaire | C7: NOM, RAISON SOCIALE | F7: TELEPHONE | G7: LOCALITE | H7: SERVICE DES IMPOTS DE RATTACHEMENT | I7: Montant total HTVA | J7: TVA | K7: TOTAL TTC
A19: TOTAL | I19: =SUM(I8:I18) -> 0 | J19: =SUM(J8:J18) -> 0 | K19: =SUM(K8:K18) -> 0

Sheet SUPPL17
A1: - 0 -
H2: ETAT SUPPLEMENTAIRE N°17
A3: Dénomination sociale de l'entité : | D3: ='[1]Liste ETATS SUPPL DGI'!C3 -> 0
A4: Adresse : | C4: ='[1]Liste ETATS SUPPL DGI'!B4 -> 0 | G4: Sigle usuel : | H4: ='[1]Liste ETATS SUPPL DGI'!I4 -> 0
A5: N° IFU : | C5: ='[1]Liste ETATS SUPPL DGI'!C5 -> 0 | E5: Exercice clos le : | F5: ='[1]Liste ETATS SUPPL DGI'!F5 -> 0 | H5: Durée (en mois) : | J5: ='[1]Liste ETATS SUPPL DGI'!I5 -> 0
A6: N° de télédéclarant (NES): | C6: ='[1]Liste ETATS SUPPL DGI'!C6 -> 0
A7: LISTE DES PRINCIPAUX CLIENTS
A8: N° IFU | B8: NOM, RAISON SOCIALE | E8: TELEPHONE | F8: LOCALITE | G8: SERVICE DES IMPOTS DE RATTACHEMENT | H8: Montant annuel HTVA | I8: TVA | J8: TOTAL TTC
A21: TOTAL | H21: =SUM(H9:H20) -> 0 | I21: =SUM(I9:I20) -> 0 | J21: =SUM(J9:J20) -> 0

Sheet SUPPL18
A1: - 0 -
H2: ETAT SUPPLEMENTAIRE N°18
A3: Dénomination sociale de l'entité : | D3: ='[1]Liste ETATS SUPPL DGI'!C3 -> 0
A4: Adresse : | C4: ='[1]Liste ETATS SUPPL DGI'!B4 -> 0 | G4: Sigle usuel : | H4: ='[1]Liste ETATS SUPPL DGI'!I4 -> 0
A5: N° IFU : | C5: ='[1]Liste ETATS SUPPL DGI'!C5 -> 0 | E5: Exercice clos le : | F5: ='[1]Liste ETATS SUPPL DGI'!F5 -> 0 | H5: Durée (en mois) : | J5: ='[1]Liste ETATS SUPPL DGI'!I5 -> 0
A6: N° de télédéclarant (NES): | C6: ='[1]Liste ETATS SUPPL DGI'!C6 -> 0
A7: LISTE DES PRINCIPAUX FOURNISSEURS
A8: N° IFU | B8: NOM, RAISON SOCIALE | E8: TELEPHONE | F8: LOCALITE | G8: SERVICE DES IMPOTS DE RATTACHEMENT | H8: Montant annuel HTVA | I8: TVA | J8: TOTAL TTC
A31: TOTAL | H31: =SUM(H9:H30) -> 0 | I31: =SUM(I9:I30) -> 0 | J31: =SUM(J9:J30) -> 0

Sheet SUPPL19 RESULTAT FISCAL
A1: - 0 -
G2: ETAT SUPPLEMENTAIRE N° 19
A3: Dénomination sociale de l'entité : | C3: ='NOTE 31'!C3 -> 0
A4: Adresse : | B4: ='NOTE 31'!B4 -> 0 | G4: Sigle usuel : | H4: ='NOTE 31'!K4 -> 0
A5: N° IFU : | C5: ='NOTE 31'!C5 -> 0 | E5: Exercice clos le : | F5: ='NOTE 31'!H5 -> 0 | G5: Durée (en mois) : | H5: ='NOTE 31'!K5 -> 0
A6: N° de télédéclarant (NES): | C6: ='NOTE 31'!C6 -> 0
A7: TABLEAU DE DETERMINATION DU RESULTAT FISCAL
A8: Libellés | H8: Montant
A9: 1 : RESULTAT NET COMPTABLE DE L'EXERCICE
A11: 2 : REINTEGRATIONS (1) | H11: =SUM(H12:H16) -> 0
A12: ……………..
A13: ……………..
A14: ……………..
A15: ……………..
A16: ……………..
A17: 3 : DEDUCTIONS (1) | H17: =SUM(H18:H22) -> 0
A18: ……………..
A19: ……………..
A20: ……………..
A21: ……………..
A22: ……………..
A23: 4 : RESULTAT IMPOSABLE AVANT DEDUCTION DES DEFICITS ( 4 = 1+2-3) | H23: =H9+H11-H17 -> 0
A25: 5 : DEFICITS ANTERIEURS A L'EXERCICE (1) | H25: =SUM(H26:H27) -> 0
A26: ……………..
A27: ……………..
A28: 6 : AMORTISSEMENTS REGULIEREMENT DIFFERES (1) | H28: =SUM(H29:H30) -> 0
A29: ……………..
A30: ……………..
A31: 7 : AMORTISSEMENTS DE L'EXERCICE A DIFFERER (1) | H31: =SUM(H32:H33) -> 0
A32: ……………..
A33: ……………..
A34: 8 : RESULTAT FISCAL DE L'EXERCICE (8= 4-5-6+7) | H34: =H23-H25-H28+H31 -> 0
A36: 9: IMPOTS SUR LE RESULTAT AU TAUX DE : | H36: =H34*D36 -> 0
A39: (1) A détailler

Sheet SUPPL20 BAV IS
A1: CACHET DU SERVICE | C1: DIRECTION GENERALE DES IMPOTS | G1: DATE DE RECEPTION
C5: BORDEREAU AVIS DE VERSEMENT
C6: DE L'IMPOT SUR LES SOCIETES (IS)
C7: Exercice comptable clos le : ……………………………..
B8: Réel normal d’imposition | E8: Réel simplifié d’imposition
A9: Supprimer cette ligne
A10: I. IDENTIFICATION DU CONTRIBUABLE
A11: N° Registre du commerce | F11: N° IFU
A12: Raison Sociale :………………………………………………………………………………………………………
A13: Code Activité | D13: Regime agrément | F13: Adhérant CGA
A14: Activité:…………………………………………………………………………………………………………………
A15: Adresse du siège: Localité:………………………Tel…………………………E_mail…………………………
A16: BP :…………… | B16: Secteur:……. | D16: N° et rue: | E16: ………………… | F16: Section:……. | G16: Lot:…………… | H16: Parcelle:……
A17: Adresses des Etablissements Secondaires (joindre un intercalaire si nécessaire) :
A18: 1)………………………………………………………………………………………………………………………
A19: 2)………………………………………………………………………………………………………………………
A20: 3)………………………………………………………………………………………………………………………
A21: II. DETERMINATION DE L'IMPOT
A23: 01 | B23: CHIFFRE D'AFFAIRES HORS TVA
A25: 02 | B25: RESULTAT FISCAL : Bénéfice Perte
A27: 03 | B27: COTISATION IS EXIGIBLE (ou Minimum Forfaitaire de Perception)
A29: 04 | B29: ACOMPTES PROVISIONNELS DECLARES
A31: 05 | B31: IRVM SUBI (Attestation jointe)
A33: 06 | B33: IRC SUBI (Attestation jointe)
A35: 07 | B35: COTISATION IS DUE [03-(04+05+06)]
A37: 08 | B37: Prélèvements à la source à titre d'acompte d'impôt sur les
B38: bénéfices imputés ( déclaration des prélèvements supportés ci
B39: annexée Montant IV)
A41: 09 | B41: Retenues à la source subies imputées ( déclaration des retenues
B42: subies et attestations de retenues ci-jointes Montant T4)
A44: 10 | B44: COTISATION IS A PAYER [ 07 - (08+09)] *
A47: Règlement joint à l'ordre du receveur des impôts
A49: - Chèque barré sur ……………..………... N° …………..………….. du …………….…... Montant ………..……
A51: -Virement (avis de credit): …………………………………………………………………………………...
A52: - Espèces d'un montant de ………………………………..………………………………………………………
D54: A……………………………..……………., le…………………..……
F56: Nom, Qualité et signature
A59: III- CADRE RESERVE A L'ADMINISTRATION
A60: PRISE EN RECETTE | C60: PRISE EN CHARGE | E60: PENALITE | G60: VISA DU RECEVEUR
A61: L.J | C61: L.J | E61: Base: | G61: Date-cachet-signature
A62: Réf . | C62: Réf . | E62: Taux :
A63: Quittance n° | C63: Réf . AMR | E63: Montant :
A64: Quittance date : | C64: Date :
A65: Montant : | C65: Montant :
A67: * Si la cotisation IS due est inférieure ou égale aux prélèvements supportés et aux rétenues subies, porter «zéro(0)» dans la case

Sheet PAGE GARDE IS
E21: DETERMINATION DU RESULTAT FISCAL ET DE L'IMPOT SUR LES SOCIETES (IS)

Sheet PAGE GARDE IBICA 
E21: DETERMINATION DU RESULTAT FISCAL ET DE L'IMPOT SUR LES BENEFICES INDUSTRIELS OU COMMERCIAUX (IBICA)

Sheet PAGE GARDE BNC
E21: DETERMINATION DU RESULTAT FISCAL ET DE L'IMPOT SUR LES DES BENEFICES NON COMMERCIAUX (IBNC)
